Workbook

Sheet BTC COINS
B1: Index | C1: BRRNY | D1: BRRNY | E1: BRRNY | F1: XBX | G1: BRRNY | H1: BRRNY | I1: Fidelity | J1: XBX | K1: MarketVector | L1: BRRNY
B2: ConId | C2: 677037663 | D2: 677037658 | E2: 677037676 | F2: 741192224 | G2: 676783288 | H2: 676783282 | I2: 676783301 | J2: 349966059 | K2: 677037670 | L2: 677037673
B3: Annual Fee | C3: 0.0021 | D3: 0.002 | E3: 0.0025 | F3: 0.0015 | G3: 0.0025 | H3: 0.0019 | I3: 0.0025 | J3: 0.015 | K3: 0 | L3: 0.0025
A4: 365 | B4: Daily Fee | C4: =C3/$A4 -> 5.7534247e-06 | D4: =D3/$A4 -> 5.4794521e-06 | E4: =E3/$A4 -> 6.8493151e-06 | F4: =F3/$A4 -> 4.109589e-06 | G4: =G3/$A4 -> 6.8493151e-06 | H4: =H3/$A4 -> 5.2054795e-06 | I4: =I3/$A4 -> 6.8493151e-06 | J4: =J3/$A4 -> 4.109589e-05 | ... L4: =L3/$A4 -> 6.8493151e-06
A6: DOW | B6: Date | C6: ARKB | D6: BITB | E6: BRRR | F6: BTC | G6: BTCW | H6: EZBC | I6: FBTC | J6: GBTC | K6: HODL | L6: IBIT | M6: Sum | N6: Change | O6: Pct Change | P6: Price | Q6: Price Change | R6: Price % Chg
A7: =scalars[[#This Row],[DOW]] -> Sunday | B7: 46082
A8: =scalars[[#This Row],[DOW]] -> Monday | B8: =B7+1 -> 46083
A9: =scalars[[#This Row],[DOW]] -> Tuesday | B9: =B8+1 -> 46084
A10: =scalars[[#This Row],[DOW]] -> Wednesday | B10: =B9+1 -> 46085
A11: =scalars[[#This Row],[DOW]] -> Thursday | B11: =B10+1 -> 46086
A12: =scalars[[#This Row],[DOW]] -> Friday | B12: =B11+1 -> 46087
A13: =scalars[[#This Row],[DOW]] -> Saturday | B13: =B12+1 -> 46088
A14: =scalars[[#This Row],[DOW]] -> Sunday | B14: =B13+1 -> 46089
A15: =scalars[[#This Row],[DOW]] -> Monday | B15: =B14+1 -> 46090
A16: =scalars[[#This Row],[DOW]] -> Tuesday | B16: =B15+1 -> 46091
A17: =scalars[[#This Row],[DOW]] -> Wednesday | B17: =B16+1 -> 46092
A18: =scalars[[#This Row],[DOW]] -> Thursday | B18: =B17+1 -> 46093
A19: =scalars[[#This Row],[DOW]] -> Friday | B19: =B18+1 -> 46094
... A21: =scalars[[#This Row],[DOW]] -> Sunday | B21: =B20+1 -> 46096
A22: =scalars[[#This Row],[DOW]] -> Monday | B22: =B21+1 -> 46097 | C22: =ARKB!G21 -> 35644.71 | D22: =BITB!H21 -> 38920.51 | E22: =BRRR!G22 -> 6256.69 | F22: =BTC!J21 -> 51689.489 | G22: =BTCW!H21 -> 2163 | H22: =H23 -> 6245.79 | J22: =GBTC!K21 -> 155874.24 | K22: =HODL!H21 -> 17153.107 | L22: =IBIT!G21 -> 784061.76 | M22: =SUM(btc_ratios3[[#This Row],[ARKB]:[IBIT]]) -> 1098009.3
A23: =scalars[[#This Row],[DOW]] -> Tuesday | B23: =B22+1 -> 46098 | C23: =ARKB!G22 -> 35677.89 | D23: =BITB!H22 -> 38920.51 | E23: =BRRR!G23 -> 6256.65 | F23: =BTC!J22 -> 51689.277 | G23: =G22 -> 2163 | H23: =EZBC!F22 -> 6245.79 | J23: =GBTC!K22 -> 155867.83 | K23: =HODL!H22 -> 17068.259 | L23: =IBIT!G22 -> 786329.17 | M23: =SUM(btc_ratios3[[#This Row],[ARKB]:[IBIT]]) -> 1100218.4 | N23: =btc_ratios3[[#This Row],[Sum]]-M22 -> 2209.0784 | O23: =btc_ratios3[[#This Row],[Sum]]/M22-1 -> 0.0020118941 | P23: =ARKB!H22 -> 74681.96
A24: =scalars[[#This Row],[DOW]] -> Wednesday | B24: =B23+1 -> 46099 | C24: =ARKB!G23 -> 35677.89 | D24: =BITB!H23 -> 38822.75 | E24: =BRRR!G24 -> 6301.75 | F24: =BTC!J23 -> 51689.064 | G24: =G23 -> 2163 | H24: =EZBC!F23 -> 6243.76 | J24: =GBTC!K23 -> 155861.43 | K24: =HODL!H23 -> 17110.684 | L24: =IBIT!G23 -> 785853.01 | M24: =SUM(btc_ratios3[[#This Row],[ARKB]:[IBIT]]) -> 1099723.3 | N24: =btc_ratios3[[#This Row],[Sum]]-M23 -> -495.0408 | O24: =btc_ratios3[[#This Row],[Sum]]/M23-1 -> -0.00044994776 | P24: =ARKB!H23 -> 71208.94 | Q24: =btc_ratios3[[#This Row],[Price]]-P23 -> -3473.02 | R24: =btc_ratios3[[#This Row],[Price]]/P23-1 -> -0.046504136
A25: =scalars[[#This Row],[DOW]] -> Thursday | B25: =B24+1 -> 46100 | C25: =ARKB!G24 -> 35462.18 | D25: =BITB!H24 -> 38578.33 | E25: =BRRR!G25 -> 6301.7 | F25: =BTC!J24 -> 51688.852 | G25: =G24 -> 2163 | H25: =AVERAGE(H24,H26) -> 6273.295 | J25: =GBTC!K24 -> 155590.2 | K25: =HODL!H24 -> 17110.681 | L25: =IBIT!G24 -> 785308.85 | M25: =SUM(btc_ratios3[[#This Row],[ARKB]:[IBIT]]) -> 1098477.1 | N25: =btc_ratios3[[#This Row],[Sum]]-M24 -> -1246.2525 | O25: =btc_ratios3[[#This Row],[Sum]]/M24-1 -> -0.0011332418 | P25: =ARKB!H24 -> 70292.52 | Q25: =btc_ratios3[[#This Row],[Price]]-P24 -> -916.42 | R25: =btc_ratios3[[#This Row],[Price]]/P24-1 -> -0.012869452
A26: =scalars[[#This Row],[DOW]] -> Friday | B26: =B25+1 -> 46101 | C26: =ARKB!G25 -> 35462.18 | D26: =BITB!H25 -> 38578.33 | E26: =BRRR!G29 -> 6301.49 | F26: =BTC!J25 -> 51754.998 | G26: =G25 -> 2163 | H26: =EZBC!F25 -> 6302.83 | J26: =GBTC!K25 -> 155505.92 | K26: =HODL!H25 -> 17110.681 | L26: =IBIT!G25 -> 784651.3 | M26: =SUM(btc_ratios3[[#This Row],[ARKB]:[IBIT]]) -> 1097830.7 | N26: =btc_ratios3[[#This Row],[Sum]]-M25 -> -646.3546 | O26: =btc_ratios3[[#This Row],[Sum]]/M25-1 -> -0.00058840973 | P26: =ARKB!H25 -> 69873.12 | Q26: =btc_ratios3[[#This Row],[Price]]-P25 -> -419.4 | R26: =btc_ratios3[[#This Row],[Price]]/P25-1 -> -0.0059664954
A27: =scalars[[#This Row],[DOW]] -> Saturday | B27: =B26+1 -> 46102
A28: =scalars[[#This Row],[DOW]] -> Sunday | B28: =B27+1 -> 46103
A29: =scalars[[#This Row],[DOW]] -> Monday | B29: =B28+1 -> 46104
A30: =scalars[[#This Row],[DOW]] -> Tuesday | B30: =B29+1 -> 46105 | C30: =ARKB!G29 -> 35329.43 | D30: =BITB!H29 -> 38339.35 | E30: =BRRR!G30 -> 6301.44 | F30: =BTC!J29 -> 51754.147 | G30: =G26 -> 2163 | H30: =EZBC!F29 -> 6302.83 | J30: =GBTC!K29 -> 155114.36 | K30: =HODL!H29 -> 17153.102 | L30: =IBIT!G29 -> 786850.58 | M30: =SUM(btc_ratios3[[#This Row],[ARKB]:[IBIT]]) -> 1099308.2 | N30: =btc_ratios3[[#This Row],[Sum]]-M26 -> 1477.5087 | O30: =btc_ratios3[[#This Row],[Sum]]/M26-1 -> 0.0013458438 | P30: =ARKB!H29 -> 69451.67 | Q30: =btc_ratios3[[#This Row],[Price]]-P26 -> -421.45 | R30: =btc_ratios3[[#This Row],[Price]]/P26-1 -> -0.0060316471
A31: =scalars[[#This Row],[DOW]] -> Wednesday | B31: =B30+1 -> 46106 | C31: =ARKB!G30 -> 35261.4 | D31: =BITB!H30 -> 38339.35 | E31: =BRRR!G31 -> 6301.4 | F31: =BTC!J30 -> 51753.934 | G31: =G30 -> 2163 | H31: =EZBC!F30 -> 6302.83 | J31: =GBTC!K30 -> 155107.98 | K31: =HODL!H30 -> 17039.977 | L31: =IBIT!G30 -> 785852.96 | M31: =SUM(btc_ratios3[[#This Row],[ARKB]:[IBIT]]) -> 1098122.8 | N31: =btc_ratios3[[#This Row],[Sum]]-M30 -> -1185.4044 | O31: =btc_ratios3[[#This Row],[Sum]]/M30-1 -> -0.0010783185 | P31: =ARKB!H30 -> 70883.73 | Q31: =btc_ratios3[[#This Row],[Price]]-P30 -> 1432.06 | R31: =btc_ratios3[[#This Row],[Price]]/P30-1 -> 0.020619519
A32: =scalars[[#This Row],[DOW]] -> Thursday | B32: =B31+1 -> 46107 | C32: =ARKB!G31 -> 34816.72 | D32: =BITB!H31 -> 37855.97 | E32: =BRRR!G32 -> 6301.4 | F32: =BTC!J31 -> 51753.722 | G32: =BTCW!H31 -> 2163 | H32: =EZBC!F31 -> 6302.83 | J32: =GBTC!K31 -> 155101.61 | K32: =HODL!H31 -> 17039.975 | L32: =IBIT!G31 -> 785240.8 | M32: =SUM(btc_ratios3[[#This Row],[ARKB]:[IBIT]]) -> 1096576 | N32: =btc_ratios3[[#This Row],[Sum]]-M31 -> -1546.8033 | O32: =btc_ratios3[[#This Row],[Sum]]/M31-1 -> -0.0014085886 | P32: =ARKB!H31 -> 68478.86 | Q32: =btc_ratios3[[#This Row],[Price]]-P31 -> -2404.87 | R32: =btc_ratios3[[#This Row],[Price]]/P31-1 -> -0.033926967
A33: =scalars[[#This Row],[DOW]] -> Friday | B33: =B32+1 -> 46108 | C33: =AVERAGE(C32,C36) -> 35023.355 | D33: =BITB!H32 -> 37573.55 | E33: =BRRR!G35 -> 6301.23 | F33: =BTC!J32 -> 51673.881 | G33: =G32 -> 2163 | H33: =H32 -> 6302.83 | J33: =GBTC!K32 -> 154729.28 | K33: =HODL!H32 -> 17004.62 | L33: =IBIT!G32 -> 782180.06 | M33: =SUM(btc_ratios3[[#This Row],[ARKB]:[IBIT]]) -> 1092951.8 | N33: =btc_ratios3[[#This Row],[Sum]]-M32 -> -3624.2225 | O33: =btc_ratios3[[#This Row],[Sum]]/M32-1 -> -0.0033050353 | P33: =BITB!J32 -> 65842.59 | Q33: =btc_ratios3[[#This Row],[Price]]-P32 -> -2636.27 | R33: =btc_ratios3[[#This Row],[Price]]/P32-1 -> -0.038497574
A34: =scalars[[#This Row],[DOW]] -> Saturday | B34: =B33+1 -> 46109
A35: =scalars[[#This Row],[DOW]] -> Sunday | B35: =B34+1 -> 46110
A36: =scalars[[#This Row],[DOW]] -> Monday | B36: =B35+1 -> 46111 | C36: =ARKB!G35 -> 35229.99 | D36: =BITB!H35 -> 37573.55 | E36: =BRRR!G36 -> 6301.18 | F36: =BTC!J35 -> 51673.244 | G36: =BTCW!H35 -> 2163 | H36: =EZBC!F35 -> 6302.83 | J36: =GBTC!K35 -> 154710.21 | K36: =HODL!H35 -> 17004.624 | L36: =IBIT!G35 -> 782293.42 | M36: =SUM(btc_ratios3[[#This Row],[ARKB]:[IBIT]]) -> 1093252 | N36: =btc_ratios3[[#This Row],[Sum]]-M33 -> 300.2346 | O36: =btc_ratios3[[#This Row],[Sum]]/M33-1 -> 0.00027470068 | P36: =ARKB!H35 -> 66355.48 | Q36: =btc_ratios3[[#This Row],[Price]]-P33 -> 512.89 | R36: =btc_ratios3[[#This Row],[Price]]/P33-1 -> 0.0077896389
A37: =scalars[[#This Row],[DOW]] -> Tuesday | B37: =B36+1 -> 46112 | C37: =ARKB!G36 -> 35246.58 | D37: =BITB!H36 -> 37593.96 | E37: =BRRR!G37 -> 6301.14 | F37: =BTC!J36 -> 51673.032 | G37: =G36 -> 2163 | H37: =EZBC!F36 -> 6302.83 | J37: =GBTC!K36 -> 154703.85 | K37: =HODL!H36 -> 17004.624 | L37: =IBIT!G36 -> 783744.4 | M37: =SUM(btc_ratios3[[#This Row],[ARKB]:[IBIT]]) -> 1094733.4 | N37: =btc_ratios3[[#This Row],[Sum]]-M36 -> 1481.371 | O37: =btc_ratios3[[#This Row],[Sum]]/M36-1 -> 0.0013550132 | P37: =ARKB!H36 -> 67831.76 | Q37: =btc_ratios3[[#This Row],[Price]]-P36 -> 1476.28 | R37: =btc_ratios3[[#This Row],[Price]]/P36-1 -> 0.022248049
A38: =scalars[[#This Row],[DOW]] -> Wednesday | B38: =B37+1 -> 46113 | C38: =ARKB!G37 -> 35246.58 | D38: =BITB!H37 -> 37512.49 | E38: =BRRR!G38 -> 6300.97 | F38: =BTC!J37 -> 51672.819 | G38: =BTCW!H37 -> 2163 | H38: =EZBC!F37 -> 6302.83 | J38: =GBTC!K37 -> 154697.49 | K38: =HODL!H37 -> 17004.625 | L38: =IBIT!G37 -> 782474.77 | M38: =SUM(btc_ratios3[[#This Row],[ARKB]:[IBIT]]) -> 1093375.6 | N38: =btc_ratios3[[#This Row],[Sum]]-M37 -> -1357.8376 | O38: =btc_ratios3[[#This Row],[Sum]]/M37-1 -> -0.0012403363 | P38: =ARKB!H37 -> 68149.22 | Q38: =btc_ratios3[[#This Row],[Price]]-P37 -> 317.46 | R38: =btc_ratios3[[#This Row],[Price]]/P37-1 -> 0.0046801086
A39: =scalars[[#This Row],[DOW]] -> Thursday | B39: =B38+1 -> 46114 | C39: =ARKB!G38 -> 35246.58 | D39: =BITB!H38 -> 37512.49 | E39: =BRRR!G42 -> 6334.78 | F39: =BTC!J38 -> 51823.011 | G39: =BTCW!H38 -> 2163 | H39: =EZBC!F38 -> 6302.83 | J39: =GBTC!K38 -> 154496.52 | K39: =HODL!H38 -> 17004.624 | L39: =IBIT!G38 -> 782429.4 | M39: =SUM(btc_ratios3[[#This Row],[ARKB]:[IBIT]]) -> 1093313.2 | N39: =btc_ratios3[[#This Row],[Sum]]-M38 -> -62.3381 | O39: =btc_ratios3[[#This Row],[Sum]]/M38-1 -> -5.7014352e-05 | P39: =ARKB!H38 -> 66994.87 | Q39: =btc_ratios3[[#This Row],[Price]]-P38 -> -1154.35 | R39: =btc_ratios3[[#This Row],[Price]]/P38-1 -> -0.016938565
A40: =scalars[[#This Row],[DOW]] -> Friday | B40: =B39+1 -> 46115 | M40: HOLIDAY
A41: =scalars[[#This Row],[DOW]] -> Saturday | B41: =B40+1 -> 46116 | Q41: =btc_ratios3[[#This Row],[Price]]-P40 -> 0
A42: =scalars[[#This Row],[DOW]] -> Sunday | B42: =B41+1 -> 46117
A43: =scalars[[#This Row],[DOW]] -> Monday | B43: =B42+1 -> 46118 | C43: =ARKB!G42 -> 36948.88 | D43: =BITB!H42 -> 37566.8 | E43: =BRRR!G43 -> 6334.74 | F43: =BTC!J42 -> 51822.159 | G43: =BTCW!H42 -> 2163 | H43: =EZBC!F42 -> 6302.83 | J43: =GBTC!K42 -> 154471.13 | K43: =HODL!H42 -> 17075.328 | L43: =IBIT!G42 -> 785036.53 | M43: =SUM(btc_ratios3[[#This Row],[ARKB]:[IBIT]]) -> 1097721.4 | N43: =btc_ratios3[[#This Row],[Sum]]-M39 -> 4408.1589 | O43: =btc_ratios3[[#This Row],[Sum]]/M39-1 -> 0.0040319268 | P43: =ARKB!H42 -> 69766.87 | Q43: =btc_ratios3[[#This Row],[Price]]-P39 -> 2772 | R43: =btc_ratios3[[#This Row],[Price]]/P39-1 -> 0.041376302
A44: =scalars[[#This Row],[DOW]] -> Tuesday | B44: =B43+1 -> 46119 | C44: =ARKB!G43 -> 36451.14 | D44: =BITB!H43 -> 37566.8 | E44: =BRRR!G44 -> 6334.69 | F44: =BTC!J43 -> 52074.089 | G44: =BTCW!H43 -> 2163 | H44: =EZBC!F43 -> 6302.83 | J44: =GBTC!K43 -> 154464.78 | K44: =HODL!H43 -> 17103.609 | L44: =IBIT!G43 -> 784619.88 | M44: =SUM(btc_ratios3[[#This Row],[ARKB]:[IBIT]]) -> 1097080.8 | N44: =btc_ratios3[[#This Row],[Sum]]-M43 -> -640.5812 | O44: =btc_ratios3[[#This Row],[Sum]]/M43-1 -> -0.00058355536 | P44: =ARKB!H43 -> 68612.35 | Q44: =btc_ratios3[[#This Row],[Price]]-P43 -> -1154.52 | R44: =btc_ratios3[[#This Row],[Price]]/P43-1 -> -0.016548256
A45: =scalars[[#This Row],[DOW]] -> Wednesday | B45: =B44+1 -> 46120 | C45: =ARKB!G44 -> 35402.56 | D45: =BITB!H44 -> 37566.8 | E45: =BRRR!G45 -> 6334.65 | F45: =BTC!J44 -> 52073.875 | G45: =BTCW!H44 -> 2162 | H45: =EZBC!F44 -> 6302.83 | J45: =GBTC!K44 -> 153851.4 | K45: =HODL!H44 -> 16806.653 | L45: =IBIT!G44 -> 785186.64 | M45: =SUM(btc_ratios3[[#This Row],[ARKB]:[IBIT]]) -> 1095687.4 | N45: =btc_ratios3[[#This Row],[Sum]]-M44 -> -1393.4079 | O45: =btc_ratios3[[#This Row],[Sum]]/M44-1 -> -0.0012701051 | P45: =ARKB!H44 -> 71239.5 | Q45: =btc_ratios3[[#This Row],[Price]]-P44 -> 2627.15 | R45: =btc_ratios3[[#This Row],[Price]]/P44-1 -> 0.038289754
A46: =scalars[[#This Row],[DOW]] -> Thursday | B46: =B45+1 -> 46121 | C46: =ARKB!G45 -> 35468.926 | D46: =BITB!H45 -> 37729.73 | E46: =BRRR!G46 -> 6334.52 | F46: =BTC!J45 -> 52073.661 | G46: =G45 -> 2162 | H46: =EZBC!F45 -> 6331.74 | J46: =GBTC!K45 -> 153689.44 | K46: =HODL!H45 -> 16806.648 | L46: =IBIT!G45 -> 788927.18 | M46: =SUM(btc_ratios3[[#This Row],[ARKB]:[IBIT]]) -> 1099523.8 | N46: =btc_ratios3[[#This Row],[Sum]]-M45 -> 3836.4353 | O46: =btc_ratios3[[#This Row],[Sum]]/M45-1 -> 0.0035013958 | P46: =ARKB!H45 -> 72005.03 | Q46: =btc_ratios3[[#This Row],[Price]]-P45 -> 765.53 | R46: =btc_ratios3[[#This Row],[Price]]/P45-1 -> 0.010745864
A47: =scalars[[#This Row],[DOW]] -> Friday | B47: =B46+1 -> 46122 | C47: =ARKB!G46 -> 35518.699 | D47: =BITB!H46 -> 37860.07 | E47: =BRRR!G49 -> 6334.48 | F47: =BTC!J46 -> 52073.447 | G47: =BTCW!H46 -> 2162 | H47: =EZBC!F46 -> 6331.74 | J47: =GBTC!K46 -> 153683.12 | K47: =HODL!H46 -> 16834.928 | L47: =IBIT!G46 -> 790808.79 | M47: =SUM(btc_ratios3[[#This Row],[ARKB]:[IBIT]]) -> 1101607.3 | N47: =btc_ratios3[[#This Row],[Sum]]-M46 -> 2083.4319 | O47: =btc_ratios3[[#This Row],[Sum]]/M46-1 -> 0.0018948492 | P47: =ARKB!H46 -> 73109.73 | Q47: =btc_ratios3[[#This Row],[Price]]-P46 -> 1104.7 | R47: =btc_ratios3[[#This Row],[Price]]/P46-1 -> 0.015341984
A48: =scalars[[#This Row],[DOW]] -> Saturday | B48: =B47+1 -> 46123
A49: =scalars[[#This Row],[DOW]] -> Sunday | B49: =B48+1 -> 46124
A50: =scalars[[#This Row],[DOW]] -> Monday | B50: =B49+1 -> 46125 | C50: =ARKB!G49 -> 34655.968 | D50: =BITB!H49 -> 38022.99 | E50: =BRRR!G50 -> 6334.43 | F50: =BTC!J49 -> 52196.663 | G50: =BTCW!H49 -> 2162 | H50: =EZBC!F49 -> 6331.74 | J50: =GBTC!K49 -> 153664.17 | K50: =HODL!H49 -> 16870.285 | L50: =IBIT!G49 -> 791284.83 | M50: =SUM(btc_ratios3[[#This Row],[ARKB]:[IBIT]]) -> 1101523.1 | N50: =btc_ratios3[[#This Row],[Sum]]-M47 -> -84.1975 | O50: =btc_ratios3[[#This Row],[Sum]]/M47-1 -> -7.6431503e-05 | P50: =ARKB!H49 -> 72892.55 | Q50: =btc_ratios3[[#This Row],[Price]]-P47 -> -217.18 | R50: =btc_ratios3[[#This Row],[Price]]/P47-1 -> -0.0029706032
A51: =scalars[[#This Row],[DOW]] -> Tuesday | B51: =B50+1 -> 46126 | C51: =ARKB!G50 -> 36179.011 | D51: =BITB!H50 -> 38191.34 | E51: =BRRR!G51 -> 6334.39 | F51: =BTC!J50 -> 52046.052 | G51: =BTCW!H50 -> 2162 | H51: =EZBC!F50 -> 6331.74 | J51: =GBTC!K50 -> 153136.56 | K51: =HODL!H50 -> 16834.931 | L51: =IBIT!G50 -> 794163.85 | M51: =SUM(btc_ratios3[[#This Row],[ARKB]:[IBIT]]) -> 1105379.9 | N51: =btc_ratios3[[#This Row],[Sum]]-M50 -> 3856.7946 | O51: =btc_ratios3[[#This Row],[Sum]]/M50-1 -> 0.0035013289 | P51: =ARKB!H50 -> 74270.1 | Q51: =btc_ratios3[[#This Row],[Price]]-P50 -> 1377.55 | R51: =btc_ratios3[[#This Row],[Price]]/P50-1 -> 0.018898365
A52: =scalars[[#This Row],[DOW]] -> Wednesday | B52: =B51+1 -> 46127 | C52: =ARKB!G51 -> 35614.924 | D52: =BITB!H51 -> 38077.3 | E52: =BRRR!G52 -> 6334.35 | F52: =BTC!J51 -> 52112.189 | G52: =BTCW!H51 -> 2163 | H52: =EZBC!F51 -> 6330.8 | J52: =GBTC!K51 -> 153130.27 | K52: =HODL!H51 -> 16919.775 | L52: =IBIT!G51 -> 798062.91 | M52: =SUM(btc_ratios3[[#This Row],[ARKB]:[IBIT]]) -> 1108745.5 | N52: =btc_ratios3[[#This Row],[Sum]]-M51 -> 3365.6445 | O52: =btc_ratios3[[#This Row],[Sum]]/M51-1 -> 0.0030447854 | P52: =ARKB!H51 -> 74853.53 | Q52: =btc_ratios3[[#This Row],[Price]]-P51 -> 583.43 | R52: =btc_ratios3[[#This Row],[Price]]/P51-1 -> 0.0078555166
A53: =scalars[[#This Row],[DOW]] -> Thursday | B53: =B52+1 -> 46128 | C53: =ARKB!G52 -> 35249.929 | D53: =BITB!H52 -> 38077.3 | E53: =BRRR!G53 -> 6334.35 | F53: =BTC!J52 -> 52111.975 | G53: =G52 -> 2163 | H53: =EZBC!F52 -> 6330.8 | J53: =GBTC!K52 -> 152812.78 | K53: =HODL!H52 -> 16870.283 | L53: =IBIT!G52 -> 799151.04 | M53: =SUM(btc_ratios3[[#This Row],[ARKB]:[IBIT]]) -> 1109101.5 | N53: =btc_ratios3[[#This Row],[Sum]]-M52 -> 355.9365 | O53: =btc_ratios3[[#This Row],[Sum]]/M52-1 -> 0.00032102633 | P53: =ARKB!H52 -> 75088.35 | Q53: =btc_ratios3[[#This Row],[Price]]-P52 -> 234.82 | R53: =btc_ratios3[[#This Row],[Price]]/P52-1 -> 0.0031370598
A54: =scalars[[#This Row],[DOW]] -> Friday | B54: =B53+1 -> 46129 | C54: =ARKB!G53 -> 36770.587 | D54: =BITB!H53 -> 38571.47 | E54: =BRRR!G56 -> 6410.33 | F54: =BTC!J53 -> 52332.929 | G54: =G53 -> 2163 | H54: =EZBC!F53 -> 6330.8 | J54: =GBTC!K53 -> 152510.88 | K54: =HODL!H53 -> 16870.288 | L54: =IBIT!G53 -> 799151.04 | M54: =SUM(btc_ratios3[[#This Row],[ARKB]:[IBIT]]) -> 1111111.3 | N54: =btc_ratios3[[#This Row],[Sum]]-M53 -> 2009.8642 | O54: =btc_ratios3[[#This Row],[Sum]]/M53-1 -> 0.0018121554 | P54: =ARKB!H53 -> 77331.74 | Q54: =btc_ratios3[[#This Row],[Price]]-P53 -> 2243.39 | R54: =btc_ratios3[[#This Row],[Price]]/P53-1 -> 0.029876672
A55: =scalars[[#This Row],[DOW]] -> Saturday | B55: =B54+1 -> 46130
A56: =scalars[[#This Row],[DOW]] -> Sunday | B56: =B55+1 -> 46131
A57: =scalars[[#This Row],[DOW]] -> Monday | B57: =B56+1 -> 46132 | C57: =ARKB!G56 -> 36770.587 | D57: =BITB!H56 -> 38571.47 | E57: =BRRR!G57 -> 6410.29 | F57: =BTC!J56 -> 52708.269 | G57: =BTCW!H56 -> 2162 | H57: =EZBC!F56 -> 6330.8 | J57: =GBTC!K56 -> 152546.53 | K57: =HODL!H56 -> 16955.133 | L57: =IBIT!G56 -> 806178.38 | M57: =SUM(btc_ratios3[[#This Row],[ARKB]:[IBIT]]) -> 1118633.5 | N57: =btc_ratios3[[#This Row],[Sum]]-M54 -> 7522.142 | O57: =btc_ratios3[[#This Row],[Sum]]/M54-1 -> 0.0067699265 | P57: =ARKB!H56 -> 76318.82 | Q57: =btc_ratios3[[#This Row],[Price]]-P54 -> -1012.92 | R57: =btc_ratios3[[#This Row],[Price]]/P54-1 -> -0.013098373
A58: =scalars[[#This Row],[DOW]] -> Tuesday | B58: =B57+1 -> 46133 | C58: =ARKB!G57 -> 36578.141 | D58: =BITB!H57 -> 38403.13 | E58: =BRRR!G58 -> 6410.25 | F58: =BTC!J57 -> 52708.053 | G58: =G57 -> 2162 | H58: =EZBC!F57 -> 6330.8 | J58: =GBTC!K57 -> 152213.57 | K58: =HODL!H57 -> 16955.134 | L58: =IBIT!G57 -> 806699.76 | M58: =SUM(btc_ratios3[[#This Row],[ARKB]:[IBIT]]) -> 1118460.8 | N58: =btc_ratios3[[#This Row],[Sum]]-M57 -> -172.6233 | O58: =btc_ratios3[[#This Row],[Sum]]/M57-1 -> -0.00015431623 | P58: =ARKB!H57 -> 75462.34 | Q58: =btc_ratios3[[#This Row],[Price]]-P57 -> -856.48 | R58: =btc_ratios3[[#This Row],[Price]]/P57-1 -> -0.011222396
A59: =scalars[[#This Row],[DOW]] -> Wednesday | B59: =B58+1 -> 46134 | C59: =ARKB!G58 -> 36729.111 | D59: =BITB!H58 -> 38598.63 | E59: =BRRR!G59 -> 6410.2 | F59: =BTC!J58 -> 52937.847 | G59: =BTCW!H58 -> 2162 | H59: =EZBC!F58 -> 6330.8 | J59: =GBTC!K58 -> 151973.98 | K59: =HODL!H58 -> 16898.569 | L59: =IBIT!G58 -> 809828.01 | M59: =SUM(btc_ratios3[[#This Row],[ARKB]:[IBIT]]) -> 1121869.1 | N59: =btc_ratios3[[#This Row],[Sum]]-M58 -> 3408.3102 | O59: =btc_ratios3[[#This Row],[Sum]]/M58-1 -> 0.0030473219 | P59: =ARKB!H58 -> 78919.77 | Q59: =btc_ratios3[[#This Row],[Price]]-P58 -> 3457.43 | R59: =btc_ratios3[[#This Row],[Price]]/P58-1 -> 0.045816629
A60: =scalars[[#This Row],[DOW]] -> Thursday | B60: =B59+1 -> 46135 | C60: =ARKB!G59 -> 37644.88 | D60: =BITB!H59 -> 38500.88 | E60: =E61 -> 6410.07 | F60: =AVERAGE(F59,F61) -> 52970.804 | G60: =G59 -> 2162 | H60: =EZBC!F59 -> 6330.8 | J60: =AVERAGE(J59,J61) -> 151862.74 | K60: =HODL!H59 -> 16948.061 | L60: =IBIT!G59 -> 811981.49 | M60: =SUM(btc_ratios3[[#This Row],[ARKB]:[IBIT]]) -> 1124811.7 | N60: =btc_ratios3[[#This Row],[Sum]]-M59 -> 2942.5798 | O60: =btc_ratios3[[#This Row],[Sum]]/M59-1 -> 0.002622926 | P60: =ARKB!H59 -> 77774.85 | Q60: =btc_ratios3[[#This Row],[Price]]-P59 -> -1144.92 | R60: =btc_ratios3[[#This Row],[Price]]/P59-1 -> -0.014507391
A61: =scalars[[#This Row],[DOW]] -> Friday | B61: =B60+1 -> 46136 | C61: =ARKB!G60 -> 37528.752 | D61: =BITB!H60 -> 38386.84 | E61: =BRRR!G63 -> 6410.07 | F61: =BTC!J60 -> 53003.76 | G61: =BTCW!H60 -> 2241 | H61: =EZBC!F60 -> 6330.8 | J61: =GBTC!K60 -> 151751.5 | K61: =HODL!H60 -> 16877.352 | L61: =IBIT!G60 -> 812276.18 | M61: =SUM(btc_ratios3[[#This Row],[ARKB]:[IBIT]]) -> 1124806.3 | N61: =btc_ratios3[[#This Row],[Sum]]-M60 -> -5.47385 | O61: =btc_ratios3[[#This Row],[Sum]]/M60-1 -> -4.8664589e-06 | P61: =ARKB!H60 -> 77638.21 | Q61: =btc_ratios3[[#This Row],[Price]]-P60 -> -136.64 | R61: =btc_ratios3[[#This Row],[Price]]/P60-1 -> -0.0017568661
A62: =scalars[[#This Row],[DOW]] -> Saturday | B62: =B61+1 -> 46137
A63: =scalars[[#This Row],[DOW]] -> Sunday | B63: =B62+1 -> 46138
A64: =scalars[[#This Row],[DOW]] -> Monday | B64: =B63+1 -> 46139 | C64: =ARKB!G63 -> 36964.704 | D64: =BITB!H63 -> 38272.8 | E64: =BRRR!G64 -> 6410.03 | F64: =BTC!J63 -> 53003.107 | G64: =BTCW!H63 -> 2242 | H64: =EZBC!F63 -> 6330.8 | J64: =GBTC!K63 -> 151732.79 | K64: =HODL!H63 -> 16877.356 | L64: =IBIT!G63 -> 812276.17 | M64: =SUM(btc_ratios3[[#This Row],[ARKB]:[IBIT]]) -> 1124109.8 | N64: =btc_ratios3[[#This Row],[Sum]]-M61 -> -696.491 | O64: =btc_ratios3[[#This Row],[Sum]]/M61-1 -> -0.00061920975 | P64: =ARKB!H63 -> 76762.25 | Q64: =btc_ratios3[[#This Row],[Price]]-P61 -> -875.96 | R64: =btc_ratios3[[#This Row],[Price]]/P61-1 -> -0.011282589
A65: =scalars[[#This Row],[DOW]] -> Tuesday | B65: =B64+1 -> 46140 | C65: =ARKB!G64 -> 37505.524 | D65: =BITB!H64 -> 38093.6 | E65: =BRRR!G65 -> 6409.98 | F65: =BTC!J64 -> 53002.889 | G65: =BTCW!H64 -> 2242 | H65: =EZBC!F64 -> 6330.8 | J65: =GBTC!K64 -> 151120.02 | K65: =HODL!H64 -> 16693.519 | L65: =IBIT!G64 -> 810802.79 | M65: =SUM(btc_ratios3[[#This Row],[ARKB]:[IBIT]]) -> 1122201.1 | N65: =btc_ratios3[[#This Row],[Sum]]-M64 -> -1908.6387 | O65: =btc_ratios3[[#This Row],[Sum]]/M64-1 -> -0.0016979113 | P65: =ARKB!H64 -> 76184.66 | Q65: =btc_ratios3[[#This Row],[Price]]-P64 -> -577.59 | R65: =btc_ratios3[[#This Row],[Price]]/P64-1 -> -0.0075244016
A66: =scalars[[#This Row],[DOW]] -> Wednesday | B66: =B65+1 -> 46141 | C66: =ARKB!G65 -> 37104.877 | D66: =BITB!H65 -> 38093.6 | E66: =BRRR!G66 -> 6409.94 | F66: =BTC!J65 -> 53002.671 | G66: 2242 | H66: =EZBC!F65 -> 6244.09 | J66: =GBTC!K65 -> 151113.81 | K66: =HODL!H65 -> 16693.521 | L66: =IBIT!G65 -> 810077.43 | M66: =SUM(btc_ratios3[[#This Row],[ARKB]:[IBIT]]) -> 1120981.9 | N66: =btc_ratios3[[#This Row],[Sum]]-M65 -> -1219.1828 | O66: =btc_ratios3[[#This Row],[Sum]]/M65-1 -> -0.0010864209 | P66: =ARKB!H65 -> 75446.31 | Q66: =btc_ratios3[[#This Row],[Price]]-P65 -> -738.35 | R66: =btc_ratios3[[#This Row],[Price]]/P65-1 -> -0.0096915836
A67: =scalars[[#This Row],[DOW]] -> Thursday | B67: =B66+1 -> 46142 | C67: =ARKB!G66 -> 37021.93 | D67: =BITB!H66 -> 38049.56 | E67: =BRRR!G67 -> 6297.07 | F67: =BTC!J66 -> 53002.454 | G67: =BTCW!H66 -> 2241 | H67: =EZBC!F66 -> 6244.09 | J67: =GBTC!K66 -> 150827.69 | K67: =HODL!H66 -> 16693.518 | L67: =IBIT!G66 -> 810326.76 | M67: =SUM(btc_ratios3[[#This Row],[ARKB]:[IBIT]]) -> 1120704.1 | N67: =btc_ratios3[[#This Row],[Sum]]-M66 -> -277.8692 | O67: =btc_ratios3[[#This Row],[Sum]]/M66-1 -> -0.00024788018 | P67: =ARKB!H66 -> 76416.86 | Q67: =btc_ratios3[[#This Row],[Price]]-P66 -> 970.55 | R67: =btc_ratios3[[#This Row],[Price]]/P66-1 -> 0.012864115
A68: =scalars[[#This Row],[DOW]] -> Friday | B68: =B67+1 -> 46143 | C68: =ARKB!G67 -> 38149.987 | D68: =BITB!H67 -> 38397.09 | E68: =BRRR!G70 -> 6296.94 | F68: =BTC!J67 -> 53002.236 | G68: =BTCW!H67 -> 2241 | H68: =EZBC!F67 -> 6244.09 | J68: =GBTC!K67 -> 150743.74 | K68: =HODL!H67 -> 16665.237 | L68: =IBIT!G67 -> 813953.5 | M68: =SUM(btc_ratios3[[#This Row],[ARKB]:[IBIT]]) -> 1125693.8 | N68: =btc_ratios3[[#This Row],[Sum]]-M67 -> 4989.7489 | O68: =btc_ratios3[[#This Row],[Sum]]/M67-1 -> 0.0044523341 | P68: =ARKB!H67 -> 78415.26 | Q68: =btc_ratios3[[#This Row],[Price]]-P67 -> 1998.4 | R68: =btc_ratios3[[#This Row],[Price]]/P67-1 -> 0.026151297
A69: =scalars[[#This Row],[DOW]] -> Saturday | B69: =B68+1 -> 46144
A70: =scalars[[#This Row],[DOW]] -> Sunday | B70: =B69+1 -> 46145
A71: =scalars[[#This Row],[DOW]] -> Monday | B71: =B70+1 -> 46146 | C71: =ARKB!G70 -> 38149.987 | D71: =BITB!H70 -> 38397.09 | E71: =BRRR!G71 -> 6296.9 | F71: =BTC!J70 -> 53081.198 | G71: =BTCW!H70 -> 2241 | H71: =EZBC!F70 -> 6244.09 | J71: =GBTC!K70 -> 150725.15 | K71: =HODL!H70 -> 16735.94 | L71: =IBIT!G70 -> 818146.84 | M71: =SUM(btc_ratios3[[#This Row],[ARKB]:[IBIT]]) -> 1130018.2 | N71: =btc_ratios3[[#This Row],[Sum]]-M68 -> 4324.3753 | O71: =btc_ratios3[[#This Row],[Sum]]/M68-1 -> 0.00384152 | P71: =ARKB!H70 -> 80004.53 | Q71: =btc_ratios3[[#This Row],[Price]]-P68 -> 1589.27 | R71: =btc_ratios3[[#This Row],[Price]]/P68-1 -> 0.020267356
A72: =scalars[[#This Row],[DOW]] -> Tuesday | B72: =B71+1 -> 46147 | C72: =ARKB!G71 -> 39281.349 | D72: =BITB!H71 -> 38576.28 | E72: =BRRR!G72 -> 6296.85 | F72: =BTC!J71 -> 53080.98 | G72: =G71 -> 2241 | H72: =EZBC!F71 -> 6244.09 | J72: =GBTC!K71 -> 150718.96 | K72: =HODL!H71 -> 16735.94 | L72: =IBIT!G71 -> 821229.49 | M72: =SUM(btc_ratios3[[#This Row],[ARKB]:[IBIT]]) -> 1134404.9 | N72: =btc_ratios3[[#This Row],[Sum]]-M71 -> 4386.7414 | O72: =btc_ratios3[[#This Row],[Sum]]/M71-1 -> 0.0038820095 | P72: =ARKB!H71 -> 81561.14 | Q72: =btc_ratios3[[#This Row],[Price]]-P71 -> 1556.61 | R72: =btc_ratios3[[#This Row],[Price]]/P71-1 -> 0.019456523
A73: =scalars[[#This Row],[DOW]] -> Wednesday | B73: =B72+1 -> 46148 | C73: =ARKB!G72 -> 39281.349 | D73: =BITB!H72 -> 38266.77 | E73: =BRRR!G73 -> 6296.81 | F73: =BTC!J72 -> 53080.762 | G73: =G72 -> 2241 | H73: =EZBC!F72 -> 6157.38 | J73: =GBTC!K72 -> 150487.33 | K73: =HODL!H72 -> 16665.238 | L73: =IBIT!G72 -> 822736.65 | M73: =SUM(btc_ratios3[[#This Row],[ARKB]:[IBIT]]) -> 1135213.3 | N73: =btc_ratios3[[#This Row],[Sum]]-M72 -> 808.3538 | O73: =btc_ratios3[[#This Row],[Sum]]/M72-1 -> 0.00071257959 | P73: =ARKB!H72 -> 81354.77 | Q73: =btc_ratios3[[#This Row],[Price]]-P72 -> -206.37 | R73: =btc_ratios3[[#This Row],[Price]]/P72-1 -> -0.0025302491
A74: =scalars[[#This Row],[DOW]] -> Thursday | B74: =B73+1 -> 46149 | C74: =ARKB!G73 -> 39123.756 | D74: =BITB!H73 -> 38266.77 | E74: =BRRR!G74 -> 6183.95 | F74: =BTC!J73 -> 53080.544 | G74: =G73 -> 2241 | H74: =EZBC!F73 -> 6157.38 | J74: =GBTC!K73 -> 150271.27 | K74: =HODL!H73 -> 16665.237 | L74: =IBIT!G73 -> 821512.67 | M74: =SUM(btc_ratios3[[#This Row],[ARKB]:[IBIT]]) -> 1133502.6 | N74: =btc_ratios3[[#This Row],[Sum]]-M73 -> -1710.7155 | O74: =btc_ratios3[[#This Row],[Sum]]/M73-1 -> -0.0015069551 | P74: =ARKB!H73 -> 80080.21 | Q74: =btc_ratios3[[#This Row],[Price]]-P73 -> -1274.56 | R74: =btc_ratios3[[#This Row],[Price]]/P73-1 -> -0.01566669
A75: =scalars[[#This Row],[DOW]] -> Friday | B75: =B74+1 -> 46150 | C75: =ARKB!G74 -> 38791.988 | D75: =BITB!H74 -> 38266.77 | E75: =BRRR!G77 -> 6183.82 | F75: =BTC!J74 -> 53151.093 | G75: =G74 -> 2241 | H75: =EZBC!F74 -> 6157.38 | J75: =GBTC!K74 -> 149930.86 | K75: =HODL!H74 -> 16601.604 | L75: =IBIT!G74 -> 821512.67 | M75: =SUM(btc_ratios3[[#This Row],[ARKB]:[IBIT]]) -> 1132837.2 | N75: =btc_ratios3[[#This Row],[Sum]]-M74 -> -665.3901 | O75: =btc_ratios3[[#This Row],[Sum]]/M74-1 -> -0.00058702125 | P75: =ARKB!H74 -> 80066.34 | Q75: =btc_ratios3[[#This Row],[Price]]-P74 -> -13.87 | R75: =btc_ratios3[[#This Row],[Price]]/P74-1 -> -0.00017320134
A76: =scalars[[#This Row],[DOW]] -> Saturday | B76: =B75+1 -> 46151
A77: =scalars[[#This Row],[DOW]] -> Sunday | B77: =B76+1 -> 46152
A78: =scalars[[#This Row],[DOW]] -> Monday | B78: =B77+1 -> 46153 | C78: =ARKB!G77 -> 38791.988 | D78: =BITB!H77 -> 38266.77 | E78: =BRRR!G78 -> 6183.78 | F78: =BTC!J77 -> 53150.438 | G78: =BTCW!H77 -> 2241 | H78: =EZBC!F77 -> 6157.38 | J78: =GBTC!K77 -> 149912.38 | K78: =HODL!H77 -> 16601.601 | L78: =IBIT!G77 -> 821082.01 | M78: =SUM(btc_ratios3[[#This Row],[ARKB]:[IBIT]]) -> 1132387.3 | N78: =btc_ratios3[[#This Row],[Sum]]-M75 -> -449.8383 | O78: =btc_ratios3[[#This Row],[Sum]]/M75-1 -> -0.00039708998 | P78: =ARKB!H77 -> 81915.01 | Q78: =btc_ratios3[[#This Row],[Price]]-P75 -> 1848.67 | R78: =btc_ratios3[[#This Row],[Price]]/P75-1 -> 0.023089228
A79: =scalars[[#This Row],[DOW]] -> Tuesday | B79: =B78+1 -> 46154 | C79: =ARKB!G78 -> 37738.636 | D79: =BITB!H78 -> 38049.58 | E79: =BRRR!G79 -> 6183.74 | F79: =BTC!J78 -> 53150.22 | G79: =G78 -> 2241 | H79: =EZBC!F78 -> 6157.38 | J79: =GBTC!K78 -> 149906.22 | K79: =HODL!H78 -> 16658.169 | L79: =IBIT!G78 -> 820674.02 | M79: =SUM(btc_ratios3[[#This Row],[ARKB]:[IBIT]]) -> 1130759 | N79: =btc_ratios3[[#This Row],[Sum]]-M78 -> -1628.3818 | O79: =btc_ratios3[[#This Row],[Sum]]/M78-1 -> -0.0014380078 | P79: =ARKB!H78 -> 80757.7 | Q79: =btc_ratios3[[#This Row],[Price]]-P78 -> -1157.31 | R79: =btc_ratios3[[#This Row],[Price]]/P78-1 -> -0.01412818
A80: =scalars[[#This Row],[DOW]] -> Wednesday | B80: =B79+1 -> 46155 | C80: =ARKB!G79 -> 35510.851 | D80: =BITB!H79 -> 37604.33 | E80: =BRRR!G80 -> 6123.06 | F80: =BTC!J79 -> 53150.001 | G80: =BTCW!H79 -> 2242 | H80: =EZBC!F79 -> 6157.38 | J80: =GBTC!K79 -> 149682.46 | K80: =HODL!H79 -> 16658.165 | L80: =IBIT!G79 -> 817092.86 | M80: =SUM(btc_ratios3[[#This Row],[ARKB]:[IBIT]]) -> 1124221.1 | N80: =btc_ratios3[[#This Row],[Sum]]-M79 -> -6537.8573 | O80: =btc_ratios3[[#This Row],[Sum]]/M79-1 -> -0.0057818311 | P80: =ARKB!H79 -> 79496.91 | Q80: =btc_ratios3[[#This Row],[Price]]-P79 -> -1260.79 | R80: =btc_ratios3[[#This Row],[Price]]/P79-1 -> -0.01561201
A81: =scalars[[#This Row],[DOW]] -> Thursday | B81: =B80+1 -> 46156 | C81: =ARKB!G80 -> 35394.735 | D81: =BITB!H80 -> 37821.52 | E81: =BRRR!G81 -> 6066.61 | F81: =BTC!J80 -> 53149.783 | G81: =G80 -> 2242 | H81: =EZBC!F80 -> 5983.97 | J81: =GBTC!K80 -> 149676.31 | K81: =HODL!H80 -> 16658.165 | L81: =IBIT!G80 -> 818860.75 | M81: =SUM(btc_ratios3[[#This Row],[ARKB]:[IBIT]]) -> 1125853.8 | N81: =btc_ratios3[[#This Row],[Sum]]-M80 -> 1632.7377 | O81: =btc_ratios3[[#This Row],[Sum]]/M80-1 -> 0.0014523279 | P81: =ARKB!H80 -> 81512.01 | Q81: =btc_ratios3[[#This Row],[Price]]-P80 -> 2015.1 | R81: =btc_ratios3[[#This Row],[Price]]/P80-1 -> 0.025348155
A82: =scalars[[#This Row],[DOW]] -> Friday | B82: =B81+1 -> 46157 | C82: =ARKB!G81 -> 34731.225 | D82: =BITB!H81 -> 37674.92 | E82: =BRRR!G84 -> 6066.48 | F82: =BTC!J81 -> 53304.365 | G82: =BTCW!H81 -> 2242 | H82: =EZBC!F81 -> 5896.35 | J82: =GBTC!K81 -> 149281.63 | K82: =HODL!H81 -> 16750.084 | L82: =IBIT!G81 -> 818860.75 | M82: =SUM(btc_ratios3[[#This Row],[ARKB]:[IBIT]]) -> 1124807.8 | N82: =btc_ratios3[[#This Row],[Sum]]-M81 -> -1046.0412 | O82: =btc_ratios3[[#This Row],[Sum]]/M81-1 -> -0.00092910923 | P82: =ARKB!H81 -> 79097.04 | Q82: =btc_ratios3[[#This Row],[Price]]-P81 -> -2414.97 | R82: =btc_ratios3[[#This Row],[Price]]/P81-1 -> -0.029627168
A83: =scalars[[#This Row],[DOW]] -> Saturday | B83: =B82+1 -> 46158
A84: =scalars[[#This Row],[DOW]] -> Sunday | B84: =B83+1 -> 46159
A85: =scalars[[#This Row],[DOW]] -> Monday | B85: =B84+1 -> 46160 | C85: =ARKB!G84 -> 33301.37 | D85: =BITB!H84 -> 37555.47 | E85: =BRRR!G85 -> 6017.08 | F85: =BTC!J84 -> 53303.707 | G85: =BTCW!H84 -> 2242 | H85: =EZBC!F84 -> 5809.64 | J85: =GBTC!K84 -> 148711.53 | K85: =HODL!H84 -> 16750.086 | L85: =IBIT!G84 -> 811290.75 | M85: =SUM(btc_ratios3[[#This Row],[ARKB]:[IBIT]]) -> 1114981.6 | N85: =btc_ratios3[[#This Row],[Sum]]-M82 -> -9826.1703 | O85: =btc_ratios3[[#This Row],[Sum]]/M82-1 -> -0.008735866 | P85: =ARKB!H84 -> 76676.08 | Q85: =btc_ratios3[[#This Row],[Price]]-P82 -> -2420.96 | R85: =btc_ratios3[[#This Row],[Price]]/P82-1 -> -0.030607466
A86: =scalars[[#This Row],[DOW]] -> Tuesday | B86: =B85+1 -> 46161 | C86: =ARKB!G85 -> 33301.37 | D86: =BITB!H85 -> 37555.47 | E86: =BRRR!G86 -> 6017.04 | F86: =BTC!J85 -> 53303.488 | G86: =G85 -> 2242 | H86: =EZBC!F85 -> 5809.64 | J86: =GBTC!K85 -> 148705.42 | K86: =HODL!H85 -> 16651.095 | L86: =IBIT!G85 -> 807052.44 | M86: =SUM(btc_ratios3[[#This Row],[ARKB]:[IBIT]]) -> 1110638 | N86: =btc_ratios3[[#This Row],[Sum]]-M85 -> -4343.6642 | O86: =btc_ratios3[[#This Row],[Sum]]/M85-1 -> -0.0038957271 | P86: =ARKB!H85 -> 76820.77 | Q86: =btc_ratios3[[#This Row],[Price]]-P85 -> 144.69 | R86: =btc_ratios3[[#This Row],[Price]]/P85-1 -> 0.0018870292
A87: =scalars[[#This Row],[DOW]] -> Wednesday | B87: =B86+1 -> 46162 | C87: =ARKB!G86 -> 33301.37 | D87: =BITB!H86 -> 37555.47 | E87: =BRRR!G87 -> 6017 | F87: =BTC!J86 -> 53303.269 | G87: =BTCW!H86 -> 2242 | H87: =EZBC!F86 -> 5809.64 | J87: =GBTC!K86 -> 148699.31 | K87: =HODL!H86 -> 16651.099 | L87: =IBIT!G86 -> 806259.18 | M87: =SUM(btc_ratios3[[#This Row],[ARKB]:[IBIT]]) -> 1109838.3 | N87: =btc_ratios3[[#This Row],[Sum]]-M86 -> -799.6284 | O87: =btc_ratios3[[#This Row],[Sum]]/M86-1 -> -0.00071997214 | P87: =ARKB!H86 -> 77467.44 | Q87: =btc_ratios3[[#This Row],[Price]]-P86 -> 646.67 | R87: =btc_ratios3[[#This Row],[Price]]/P86-1 -> 0.0084179057
A88: =scalars[[#This Row],[DOW]] -> Thursday | B88: =B87+1 -> 46163 | C88: =ARKB!G87 -> 33337.862 | D88: =BITB!H87 -> 37555.47 | E88: =BRRR!G88 -> 6016.96 | F88: =BTC!J87 -> 53303.05 | G88: =BTCW!H87 -> 2242 | H88: =EZBC!F87 -> 5809.64 | J88: =GBTC!K87 -> 148693.2 | K88: =HODL!H87 -> 16651.096 | L88: =IBIT!G87 -> 804921.97 | M88: =SUM(btc_ratios3[[#This Row],[ARKB]:[IBIT]]) -> 1108531.3 | N88: =btc_ratios3[[#This Row],[Sum]]-M87 -> -1307.0903 | O88: =btc_ratios3[[#This Row],[Sum]]/M87-1 -> -0.0011777304 | P88: =ARKB!H87 -> 77515.76 | Q88: =btc_ratios3[[#This Row],[Price]]-P87 -> 48.32 | R88: =btc_ratios3[[#This Row],[Price]]/P87-1 -> 0.00062374592
A89: =scalars[[#This Row],[DOW]] -> Friday | B89: =B88+1 -> 46164 | C89: =ARKB!G88 -> 33337.862 | D89: =BITB!H88 -> 37555.47 | E89: =BRRR!G92 -> 6016.8 | F89: =BTC!J88 -> 53302.831 | G89: =BTCW!H88 -> 2242 | H89: =EZBC!F88 -> 5809.64 | J89: =GBTC!K88 -> 148687.09 | K89: =HODL!H88 -> 16651.101 | L89: =IBIT!G88 -> 804015.42 | M89: =SUM(btc_ratios3[[#This Row],[ARKB]:[IBIT]]) -> 1107618.2 | N89: =btc_ratios3[[#This Row],[Sum]]-M88 -> -913.0394 | O89: =btc_ratios3[[#This Row],[Sum]]/M88-1 -> -0.00082364787 | P89: =ARKB!H88 -> 75996.63 | Q89: =btc_ratios3[[#This Row],[Price]]-P88 -> -1519.13 | R89: =btc_ratios3[[#This Row],[Price]]/P88-1 -> -0.019597692
A90: =scalars[[#This Row],[DOW]] -> Saturday | B90: =B89+1 -> 46165
A91: =scalars[[#This Row],[DOW]] -> Sunday | B91: =B90+1 -> 46166
A92: =scalars[[#This Row],[DOW]] -> Monday | B92: =B91+1 -> 46167 | M92: HOLIDAY
A93: =scalars[[#This Row],[DOW]] -> Tuesday | B93: =B92+1 -> 46168 | C93: =ARKB!G92 -> 33337.862 | D93: =BITB!H92 -> 37175.41 | E93: =BRRR!G93 -> 6016.75 | F93: =BTC!J92 -> 53301.955 | G93: =BTCW!H92 -> 2242 | H93: =EZBC!F92 -> 5809.64 | J93: =GBTC!K92 -> 148662.65 | K93: =HODL!H92 -> 16651.096 | L93: =IBIT!G92 -> 801477.14 | M93: =SUM(btc_ratios3[[#This Row],[ARKB]:[IBIT]]) -> 1104674.5 | N93: =btc_ratios3[[#This Row],[Sum]]-M89 -> -2943.7135 | O93: =btc_ratios3[[#This Row],[Sum]]/M89-1 -> -0.0026576969 | P93: =ARKB!H92 -> 75814.45 | Q93: =btc_ratios3[[#This Row],[Price]]-P89 -> -182.18 | R93: =btc_ratios3[[#This Row],[Price]]/P89-1 -> -0.0023972116
A94: =scalars[[#This Row],[DOW]] -> Wednesday | B94: =B93+1 -> 46169 | C94: =ARKB!G93 -> 33105.647 | D94: =BITB!H93 -> 36941.94 | E94: =BRRR!G94 -> 6016.71 | F94: =BTC!J93 -> 53124.83 | G94: =BTCW!H93 -> 2242 | H94: =EZBC!F93 -> 5809.64 | J94: =GBTC!K93 -> 148112.86 | K94: =HODL!H93 -> 16651.1 | L94: =IBIT!G93 -> 794428.81 | M94: =SUM(btc_ratios3[[#This Row],[ARKB]:[IBIT]]) -> 1096433.5 | N94: =btc_ratios3[[#This Row],[Sum]]-M93 -> -8240.9552 | O94: =btc_ratios3[[#This Row],[Sum]]/M93-1 -> -0.0074600755 | P94: =ARKB!H93 -> 74889.84 | Q94: =btc_ratios3[[#This Row],[Price]]-P93 -> -924.61 | R94: =btc_ratios3[[#This Row],[Price]]/P93-1 -> -0.012195696
A95: =scalars[[#This Row],[DOW]] -> Thursday | B95: =B94+1 -> 46170 | C95: =ARKB!G94 -> 33099.647 | D95: =BITB!H94 -> 36941.94 | E95: =BRRR!G95 -> 5940.53 | F95: =BTC!J94 -> 52991.933 | G95: =BTCW!H94 -> 2242 | H95: =EZBC!F94 -> 5809.64 | J95: =GBTC!K94 -> 146708.81 | K95: =HODL!H94 -> 16651.095 | L95: =IBIT!G94 -> 792003.89 | M95: =SUM(btc_ratios3[[#This Row],[ARKB]:[IBIT]]) -> 1092389.5 | N95: =btc_ratios3[[#This Row],[Sum]]-M94 -> -4044.0513 | O95: =btc_ratios3[[#This Row],[Sum]]/M94-1 -> -0.0036883688 | P95: =ARKB!H94 -> 73380.52 | Q95: =btc_ratios3[[#This Row],[Price]]-P94 -> -1509.32 | R95: =btc_ratios3[[#This Row],[Price]]/P94-1 -> -0.020153869
A96: =scalars[[#This Row],[DOW]] -> Friday | B96: =B95+1 -> 46171 | C96: =ARKB!G95 -> 33000.129 | D96: =BITB!H95 -> 36935.12 | E96: =BRRR!G98 -> 5940.41 | F96: =BTC!J95 -> 52991.715 | G96: =BTCW!H95 -> 2242 | H96: =EZBC!F95 -> 5809.64 | J96: =GBTC!K95 -> 146345.54 | K96: =HODL!H95 -> 16651.095 | L96: =IBIT!G95 -> 791074.71 | M96: =SUM(btc_ratios3[[#This Row],[ARKB]:[IBIT]]) -> 1090990.4 | N96: =btc_ratios3[[#This Row],[Sum]]-M95 -> -1399.1381 | O96: =btc_ratios3[[#This Row],[Sum]]/M95-1 -> -0.0012808052 | P96: =ARKB!H95 -> 73398.11 | Q96: =btc_ratios3[[#This Row],[Price]]-P95 -> 17.59 | R96: =btc_ratios3[[#This Row],[Price]]/P95-1 -> 0.00023970939
A97: =scalars[[#This Row],[DOW]] -> Saturday | B97: =B96+1 -> 46172
A98: =scalars[[#This Row],[DOW]] -> Sunday | B98: =B97+1 -> 46173
A99: =scalars[[#This Row],[DOW]] -> Monday | B99: =B98+1 -> 46174 | C99: =ARKB!G98 -> 32827.631 | D99: =BITB!H98 -> 36935.12 | E99: =BRRR!G99 -> 5940.37 | F99: =BTC!J98 -> 52858.384 | G99: =BTCW!H98 -> 2242 | H99: =EZBC!F98 -> 5809.64 | J99: =GBTC!K98 -> 146288.67 | K99: =HODL!H98 -> 16651.096 | L99: =IBIT!G98 -> 784910.53 | M99: =SUM(btc_ratios3[[#This Row],[ARKB]:[IBIT]]) -> 1084463.4 | N99: =btc_ratios3[[#This Row],[Sum]]-M96 -> -6526.9102 | O99: =btc_ratios3[[#This Row],[Sum]]/M96-1 -> -0.0059825554 | P99: =ARKB!H98 -> 71428.74 | Q99: =btc_ratios3[[#This Row],[Price]]-P96 -> -1969.37 | R99: =btc_ratios3[[#This Row],[Price]]/P96-1 -> -0.026831345
A100: =scalars[[#This Row],[DOW]] -> Tuesday | B100: =B99+1 -> 46175 | C100: =ARKB!G99 -> 32578.838 | D100: =BITB!H99 -> 36935.12 | E100: =BRRR!G100 -> 5940.33 | F100: =BTC!J99 -> 52858.167 | G100: =BTCW!H99 -> 2242 | H100: =EZBC!F99 -> 5809.64 | J100: =GBTC!K99 -> 146282.66 | K100: =HODL!H99 -> 16651.095 | L100: =IBIT!G99 -> 779109.02 | M100: =SUM(btc_ratios3[[#This Row],[ARKB]:[IBIT]]) -> 1078406.9 | N100: =btc_ratios3[[#This Row],[Sum]]-M99 -> -6056.574 | O100: =btc_ratios3[[#This Row],[Sum]]/M99-1 -> -0.0055848577 | P100: =ARKB!H99 -> 66991.23 | Q100: =btc_ratios3[[#This Row],[Price]]-P99 -> -4437.51 | R100: =btc_ratios3[[#This Row],[Price]]/P99-1 -> -0.062124993
A101: =scalars[[#This Row],[DOW]] -> Wednesday | B101: =B100+1 -> 46176 | C101: =ARKB!G100 -> 32578.838 | D101: =BITB!H100 -> 36935.12 | E101: =BRRR!G101 -> 5940.29 | F101: =BTC!J100 -> 52857.95 | G101: =BTCW!H100 -> 2241 | H101: =EZBC!F100 -> 5809.64 | J101: =GBTC!K100 -> 145034.31 | K101: =HODL!H100 -> 16651.094 | L101: =IBIT!G100 -> 773896.83 | M101: =SUM(btc_ratios3[[#This Row],[ARKB]:[IBIT]]) -> 1071945.1 | N101: =btc_ratios3[[#This Row],[Sum]]-M100 -> -6461.796 | O101: =btc_ratios3[[#This Row],[Sum]]/M100-1 -> -0.0059919833 | P101: =ARKB!H100 -> 65682.1 | Q101: =btc_ratios3[[#This Row],[Price]]-P100 -> -1309.13 | R101: =btc_ratios3[[#This Row],[Price]]/P100-1 -> -0.019541812
A102: =scalars[[#This Row],[DOW]] -> Thursday | B102: =B101+1 -> 46177 | C102: =ARKB!G101 -> 32253.752 | D102: =BITB!H101 -> 36690.81 | E102: =BRRR!G102 -> 5940.25 | F102: =BTC!J101 -> 52857.732 | G102: =BTCW!H101 -> 2241 | H102: =EZBC!F101 -> 5809.64 | J102: =GBTC!K101 -> 145028.35 | K102: =HODL!H101 -> 16651.095 | L102: =IBIT!G101 -> 774434.14 | M102: =SUM(btc_ratios3[[#This Row],[ARKB]:[IBIT]]) -> 1071906.8 | N102: =btc_ratios3[[#This Row],[Sum]]-M101 -> -38.3019 | O102: =btc_ratios3[[#This Row],[Sum]]/M101-1 -> -3.5731215e-05 | P102: =ARKB!H101 -> 63732.67 | Q102: =btc_ratios3[[#This Row],[Price]]-P101 -> -1949.43 | R102: =btc_ratios3[[#This Row],[Price]]/P101-1 -> -0.029679776
...

Sheet SCALARS
B1: Index | C1: BRRNY | D1: BRRNY | E1: BRRNY | F1: XBX | G1: BRRNY | H1: BRRNY | I1: Fidelity | J1: XBX | K1: MarketVector | L1: BRRNY | N1: BTCO — Invesco Galaxy Bitcoin ETF
B2: ConId | C2: 677037663 | D2: 677037658 | E2: 677037676 | F2: 741192224 | G2: 676783288 | H2: 676783282 | I2: 676783301 | J2: 349966059 | K2: 677037670 | L2: 677037673 | N2: MSBT - Morgan Stanley
B3: Annual Fee | C3: 0.0021 | D3: 0.002 | E3: 0.0025 | F3: 0.0015 | G3: 0.0025 | H3: 0.0019 | I3: 0.0025 | J3: 0.015 | K3: 0 | L3: 0.0025 | N3: Bitcoin ETF Fees Comparison - MooLoo
A4: 365 | B4: Daily Fee | C4: =C3/$A4 -> 5.7534247e-06 | D4: =D3/$A4 -> 5.4794521e-06 | E4: =E3/$A4 -> 6.8493151e-06 | F4: =F3/$A4 -> 4.109589e-06 | G4: =G3/$A4 -> 6.8493151e-06 | H4: =H3/$A4 -> 5.2054795e-06 | I4: =I3/$A4 -> 6.8493151e-06 | J4: =J3/$A4 -> 4.109589e-05 | ... L4: =L3/$A4 -> 6.8493151e-06
B5: Market Bias | C5: 0 | D5: 0 | E5: 0 | F5: 0 | G5: 0 | H5: 0 | I5: 0 | J5: 0 | K5: 0 | L5: 0
A6: DOW | B6: Date | C6: ARKB | D6: BITB | E6: BRRR | F6: BTC | G6: BTCW | H6: EZBC | I6: FBTC | J6: GBTC | K6: HODL | L6: IBIT | N6: Number | O6: Day
A7: Sunday | B7: 46082 | C7: =3012.9766+C5 -> 3012.9766 | D7: =1840.9691+D5 -> 1840.9691 | E7: =3543.8163+E5 -> 3543.8163 | F7: =2260.2814+F5 -> 2260.2814 | G7: =945.3954+G5 -> 945.3954 | H7: =1729.0918+H5 -> 1729.0918 | I7: =1147.9526+I5 -> 1147.9526 | J7: =1282.9366+J5 -> 1282.9366 | K7: =3535.8029+K5 -> 3535.8029 | L7: =1763.6799+L5 -> 1763.6799 | N7: 1 | O7: Sunday
A8: =VLOOKUP(WEEKDAY(B8),$N$7:$O$13,2) -> Monday | B8: =B7+1 -> 46083 | C8: =ROUND(C7*(1+C$4),4) -> 3012.9939 | D8: =ROUND(D7*(1+D$4),4) -> 1840.9792 | E8: =ROUND(E7*(1+E$4),4) -> 3543.8406 | F8: =ROUND(F7*(1+F$4),4) -> 2260.2907 | G8: =ROUND(G7*(1+G$4),4) -> 945.4019 | H8: =ROUND(H7*(1+H$4),4) -> 1729.1008 | I8: =ROUND(I7*(1+I$4),4) -> 1147.9605 | J8: =ROUND(J7*(1+J$4),4) -> 1282.9893 | ... L8: =ROUND(L7*(1+L$4),4) -> 1763.692 | N8: 2 | O8: Monday
A9: =VLOOKUP(WEEKDAY(B9),$N$7:$O$13,2) -> Tuesday | B9: =B8+1 -> 46084 | C9: =ROUND(C8*(1+C$4),4) -> 3013.0112 | D9: =ROUND(D8*(1+D$4),4) -> 1840.9893 | E9: =ROUND(E8*(1+E$4),4) -> 3543.8649 | F9: =ROUND(F8*(1+F$4),4) -> 2260.3 | G9: =ROUND(G8*(1+G$4),4) -> 945.4084 | H9: =ROUND(H8*(1+H$4),4) -> 1729.1098 | I9: =ROUND(I8*(1+I$4),4) -> 1147.9684 | J9: =ROUND(J8*(1+J$4),4) -> 1283.042 | ... L9: =ROUND(L8*(1+L$4),4) -> 1763.7041 | N9: 3 | O9: Tuesday
A10: =VLOOKUP(WEEKDAY(B10),$N$7:$O$13,2) -> Wednesday | B10: =B9+1 -> 46085 | C10: =ROUND(C9*(1+C$4),4) -> 3013.0285 | D10: =ROUND(D9*(1+D$4),4) -> 1840.9994 | E10: =ROUND(E9*(1+E$4),4) -> 3543.8892 | F10: =ROUND(F9*(1+F$4),4) -> 2260.3093 | G10: =ROUND(G9*(1+G$4),4) -> 945.4149 | H10: =ROUND(H9*(1+H$4),4) -> 1729.1188 | I10: =ROUND(I9*(1+I$4),4) -> 1147.9763 | J10: =ROUND(J9*(1+J$4),4) -> 1283.0947 | ... L10: =ROUND(L9*(1+L$4),4) -> 1763.7162 | N10: 4 | O10: Wednesday
A11: =VLOOKUP(WEEKDAY(B11),$N$7:$O$13,2) -> Thursday | B11: =B10+1 -> 46086 | C11: =ROUND(C10*(1+C$4),4) -> 3013.0458 | D11: =ROUND(D10*(1+D$4),4) -> 1841.0095 | E11: =ROUND(E10*(1+E$4),4) -> 3543.9135 | F11: =ROUND(F10*(1+F$4),4) -> 2260.3186 | G11: =ROUND(G10*(1+G$4),4) -> 945.4214 | H11: =ROUND(H10*(1+H$4),4) -> 1729.1278 | I11: =ROUND(I10*(1+I$4),4) -> 1147.9842 | J11: =ROUND(J10*(1+J$4),4) -> 1283.1474 | ... L11: =ROUND(L10*(1+L$4),4) -> 1763.7283 | N11: 5 | O11: Thursday
A12: =VLOOKUP(WEEKDAY(B12),$N$7:$O$13,2) -> Friday | B12: =B11+1 -> 46087 | C12: =ROUND(C11*(1+C$4),4) -> 3013.0631 | D12: =ROUND(D11*(1+D$4),4) -> 1841.0196 | E12: =ROUND(E11*(1+E$4),4) -> 3543.9378 | F12: =ROUND(F11*(1+F$4),4) -> 2260.3279 | G12: =ROUND(G11*(1+G$4),4) -> 945.4279 | H12: =ROUND(H11*(1+H$4),4) -> 1729.1368 | I12: =ROUND(I11*(1+I$4),4) -> 1147.9921 | J12: =ROUND(J11*(1+J$4),4) -> 1283.2001 | ... L12: =ROUND(L11*(1+L$4),4) -> 1763.7404 | N12: 6 | O12: Friday
A13: =VLOOKUP(WEEKDAY(B13),$N$7:$O$13,2) -> Saturday | B13: =B12+1 -> 46088 | C13: =ROUND(C12*(1+C$4),4) -> 3013.0804 | D13: =ROUND(D12*(1+D$4),4) -> 1841.0297 | E13: =ROUND(E12*(1+E$4),4) -> 3543.9621 | F13: =ROUND(F12*(1+F$4),4) -> 2260.3372 | G13: =ROUND(G12*(1+G$4),4) -> 945.4344 | H13: =ROUND(H12*(1+H$4),4) -> 1729.1458 | I13: =ROUND(I12*(1+I$4),4) -> 1148 | J13: =ROUND(J12*(1+J$4),4) -> 1283.2528 | ... L13: =ROUND(L12*(1+L$4),4) -> 1763.7525 | N13: 7 | O13: Saturday
A14: =VLOOKUP(WEEKDAY(B14),$N$7:$O$13,2) -> Sunday | B14: =B13+1 -> 46089 | C14: =ROUND(C13*(1+C$4),4) -> 3013.0977 | D14: =ROUND(D13*(1+D$4),4) -> 1841.0398 | E14: =ROUND(E13*(1+E$4),4) -> 3543.9864 | F14: =ROUND(F13*(1+F$4),4) -> 2260.3465 | G14: =ROUND(G13*(1+G$4),4) -> 945.4409 | H14: =ROUND(H13*(1+H$4),4) -> 1729.1548 | I14: =ROUND(I13*(1+I$4),4) -> 1148.0079 | J14: =ROUND(J13*(1+J$4),4) -> 1283.3055 | ... L14: =ROUND(L13*(1+L$4),4) -> 1763.7646
A15: =VLOOKUP(WEEKDAY(B15),$N$7:$O$13,2) -> Monday | B15: =B14+1 -> 46090 | C15: =ROUND(C14*(1+C$4),4) -> 3013.115 | D15: =ROUND(D14*(1+D$4),4) -> 1841.0499 | E15: =ROUND(E14*(1+E$4),4) -> 3544.0107 | F15: =ROUND(F14*(1+F$4),4) -> 2260.3558 | G15: =ROUND(G14*(1+G$4),4) -> 945.4474 | H15: =ROUND(H14*(1+H$4),4) -> 1729.1638 | I15: =ROUND(I14*(1+I$4),4) -> 1148.0158 | J15: =ROUND(J14*(1+J$4),4) -> 1283.3582 | ... L15: =ROUND(L14*(1+L$4),4) -> 1763.7767
A16: =VLOOKUP(WEEKDAY(B16),$N$7:$O$13,2) -> Tuesday | B16: =B15+1 -> 46091 | C16: =ROUND(C15*(1+C$4),4) -> 3013.1323 | D16: =ROUND(D15*(1+D$4),4) -> 1841.06 | E16: =ROUND(E15*(1+E$4),4) -> 3544.035 | F16: =ROUND(F15*(1+F$4),4) -> 2260.3651 | G16: =ROUND(G15*(1+G$4),4) -> 945.4539 | H16: =ROUND(H15*(1+H$4),4) -> 1729.1728 | I16: =ROUND(I15*(1+I$4),4) -> 1148.0237 | J16: =ROUND(J15*(1+J$4),4) -> 1283.4109 | ... L16: =ROUND(L15*(1+L$4),4) -> 1763.7888
A17: =VLOOKUP(WEEKDAY(B17),$N$7:$O$13,2) -> Wednesday | B17: =B16+1 -> 46092 | C17: =ROUND(C16*(1+C$4),4) -> 3013.1496 | D17: =ROUND(D16*(1+D$4),4) -> 1841.0701 | E17: =ROUND(E16*(1+E$4),4) -> 3544.0593 | F17: =ROUND(F16*(1+F$4),4) -> 2260.3744 | G17: =ROUND(G16*(1+G$4),4) -> 945.4604 | H17: =ROUND(H16*(1+H$4),4) -> 1729.1818 | I17: =ROUND(I16*(1+I$4),4) -> 1148.0316 | J17: =ROUND(J16*(1+J$4),4) -> 1283.4636 | ... L17: =ROUND(L16*(1+L$4),4) -> 1763.8009
A18: =VLOOKUP(WEEKDAY(B18),$N$7:$O$13,2) -> Thursday | B18: =B17+1 -> 46093 | C18: =ROUND(C17*(1+C$4),4) -> 3013.1669 | D18: =ROUND(D17*(1+D$4),4) -> 1841.0802 | E18: =ROUND(E17*(1+E$4),4) -> 3544.0836 | F18: =ROUND(F17*(1+F$4),4) -> 2260.3837 | G18: =ROUND(G17*(1+G$4),4) -> 945.4669 | H18: =ROUND(H17*(1+H$4),4) -> 1729.1908 | I18: =ROUND(I17*(1+I$4),4) -> 1148.0395 | J18: =ROUND(J17*(1+J$4),4) -> 1283.5163 | ... L18: =ROUND(L17*(1+L$4),4) -> 1763.813
A19: =VLOOKUP(WEEKDAY(B19),$N$7:$O$13,2) -> Friday | B19: =B18+1 -> 46094 | C19: =ROUND(C18*(1+C$4),4) -> 3013.1842 | D19: =ROUND(D18*(1+D$4),4) -> 1841.0903 | E19: =ROUND(E18*(1+E$4),4) -> 3544.1079 | F19: =ROUND(F18*(1+F$4),4) -> 2260.393 | G19: =ROUND(G18*(1+G$4),4) -> 945.4734 | H19: =ROUND(H18*(1+H$4),4) -> 1729.1998 | I19: =ROUND(I18*(1+I$4),4) -> 1148.0474 | J19: =ROUND(J18*(1+J$4),4) -> 1283.569 | ... L19: =ROUND(L18*(1+L$4),4) -> 1763.8251
A20: =VLOOKUP(WEEKDAY(B20),$N$7:$O$13,2) -> Saturday | B20: =B19+1 -> 46095 | C20: =ROUND(C19*(1+C$4),4) -> 3013.2015 | D20: =ROUND(D19*(1+D$4),4) -> 1841.1004 | E20: =ROUND(E19*(1+E$4),4) -> 3544.1322 | F20: =ROUND(F19*(1+F$4),4) -> 2260.4023 | G20: =ROUND(G19*(1+G$4),4) -> 945.4799 | H20: =ROUND(H19*(1+H$4),4) -> 1729.2088 | I20: =ROUND(I19*(1+I$4),4) -> 1148.0553 | J20: =ROUND(J19*(1+J$4),4) -> 1283.6217 | ... L20: =ROUND(L19*(1+L$4),4) -> 1763.8372
A21: =VLOOKUP(WEEKDAY(B21),$N$7:$O$13,2) -> Sunday | B21: =B20+1 -> 46096 | C21: =ROUND(C20*(1+C$4),4) -> 3013.2188 | D21: =ROUND(D20*(1+D$4),4) -> 1841.1105 | E21: =ROUND(E20*(1+E$4),4) -> 3544.1565 | F21: =ROUND(F20*(1+F$4),4) -> 2260.4116 | G21: =ROUND(G20*(1+G$4),4) -> 945.4864 | H21: =ROUND(H20*(1+H$4),4) -> 1729.2178 | I21: =ROUND(I20*(1+I$4),4) -> 1148.0632 | J21: =ROUND(J20*(1+J$4),4) -> 1283.6745 | ... L21: =ROUND(L20*(1+L$4),4) -> 1763.8493
A22: =VLOOKUP(WEEKDAY(B22),$N$7:$O$13,2) -> Monday | B22: =B21+1 -> 46097 | C22: =ROUND(C21*(1+C$4),4) -> 3013.2361 | D22: =ROUND(D21*(1+D$4),4) -> 1841.1206 | E22: =ROUND(E21*(1+E$4),4) -> 3544.1808 | F22: =ROUND(F21*(1+F$4),4) -> 2260.4209 | G22: =ROUND(G21*(1+G$4),4) -> 945.4929 | H22: =ROUND(H21*(1+H$4),4) -> 1729.2268 | I22: =ROUND(I21*(1+I$4),4) -> 1148.0711 | J22: =ROUND(J21*(1+J$4),4) -> 1283.7273 | ... L22: =ROUND(L21*(1+L$4),4) -> 1763.8614
A23: =VLOOKUP(WEEKDAY(B23),$N$7:$O$13,2) -> Tuesday | B23: =B22+1 -> 46098 | C23: =ROUND(C22*(1+C$4),4) -> 3013.2534 | D23: =ROUND(D22*(1+D$4),4) -> 1841.1307 | E23: =ROUND(E22*(1+E$4),4) -> 3544.2051 | F23: =ROUND(F22*(1+F$4),4) -> 2260.4302 | G23: =ROUND(G22*(1+G$4),4) -> 945.4994 | H23: =ROUND(H22*(1+H$4),4) -> 1729.2358 | I23: =ROUND(I22*(1+I$4),4) -> 1148.079 | J23: =ROUND(J22*(1+J$4),4) -> 1283.7801 | ... L23: =ROUND(L22*(1+L$4),4) -> 1763.8735
A24: =VLOOKUP(WEEKDAY(B24),$N$7:$O$13,2) -> Wednesday | B24: =B23+1 -> 46099 | C24: =ROUND(C23*(1+C$4),4) -> 3013.2707 | D24: =ROUND(D23*(1+D$4),4) -> 1841.1408 | E24: =ROUND(E23*(1+E$4),4) -> 3544.2294 | F24: =ROUND(F23*(1+F$4),4) -> 2260.4395 | G24: =ROUND(G23*(1+G$4),4) -> 945.5059 | H24: =ROUND(H23*(1+H$4),4) -> 1729.2448 | I24: =ROUND(I23*(1+I$4),4) -> 1148.0869 | J24: =ROUND(J23*(1+J$4),4) -> 1283.8329 | ... L24: =ROUND(L23*(1+L$4),4) -> 1763.8856
A25: =VLOOKUP(WEEKDAY(B25),$N$7:$O$13,2) -> Thursday | B25: =B24+1 -> 46100 | C25: =ROUND(C24*(1+C$4),4) -> 3013.288 | D25: =ROUND(D24*(1+D$4),4) -> 1841.1509 | E25: =ROUND(E24*(1+E$4),4) -> 3544.2537 | F25: =ROUND(F24*(1+F$4),4) -> 2260.4488 | G25: =ROUND(G24*(1+G$4),4) -> 945.5124 | H25: =ROUND(H24*(1+H$4),4) -> 1729.2538 | I25: =ROUND(I24*(1+I$4),4) -> 1148.0948 | J25: =ROUND(J24*(1+J$4),4) -> 1283.8857 | ... L25: =ROUND(L24*(1+L$4),4) -> 1763.8977
... A371: =VLOOKUP(WEEKDAY(B371),$N$7:$O$13,2) -> Sunday | B371: =B370+1 -> 46446 | C371: =ROUND(C370*(1+C$4),4) -> 3019.295 | D371: =ROUND(D370*(1+D$4),4) -> 1844.6455 | E371: =ROUND(E370*(1+E$4),4) -> 3552.6615 | F371: =ROUND(F370*(1+F$4),4) -> 2263.6666 | G371: =ROUND(G370*(1+G$4),4) -> 947.7614 | H371: =ROUND(H370*(1+H$4),4) -> 1732.3678 | I371: =ROUND(I370*(1+I$4),4) -> 1150.8282 | J371: =ROUND(J370*(1+J$4),4) -> 1302.2717 | ... L371: =ROUND(L370*(1+L$4),4) -> 1768.0843

Sheet BITO and EETH
A1: https://www.proshares.com/our-etfs/strategic/bito
A2: https://www.proshares.com/our-etfs/strategic/eeth
C4: BTC | J4: ETH
A5: DOW | B5: Date | C5: CME 1ST | D5: CME 2ND | E5: CME TOTAL | F5: CB 1ST | G5: CB 2ND | H5: CB TOTAL | J5: CME 1ST | K5: CME 2ND | L5: CME TOTAL
A6: =SCALARS!A7 -> Sunday | B6: =SCALARS!B7 -> 46082
A7: =SCALARS!A8 -> Monday | B7: =SCALARS!B8 -> 46083
A8: =SCALARS!A9 -> Tuesday | B8: =SCALARS!B9 -> 46084
A9: =SCALARS!A10 -> Wednesday | B9: =SCALARS!B10 -> 46085
A10: =SCALARS!A11 -> Thursday | B10: =SCALARS!B11 -> 46086
A11: =SCALARS!A12 -> Friday | B11: =SCALARS!B12 -> 46087
A12: =SCALARS!A13 -> Saturday | B12: =SCALARS!B13 -> 46088
A13: =SCALARS!A14 -> Sunday | B13: =SCALARS!B14 -> 46089
A14: =SCALARS!A15 -> Monday | B14: =SCALARS!B15 -> 46090
A15: =SCALARS!A16 -> Tuesday | B15: =SCALARS!B16 -> 46091
A16: =SCALARS!A17 -> Wednesday | B16: =SCALARS!B17 -> 46092
A17: =SCALARS!A18 -> Thursday | B17: =SCALARS!B18 -> 46093
... A85: =SCALARS!A86 -> Tuesday | B85: =SCALARS!B86 -> 46161
A86: =SCALARS!A87 -> Wednesday | B86: =SCALARS!B87 -> 46162 | C86: 4435 | E86: =SUM(C86:D86) -> 4435 | H86: =SUM(F86:G86) -> 0
A87: =SCALARS!A88 -> Thursday | B87: =SCALARS!B88 -> 46163 | C87: 3465 | D87: 970 | E87: =SUM(C87:D87) -> 4435 | H87: =SUM(F87:G87) -> 0 | N87: FIRST MOVE
A88: =SCALARS!A89 -> Friday | B88: =SCALARS!B89 -> 46164 | C88: 2425 | D88: 2010 | E88: =SUM(C88:D88) -> 4435 | H88: =SUM(F88:G88) -> 0 | J88: 374 | K88: 232 | L88: =SUM(J88:K88) -> 606
A89: =SCALARS!A90 -> Saturday | B89: =SCALARS!B90 -> 46165
A90: =SCALARS!A91 -> Sunday | B90: =SCALARS!B91 -> 46166
A91: =SCALARS!A92 -> Monday | B91: =SCALARS!B92 -> 46167 | C91: HOLIDAY
A92: =SCALARS!A93 -> Tuesday | B92: =SCALARS!B93 -> 46168 | C92: 3030 | D92: 1405 | E92: =SUM(C92:D92) -> 4435 | H92: =SUM(F92:G92) -> 0 | J92: 254 | K92: 352 | L92: =SUM(J92:K92) -> 606
A93: =SCALARS!A94 -> Wednesday | B93: =SCALARS!B94 -> 46169 | C93: 3870 | D93: 600 | E93: =SUM(C93:D93) -> 4470 | H93: =SUM(F93:G93) -> 0 | J93: 472 | K93: 134 | L93: =SUM(J93:K93) -> 606
A94: =SCALARS!A95 -> Thursday | B94: =SCALARS!B95 -> 46170 | D94: 4230 | E94: =SUM(C94:D94) -> 4230 | G94: 1000 | H94: =SUM(F94:G94) -> 1000 | K94: 605 | L94: =SUM(J94:K94) -> 605
A95: =SCALARS!A96 -> Friday | B95: =SCALARS!B96 -> 46171 | D95: 4220 | E95: =SUM(C95:D95) -> 4220 | G95: 1000 | H95: =SUM(F95:G95) -> 1000 | K95: 605 | L95: =SUM(J95:K95) -> 605 | N95: EXPIRATION DAY
A96: =SCALARS!A97 -> Saturday | B96: =SCALARS!B97 -> 46172
A97: =SCALARS!A98 -> Sunday | B97: =SCALARS!B98 -> 46173
A98: =SCALARS!A99 -> Monday | B98: =SCALARS!B99 -> 46174 | C98: 4220 | E98: =SUM(C98:D98) -> 4220 | F98: 1000 | H98: =SUM(F98:G98) -> 1000 | J98: 605 | L98: =SUM(J98:K98) -> 605
A99: =SCALARS!A100 -> Tuesday | B99: =SCALARS!B100 -> 46175 | C99: 4235 | E99: =SUM(C99:D99) -> 4235 | F99: 1000 | H99: =SUM(F99:G99) -> 1000 | J99: 605 | L99: =SUM(J99:K99) -> 605
A100: =SCALARS!A101 -> Wednesday | B100: =SCALARS!B101 -> 46176 | C100: 4305 | E100: =SUM(C100:D100) -> 4305 | F100: 1000 | H100: =SUM(F100:G100) -> 1000 | J100: 605 | L100: =SUM(J100:K100) -> 605
A101: =SCALARS!A102 -> Thursday | B101: =SCALARS!B102 -> 46177 | C101: 4305 | E101: =SUM(C101:D101) -> 4305 | F101: 1000 | H101: =SUM(F101:G101) -> 1000 | J101: 599 | L101: =SUM(J101:K101) -> 599
A102: =SCALARS!A103 -> Friday | B102: =SCALARS!B103 -> 46178 | C102: 4230 | E102: =SUM(C102:D102) -> 4230 | F102: 1000 | H102: =SUM(F102:G102) -> 1000 | J102: 624 | L102: =SUM(J102:K102) -> 624
A103: =SCALARS!A104 -> Saturday | B103: =SCALARS!B104 -> 46179 | E103: =SUM(C103:D103) -> 0 | H103: =SUM(F103:G103) -> 0 | L103: =SUM(J103:K103) -> 0
A104: =SCALARS!A105 -> Sunday | B104: =SCALARS!B105 -> 46180 | E104: =SUM(C104:D104) -> 0 | H104: =SUM(F104:G104) -> 0 | L104: =SUM(J104:K104) -> 0
A105: =SCALARS!A106 -> Monday | B105: =SCALARS!B106 -> 46181 | C105: 4230 | E105: =SUM(C105:D105) -> 4230 | F105: 1000 | H105: =SUM(F105:G105) -> 1000 | J105: 624 | L105: =SUM(J105:K105) -> 624
A106: =SCALARS!A107 -> Tuesday | B106: =SCALARS!B107 -> 46182 | C106: 4230 | E106: =SUM(C106:D106) -> 4230 | F106: 1000 | H106: =SUM(F106:G106) -> 1000 | J106: 624 | L106: =SUM(J106:K106) -> 624
A107: =SCALARS!A108 -> Wednesday | B107: =SCALARS!B108 -> 46183 | C107: 4215 | E107: =SUM(C107:D107) -> 4215 | F107: 1000 | H107: =SUM(F107:G107) -> 1000 | J107: 624 | L107: =SUM(J107:K107) -> 624
A108: =SCALARS!A109 -> Thursday | B108: =SCALARS!B109 -> 46184 | C108: 4130 | E108: =SUM(C108:D108) -> 4130 | F108: 1000 | H108: =SUM(F108:G108) -> 1000 | J108: 616 | L108: =SUM(J108:K108) -> 616
A109: =SCALARS!A110 -> Friday | B109: =SCALARS!B110 -> 46185 | C109: 4130 | E109: =SUM(C109:D109) -> 4130 | F109: 1000 | H109: =SUM(F109:G109) -> 1000 | J109: 616 | L109: =SUM(J109:K109) -> 616
A110: =SCALARS!A111 -> Saturday | B110: =SCALARS!B111 -> 46186 | E110: =SUM(C110:D110) -> 0 | H110: =SUM(F110:G110) -> 0 | L110: =SUM(J110:K110) -> 0
A111: =SCALARS!A112 -> Sunday | B111: =SCALARS!B112 -> 46187 | E111: =SUM(C111:D111) -> 0 | H111: =SUM(F111:G111) -> 0 | L111: =SUM(J111:K111) -> 0
A112: =SCALARS!A113 -> Monday | B112: =SCALARS!B113 -> 46188 | C112: 4110 | E112: =SUM(C112:D112) -> 4110 | F112: 1000 | H112: =SUM(F112:G112) -> 1000 | J112: 616 | L112: =SUM(J112:K112) -> 616
A113: =SCALARS!A114 -> Tuesday | B113: =SCALARS!B114 -> 46189 | C113: 4110 | E113: =SUM(C113:D113) -> 4110 | F113: 1000 | H113: =SUM(F113:G113) -> 1000 | J113: 616 | L113: =SUM(J113:K113) -> 616
A114: =SCALARS!A115 -> Wednesday | B114: =SCALARS!B115 -> 46190 | C114: 4120 | E114: =SUM(C114:D114) -> 4120 | F114: 1000 | H114: =SUM(F114:G114) -> 1000 | J114: 616 | L114: =SUM(J114:K114) -> 616
A115: =SCALARS!A116 -> Thursday | B115: =SCALARS!B116 -> 46191 | C115: 3185 | D115: 750 | E115: =SUM(C115:D115) -> 3935 | G115: 2000 | H115: =SUM(F115:G115) -> 2000 | J115: 491 | K115: 125 | L115: =SUM(J115:K115) -> 616 | N115: FIRST MOVE
A116: =SCALARS!A117 -> Friday | B116: =SCALARS!B117 -> 46192 | C116: HOLIDAY
A117: =SCALARS!A118 -> Saturday | B117: =SCALARS!B118 -> 46193 | E117: =SUM(C117:D117) -> 0 | H117: =SUM(F117:G117) -> 0 | L117: =SUM(J117:K117) -> 0
A118: =SCALARS!A119 -> Sunday | B118: =SCALARS!B119 -> 46194 | E118: =SUM(C118:D118) -> 0 | H118: =SUM(F118:G118) -> 0 | L118: =SUM(J118:K118) -> 0
A119: =SCALARS!A120 -> Monday | B119: =SCALARS!B120 -> 46195 | C119: 2485 | D119: 1530 | E119: =SUM(C119:D119) -> 4015 | G119: 2000 | H119: =SUM(F119:G119) -> 2000 | J119: 366 | K119: 250 | L119: =SUM(J119:K119) -> 616
A120: =SCALARS!A121 -> Tuesday | B120: =SCALARS!B121 -> 46196 | C120: 1590 | D120: 2480 | E120: =SUM(C120:D120) -> 4070 | G120: 2000 | H120: =SUM(F120:G120) -> 2000 | J120: 241 | K120: 375 | L120: =SUM(J120:K120) -> 616
A121: =SCALARS!A122 -> Wednesday | B121: =SCALARS!B122 -> 46197 | C121: 670 | D121: 3400 | E121: =SUM(C121:D121) -> 4070 | G121: 2000 | H121: =SUM(F121:G121) -> 2000 | J121: 115 | K121: 500 | L121: =SUM(J121:K121) -> 615
A122: =SCALARS!A123 -> Thursday | B122: =SCALARS!B123 -> 46198 | D122: 3780 | E122: =SUM(C122:D122) -> 3780 | G122: 3000 | H122: =SUM(F122:G122) -> 3000 | K122: 615 | L122: =SUM(J122:K122) -> 615
A123: =SCALARS!A124 -> Friday | B123: =SCALARS!B124 -> 46199 | D123: 3780 | E123: =SUM(C123:D123) -> 3780 | G123: 3000 | H123: =SUM(F123:G123) -> 3000 | K123: 615 | L123: =SUM(J123:K123) -> 615 | N123: EXPIRATION DAY
A124: =SCALARS!A125 -> Saturday | B124: =SCALARS!B125 -> 46200 | E124: =SUM(C124:D124) -> 0 | H124: =SUM(F124:G124) -> 0 | L124: =SUM(J124:K124) -> 0
A125: =SCALARS!A126 -> Sunday | B125: =SCALARS!B126 -> 46201 | E125: =SUM(C125:D125) -> 0 | H125: =SUM(F125:G125) -> 0 | L125: =SUM(J125:K125) -> 0
A126: =SCALARS!A127 -> Monday | B126: =SCALARS!B127 -> 46202 | C126: 3750 | E126: =SUM(C126:D126) -> 3750 | F126: 3000 | H126: =SUM(F126:G126) -> 3000 | J126: 607 | L126: =SUM(J126:K126) -> 607
A127: =SCALARS!A128 -> Tuesday | B127: =SCALARS!B128 -> 46203 | C127: 3780 | E127: =SUM(C127:D127) -> 3780 | F127: 3000 | H127: =SUM(F127:G127) -> 3000 | J127: 607 | L127: =SUM(J127:K127) -> 607
A128: =SCALARS!A129 -> Wednesday | B128: =SCALARS!B129 -> 46204 | C128: 3760 | E128: =SUM(C128:D128) -> 3760 | F128: 3000 | H128: =SUM(F128:G128) -> 3000 | J128: 607 | L128: =SUM(J128:K128) -> 607
A129: =SCALARS!A130 -> Thursday | B129: =SCALARS!B130 -> 46205 | C129: 3700 | E129: =SUM(C129:D129) -> 3700 | F129: 3000 | H129: =SUM(F129:G129) -> 3000 | J129: 607 | L129: =SUM(J129:K129) -> 607
A130: =SCALARS!A131 -> Friday | B130: =SCALARS!B131 -> 46206 | C130: HOLIDAY
A131: =SCALARS!A132 -> Saturday | B131: =SCALARS!B132 -> 46207 | E131: =SUM(C131:D131) -> 0 | H131: =SUM(F131:G131) -> 0 | L131: =SUM(J131:K131) -> 0
A132: =SCALARS!A133 -> Sunday | B132: =SCALARS!B133 -> 46208 | E132: =SUM(C132:D132) -> 0 | H132: =SUM(F132:G132) -> 0 | L132: =SUM(J132:K132) -> 0
A133: =SCALARS!A134 -> Monday | B133: =SCALARS!B134 -> 46209 | C133: 3770 | E133: =SUM(C133:D133) -> 3770 | F133: 3000 | H133: =SUM(F133:G133) -> 3000 | J133: 601 | L133: =SUM(J133:K133) -> 601
A134: =SCALARS!A135 -> Tuesday | B134: =SCALARS!B135 -> 46210 | C134: 3690 | E134: =SUM(C134:D134) -> 3690 | F134: 3000 | H134: =SUM(F134:G134) -> 3000 | J134: 601 | L134: =SUM(J134:K134) -> 601
A135: =SCALARS!A136 -> Wednesday | B135: =SCALARS!B136 -> 46211 | C135: 3690 | E135: =SUM(C135:D135) -> 3690 | F135: 3000 | H135: =SUM(F135:G135) -> 3000 | J135: 601 | L135: =SUM(J135:K135) -> 601
A136: =SCALARS!A137 -> Thursday | B136: =SCALARS!B137 -> 46212 | C136: 3732 | E136: =SUM(C136:D136) -> 3732 | F136: 3000 | H136: =SUM(F136:G136) -> 3000 | J136: 596 | L136: =SUM(J136:K136) -> 596
A137: =SCALARS!A138 -> Friday | B137: =SCALARS!B138 -> 46213 | C137: 3622 | E137: =SUM(C137:D137) -> 3622 | F137: 3000 | H137: =SUM(F137:G137) -> 3000 | J137: 596 | L137: =SUM(J137:K137) -> 596
A138: =SCALARS!A139 -> Saturday | B138: =SCALARS!B139 -> 46214 | E138: =SUM(C138:D138) -> 0 | H138: =SUM(F138:G138) -> 0 | L138: =SUM(J138:K138) -> 0
A139: =SCALARS!A140 -> Sunday | B139: =SCALARS!B140 -> 46215 | E139: =SUM(C139:D139) -> 0 | H139: =SUM(F139:G139) -> 0 | L139: =SUM(J139:K139) -> 0
A140: =SCALARS!A141 -> Monday | B140: =SCALARS!B141 -> 46216 | C140: 3584 | E140: =SUM(C140:D140) -> 3584 | F140: 3000 | H140: =SUM(F140:G140) -> 3000 | J140: 594 | L140: =SUM(J140:K140) -> 594
A141: =SCALARS!A142 -> Tuesday | B141: =SCALARS!B142 -> 46217 | C141: 3629 | E141: =SUM(C141:D141) -> 3629 | F141: 3000 | H141: =SUM(F141:G141) -> 3000 | J141: 594 | L141: =SUM(J141:K141) -> 594
A142: =SCALARS!A143 -> Wednesday | B142: =SCALARS!B143 -> 46218 | C142: 3614 | E142: =SUM(C142:D142) -> 3614 | F142: 3000 | H142: =SUM(F142:G142) -> 3000 | J142: 582 | L142: =SUM(J142:K142) -> 582
A143: =SCALARS!A144 -> Thursday | B143: =SCALARS!B144 -> 46219 | C143: 3588 | E143: =SUM(C143:D143) -> 3588 | F143: 3000 | H143: =SUM(F143:G143) -> 3000 | J143: 582 | L143: =SUM(J143:K143) -> 582
A144: =SCALARS!A145 -> Friday | B144: =SCALARS!B145 -> 46220 | C144: 3609 | E144: =SUM(C144:D144) -> 3609 | F144: 3000 | H144: =SUM(F144:G144) -> 3000 | J144: 558 | L144: =SUM(J144:K144) -> 558
A145: =SCALARS!A146 -> Saturday | B145: =SCALARS!B146 -> 46221 | E145: =SUM(C145:D145) -> 0 | H145: =SUM(F145:G145) -> 0 | L145: =SUM(J145:K145) -> 0
A146: =SCALARS!A147 -> Sunday | B146: =SCALARS!B147 -> 46222 | E146: =SUM(C146:D146) -> 0 | H146: =SUM(F146:G146) -> 0 | L146: =SUM(J146:K146) -> 0
A147: =SCALARS!A148 -> Monday | B147: =SCALARS!B148 -> 46223 | C147: 3569 | E147: =SUM(C147:D147) -> 3569 | F147: 3000 | H147: =SUM(F147:G147) -> 3000 | J147: 558 | L147: =SUM(J147:K147) -> 558
A148: =SCALARS!A149 -> Tuesday | B148: =SCALARS!B149 -> 46224 | C148: 3542 | E148: =SUM(C148:D148) -> 3542 | F148: 3000 | H148: =SUM(F148:G148) -> 3000 | J148: 580 | L148: =SUM(J148:K148) -> 580
A149: =SCALARS!A150 -> Wednesday | B149: =SCALARS!B150 -> 46225 | C149: 3542 | E149: =SUM(C149:D149) -> 3542 | F149: 3000 | H149: =SUM(F149:G149) -> 3000 | J149: 580 | L149: =SUM(J149:K149) -> 580
A150: =SCALARS!A151 -> Thursday | B150: =SCALARS!B151 -> 46226 | C150: 3587 | E150: =SUM(C150:D150) -> 3587 | F150: 3000 | H150: =SUM(F150:G150) -> 3000 | J150: 580 | L150: =SUM(J150:K150) -> 580
A151: =SCALARS!A152 -> Friday | B151: =SCALARS!B152 -> 46227 | C151: 3022 | D151: 590 | E151: =SUM(C151:D151) -> 3612 | F151: 3000 | H151: =SUM(F151:G151) -> 3000 | J151: 460 | K151: 120 | L151: =SUM(J151:K151) -> 580 | N151: FIRST MOVE
A152: =SCALARS!A153 -> Saturday | B152: =SCALARS!B153 -> 46228 | E152: =SUM(C152:D152) -> 0 | H152: =SUM(F152:G152) -> 0 | L152: =SUM(J152:K152) -> 0
A153: =SCALARS!A154 -> Sunday | B153: =SCALARS!B154 -> 46229 | E153: =SUM(C153:D153) -> 0 | H153: =SUM(F153:G153) -> 0 | L153: =SUM(J153:K153) -> 0
A154: =SCALARS!A155 -> Monday | B154: =SCALARS!B155 -> 46230 | C154: 2360 | D154: 1290 | E154: =SUM(C154:D154) -> 3650 | F154: 3000 | H154: =SUM(F154:G154) -> 3000 | J154: 340 | K154: 240 | L154: =SUM(J154:K154) -> 580
A155: =SCALARS!A156 -> Tuesday | B155: =SCALARS!B156 -> 46231 | C155: 2260 | D155: 1465 | E155: =SUM(C155:D155) -> 3725 | F155: 3000 | H155: =SUM(F155:G155) -> 3000 | J155: 375 | K155: 205 | L155: =SUM(J155:K155) -> 580
A156: =SCALARS!A157 -> Wednesday | B156: =SCALARS!B157 -> 46232 | C156: 765 | D156: 2945 | E156: =SUM(C156:D156) -> 3710 | F156: 1000 | G156: 2000 | H156: =SUM(F156:G156) -> 3000 | J156: 105 | K156: 475 | L156: =SUM(J156:K156) -> 580
A157: =SCALARS!A158 -> Thursday | B157: =SCALARS!B158 -> 46233 | E157: =SUM(C157:D157) -> 0 | H157: =SUM(F157:G157) -> 0 | L157: =SUM(J157:K157) -> 0
A158: =SCALARS!A159 -> Friday | B158: =SCALARS!B159 -> 46234 | E158: =SUM(C158:D158) -> 0 | H158: =SUM(F158:G158) -> 0 | L158: =SUM(J158:K158) -> 0 | N158: EXPIRATION DAY

Sheet ARKB
A1: https://www.21shares.com/en-us/product/arkb
E4: WEEKLY PATTERN
A5: DOW | B5: Date | C5: TODAY'S RATIO | D5: SHS/ADJ BTC | E5: PREDICTED BIAS | F5: DIFF | G5: COIN ENTITLEMENT | H5: REF PRICE | I5: AUM | J5: SECUTITIES OUTSTANDING | K5: ADJ BTC | L5: SHS/BTC
A6: =SCALARS!A7 -> Sunday | B6: =SCALARS!B7 -> 46082 | C6: =SCALARS!C7 -> 3012.9766
A7: =SCALARS!A8 -> Monday | B7: =SCALARS!B8 -> 46083 | C7: =SCALARS!C8 -> 3012.9939
A8: =SCALARS!A9 -> Tuesday | B8: =SCALARS!B9 -> 46084 | C8: =SCALARS!C9 -> 3013.0112
A9: =SCALARS!A10 -> Wednesday | B9: =SCALARS!B10 -> 46085 | C9: =SCALARS!C10 -> 3013.0285
A10: =SCALARS!A11 -> Thursday | B10: =SCALARS!B11 -> 46086 | C10: =SCALARS!C11 -> 3013.0458
A11: =SCALARS!A12 -> Friday | B11: =SCALARS!B12 -> 46087 | C11: =SCALARS!C12 -> 3013.0631
A12: =SCALARS!A13 -> Saturday | B12: =SCALARS!B13 -> 46088 | C12: =SCALARS!C13 -> 3013.0804
A13: =SCALARS!A14 -> Sunday | B13: =SCALARS!B14 -> 46089 | C13: =SCALARS!C14 -> 3013.0977
A14: =SCALARS!A15 -> Monday | B14: =SCALARS!B15 -> 46090 | C14: =SCALARS!C15 -> 3013.115 | D14: =J14/K14 -> 3013.0963 | E14: =C14-C13 -> 0.0173 | F14: =C14-(D14+E14) -> 0.0013655606 | G14: 35566.78 | H14: 68865.77 | I14: 2.4482793e+09 | J14: 107120000 | K14: =I14/H14 -> 35551.469 | L14: =J14/G14 -> 3011.7992
A15: =SCALARS!A16 -> Tuesday | B15: =SCALARS!B16 -> 46091 | C15: =SCALARS!C16 -> 3013.1323 | D15: =J15/K15 -> 3013.1137 | E15: =C15-C14 -> 0.0173 | F15: =C15-(D15+E15) -> 0.0013298274 | G15: 35624.86 | H15: 70019.35 | I15: 2.4933431e+09 | J15: 107295000 | K15: =I15/H15 -> 35609.344 | L15: =J15/G15 -> 3011.8013
A16: =SCALARS!A17 -> Wednesday | B16: =SCALARS!B17 -> 46092 | C16: =SCALARS!C17 -> 3013.1496 | D16: =J16/K16 -> 3013.131 | E16: =C16-C15 -> 0.0173 | F16: =C16-(D16+E16) -> 0.0012940042 | G16: 35624.86 | H16: 70600.43 | I16: 2.5140205e+09 | J16: 107295000 | K16: =I16/H16 -> 35609.139 | L16: =J16/G16 -> 3011.8013
A17: =SCALARS!A18 -> Thursday | B17: =SCALARS!B18 -> 46093 | C17: =SCALARS!C18 -> 3013.1669 | D17: =J17/K17 -> 3013.183 | E17: =C17-C18 -> -0.0173 | F17: =C17-(D17+E17) -> 0.0011859399 | G17: 35668 | H17: 70182.71 | I17: 2502130666 | J17: 107425000 | K17: =I17/H17 -> 35651.668 | L17: =J17/G17 -> 3011.8033
A18: =SCALARS!A19 -> Friday | B18: =SCALARS!B19 -> 46094 | C18: =SCALARS!C19 -> 3013.1842 | D18: =J18/K18 -> 3013.2004 | E18: =C18-C19 -> -0.0173 | F18: =C18-(D18+E18) -> 0.0011497222 | G18: 35701.19 | H18: 71153.47 | I18: 2.5390867e+09 | J18: 107525000 | K18: =I18/H18 -> 35684.65 | L18: =J18/G18 -> 3011.8044
A19: =SCALARS!A20 -> Saturday | B19: =SCALARS!B20 -> 46095 | C19: =SCALARS!C20 -> 3013.2015
A20: =SCALARS!A21 -> Sunday | B20: =SCALARS!B21 -> 46096 | C20: =SCALARS!C21 -> 3013.2188
A21: =SCALARS!A22 -> Monday | B21: =SCALARS!B22 -> 46097 | C21: =SCALARS!C22 -> 3013.2361 | D21: =J21/K21 -> 3013.2177 | E21: =C21-C20 -> 0.0173 | F21: =C21-(D21+E21) -> 0.0011133911 | G21: 35644.71 | H21: 74073.23 | I21: 2.6401892e+09 | J21: 107400000 | K21: =I21/H21 -> 35642.961 | L21: =J21/G21 -> 3013.0698
A22: =SCALARS!A23 -> Tuesday | B22: =SCALARS!B23 -> 46098 | C22: =SCALARS!C23 -> 3013.2534 | D22: =J22/K22 -> 3013.235 | E22: =C22-C21 -> 0.0173 | F22: =C22-(D22+E22) -> 0.0010769842 | G22: 35677.89 | H22: 74681.96 | I22: 2.6643493e+09 | J22: 107500000 | K22: =I22/H22 -> 35675.943 | L22: =J22/G22 -> 3013.0706
A23: =SCALARS!A24 -> Wednesday | B23: =SCALARS!B24 -> 46099 | C23: =SCALARS!C24 -> 3013.2707 | D23: =J23/K23 -> 3013.2524 | E23: =C23-C22 -> 0.0173 | F23: =C23-(D23+E23) -> 0.0010404576 | G23: 35677.89 | H23: 71208.94 | I23: 2.5404314e+09 | J23: 107500000 | K23: =I23/H23 -> 35675.737 | L23: =J23/G23 -> 3013.0706
A24: =SCALARS!A25 -> Thursday | B24: =SCALARS!B25 -> 46100 | C24: =SCALARS!C25 -> 3013.288 | D24: =J24/K24 -> 3013.3044 | E24: =C24-C25 -> -0.0173 | F24: =C24-(D24+E24) -> 0.00093030269 | G24: 35462.18 | H24: 70292.52 | I24: 2.4925314e+09 | J24: 106850000 | K24: =I24/H24 -> 35459.412 | L24: =J24/G24 -> 3013.0691
A25: =SCALARS!A26 -> Friday | B25: =SCALARS!B26 -> 46101 | C25: =SCALARS!C26 -> 3013.3053 | D25: =J25/K25 -> 3013.3217 | E25: =C25-C26 -> -0.0173 | F25: =C25-(D25+E25) -> 0.00089337666 | G25: 35462.18 | H25: 69873.12 | I25: 2.4776455e+09 | J25: 106850000 | K25: =I25/H25 -> 35459.208 | L25: =J25/G25 -> 3013.0691
A26: =SCALARS!A27 -> Saturday | B26: =SCALARS!B27 -> 46102 | C26: =SCALARS!C27 -> 3013.3226
A27: =SCALARS!A28 -> Sunday | B27: =SCALARS!B28 -> 46103 | C27: =SCALARS!C28 -> 3013.3399
A28: =SCALARS!A29 -> Monday | B28: =SCALARS!B29 -> 46104 | C28: =SCALARS!C29 -> 3013.3572 | E28: =C28-C27 -> 0.0173
A29: =SCALARS!A30 -> Tuesday | B29: =SCALARS!B30 -> 46105 | C29: =SCALARS!C30 -> 3013.3745 | D29: =J29/K29 -> 3013.3564 | E29: =C29-C28 -> 0.0173 | F29: =C29-(D29+E29) -> 0.00081924574 | G29: 35329.43 | H29: 69451.67 | I29: 2.4534537e+09 | J29: 106450000 | K29: =I29/H29 -> 35326.057 | L29: =J29/G29 -> 3013.0687
A30: =SCALARS!A31 -> Wednesday | B30: =SCALARS!B31 -> 46106 | C30: =SCALARS!C31 -> 3013.3918 | D30: =J30/K30 -> 3013.3737 | E30: =C30-C29 -> 0.0173 | F30: =C30-(D30+E30) -> 0.00078202957 | G30: 35261.4 | H30: 70883.73 | I30: 2.4992061e+09 | J30: 106245000 | K30: =I30/H30 -> 35257.824 | L30: =J30/G30 -> 3013.0681
A31: =SCALARS!A32 -> Thursday | B31: =SCALARS!B32 -> 46107 | C31: =SCALARS!C32 -> 3013.4091 | D31: =J31/K31 -> 3013.4257 | E31: =C31-C32 -> -0.0173 | F31: =C31-(D31+E31) -> 0.00066977293 | G31: 34816.72 | H31: 68478.86 | I31: 2.383923e+09 | J31: 104905000 | K31: =I31/H31 -> 34812.539 | L31: =J31/G31 -> 3013.0638
A32: =SCALARS!A33 -> Friday | B32: =SCALARS!B33 -> 46108 | C32: =SCALARS!C33 -> 3013.4264 | E32: =C32-C33 -> -0.0173
A33: =SCALARS!A34 -> Saturday | B33: =SCALARS!B34 -> 46109 | C33: =SCALARS!C34 -> 3013.4437
A34: =SCALARS!A35 -> Sunday | B34: =SCALARS!B35 -> 46110 | C34: =SCALARS!C35 -> 3013.461
A35: =SCALARS!A36 -> Monday | B35: =SCALARS!B36 -> 46111 | C35: =SCALARS!C36 -> 3013.4783 | D35: =J35/K35 -> 3013.4604 | E35: =C35-C34 -> 0.0173 | F35: =C35-(D35+E35) -> 0.00059443017 | G35: 35229.99 | H35: 66355.48 | I35: 2.3376109e+09 | J35: 106160000 | K35: =I35/H35 -> 35228.603 | L35: =J35/G35 -> 3013.3418
A36: =SCALARS!A37 -> Tuesday | B36: =SCALARS!B37 -> 46112 | C36: =SCALARS!C37 -> 3013.4956 | D36: =J36/K36 -> 3013.4777 | E36: =C36-C35 -> 0.0173 | F36: =C36-(D36+E36) -> 0.00055660784 | G36: 35246.58 | H36: 67831.76 | I36: 2390729862 | J36: 106210000 | K36: =I36/H36 -> 35244.992 | L36: =J36/G36 -> 3013.342
A37: =SCALARS!A38 -> Wednesday | B37: =SCALARS!B38 -> 46113 | C37: =SCALARS!C38 -> 3013.5129 | D37: =J37/K37 -> 3013.5471 | E37: =C37-C36 -> 0.0173 | G37: 35246.58 | H37: 68149.22 | I37: 2.4018635e+09 | J37: 106210000 | K37: =I37/H37 -> 35244.181 | L37: =J37/G37 -> 3013.342
A38: =SCALARS!A39 -> Thursday | B38: =SCALARS!B39 -> 46114 | C38: =SCALARS!C39 -> 3013.5302 | D38: =J38/K38 -> 3013.5644 | E38: =C38-C39 -> -0.0173 | G38: 35246.58 | H38: 66994.87 | I38: 2.3611658e+09 | J38: 106210000 | K38: =I38/H38 -> 35243.978 | L38: =J38/G38 -> 3013.342
A39: =SCALARS!A40 -> Friday | B39: =SCALARS!B40 -> 46115 | C39: =SCALARS!C40 -> 3013.5475 | E39: =C39-C40 -> -0.0173 | F39: HOLIDAY
A40: =SCALARS!A41 -> Saturday | B40: =SCALARS!B41 -> 46116 | C40: =SCALARS!C41 -> 3013.5648
A41: =SCALARS!A42 -> Sunday | B41: =SCALARS!B42 -> 46117 | C41: =SCALARS!C42 -> 3013.5821
A42: =SCALARS!A43 -> Monday | B42: =SCALARS!B43 -> 46118 | C42: =SCALARS!C43 -> 3013.5994 | D42: =J42/K42 -> 3013.5818 | E42: =C42-C41 -> 0.0173 | F42: =C42-(D42+E42) -> 0.00032765429 | G42: 36948.88 | H42: 69766.87 | I42: 2.5776116e+09 | J42: 111340000 | K42: =I42/H42 -> 36946.069 | L42: =J42/G42 -> 3013.3525
A43: =SCALARS!A44 -> Tuesday | B43: =SCALARS!B44 -> 46119 | C43: =SCALARS!C44 -> 3013.6167 | D43: =J43/K43 -> 3013.5991 | E43: =C43-C42 -> 0.0173 | F43: =C43-(D43+E43) -> 0.00028913147 | G43: 36451.14 | H43: 68612.35 | I43: 2.5007907e+09 | J43: 109840000 | K43: =I43/H43 -> 36448.113 | L43: =J43/G43 -> 3013.3488
A44: =SCALARS!A45 -> Wednesday | B44: =SCALARS!B45 -> 46120 | C44: =SCALARS!C45 -> 3013.634 | D44: =J44/K44 -> 3013.6107 | E44: =C44-C43 -> 0.0173 | G44: 35402.56 | H44: 71239.5 | I44: 2.5218353e+09 | J44: 106680000 | K44: =I44/H44 -> 35399.397 | L44: =J44/G44 -> 3013.3414
A45: =SCALARS!A46 -> Thursday | B45: =SCALARS!B46 -> 46121 | C45: =SCALARS!C46 -> 3013.6513 | D45: =J45/K45 -> 3013.6685 | E45: =C45-C46 -> -0.0173 | F45: =C45-(D45+E45) -> 0.0001448763 | G45: 35468.926 | H45: 72005.03 | I45: 2.5536643e+09 | J45: 106880000 | K45: =I45/H45 -> 35465.082 | L45: =J45/G45 -> 3013.3419
A46: =SCALARS!A47 -> Friday | B46: =SCALARS!B47 -> 46122 | C46: =SCALARS!C47 -> 3013.6686 | D46: =J46/K46 -> 3013.6858 | E46: =C46-C47 -> -0.0173 | F46: =C46-(D46+E46) -> 0.00010584839 | G46: 35518.699 | H46: 73109.73 | I46: 2.5964666e+09 | J46: 107030000 | K46: =I46/H46 -> 35514.651 | L46: =J46/G46 -> 3013.3424
A47: =SCALARS!A48 -> Saturday | B47: =SCALARS!B48 -> 46123 | C47: =SCALARS!C48 -> 3013.6859
A48: =SCALARS!A49 -> Sunday | B48: =SCALARS!B49 -> 46124 | C48: =SCALARS!C49 -> 3013.7032
A49: =SCALARS!A50 -> Monday | B49: =SCALARS!B50 -> 46125 | C49: =SCALARS!C50 -> 3013.7205 | D49: =J49/K49 -> 3013.7031 | E49: =C49-C48 -> 0.0173 | F49: =C49-(D49+E49) -> 6.6731458e-05 | G49: 34655.968 | H49: 72892.55 | I49: 2.5258523e+09 | J49: 104430000 | K49: =I49/H49 -> 34651.721 | L49: =J49/G49 -> 3013.3338
A50: =SCALARS!A51 -> Tuesday | B50: =SCALARS!B51 -> 46126 | C50: =SCALARS!C51 -> 3013.7378 | D50: =J50/K50 -> 3013.7205 | E50: =C50-C49 -> 0.0173 | F50: =C50-(D50+E50) -> 2.7515769e-05 | G50: 36179.011 | H50: 74270.1 | I50: 2.6866879e+09 | J50: 109020000 | K50: =I50/H50 -> 36174.556 | L50: =J50/G50 -> 3013.3494
A51: =SCALARS!A52 -> Wednesday | B51: =SCALARS!B52 -> 46127 | C51: =SCALARS!C52 -> 3013.7551 | D51: =J51/K51 -> 3013.7378 | E51: =C51-C50 -> 0.0173 | F51: =C51-(D51+E51) -> -1.1790862e-05 | G51: 35614.924 | H51: 74853.53 | I51: 2.665554e+09 | J51: 107320000 | K51: =I51/H51 -> 35610.264 | L51: =J51/G51 -> 3013.3435
A52: =SCALARS!A53 -> Thursday | B52: =SCALARS!B53 -> 46128 | C52: =SCALARS!C53 -> 3013.7724 | D52: =J52/K52 -> 3013.7898 | E52: =C52-C53 -> -0.0173 | F52: =C52-(D52+E52) -> -0.00013032408 | G52: 35249.929 | H52: 75088.35 | I52: 2.6464634e+09 | J52: 106220000 | K52: =I52/H52 -> 35244.661 | L52: =J52/G52 -> 3013.3394
A53: =SCALARS!A54 -> Friday | B53: =SCALARS!B54 -> 46129 | C53: =SCALARS!C54 -> 3013.7897 | D53: =J53/K53 -> 3013.8072 | E53: =C53-C54 -> -0.0173 | F53: =C53-(D53+E53) -> -0.00017003391 | G53: 36770.587 | H53: 77331.74 | I53: 2.8434191e+09 | J53: 110815000 | K53: =I53/H53 -> 36769.108 | L53: =J53/G53 -> 3013.6859
A54: =SCALARS!A55 -> Saturday | B54: =SCALARS!B55 -> 46130 | C54: =SCALARS!C55 -> 3013.807
A55: =SCALARS!A56 -> Sunday | B55: =SCALARS!B56 -> 46131 | C55: =SCALARS!C56 -> 3013.8243
A56: =SCALARS!A57 -> Monday | B56: =SCALARS!B57 -> 46132 | C56: =SCALARS!C57 -> 3013.8416 | D56: =J56/K56 -> 3013.8244 | E56: =C56-C55 -> 0.0173 | F56: =C56-(D56+E56) -> -0.00013005251 | G56: 36770.587 | H56: 76318.82 | I56: 2.8061588e+09 | J56: 110815000 | K56: =I56/H56 -> 36768.897 | L56: =J56/G56 -> 3013.6859
A57: =SCALARS!A58 -> Tuesday | B57: =SCALARS!B58 -> 46133 | C57: =SCALARS!C58 -> 3013.8589 | D57: =J57/K57 -> 3013.8417 | E57: =C57-C56 -> 0.0173 | F57: =C57-(D57+E57) -> -0.00012984656 | G57: 36578.141 | H57: 75462.34 | I57: 2.7601287e+09 | J57: 110235000 | K57: =I57/H57 -> 36576.241 | L57: =J57/G57 -> 3013.6851
A58: =SCALARS!A59 -> Wednesday | B58: =SCALARS!B59 -> 46134 | C58: =SCALARS!C59 -> 3013.8762 | D58: =J58/K58 -> 3013.859 | E58: =C58-C57 -> 0.0173 | F58: =C58-(D58+E58) -> -9.8602617e-05 | G58: 36729.111 | H58: 78919.77 | I58: 2.8984864e+09 | J58: 110690000 | K58: =I58/H58 -> 36727 | L58: =J58/G58 -> 3013.6858
A59: =SCALARS!A60 -> Thursday | B59: =SCALARS!B60 -> 46135 | C59: =SCALARS!C60 -> 3013.8935 | D59: =J59/K59 -> 3013.9108 | E59: =C59-C60 -> -0.0173 | F59: =C59-(D59+E59) -> -1.0603222e-05 | G59: 37644.88 | H59: 77774.85 | I59: 2.9276104e+09 | J59: 113450000 | K59: =I59/H59 -> 37642.123 | L59: =J59/G59 -> 3013.69
A60: =SCALARS!A61 -> Friday | B60: =SCALARS!B61 -> 46136 | C60: =SCALARS!C61 -> 3013.9108 | D60: =J60/K60 -> 3013.9281 | E60: =C60-C61 -> -0.0173 | F60: =C60-(D60+E60) -> 1.8751833e-05 | G60: 37528.752 | H60: 77638.21 | I60: 2.9134343e+09 | J60: 113100000 | K60: =I60/H60 -> 37525.779 | L60: =J60/G60 -> 3013.6893
A61: =SCALARS!A62 -> Saturday | B61: =SCALARS!B62 -> 46137 | C61: =SCALARS!C62 -> 3013.9281
A62: =SCALARS!A63 -> Sunday | B62: =SCALARS!B63 -> 46138 | C62: =SCALARS!C63 -> 3013.9454
A63: =SCALARS!A64 -> Monday | B63: =SCALARS!B64 -> 46139 | C63: =SCALARS!C64 -> 3013.9627 | D63: =J63/K63 -> 3013.9454 | E63: =C63-C62 -> 0.0173 | F63: =C63-(D63+E63) -> 4.9074203e-05 | G63: 36964.704 | H63: 76762.25 | I63: 2.8372494e+09 | J63: 111400000 | K63: =I63/H63 -> 36961.52 | L63: =J63/G63 -> 3013.6857
A64: =SCALARS!A65 -> Tuesday | B64: =SCALARS!B65 -> 46140 | C64: =SCALARS!C65 -> 3013.98 | D64: =J64/K64 -> 3013.9627 | E64: =C64-C63 -> 0.0173 | F64: =C64-(D64+E64) -> 2.0008863e-05 | G64: 37505.524 | H64: 76184.66 | I64: 2.8570865e+09 | J64: 113030000 | K64: =I64/H64 -> 37502.123 | L64: =J64/G64 -> 3013.6894
A65: =SCALARS!A66 -> Wednesday | B65: =SCALARS!B66 -> 46141 | C65: =SCALARS!C66 -> 3013.9973 | D65: =J65/K65 -> 3013.98 | E65: =C65-C64 -> 0.0173 | F65: =C65-(D65+E65) -> -9.0641579e-06 | G65: 37104.877 | H65: 75446.31 | I65: 2.799342e+09 | J65: 111830000 | K65: =I65/H65 -> 37103.763 | L65: =J65/G65 -> 3013.8895
A66: =SCALARS!A67 -> Thursday | B66: =SCALARS!B67 -> 46142 | C66: =SCALARS!C67 -> 3014.0146 | D66: =J66/K66 -> 3014.032 | E66: =C66-C67 -> -0.0173 | F66: =C66-(D66+E66) -> -9.679978e-05 | G66: 37021.93 | H66: 76416.86 | I66: 2.8289657e+09 | J66: 111580000 | K66: =I66/H66 -> 37020.178 | L66: =J66/G66 -> 3013.8893
A67: =SCALARS!A68 -> Friday | B67: =SCALARS!B68 -> 46143 | C67: =SCALARS!C68 -> 3014.0319 | D67: =J67/K67 -> 3014.0493 | E67: =C67-C68 -> -0.0173 | F67: =C67-(D67+E67) -> -9.196758e-05 | G67: 38149.987 | H67: 78415.26 | I67: 2.9913866e+09 | J67: 114980000 | K67: =I67/H67 -> 38148.016 | L67: =J67/G67 -> 3013.8936
A68: =SCALARS!A69 -> Saturday | B68: =SCALARS!B69 -> 46144 | C68: =SCALARS!C69 -> 3014.0492
A69: =SCALARS!A70 -> Sunday | B69: =SCALARS!B70 -> 46145 | C69: =SCALARS!C70 -> 3014.0665
A70: =SCALARS!A71 -> Monday | B70: =SCALARS!B71 -> 46146 | C70: =SCALARS!C71 -> 3014.0838 | D70: =J70/K70 -> 3014.0666 | E70: =C70-C69 -> 0.0173 | F70: =C70-(D70+E70) -> -8.7163e-05 | G70: 38149.987 | H70: 80004.53 | I70: 3.0519966e+09 | J70: 114980000 | K70: =I70/H70 -> 38147.797 | L70: =J70/G70 -> 3013.8936
A71: =SCALARS!A72 -> Tuesday | B71: =SCALARS!B72 -> 46147 | C71: =SCALARS!C72 -> 3014.1011 | D71: =J71/K71 -> 3014.0839 | E71: =C71-C70 -> 0.0173 | F71: =C71-(D71+E71) -> -5.4556685e-05 | G71: 39281.349 | H71: 81561.14 | I71: 3.2036346e+09 | J71: 118390000 | K71: =I71/H71 -> 39278.934 | L71: =J71/G71 -> 3013.8985
A72: =SCALARS!A73 -> Wednesday | B72: =SCALARS!B73 -> 46148 | C72: =SCALARS!C73 -> 3014.1184 | D72: =J72/K72 -> 3014.1011 | E72: =C72-C71 -> 0.0173 | F72: =C72-(D72+E72) -> -2.1984807e-05 | G72: 39281.349 | H72: 81354.77 | I72: 3.1955103e+09 | J72: 118390000 | K72: =I72/H72 -> 39278.709 | L72: =J72/G72 -> 3013.8985
A73: =SCALARS!A74 -> Thursday | B73: =SCALARS!B74 -> 46149 | C73: =SCALARS!C74 -> 3014.1357 | D73: =J73/K73 -> 3014.1529 | E73: =C73-C74 -> -0.0173 | F73: =C73-(D73+E73) -> 7.60366e-05 | G73: 39123.756 | H73: 80080.21 | I73: 3.1327734e+09 | J73: 117915000 | K73: =I73/H73 -> 39120.444 | L73: =J73/G73 -> 3013.8977
A74: =SCALARS!A75 -> Friday | B74: =SCALARS!B75 -> 46150 | C74: =SCALARS!C75 -> 3014.153 | D74: =J74/K74 -> 3014.1702 | E74: =C74-C75 -> -0.0173 | F74: =C74-(D74+E74) -> 0.00010914824 | G74: 38791.988 | H74: 80066.34 | I74: 3.1056495e+09 | J74: 116915000 | K74: =I74/H74 -> 38788.453 | L74: =J74/G74 -> 3013.8955
A75: =SCALARS!A76 -> Saturday | B75: =SCALARS!B76 -> 46151 | C75: =SCALARS!C76 -> 3014.1703
A76: =SCALARS!A77 -> Sunday | B76: =SCALARS!B77 -> 46152 | C76: =SCALARS!C77 -> 3014.1876
A77: =SCALARS!A78 -> Monday | B77: =SCALARS!B78 -> 46153 | C77: =SCALARS!C78 -> 3014.2049 | D77: =J77/K77 -> 3014.1875 | E77: =C77-C76 -> 0.0173 | F77: =C77-(D77+E77) -> 0.00014216893 | G77: 38791.988 | H77: 81915.01 | I77: 3.1773383e+09 | J77: 116915000 | K77: =I77/H77 -> 38788.231 | L77: =J77/G77 -> 3013.8955
A78: =SCALARS!A79 -> Tuesday | B78: =SCALARS!B79 -> 46154 | C78: =SCALARS!C79 -> 3014.2222 | D78: =J78/K78 -> 3014.2047 | E78: =C78-C77 -> 0.0173 | F78: =C78-(D78+E78) -> 0.00017717634 | G78: 37738.636 | H78: 80757.7 | I78: 3.0473646e+09 | J78: 113740000 | K78: =I78/H78 -> 37734.663 | L78: =J78/G78 -> 3013.8874
A79: =SCALARS!A80 -> Wednesday | B79: =SCALARS!B80 -> 46155 | C79: =SCALARS!C80 -> 3014.2395 | D79: =J79/K79 -> 3014.222 | E79: =C79-C78 -> 0.0173 | F79: =C79-(D79+E79) -> 0.00015698899 | G79: 35510.851 | H79: 79496.91 | I79: 2.8226709e+09 | J79: 107025000 | K79: =I79/H79 -> 35506.674 | L79: =J79/G79 -> 3013.8675
A80: =SCALARS!A81 -> Thursday | B80: =SCALARS!B81 -> 46156 | C80: =SCALARS!C81 -> 3014.2568 | D80: =J80/K80 -> 3014.274 | E80: =C80-C81 -> -0.0173 | F80: =C80-(D80+E80) -> 9.5944442e-05 | G80: 35394.735 | H80: 81512.01 | I80: 2.8847058e+09 | J80: 106675000 | K80: =I80/H80 -> 35389.948 | L80: =J80/G80 -> 3013.8663
A81: =SCALARS!A82 -> Friday | B81: =SCALARS!B82 -> 46157 | C81: =SCALARS!C82 -> 3014.2741 | D81: =J81/K81 -> 3014.2913 | E81: =C81-C82 -> -0.0173 | F81: =C81-(D81+E81) -> 7.5831071e-05 | G81: 34731.225 | H81: 79097.04 | I81: 2.7467427e+09 | J81: 104675000 | K81: =I81/H81 -> 34726.239 | L81: =J81/G81 -> 3013.8585
A82: =SCALARS!A83 -> Saturday | B82: =SCALARS!B83 -> 46158 | C82: =SCALARS!C83 -> 3014.2914
A83: =SCALARS!A84 -> Sunday | B83: =SCALARS!B84 -> 46159 | C83: =SCALARS!C84 -> 3014.3087
A84: =SCALARS!A85 -> Monday | B84: =SCALARS!B85 -> 46160 | C84: =SCALARS!C85 -> 3014.326 | D84: =J84/K84 -> 3014.3087 | E84: =C84-C83 -> 0.0173 | F84: =C84-(D84+E84) -> -1.5987545e-05 | G84: 33301.37 | H84: 76676.08 | I84: 2.5530214e+09 | J84: 100365000 | K84: =I84/H84 -> 33296.191 | L84: =J84/G84 -> 3013.84
A85: =SCALARS!A86 -> Tuesday | B85: =SCALARS!B86 -> 46161 | C85: =SCALARS!C86 -> 3014.3433 | D85: =J85/K85 -> 3014.3261 | E85: =C85-C84 -> 0.0173 | F85: =C85-(D85+E85) -> -0.00010787712 | G85: 33301.37 | H85: 76820.77 | I85: 2.5578243e+09 | J85: 100365000 | K85: =I85/H85 -> 33295.999 | L85: =J85/G85 -> 3013.84
A86: =SCALARS!A87 -> Wednesday | B86: =SCALARS!B87 -> 46162 | C86: =SCALARS!C87 -> 3014.3606 | D86: =J86/K86 -> 3014.3435 | E86: =C86-C85 -> 0.0173 | F86: =C86-(D86+E86) -> -0.00019990165 | G86: 33301.37 | H86: 77467.44 | I86: 2.5793409e+09 | J86: 100365000 | K86: =I86/H86 -> 33295.807 | L86: =J86/G86 -> 3013.84
A87: =SCALARS!A88 -> Thursday | B87: =SCALARS!B88 -> 46163 | C87: =SCALARS!C88 -> 3014.3779 | D87: =J87/G87 -> 3013.8405 | F87: =C87-D87 -> 0.53739654 | G87: 33337.862 | H87: 77515.76 | I87: 2.5837189e+09 | J87: 100475000 | K87: =I87/H87 -> 33331.53 | L87: =J87/K87 -> 3014.4131
A88: =SCALARS!A89 -> Friday | B88: =SCALARS!B89 -> 46164 | C88: =SCALARS!C89 -> 3014.3952 | D88: =J88/G88 -> 3013.8405 | F88: =C88-D88 -> 0.55469654 | G88: 33337.862 | H88: 75996.63 | I88: 2.5330693e+09 | J88: 100475000 | K88: =I88/H88 -> 33331.338 | L88: =J88/K88 -> 3014.4305
A89: =SCALARS!A90 -> Saturday | B89: =SCALARS!B90 -> 46165 | C89: =SCALARS!C90 -> 3014.4125
A90: =SCALARS!A91 -> Sunday | B90: =SCALARS!B91 -> 46166 | C90: =SCALARS!C91 -> 3014.4298
A91: =SCALARS!A92 -> Monday | B91: =SCALARS!B92 -> 46167 | C91: =SCALARS!C92 -> 3014.4471 | D91: SHS/BTC | L91: SHS/ADJ BTC
A92: =SCALARS!A93 -> Tuesday | B92: =SCALARS!B93 -> 46168 | C92: =SCALARS!C93 -> 3014.4644 | D92: =J92/G92 -> 3013.8405 | F92: =C92-D92 -> 0.62389654 | G92: 33337.862 | H92: 75814.45 | I92: 2.5269825e+09 | J92: 100475000 | K92: =I92/H92 -> 33331.145 | L92: =J92/K92 -> 3014.4479
A93: =SCALARS!A94 -> Wednesday | B93: =SCALARS!B94 -> 46169 | C93: =SCALARS!C94 -> 3014.4817 | D93: =J93/G93 -> 3013.8362 | F93: =C93-D93 -> 0.64545646 | G93: 33105.647 | H93: 74889.84 | I93: 2.4787593e+09 | J93: 99775000 | K93: =I93/H93 -> 33098.74 | L93: =J93/K93 -> 3014.4652
A94: =SCALARS!A95 -> Thursday | B94: =SCALARS!B95 -> 46170 | C94: =SCALARS!C95 -> 3014.499 | D94: =J94/G94 -> 3014.3826 | F94: =C94-D94 -> 0.11643591 | G94: 33099.647 | H94: 73380.52 | I94: 2428760676 | J94: 99775000 | K94: =I94/H94 -> 33098.167 | L94: =J94/K94 -> 3014.5174
A95: =SCALARS!A96 -> Friday | B95: =SCALARS!B96 -> 46171 | C95: =SCALARS!C96 -> 3014.5163 | D95: =J95/G95 -> 3014.3822 | F95: =C95-D95 -> 0.1341441 | G95: 33000.129 | H95: 73398.11 | I95: 2.4220244e+09 | J95: 99475000 | K95: =I95/H95 -> 32998.458 | L95: =J95/K95 -> 3014.5348
A96: =SCALARS!A97 -> Saturday | B96: =SCALARS!B97 -> 46172 | C96: =SCALARS!C97 -> 3014.5336
A97: =SCALARS!A98 -> Sunday | B97: =SCALARS!B98 -> 46173 | C97: =SCALARS!C98 -> 3014.5509
A98: =SCALARS!A99 -> Monday | B98: =SCALARS!B99 -> 46174 | C98: =SCALARS!C99 -> 3014.5682 | D98: =J98/G98 -> 3014.3814 | F98: =C98-D98 -> 0.18684564 | G98: 32827.631 | H98: 71428.74 | I98: 2.3447034e+09 | J98: 98955000 | K98: =I98/H98 -> 32825.77 | L98: =J98/K98 -> 3014.5523
A99: =SCALARS!A100 -> Tuesday | B99: =SCALARS!B100 -> 46175 | C99: =SCALARS!C100 -> 3014.5855 | D99: =J99/G99 -> 3014.3801 | F99: =C99-D99 -> 0.20544761 | G99: 32578.838 | H99: 66991.23 | I99: 2.1823591e+09 | J99: 98205000 | K99: =I99/H99 -> 32576.788 | L99: =J99/K99 -> 3014.5698
A100: =SCALARS!A101 -> Wednesday | B100: =SCALARS!B101 -> 46176 | C100: =SCALARS!C101 -> 3014.6028 | D100: =J100/G100 -> 3014.3801 | F100: =C100-D100 -> 0.22274761 | G100: 32578.838 | H100: 65682.1 | I100: 2.1396994e+09 | J100: 98205000 | K100: =I100/H100 -> 32576.599 | L100: =J100/K100 -> 3014.5873
A101: =SCALARS!A102 -> Thursday | B101: =SCALARS!B102 -> 46177 | C101: =SCALARS!C102 -> 3014.6201 | D101: =J101/G101 -> 3014.378 | F101: =C101-D101 -> 0.24214187 | G101: 32253.752 | H101: 63732.67 | I101: 2.0554392e+09 | J101: 97225000 | K101: =I101/H101 -> 32250.951 | L101: =J101/K101 -> 3014.6397
A102: =SCALARS!A103 -> Friday | B102: =SCALARS!B103 -> 46178 | C102: =SCALARS!C103 -> 3014.6374 | D102: =J102/G102 -> 3014.378 | F102: =C102-D102 -> 0.25944187 | G102: 32253.752 | H102: 59673.45 | I102: 1.9245144e+09 | J102: 97225000 | K102: =I102/H102 -> 32250.764 | L102: =J102/K102 -> 3014.6572
...

Sheet BTCW
A1: BTCW - Bitcoin ETF | WisdomTree
A5: DOW | B5: Date | C5: TODAY'S RATIO | D5: SHS/ADJ BTC | E5: DIFF | F5: TOTAL ASSETS | G5: SHARES OUTSTANDING | H5: BITCOIN IN TRUST | I5: REF PRICE | J5: ADJ BTC | K5: SHS/BTC
A6: =SCALARS!A7 -> Sunday | B6: =SCALARS!B7 -> 46082 | C6: =SCALARS!G7 -> 945.3954
A7: =SCALARS!A8 -> Monday | B7: =SCALARS!B8 -> 46083 | C7: =SCALARS!G8 -> 945.4019
A8: =SCALARS!A9 -> Tuesday | B8: =SCALARS!B9 -> 46084 | C8: =SCALARS!G9 -> 945.4084
A9: =SCALARS!A10 -> Wednesday | B9: =SCALARS!B10 -> 46085 | C9: =SCALARS!G10 -> 945.4149
A10: =SCALARS!A11 -> Thursday | B10: =SCALARS!B11 -> 46086 | C10: =SCALARS!G11 -> 945.4214
A11: =SCALARS!A12 -> Friday | B11: =SCALARS!B12 -> 46087 | C11: =SCALARS!G12 -> 945.4279
A12: =SCALARS!A13 -> Saturday | B12: =SCALARS!B13 -> 46088 | C12: =SCALARS!G13 -> 945.4344
A13: =SCALARS!A14 -> Sunday | B13: =SCALARS!B14 -> 46089 | C13: =SCALARS!G14 -> 945.4409
A14: =SCALARS!A15 -> Monday | B14: =SCALARS!B15 -> 46090 | C14: =SCALARS!G15 -> 945.4474 | D14: =G14/J14 -> 945.44608 | E14: =C14-D14 -> 0.0013206133 | F14: 148956.67 | G14: 2045000 | H14: 2163 | I14: =ARKB!H14 -> 68865.77 | J14: =1000*F14/I14 -> 2163.0001 | K14: =G14/H14 -> 945.44614
A15: =SCALARS!A16 -> Tuesday | B15: =SCALARS!B16 -> 46091 | C15: =SCALARS!G16 -> 945.4539 | D15: =G15/J15 -> 945.45128 | E15: =C15-D15 -> 0.0026161758 | F15: 151451.03 | G15: 2045000 | H15: 2163 | I15: =ARKB!H15 -> 70019.35 | J15: =1000*F15/I15 -> 2162.9882 | K15: =G15/H15 -> 945.44614
A16: =SCALARS!A17 -> Wednesday | B16: =SCALARS!B17 -> 46092 | C16: =SCALARS!G17 -> 945.4604 | D16: =G16/J16 -> 945.45722 | E16: =C16-D16 -> 0.0031774926 | F16: 152706.94 | G16: 2045000 | I16: =ARKB!H16 -> 70600.43 | J16: =1000*F16/I16 -> 2162.9746
A17: =SCALARS!A18 -> Thursday | B17: =SCALARS!B18 -> 46093 | C17: =SCALARS!G18 -> 945.4669 | D17: =G17/J17 -> 945.46415 | E17: =C17-D17 -> 0.0027502779 | F17: 151802.31 | G17: 2045000 | H17: 2163 | I17: =ARKB!H17 -> 70182.71 | J17: =1000*F17/I17 -> 2162.9588 | K17: =G17/H17 -> 945.44614
A18: =SCALARS!A19 -> Friday | B18: =SCALARS!B19 -> 46094 | C18: =SCALARS!G19 -> 945.4734 | D18: =G18/J18 -> 945.46952 | E18: =C18-D18 -> 0.003881741 | F18: 153901.15 | G18: 2045000 | H18: 2163 | I18: =ARKB!H18 -> 71153.47 | J18: =1000*F18/I18 -> 2162.9465 | K18: =G18/H18 -> 945.44614
A19: =SCALARS!A20 -> Saturday | B19: =SCALARS!B20 -> 46095 | C19: =SCALARS!G20 -> 945.4799 | F19: 0
A20: =SCALARS!A21 -> Sunday | B20: =SCALARS!B21 -> 46096 | C20: =SCALARS!G21 -> 945.4864 | F20: 0
A21: =SCALARS!A22 -> Monday | B21: =SCALARS!B22 -> 46097 | C21: =SCALARS!G22 -> 945.4929 | D21: =G21/J21 -> 945.48507 | E21: =C21-D21 -> 0.0078334826 | F21: 160213.8 | G21: 2045000 | H21: 2163 | I21: =ARKB!H21 -> 74073.23 | J21: =1000*F21/I21 -> 2162.9109 | K21: =G21/H21 -> 945.44614
A22: =SCALARS!A23 -> Tuesday | B22: =SCALARS!B23 -> 46098 | C22: =SCALARS!G23 -> 945.4994 | F22: 0
A23: =SCALARS!A24 -> Wednesday | B23: =SCALARS!B24 -> 46099 | C23: =SCALARS!G24 -> 945.5059 | D23: =G23/J23 -> 945.50241 | E23: =C23-D23 -> 0.0034861887 | F23: 154015.77 | G23: 2045000 | I23: =ARKB!H23 -> 71208.94 | J23: =1000*F23/I23 -> 2162.8713
A24: =SCALARS!A25 -> Thursday | B24: =SCALARS!B25 -> 46100 | C24: =SCALARS!G25 -> 945.5124 | D24: =G24/J24 -> 945.51045 | E24: =C24-D24 -> 0.0019541331 | F24: 152032.38 | G24: 2045000 | I24: =ARKB!H24 -> 70292.52 | J24: =1000*F24/I24 -> 2162.8529
A25: =SCALARS!A26 -> Friday | B25: =SCALARS!B26 -> 46101 | C25: =SCALARS!G26 -> 945.5189 | D25: =G25/J25 -> 945.51764 | E25: =C25-D25 -> 0.0012622806 | F25: 151124.13 | G25: 2045000 | I25: =ARKB!H25 -> 69873.12 | J25: =1000*F25/I25 -> 2162.8364
A26: =SCALARS!A27 -> Saturday | B26: =SCALARS!B27 -> 46102 | C26: =SCALARS!G27 -> 945.5254 | F26: 0
A27: =SCALARS!A28 -> Sunday | B27: =SCALARS!B28 -> 46103 | C27: =SCALARS!G28 -> 945.5319 | F27: 0
A28: =SCALARS!A29 -> Monday | B28: =SCALARS!B29 -> 46104 | C28: =SCALARS!G29 -> 945.5384 | F28: 0
A29: =SCALARS!A30 -> Tuesday | B29: =SCALARS!B30 -> 46105 | C29: =SCALARS!G30 -> 945.5449 | D29: =G29/J29 -> 945.5446 | E29: =C29-D29 -> 0.00030466733 | F29: 150208.32 | G29: 2045000 | I29: =ARKB!H29 -> 69451.67 | J29: =1000*F29/I29 -> 2162.7748
A30: =SCALARS!A31 -> Wednesday | B30: =SCALARS!B31 -> 46106 | C30: =SCALARS!G31 -> 945.5514 | D30: =G30/J30 -> 945.54782 | E30: =C30-D30 -> 0.0035774303 | F30: 153305.02 | G30: 2045000 | I30: =ARKB!H30 -> 70883.73 | J30: =1000*F30/I30 -> 2162.7674
A31: =SCALARS!A32 -> Thursday | B31: =SCALARS!B32 -> 46107 | C31: =SCALARS!G32 -> 945.5579 | D31: =G31/J31 -> 945.56005 | E31: =C31-D31 -> -0.0021524585 | F31: 148101.93 | G31: 2045000 | H31: 2163 | I31: =ARKB!H31 -> 68478.86 | J31: =1000*F31/I31 -> 2162.7394
A32: =SCALARS!A33 -> Friday | B32: =SCALARS!B33 -> 46108 | C32: =SCALARS!G33 -> 945.5644 | F32: 0
A33: =SCALARS!A34 -> Saturday | B33: =SCALARS!B34 -> 46109 | C33: =SCALARS!G34 -> 945.5709 | F33: 0
A34: =SCALARS!A35 -> Sunday | B34: =SCALARS!B35 -> 46110 | C34: =SCALARS!G35 -> 945.5774 | F34: 0
A35: =SCALARS!A36 -> Monday | B35: =SCALARS!B36 -> 46111 | C35: =SCALARS!G36 -> 945.5839 | D35: =G35/J35 -> 945.59143 | E35: =C35-D35 -> -0.0075319272 | F35: 143504.85 | G35: 2045000 | H35: 2163 | I35: =ARKB!H35 -> 66355.48 | J35: =1000*F35/I35 -> 2162.6677
A36: =SCALARS!A37 -> Tuesday | B36: =SCALARS!B37 -> 46112 | C36: =SCALARS!G37 -> 945.5904 | D36: =G36/J36 -> 945.59339 | E36: =C36-D36 -> -0.0029850157 | F36: 146697.25 | G36: 2045000 | I36: =ARKB!H36 -> 67831.76 | J36: =1000*F36/I36 -> 2162.6632
A37: =SCALARS!A38 -> Wednesday | B37: =SCALARS!B38 -> 46113 | C37: =SCALARS!G38 -> 945.5969 | D37: =G37/J37 -> 945.5989 | E37: =C37-D37 -> -0.0019966159 | F37: 147382.95 | G37: 2045000 | H37: 2163 | I37: =ARKB!H37 -> 68149.22 | J37: =1000*F37/I37 -> 2162.6506 | K37: =G37/H37 -> 945.44614
A38: =SCALARS!A39 -> Thursday | B38: =SCALARS!B39 -> 46114 | C38: =SCALARS!G39 -> 945.6034 | D38: =G38/J38 -> 945.60904 | E38: =C38-D38 -> -0.0056408706 | F38: 144884.94 | G38: 2045000 | H38: 2163 | I38: =ARKB!H38 -> 66994.87 | J38: =1000*F38/I38 -> 2162.6274 | K38: =G38/H38 -> 945.44614
A39: =SCALARS!A40 -> Friday | B39: =SCALARS!B40 -> 46115 | C39: =SCALARS!G40 -> 945.6099 | F39: 0
A40: =SCALARS!A41 -> Saturday | B40: =SCALARS!B41 -> 46116 | C40: =SCALARS!G41 -> 945.6164 | F40: 0
A41: =SCALARS!A42 -> Sunday | B41: =SCALARS!B42 -> 46117 | C41: =SCALARS!G42 -> 945.6229 | F41: 0
A42: =SCALARS!A43 -> Monday | B42: =SCALARS!B43 -> 46118 | C42: =SCALARS!G43 -> 945.6294 | D42: =G42/J42 -> 945.63708 | E42: =C42-D42 -> -0.0076759105 | F42: 150875.27 | G42: 2045000 | H42: 2163 | I42: =ARKB!H42 -> 69766.87 | J42: =1000*F42/I42 -> 2162.5633 | K42: =G42/H42 -> 945.44614
A43: =SCALARS!A44 -> Tuesday | B43: =SCALARS!B44 -> 46119 | C43: =SCALARS!G44 -> 945.6359 | D43: =G43/J43 -> 945.64426 | E43: =C43-D43 -> -0.0083614382 | F43: 148377.42 | G43: 2045000 | H43: 2163 | I43: =ARKB!H43 -> 68612.35 | J43: =1000*F43/I43 -> 2162.5468 | K43: =G43/H43 -> 945.44614
A44: =SCALARS!A45 -> Wednesday | B44: =SCALARS!B45 -> 46120 | C44: =SCALARS!G45 -> 945.6424 | D44: =G44/J44 -> 945.64883 | E44: =C44-D44 -> -0.0064338386 | F44: 154058.01 | G44: 2045000 | H44: 2162 | I44: =ARKB!H44 -> 71239.5 | J44: =1000*F44/I44 -> 2162.5364 | K44: =G44/H44 -> 945.88344
A45: =SCALARS!A46 -> Thursday | B45: =SCALARS!B46 -> 46121 | C45: =SCALARS!G46 -> 945.6489 | D45: =G45/J45 -> 945.65476 | E45: =C45-D45 -> -0.0058639843 | F45: 155712.52 | G45: 2045000 | I45: =ARKB!H45 -> 72005.03 | J45: =1000*F45/I45 -> 2162.5228
A46: =SCALARS!A47 -> Friday | B46: =SCALARS!B47 -> 46122 | C46: =SCALARS!G47 -> 945.6554 | D46: =G46/J46 -> 945.66032 | E46: =C46-D46 -> -0.004920367 | F46: 158100.53 | G46: 2045000 | H46: 2162 | I46: =ARKB!H46 -> 73109.73 | J46: =1000*F46/I46 -> 2162.5101 | K46: =G46/H46 -> 945.88344
A47: =SCALARS!A48 -> Saturday | B47: =SCALARS!B48 -> 46123 | C47: =SCALARS!G48 -> 945.6619 | F47: 0
A48: =SCALARS!A49 -> Sunday | B48: =SCALARS!B49 -> 46124 | C48: =SCALARS!G49 -> 945.6684 | F48: 0
A49: =SCALARS!A50 -> Monday | B49: =SCALARS!B50 -> 46125 | C49: =SCALARS!G50 -> 945.6749 | D49: =G49/J49 -> 945.67997 | E49: =C49-D49 -> -0.0050745095 | F49: 157627.6 | G49: 2045000 | H49: 2162 | I49: =ARKB!H49 -> 72892.55 | J49: =1000*F49/I49 -> 2162.4652 | K49: =G49/H49 -> 945.88344 | P49: =J49-J50 -> 0.011093091
A50: =SCALARS!A51 -> Tuesday | B50: =SCALARS!B51 -> 46126 | C50: =SCALARS!G51 -> 945.6814 | D50: =G50/J50 -> 945.68483 | E50: =C50-D50 -> -0.0034257172 | F50: 160605.68 | G50: 2045000 | H50: 2162 | I50: =ARKB!H50 -> 74270.1 | J50: =1000*F50/I50 -> 2162.4541 | K50: =G50/H50 -> 945.88344 | P50: =J50-J51 -> 0.013233549
A51: =SCALARS!A52 -> Wednesday | B51: =SCALARS!B52 -> 46127 | C51: =SCALARS!G52 -> 945.6879 | D51: =G51/J51 -> 945.69061 | E51: =C51-D51 -> -0.0027130509 | F51: 161866.33 | G51: 2045000 | H51: 2163 | I51: =ARKB!H51 -> 74853.53 | J51: =1000*F51/I51 -> 2162.4408 | K51: =G51/H51 -> 945.44614 | P51: =J51-J52 -> 0.014041554
A52: =SCALARS!A53 -> Thursday | B52: =SCALARS!B53 -> 46128 | C52: =SCALARS!G53 -> 945.6944 | D52: =G52/J52 -> 945.69675 | E52: =C52-D52 -> -0.0023538211 | F52: 162373.06 | G52: 2045000 | I52: =ARKB!H52 -> 75088.35 | J52: =1000*F52/I52 -> 2162.4268 | P52: =J52-J53 -> 0.0079740436
A53: =SCALARS!A54 -> Friday | B53: =SCALARS!B54 -> 46129 | C53: =SCALARS!G54 -> 945.7009 | D53: =G53/J53 -> 945.70024 | E53: =C53-D53 -> 0.00065886778 | F53: 167223.61 | G53: 2045000 | I53: =ARKB!H53 -> 77331.74 | J53: =1000*F53/I53 -> 2162.4188 | P53: =J53-J54 -> 2162.4188
A54: =SCALARS!A55 -> Saturday | B54: =SCALARS!B55 -> 46130 | C54: =SCALARS!G55 -> 945.7074 | F54: 0
A55: =SCALARS!A56 -> Sunday | B55: =SCALARS!B56 -> 46131 | C55: =SCALARS!G56 -> 945.7139 | F55: 0
A56: =SCALARS!A57 -> Monday | B56: =SCALARS!B57 -> 46132 | C56: =SCALARS!G57 -> 945.7204 | D56: =G56/J56 -> 945.72129 | E56: =C56-D56 -> -0.00088766249 | F56: 165029.58 | G56: 2045000 | H56: 2162 | I56: =ARKB!H56 -> 76318.82 | J56: =1000*F56/I56 -> 2162.3707 | K56: =G56/H56 -> 945.88344
A57: =SCALARS!A58 -> Tuesday | B57: =SCALARS!B58 -> 46133 | C57: =SCALARS!G58 -> 945.7269 | D57: =G57/J57 -> 945.72919 | E57: =C57-D57 -> -0.0022857348 | F57: 163176.19 | G57: 2045000 | I57: =ARKB!H57 -> 75462.34 | J57: =1000*F57/I57 -> 2162.3526
A58: =SCALARS!A59 -> Wednesday | B58: =SCALARS!B59 -> 46134 | C58: =SCALARS!G59 -> 945.7334 | D58: =G58/J58 -> 945.7297 | E58: =C58-D58 -> 0.0036995237 | F58: 170652.28 | G58: 2045000 | H58: 2162 | I58: =ARKB!H58 -> 78919.77 | J58: =1000*F58/I58 -> 2162.3515 | K58: =G58/H58 -> 945.88344
A59: =SCALARS!A60 -> Thursday | B59: =SCALARS!B60 -> 46135 | C59: =SCALARS!G60 -> 945.7399 | D59: =G59/J59 -> 945.73792 | E59: =C59-D59 -> 0.0019808913 | F59: 174342.89 | G59: 2120000 | I59: =ARKB!H59 -> 77774.85 | J59: =1000*F59/I59 -> 2241.6358
A60: =SCALARS!A61 -> Friday | B60: =SCALARS!B61 -> 46136 | C60: =SCALARS!G61 -> 945.7464 | D60: =G60/J60 -> 945.74462 | E60: =C60-D60 -> 0.0017812053 | F60: 174035.36 | G60: 2120000 | H60: 2241 | I60: =ARKB!H60 -> 77638.21 | J60: =1000*F60/I60 -> 2241.6199 | K60: =G60/H60 -> 946.00625
A61: =SCALARS!A62 -> Saturday | B61: =SCALARS!B62 -> 46137 | C61: =SCALARS!G62 -> 945.7529 | F61: 0
A62: =SCALARS!A63 -> Sunday | B62: =SCALARS!B63 -> 46138 | C62: =SCALARS!G63 -> 945.7594 | F62: 0
A63: =SCALARS!A64 -> Monday | B63: =SCALARS!B64 -> 46139 | C63: =SCALARS!G64 -> 945.7659 | D63: =G63/J63 -> 945.76589 | E63: =C63-D63 -> 7.0898047e-06 | F63: 172067.92 | G63: 2120000 | H63: 2242 | I63: =ARKB!H63 -> 76762.25 | J63: =1000*F63/I63 -> 2241.5695 | K63: =G63/H63 -> 945.5843
A64: =SCALARS!A65 -> Tuesday | B64: =SCALARS!B65 -> 46140 | C64: =SCALARS!G65 -> 945.7724 | D64: =G64/J64 -> 945.7736 | E64: =C64-D64 -> -0.0012012885 | F64: 170771.82 | G64: 2120000 | H64: 2242 | I64: =ARKB!H64 -> 76184.66 | J64: =1000*F64/I64 -> 2241.5513 | K64: =G64/H64 -> 945.5843
A65: =SCALARS!A66 -> Wednesday | B65: =SCALARS!B66 -> 46141 | C65: =SCALARS!G66 -> 945.7789 | D65: =G65/J65 -> 945.78205 | E65: =C65-D65 -> -0.0031494732 | F65: 169115.26 | G65: 2120000 | I65: =ARKB!H65 -> 75446.31 | J65: =1000*F65/I65 -> 2241.5312
A66: =SCALARS!A67 -> Thursday | B66: =SCALARS!B67 -> 46142 | C66: =SCALARS!G67 -> 945.7854 | D66: =G66/J66 -> 945.78618 | E66: =C66-D66 -> -0.00078031651 | F66: 171290.03 | G66: 2120000 | H66: 2241 | I66: =ARKB!H66 -> 76416.86 | J66: =1000*F66/I66 -> 2241.5214 | K66: =G66/H66 -> 946.00625
A67: =SCALARS!A68 -> Friday | B67: =SCALARS!B68 -> 46143 | C67: =SCALARS!G68 -> 945.7919 | D67: =G67/J67 -> 945.78788 | E67: =C67-D67 -> 0.0040169486 | F67: 175769.17 | G67: 2120000 | H67: 2241 | I67: =ARKB!H67 -> 78415.26 | J67: =1000*F67/I67 -> 2241.5174 | K67: =G67/H67 -> 946.00625
A68: =SCALARS!A69 -> Saturday | B68: =SCALARS!B69 -> 46144 | C68: =SCALARS!G69 -> 945.7984 | F68: 0
A69: =SCALARS!A70 -> Sunday | B69: =SCALARS!B70 -> 46145 | C69: =SCALARS!G70 -> 945.8049 | F69: 0
A70: =SCALARS!A71 -> Monday | B70: =SCALARS!B71 -> 46146 | C70: =SCALARS!G71 -> 945.8114 | D70: =G70/J70 -> 945.80326 | E70: =C70-D70 -> 0.0081359032 | F70: 179328.63 | G70: 2120000 | H70: 2241 | I70: =ARKB!H70 -> 80004.53 | J70: =1000*F70/I70 -> 2241.481 | K70: =G70/H70 -> 946.00625
A71: =SCALARS!A72 -> Tuesday | B71: =SCALARS!B72 -> 46147 | C71: =SCALARS!G72 -> 945.8179 | D71: =G71/J71 -> 945.81145 | E71: =C71-D71 -> 0.0064531345 | F71: 182816.16 | G71: 2120000 | I71: =ARKB!H71 -> 81561.14 | J71: =1000*F71/I71 -> 2241.4616
A72: =SCALARS!A73 -> Wednesday | B72: =SCALARS!B73 -> 46148 | C72: =SCALARS!G73 -> 945.8244 | D72: =G72/J72 -> 945.81803 | E72: =C72-D72 -> 0.0063681812 | F72: 182352.32 | G72: 2120000 | I72: =ARKB!H72 -> 81354.77 | J72: =1000*F72/I72 -> 2241.446
A73: =SCALARS!A74 -> Thursday | B73: =SCALARS!B74 -> 46149 | C73: =SCALARS!G74 -> 945.8309 | D73: =G73/J73 -> 945.82505 | E73: =C73-D73 -> 0.0058459996 | F73: 179494.13 | G73: 2120000 | I73: =ARKB!H73 -> 80080.21 | J73: =1000*F73/I73 -> 2241.4293
A74: =SCALARS!A75 -> Friday | B74: =SCALARS!B75 -> 46150 | C74: =SCALARS!G75 -> 945.8374 | D74: =G74/J74 -> 945.83154 | E74: =C74-D74 -> 0.0058562303 | F74: 179461.81 | G74: 2120000 | I74: =ARKB!H74 -> 80066.34 | J74: =1000*F74/I74 -> 2241.4139
A75: =SCALARS!A76 -> Saturday | B75: =SCALARS!B76 -> 46151 | C75: =SCALARS!G76 -> 945.8439 | F75: 0
A76: =SCALARS!A77 -> Sunday | B76: =SCALARS!B77 -> 46152 | C76: =SCALARS!G77 -> 945.8504 | F76: 0
A77: =SCALARS!A78 -> Monday | B77: =SCALARS!B78 -> 46153 | C77: =SCALARS!G78 -> 945.8569 | D77: =G77/J77 -> 945.84939 | E77: =C77-D77 -> 0.007507744 | F77: 183601.98 | G77: 2120000 | H77: 2241 | I77: =ARKB!H77 -> 81915.01 | J77: =1000*F77/I77 -> 2241.3716 | K77: =G77/H77 -> 946.00625
A78: =SCALARS!A79 -> Tuesday | B78: =SCALARS!B79 -> 46154 | C78: =SCALARS!G79 -> 945.8634 | D78: =G78/J78 -> 945.85696 | E78: =C78-D78 -> 0.0064402222 | F78: 181006.57 | G78: 2120000 | I78: =ARKB!H78 -> 80757.7 | J78: =1000*F78/I78 -> 2241.3537 | K78: =G78/H78 -> #DIV/0!
A79: =SCALARS!A80 -> Wednesday | B79: =SCALARS!B80 -> 46155 | C79: =SCALARS!G80 -> 945.8699 | D79: =G79/J79 -> 945.86473 | E79: =C79-D79 -> 0.0051704241 | F79: 178179.23 | G79: 2120000 | H79: 2242 | I79: =ARKB!H79 -> 79496.91 | J79: =1000*F79/I79 -> 2241.3353 | K79: =G79/H79 -> 945.5843
A80: =SCALARS!A81 -> Thursday | B80: =SCALARS!B81 -> 46156 | C80: =SCALARS!G81 -> 945.8764 | D80: =G80/J80 -> 945.86895 | E80: =C80-D80 -> 0.007452241 | F80: 182694.93 | G80: 2120000 | I80: =ARKB!H80 -> 81512.01 | J80: =1000*F80/I80 -> 2241.3253 | K80: =G80/H80 -> #DIV/0!
A81: =SCALARS!A82 -> Friday | B81: =SCALARS!B82 -> 46157 | C81: =SCALARS!G82 -> 945.8829 | D81: =G81/J81 -> 945.87832 | E81: =C81-D81 -> 0.0045797521 | F81: 177280.44 | G81: 2120000 | H81: 2242 | I81: =ARKB!H81 -> 79097.04 | J81: =1000*F81/I81 -> 2241.3031 | K81: =G81/H81 -> 945.5843 | M81: -18400
A82: =SCALARS!A83 -> Saturday | B82: =SCALARS!B83 -> 46158 | C82: =SCALARS!G83 -> 945.8894 | F82: 0
A83: =SCALARS!A84 -> Sunday | B83: =SCALARS!B84 -> 46159 | C83: =SCALARS!G84 -> 945.8959 | F83: 0
A84: =SCALARS!A85 -> Monday | B84: =SCALARS!B85 -> 46160 | C84: =SCALARS!G85 -> 945.9024 | D84: =G84/J84 -> 945.90146 | E84: =C84-D84 -> 0.00093574158 | F84: 171850.13 | G84: 2120000 | H84: 2242 | I84: =ARKB!H84 -> 76676.08 | J84: =1000*F84/I84 -> 2241.2482 | K84: =G84/H84 -> 945.5843 | M84: -22043
A85: =SCALARS!A86 -> Tuesday | B85: =SCALARS!B86 -> 46161 | C85: =SCALARS!G86 -> 945.9089 | D85: =G85/J85 -> 945.90771 | E85: =C85-D85 -> 0.0011935313 | F85: 172173.28 | G85: 2120000 | I85: =ARKB!H85 -> 76820.77 | J85: =1000*F85/I85 -> 2241.2335 | K85: =G85/H85 -> #DIV/0!
A86: =SCALARS!A87 -> Wednesday | B86: =SCALARS!B87 -> 46162 | C86: =SCALARS!G87 -> 945.9154 | D86: =G86/J86 -> 945.91315 | E86: =C86-D86 -> 0.0022539298 | F86: 173621.62 | G86: 2120000 | H86: 2242 | I86: =ARKB!H86 -> 77467.44 | J86: =1000*F86/I86 -> 2241.2206 | K86: =G86/H86 -> 945.5843
A87: =SCALARS!A88 -> Thursday | B87: =SCALARS!B88 -> 46163 | C87: =SCALARS!G88 -> 945.9219 | D87: =G87/J87 -> 945.91955 | E87: =C87-D87 -> 0.0023520887 | F87: 173728.74 | G87: 2120000 | H87: 2242 | I87: =ARKB!H87 -> 77515.76 | J87: =1000*F87/I87 -> 2241.2054 | K87: =G87/H87 -> 945.5843 | M87: -25588
A88: =SCALARS!A89 -> Friday | B88: =SCALARS!B89 -> 46164 | C88: =SCALARS!G89 -> 945.9284 | D88: =G88/J88 -> 945.92892 | E88: =C88-D88 -> -0.00052055224 | F88: 170322.37 | G88: 2120000 | H88: 2242 | I88: =ARKB!H88 -> 75996.63 | J88: =1000*F88/I88 -> 2241.1832 | K88: =G88/H88 -> 945.5843
A89: =SCALARS!A90 -> Saturday | B89: =SCALARS!B90 -> 46165 | C89: =SCALARS!G90 -> 945.9349 | F89: 0
A90: =SCALARS!A91 -> Sunday | B90: =SCALARS!B91 -> 46166 | C90: =SCALARS!G91 -> 945.9414 | F90: 0
A91: =SCALARS!A92 -> Monday | B91: =SCALARS!B92 -> 46167 | C91: =SCALARS!G92 -> 945.9479 | F91: 0
A92: =SCALARS!A93 -> Tuesday | B92: =SCALARS!B93 -> 46168 | C92: =SCALARS!G93 -> 945.9544 | D92: =G92/J92 -> 945.9552 | E92: =C92-D92 -> -0.00080493722 | F92: 169909.35 | G92: 2120000 | H92: 2242 | I92: =ARKB!H92 -> 75814.45 | J92: =1000*F92/I92 -> 2241.1209 | K92: =G92/H92 -> 945.5843 | M92: -31444 | O92: =1000*F92 -> 169909350 | P92: =+O92-M92 -> 169940794 | Q92: =+P92/I92 -> 2241.5357 | R92: =+G92/Q92 -> 945.78018
A93: =SCALARS!A94 -> Wednesday | B93: =SCALARS!B94 -> 46169 | C93: =SCALARS!G94 -> 945.9609 | D93: =G93/J93 -> 945.96398 | E93: =C93-D93 -> -0.0030815455 | F93: 167835.63 | G93: 2120000 | H93: 2242 | I93: =ARKB!H93 -> 74889.84 | J93: =1000*F93/I93 -> 2241.1001 | K93: =G93/H93 -> 945.5843 | M93: -32608 | O93: =1000*F93 -> 167835630 | P93: =+O93-M93 -> 167868238 | Q93: =+P93/I93 -> 2241.5355 | R93: =+G93/Q93 -> 945.78023
A94: =SCALARS!A95 -> Thursday | B94: =SCALARS!B95 -> 46170 | C94: =SCALARS!G95 -> 945.9674 | D94: =G94/J94 -> 945.97441 | E94: =C94-D94 -> -0.0070089556 | F94: 164451.28 | G94: 2120000 | H94: 2242 | I94: =ARKB!H94 -> 73380.52 | J94: =1000*F94/I94 -> 2241.0754 | K94: =G94/H94 -> 945.5843 | M94: -33758 | O94: =1000*F94 -> 164451280 | P94: =+O94-M94 -> 164485038 | Q94: =+P94/I94 -> 2241.5355 | R94: =+G94/Q94 -> 945.78026
A95: =SCALARS!A96 -> Friday | B95: =SCALARS!B96 -> 46171 | C95: =SCALARS!G96 -> 945.9739 | D95: =G95/J95 -> 945.9808 | E95: =C95-D95 -> -0.006895502 | F95: 164489.59 | G95: 2120000 | H95: 2242 | I95: =ARKB!H95 -> 73398.11 | J95: =1000*F95/I95 -> 2241.0603 | K95: =G95/H95 -> 945.5843 | M95: -34884 | O95: =1000*F95 -> 164489590 | P95: =+O95-M95 -> 164524474 | Q95: =+P95/I95 -> 2241.5356 | R95: =+G95/Q95 -> 945.78022
A96: =SCALARS!A97 -> Saturday | B96: =SCALARS!B97 -> 46172 | C96: =SCALARS!G97 -> 945.9804
A97: =SCALARS!A98 -> Sunday | B97: =SCALARS!B98 -> 46173 | C97: =SCALARS!G98 -> 945.9869
A98: =SCALARS!A99 -> Monday | B98: =SCALARS!B99 -> 46174 | C98: =SCALARS!G99 -> 945.9934 | D98: =G98/J98 -> 946.00623 | E98: =C98-D98 -> -0.012825581 | F98: 160071.81 | G98: 2120000 | H98: 2242 | I98: =ARKB!H98 -> 71428.74 | J98: =1000*F98/I98 -> 2241.0001 | K98: =G98/H98 -> 945.5843 | M98: -38264 | O98: =1000*F98 -> 160071810 | P98: =+O98-M98 -> 160110074 | Q98: =+P98/I98 -> 2241.5357 | R98: =+G98/Q98 -> 945.78014
A99: =SCALARS!A100 -> Tuesday | B99: =SCALARS!B100 -> 46175 | C99: =SCALARS!G100 -> 945.9999 | D99: =G99/J99 -> 946.02815 | E99: =C99-D99 -> -0.02825395 | F99: 150123.87 | G99: 2120000 | H99: 2242 | I99: =ARKB!H99 -> 66991.23 | J99: =1000*F99/I99 -> 2240.9481 | K99: =G99/H99 -> 945.5843 | M99: -39360 | O99: =1000*F99 -> 150123870 | P99: =+O99-M99 -> 150163230 | Q99: =+P99/I99 -> 2241.5356 | R99: =+G99/Q99 -> 945.78019
A100: =SCALARS!A101 -> Wednesday | B100: =SCALARS!B101 -> 46176 | C100: =SCALARS!G101 -> 946.0064 | D100: =G100/J100 -> 946.03206 | E100: =C100-D100 -> -0.025659201 | F100: 147189.57 | G100: 2120000 | H100: 2241 | I100: =ARKB!H100 -> 65682.1 | J100: =1000*F100/I100 -> 2240.9389 | K100: =G100/H100 -> 946.00625 | M100: -3251 | O100: =1000*F100 -> 147189570 | P100: =+O100-M100 -> 147192821 | Q100: =+P100/I100 -> 2240.9884 | R100: =+G100/Q100 -> 946.01116
A101: =SCALARS!A102 -> Thursday | B101: =SCALARS!B102 -> 46177 | C101: =SCALARS!G102 -> 946.0129 | D101: =G101/J101 -> 946.03932 | E101: =C101-D101 -> -0.026422806 | F101: 142819.92 | G101: 2120000 | H101: 2241 | I101: =ARKB!H101 -> 63732.67 | J101: =1000*F101/I101 -> 2240.9216 | K101: =G101/H101 -> 946.00625 | M101: -4259 | O101: =1000*F101 -> 142819920 | P101: =+O101-M101 -> 142824179 | Q101: =+P101/I101 -> 2240.9885 | R101: =+G101/Q101 -> 946.01111
A102: =SCALARS!A103 -> Friday | B102: =SCALARS!B103 -> 46178 | C102: =SCALARS!G103 -> 946.0194 | D102: =G102/J102 -> 946.04821 | E102: =C102-D102 -> -0.028808724 | F102: 133722.27 | G102: 2120000 | H102: 2241 | I102: =ARKB!H102 -> 59673.45 | J102: =1000*F102/I102 -> 2240.9006 | K102: =G102/H102 -> 946.00625 | M102: -5237 | O102: =1000*F102 -> 1.3372227e+08 | P102: =+O102-M102 -> 1.3372751e+08 | Q102: =+P102/I102 -> 2240.9884 | R102: =+G102/Q102 -> 946.01116
A103: =SCALARS!A104 -> Saturday | B103: =SCALARS!B104 -> 46179 | C103: =SCALARS!G104 -> 946.0259
...

Sheet BITB
A1: https://bitbetf.com
A5: DOW | B5: Date | C5: TODAY'S RATIO | D5: SHS/ADJ BTC | E5: DIFF | F5: NET ASSETS (AUM) | G5: SHARES OUTSTANDING | H5: BITCOIN IN TRUST | I5: BITCOIN PER SHARE | J5: REF PRICE | K5: ADJ BTC | L5: ROUND DOWN BTC / SH | M5: ROUND UP BTC/SH | N5: HIGH BOUND SHS/BTC | O5: LOW BOUND SHS/BTC | P5: SHS/BTC
A6: =SCALARS!A7 -> Sunday | B6: =SCALARS!B7 -> 46082 | C6: =SCALARS!D7 -> 1840.9691
A7: =SCALARS!A8 -> Monday | B7: =SCALARS!B8 -> 46083 | C7: =SCALARS!D8 -> 1840.9792
A8: =SCALARS!A9 -> Tuesday | B8: =SCALARS!B9 -> 46084 | C8: =SCALARS!D9 -> 1840.9893
A9: =SCALARS!A10 -> Wednesday | B9: =SCALARS!B10 -> 46085 | C9: =SCALARS!D10 -> 1840.9994
A10: =SCALARS!A11 -> Thursday | B10: =SCALARS!B11 -> 46086 | C10: =SCALARS!D11 -> 1841.0095
A11: =SCALARS!A12 -> Friday | B11: =SCALARS!B12 -> 46087 | C11: =SCALARS!D12 -> 1841.0196
A12: =SCALARS!A13 -> Saturday | B12: =SCALARS!B13 -> 46088 | C12: =SCALARS!D13 -> 1841.0297
A13: =SCALARS!A14 -> Sunday | B13: =SCALARS!B14 -> 46089 | C13: =SCALARS!D14 -> 1841.0398
A14: =SCALARS!A15 -> Monday | B14: =SCALARS!B15 -> 46090 | C14: =SCALARS!D15 -> 1841.0499 | D14: =G14/K14 -> 1841.0329 | E14: =C14-D14 -> 0.016994513 | F14: 2664058923 | G14: 71220000 | H14: 38686.95 | I14: 0.000543 | J14: 68865.77 | K14: =F14/J14 -> 38684.806 | L14: =I14-0.0000005 -> 0.0005425 | M14: =I14+0.0000005 -> 0.0005435 | N14: =1/L14 -> 1843.318 | O14: =1/M14 -> 1839.9264 | P14: =1/I14 -> 1841.6206
A15: =SCALARS!A16 -> Tuesday | B15: =SCALARS!B16 -> 46091 | C15: =SCALARS!D16 -> 1841.06 | D15: =G15/K15 -> 1841.0415 | E15: =C15-D15 -> 0.018516298 | F15: 2725026281 | G15: 71650000 | H15: 38920.51 | I15: 0.000543 | J15: 70019.35 | K15: =F15/J15 -> 38918.189 | L15: =I15-0.0000005 -> 0.0005425 | M15: =I15+0.0000005 -> 0.0005435 | N15: =1/L15 -> 1843.318 | O15: =1/M15 -> 1839.9264 | P15: =1/I15 -> 1841.6206
A16: =SCALARS!A17 -> Wednesday | B16: =SCALARS!B17 -> 46092 | C16: =SCALARS!D17 -> 1841.0701 | D16: =G16/K16 -> 1841.0507 | E16: =C16-D16 -> 0.019352128 | F16: 2747627036 | G16: 71650000 | H16: 38920.51 | I16: 0.000543 | J16: =ARKB!H16 -> 70600.43 | K16: =F16/J16 -> 38917.993 | L16: =I16-0.0000005 -> 0.0005425 | M16: =I16+0.0000005 -> 0.0005435 | N16: =1/L16 -> 1843.318 | O16: =1/M16 -> 1839.9264 | P16: =1/I16 -> 1841.6206
A17: =SCALARS!A18 -> Thursday | B17: =SCALARS!B18 -> 46093 | C17: =SCALARS!D18 -> 1841.0802 | D17: =G17/K17 -> 1841.0817 | E17: =C17-D17 -> -0.0014664659 | F17: 2725606287 | G17: 71500000 | H17: 38839.04 | I17: 0.000543 | J17: =ARKB!H17 -> 70182.71 | K17: =F17/J17 -> 38835.866 | L17: =I17-0.0000005 -> 0.0005425 | M17: =I17+0.0000005 -> 0.0005435 | N17: =1/L17 -> 1843.318 | O17: =1/M17 -> 1839.9264 | P17: =1/I17 -> 1841.6206
A18: =SCALARS!A19 -> Friday | B18: =SCALARS!B19 -> 46094 | C18: =SCALARS!D19 -> 1841.0903 | D18: =G18/K18 -> 1841.0901 | E18: =C18-D18 -> 0.00018585247 | F18: 2766385710 | G18: 71580000 | H18: 38882.49 | I18: 0.000543 | J18: =ARKB!H18 -> 71153.47 | K18: =F18/J18 -> 38879.14 | L18: =I18-0.0000005 -> 0.0005425 | M18: =I18+0.0000005 -> 0.0005435 | N18: =1/L18 -> 1843.318 | O18: =1/M18 -> 1839.9264 | P18: =1/I18 -> 1841.6206
A19: =SCALARS!A20 -> Saturday | B19: =SCALARS!B20 -> 46095 | C19: =SCALARS!D20 -> 1841.1004
A20: =SCALARS!A21 -> Sunday | B20: =SCALARS!B21 -> 46096 | C20: =SCALARS!D21 -> 1841.1105
A21: =SCALARS!A22 -> Monday | B21: =SCALARS!B22 -> 46097 | C21: =SCALARS!D22 -> 1841.1206 | D21: =G21/K21 -> 1841.0943 | E21: =C21-D21 -> 0.026260377 | F21: 2882713186 | G21: 71650000 | H21: 38920.51 | I21: 0.000543 | J21: =ARKB!H21 -> 74073.23 | K21: =F21/J21 -> 38917.071 | L21: =I21-0.0000005 -> 0.0005425 | M21: =I21+0.0000005 -> 0.0005435 | N21: =1/L21 -> 1843.318 | O21: =1/M21 -> 1839.9264 | P21: =1/I21 -> 1841.6206
A22: =SCALARS!A23 -> Tuesday | B22: =SCALARS!B23 -> 46098 | C22: =SCALARS!D23 -> 1841.1307 | D22: =G22/K22 -> 1841.1032 | E22: =C22-D22 -> 0.027518533 | F22: 2906389217 | G22: 71650000 | H22: 38920.51 | I22: 0.000543 | J22: =ARKB!H22 -> 74681.96 | K22: =F22/J22 -> 38916.885 | L22: =I22-0.0000005 -> 0.0005425 | M22: =I22+0.0000005 -> 0.0005435 | N22: =1/L22 -> 1843.318 | O22: =1/M22 -> 1839.9264 | P22: =1/I22 -> 1841.6206
A23: =SCALARS!A24 -> Wednesday | B23: =SCALARS!B24 -> 46099 | C23: =SCALARS!D24 -> 1841.1408 | D23: =G23/K23 -> 1841.1212 | E23: =C23-D23 -> 0.019616301 | F23: 2764241152 | G23: 71470000 | H23: 38822.75 | I23: 0.000543 | J23: =ARKB!H23 -> 71208.94 | K23: =F23/J23 -> 38818.738 | L23: =I23-0.0000005 -> 0.0005425 | M23: =I23+0.0000005 -> 0.0005435 | N23: =1/L23 -> 1843.318 | O23: =1/M23 -> 1839.9264 | P23: =1/I23 -> 1841.6206
A24: =SCALARS!A25 -> Thursday | B24: =SCALARS!B25 -> 46100 | C24: =SCALARS!D25 -> 1841.1509 | D24: =G24/K24 -> 1841.1538 | E24: =C24-D24 -> -0.0029173704 | F24: 2711438188 | G24: 71020000 | H24: 38578.33 | I24: 0.000543 | J24: =ARKB!H24 -> 70292.52 | K24: =F24/J24 -> 38573.638 | L24: =I24-0.0000005 -> 0.0005425 | M24: =I24+0.0000005 -> 0.0005435 | N24: =1/L24 -> 1843.318 | O24: =1/M24 -> 1839.9264 | P24: =1/I24 -> 1841.6206
A25: =SCALARS!A26 -> Friday | B25: =SCALARS!B26 -> 46101 | C25: =SCALARS!D26 -> 1841.161 | D25: =G25/K25 -> 1841.1651 | E25: =C25-D25 -> -0.0040705615 | F25: 2695243931 | G25: 71020000 | H25: 38578.33 | I25: 0.000543 | J25: =ARKB!H25 -> 69873.12 | K25: =F25/J25 -> 38573.402 | L25: =I25-0.0000005 -> 0.0005425 | M25: =I25+0.0000005 -> 0.0005435 | N25: =1/L25 -> 1843.318 | O25: =1/M25 -> 1839.9264 | P25: =1/I25 -> 1841.6206
A26: =SCALARS!A27 -> Saturday | B26: =SCALARS!B27 -> 46102 | C26: =SCALARS!D27 -> 1841.1711
A27: =SCALARS!A28 -> Sunday | B27: =SCALARS!B28 -> 46103 | C27: =SCALARS!D28 -> 1841.1812
A28: =SCALARS!A29 -> Monday | B28: =SCALARS!B29 -> 46104 | C28: =SCALARS!D29 -> 1841.1913
A29: =SCALARS!A30 -> Tuesday | B29: =SCALARS!B30 -> 46105 | C29: =SCALARS!D30 -> 1841.2014 | D29: =G29/K29 -> 1841.1869 | E29: =C29-D29 -> 0.014537072 | F29: 2662358160 | G29: 70580000 | H29: 38339.35 | I29: 0.000543 | J29: =ARKB!H29 -> 69451.67 | K29: =F29/J29 -> 38333.969 | L29: =I29-0.0000005 -> 0.0005425 | M29: =I29+0.0000005 -> 0.0005435 | N29: =1/L29 -> 1843.318 | O29: =1/M29 -> 1839.9264 | P29: =1/I29 -> 1841.6206
A30: =SCALARS!A31 -> Wednesday | B30: =SCALARS!B31 -> 46106 | C30: =SCALARS!D31 -> 1841.2115 | D30: =G30/K30 -> 1841.1919 | E30: =C30-D30 -> 0.019571018 | F30: 2717247227 | G30: 70580000 | H30: 38339.35 | I30: 0.000543 | J30: =ARKB!H30 -> 70883.73 | K30: =F30/J30 -> 38333.863 | L30: =I30-0.0000005 -> 0.0005425 | M30: =I30+0.0000005 -> 0.0005435 | N30: =1/L30 -> 1843.318 | O30: =1/M30 -> 1839.9264 | P30: =1/I30 -> 1841.6206
A31: =SCALARS!A32 -> Thursday | B31: =SCALARS!B32 -> 46107 | C31: =SCALARS!D32 -> 1841.2216 | D31: =G31/K31 -> 1841.2312 | E31: =C31-D31 -> -0.0096253265 | F31: 2591902466 | G31: 69690000 | H31: 37855.97 | I31: 0.000543 | J31: =ARKB!H31 -> 68478.86 | K31: =F31/J31 -> 37849.673 | L31: =I31-0.0000005 -> 0.0005425 | M31: =I31+0.0000005 -> 0.0005435 | N31: =1/L31 -> 1843.318 | O31: =1/M31 -> 1839.9264 | P31: =1/I31 -> 1841.6206
A32: =SCALARS!A33 -> Friday | B32: =SCALARS!B33 -> 46108 | C32: =SCALARS!D33 -> 1841.2317 | D32: =G32/K32 -> 1841.2524 | E32: =C32-D32 -> -0.02067602 | F32: 2473496849 | G32: 69170000 | H32: 37573.55 | I32: 0.000543 | J32: 65842.59 | K32: =F32/J32 -> 37566.822 | L32: =I32-0.0000005 -> 0.0005425 | M32: =I32+0.0000005 -> 0.0005435 | N32: =1/L32 -> 1843.318 | O32: =1/M32 -> 1839.9264 | P32: =1/I32 -> 1841.6206
A33: =SCALARS!A34 -> Saturday | B33: =SCALARS!B34 -> 46109 | C33: =SCALARS!D34 -> 1841.2418
A34: =SCALARS!A35 -> Sunday | B34: =SCALARS!B35 -> 46110 | C34: =SCALARS!D35 -> 1841.2519
A35: =SCALARS!A36 -> Monday | B35: =SCALARS!B36 -> 46111 | C35: =SCALARS!D36 -> 1841.262 | D35: =G35/K35 -> 1841.2601 | E35: =C35-D35 -> 0.0019227073 | F35: 2492754070 | G35: 69170000 | H35: 37573.55 | I35: 0.000543 | J35: =ARKB!H35 -> 66355.48 | K35: =F35/J35 -> 37566.665 | L35: =I35-0.0000005 -> 0.0005425 | M35: =I35+0.0000005 -> 0.0005435 | N35: =1/L35 -> 1843.318 | O35: =1/M35 -> 1839.9264 | P35: =1/I35 -> 1841.6206
A36: =SCALARS!A37 -> Tuesday | B36: =SCALARS!B37 -> 46112 | C36: =SCALARS!D37 -> 1841.2721 | D36: =G36/K36 -> 1841.263 | E36: =C36-D36 -> 0.0090581862 | F36: 2550050873 | G36: 69220000 | H36: 37593.96 | I36: 0.000543 | J36: =ARKB!H36 -> 67831.76 | K36: =F36/J36 -> 37593.76 | L36: =I36-0.0000005 -> 0.0005425 | M36: =I36+0.0000005 -> 0.0005435 | N36: =1/L36 -> 1843.318 | O36: =1/M36 -> 1839.9264 | P36: =1/I36 -> 1841.6206
A37: =SCALARS!A38 -> Wednesday | B37: =SCALARS!B38 -> 46113 | C37: =SCALARS!D38 -> 1841.2822 | D37: =G37/K37 -> 1841.3034 | E37: =C37-D37 -> -0.021199521 | F37: 2556377524 | G37: 69070000 | H37: 37512.49 | I37: 0.000543 | J37: =ARKB!H37 -> 68149.22 | K37: =F37/J37 -> 37511.472 | L37: =I37-0.0000005 -> 0.0005425 | M37: =I37+0.0000005 -> 0.0005435 | N37: =1/L37 -> 1843.318 | O37: =1/M37 -> 1839.9264 | P37: =1/I37 -> 1841.6206
A38: =SCALARS!A39 -> Thursday | B38: =SCALARS!B39 -> 46114 | C38: =SCALARS!D39 -> 1841.2923 | D38: =G38/K38 -> 1841.3137 | E38: =C38-D38 -> -0.021362991 | F38: 2513062149 | G38: 69070000 | H38: 37512.49 | I38: 0.000543 | J38: =ARKB!H38 -> 66994.87 | K38: =F38/J38 -> 37511.262 | L38: =I38-0.0000005 -> 0.0005425 | M38: =I38+0.0000005 -> 0.0005435 | N38: =1/L38 -> 1843.318 | O38: =1/M38 -> 1839.9264 | P38: =1/I38 -> 1841.6206
A39: =SCALARS!A40 -> Friday | B39: =SCALARS!B40 -> 46115 | C39: =SCALARS!D40 -> 1841.3024 | E39: HOLIDAY
A40: =SCALARS!A41 -> Saturday | B40: =SCALARS!B41 -> 46116 | C40: =SCALARS!D41 -> 1841.3125
A41: =SCALARS!A42 -> Sunday | B41: =SCALARS!B42 -> 46117 | C41: =SCALARS!D42 -> 1841.3226
A42: =SCALARS!A43 -> Monday | B42: =SCALARS!B43 -> 46118 | C42: =SCALARS!D43 -> 1841.3327 | D42: =G42/K42 -> 1841.3217 | E42: =C42-D42 -> 0.010956733 | F42: 2620820840 | G42: 69170000 | H42: 37566.8 | I42: 0.000543 | J42: =ARKB!H42 -> 69766.87 | K42: =F42/J42 -> 37565.407 | L42: =I42-0.0000005 -> 0.0005425 | M42: =I42+0.0000005 -> 0.0005435 | N42: =1/L42 -> 1843.318 | O42: =1/M42 -> 1839.9264 | P42: =1/I42 -> 1841.6206
A43: =SCALARS!A44 -> Tuesday | B43: =SCALARS!B44 -> 46119 | C43: =SCALARS!D44 -> 1841.3428 | D43: =G43/K43 -> 1841.3328 | E43: =C43-D43 -> 0.0099801264 | F43: 2577435322 | G43: 69170000 | H43: 37566.8 | I43: 0.000543 | J43: =ARKB!H43 -> 68612.35 | K43: =F43/J43 -> 37565.181 | L43: =I43-0.0000005 -> 0.0005425 | M43: =I43+0.0000005 -> 0.0005435 | N43: =1/L43 -> 1843.318 | O43: =1/M43 -> 1839.9264 | P43: =1/I43 -> 1841.6206
A44: =SCALARS!A45 -> Wednesday | B44: =SCALARS!B45 -> 46120 | C44: =SCALARS!D45 -> 1841.3529 | D44: =G44/K44 -> 1841.3403 | E44: =C44-D44 -> 0.01256076 | F44: 2676113758 | G44: 69170000 | H44: 37566.8 | I44: 0.000543 | J44: =ARKB!H44 -> 71239.5 | K44: =F44/J44 -> 37565.027 | L44: =I44-0.0000005 -> 0.0005425 | M44: =I44+0.0000005 -> 0.0005435 | N44: =1/L44 -> 1843.318 | O44: =1/M44 -> 1839.9264 | P44: =1/I44 -> 1841.6206
A45: =SCALARS!A46 -> Thursday | B45: =SCALARS!B46 -> 46121 | C45: =SCALARS!D46 -> 1841.363 | D45: =G45/K45 -> 1841.3698 | E45: =C45-D45 -> -0.0067920213 | F45: 2716558866 | G45: 69470000 | H45: 37729.73 | I45: 0.000543 | J45: =ARKB!H45 -> 72005.03 | K45: =F45/J45 -> 37727.349 | L45: =I45-0.0000005 -> 0.0005425 | M45: =I45+0.0000005 -> 0.0005435 | N45: =1/L45 -> 1843.318 | O45: =1/M45 -> 1839.9264 | P45: =1/I45 -> 1841.6206
A46: =SCALARS!A47 -> Friday | B46: =SCALARS!B47 -> 46122 | C46: =SCALARS!D47 -> 1841.3731 | D46: =G46/K46 -> 1841.3786 | E46: =C46-D46 -> -0.0054851216 | F46: 2767752009 | G46: 69710000 | H46: 37860.07 | I46: 0.000543 | J46: =ARKB!H46 -> 73109.73 | K46: =F46/J46 -> 37857.506 | L46: =I46-0.0000005 -> 0.0005425 | M46: =I46+0.0000005 -> 0.0005435 | N46: =1/L46 -> 1843.318 | O46: =1/M46 -> 1839.9264 | P46: =1/I46 -> 1841.6206
A47: =SCALARS!A48 -> Saturday | B47: =SCALARS!B48 -> 46123 | C47: =SCALARS!D48 -> 1841.3832
A48: =SCALARS!A49 -> Sunday | B48: =SCALARS!B49 -> 46124 | C48: =SCALARS!D49 -> 1841.3933
A49: =SCALARS!A50 -> Monday | B49: =SCALARS!B50 -> 46125 | C49: =SCALARS!D50 -> 1841.4034 | D49: =G49/K49 -> 1841.389 | E49: =C49-D49 -> 0.014383983 | F49: 2771390174 | G49: 70010000 | H49: 38022.99 | I49: 0.000543 | J49: =ARKB!H49 -> 72892.55 | K49: =F49/J49 -> 38020.212 | L49: =I49-0.0000005 -> 0.0005425 | M49: =I49+0.0000005 -> 0.0005435 | N49: =1/L49 -> 1843.318 | O49: =1/M49 -> 1839.9264 | P49: =1/I49 -> 1841.6206
A50: =SCALARS!A51 -> Tuesday | B50: =SCALARS!B51 -> 46126 | C50: =SCALARS!D51 -> 1841.4135 | D50: =G50/K50 -> 1841.3968 | E50: =C50-D50 -> 0.016694566 | F50: 2836256377 | G50: 70320000 | H50: 38191.34 | I50: 0.000543 | J50: =ARKB!H50 -> 74270.1 | K50: =F50/J50 -> 38188.401 | L50: =I50-0.0000005 -> 0.0005425 | M50: =I50+0.0000005 -> 0.0005435 | N50: =1/L50 -> 1843.318 | O50: =1/M50 -> 1839.9264 | P50: =1/I50 -> 1841.6206
A51: =SCALARS!A52 -> Wednesday | B51: =SCALARS!B52 -> 46127 | C51: =SCALARS!D52 -> 1841.4236 | D51: =G51/K51 -> 1841.4059 | E51: =C51-D51 -> 0.017733942 | F51: 2849986027 | G51: 70110000 | H51: 38077.3 | I51: 0.000543 | J51: =ARKB!H51 -> 74853.53 | K51: =F51/J51 -> 38074.17 | L51: =I51-0.0000005 -> 0.0005425 | M51: =I51+0.0000005 -> 0.0005435 | N51: =1/L51 -> 1843.318 | O51: =1/M51 -> 1839.9264 | P51: =1/I51 -> 1841.6206
A52: =SCALARS!A53 -> Thursday | B52: =SCALARS!B53 -> 46128 | C52: =SCALARS!D53 -> 1841.4337 | D52: =G52/K52 -> 1841.4357 | E52: =C52-D52 -> -0.0019966657 | F52: 2858880290 | G52: 70110000 | H52: 38077.3 | I52: 0.000543 | J52: =ARKB!H52 -> 75088.35 | K52: =F52/J52 -> 38073.553 | L52: =I52-0.0000005 -> 0.0005425 | M52: =I52+0.0000005 -> 0.0005435 | N52: =1/L52 -> 1843.318 | O52: =1/M52 -> 1839.9264 | P52: =1/I52 -> 1841.6206
A53: =SCALARS!A54 -> Friday | B53: =SCALARS!B54 -> 46129 | C53: =SCALARS!D54 -> 1841.4438 | D53: =G53/K53 -> 1841.4415 | E53: =C53-D53 -> 0.0023349965 | F53: 2982500546 | G53: 71020000 | H53: 38571.47 | I53: 0.000543 | J53: =ARKB!H53 -> 77331.74 | K53: =F53/J53 -> 38567.612 | L53: =I53-0.0000005 -> 0.0005425 | M53: =I53+0.0000005 -> 0.0005435 | N53: =1/L53 -> 1843.318 | O53: =1/M53 -> 1839.9264 | P53: =1/I53 -> 1841.6206
A54: =SCALARS!A55 -> Saturday | B54: =SCALARS!B55 -> 46130 | C54: =SCALARS!D55 -> 1841.4539
A55: =SCALARS!A56 -> Sunday | B55: =SCALARS!B56 -> 46131 | C55: =SCALARS!D56 -> 1841.464
A56: =SCALARS!A57 -> Monday | B56: =SCALARS!B57 -> 46132 | C56: =SCALARS!D57 -> 1841.4741 | D56: =G56/K56 -> 1841.4539 | E56: =C56-D56 -> 0.020226931 | F56: 2943414807 | G56: 71020000 | H56: 38571.47 | I56: 0.000543 | J56: =ARKB!H56 -> 76318.82 | K56: =F56/J56 -> 38567.352 | L56: =I56-0.0000005 -> 0.0005425 | M56: =I56+0.0000005 -> 0.0005435 | N56: =1/L56 -> 1843.318 | O56: =1/M56 -> 1839.9264 | P56: =1/I56 -> 1841.6206
A57: =SCALARS!A58 -> Tuesday | B57: =SCALARS!B58 -> 46133 | C57: =SCALARS!D58 -> 1841.4842 | D57: =G57/K57 -> 1841.4661 | E57: =C57-D57 -> 0.018103623 | F57: 2897659681 | G57: 70710000 | H57: 38403.13 | I57: 0.000543 | J57: =ARKB!H57 -> 75462.34 | K57: =F57/J57 -> 38398.752 | L57: =I57-0.0000005 -> 0.0005425 | M57: =I57+0.0000005 -> 0.0005435 | N57: =1/L57 -> 1843.318 | O57: =1/M57 -> 1839.9264 | P57: =1/I57 -> 1841.6206
A58: =SCALARS!A59 -> Wednesday | B58: =SCALARS!B59 -> 46134 | C58: =SCALARS!D59 -> 1841.4943 | D58: =G58/K58 -> 1841.4675 | E58: =C58-D58 -> 0.02683336 | F58: 3045846943 | G58: 71070000 | H58: 38598.63 | I58: 0.000543 | J58: =ARKB!H58 -> 78919.77 | K58: =F58/J58 -> 38594.22 | L58: =I58-0.0000005 -> 0.0005425 | M58: =I58+0.0000005 -> 0.0005435 | N58: =1/L58 -> 1843.318 | O58: =1/M58 -> 1839.9264 | P58: =1/I58 -> 1841.6206
A59: =SCALARS!A60 -> Thursday | B59: =SCALARS!B60 -> 46135 | C59: =SCALARS!D60 -> 1841.5044 | D59: =G59/K59 -> 1841.5007 | E59: =C59-D59 -> 0.0037009515 | F59: 2994003271 | G59: 70890000 | H59: 38500.88 | I59: 0.000543 | J59: =ARKB!H59 -> 77774.85 | K59: =F59/J59 -> 38495.777 | L59: =I59-0.0000005 -> 0.0005425 | M59: =I59+0.0000005 -> 0.0005435 | N59: =1/L59 -> 1843.318 | O59: =1/M59 -> 1839.9264 | P59: =1/I59 -> 1841.6206
A60: =SCALARS!A61 -> Friday | B60: =SCALARS!B61 -> 46136 | C60: =SCALARS!D61 -> 1841.5145 | D60: =G60/K60 -> 1841.5112 | E60: =C60-D60 -> 0.0033315049 | F60: 2979872605 | G60: 70680000 | H60: 38386.84 | I60: 0.000543 | J60: =ARKB!H60 -> 77638.21 | K60: =F60/J60 -> 38381.521 | L60: =I60-0.0000005 -> 0.0005425 | M60: =I60+0.0000005 -> 0.0005435 | N60: =1/L60 -> 1843.318 | O60: =1/M60 -> 1839.9264 | P60: =1/I60 -> 1841.6206
A61: =SCALARS!A62 -> Saturday | B61: =SCALARS!B62 -> 46137 | C61: =SCALARS!D62 -> 1841.5246
A62: =SCALARS!A63 -> Sunday | B62: =SCALARS!B63 -> 46138 | C62: =SCALARS!D63 -> 1841.5347
A63: =SCALARS!A64 -> Monday | B63: =SCALARS!B64 -> 46139 | C63: =SCALARS!D64 -> 1841.5448 | D63: =G63/K63 -> 1841.5241 | E63: =C63-D63 -> 0.020731727 | F63: 2937477631 | G63: 70470000 | H63: 38272.8 | I63: 0.000543 | J63: =ARKB!H63 -> 76762.25 | K63: =F63/J63 -> 38267.216 | L63: =I63-0.0000005 -> 0.0005425 | M63: =I63+0.0000005 -> 0.0005435 | N63: =1/L63 -> 1843.318 | O63: =1/M63 -> 1839.9264 | P63: =1/I63 -> 1841.6206
A64: =SCALARS!A65 -> Tuesday | B64: =SCALARS!B65 -> 46140 | C64: =SCALARS!D65 -> 1841.5549 | D64: =G64/K64 -> 1841.5361 | E64: =C64-D64 -> 0.018767013 | F64: 2901703614 | G64: 70140000 | H64: 38093.6 | I64: 0.000543 | J64: =ARKB!H64 -> 76184.66 | K64: =F64/J64 -> 38087.767 | L64: =I64-0.0000005 -> 0.0005425 | M64: =I64+0.0000005 -> 0.0005435 | N64: =1/L64 -> 1843.318 | O64: =1/M64 -> 1839.9264 | P64: =1/I64 -> 1841.6206
A65: =SCALARS!A66 -> Wednesday | B65: =SCALARS!B66 -> 46141 | C65: =SCALARS!D66 -> 1841.565 | D65: =G65/K65 -> 1841.5489 | E65: =C65-D65 -> 0.016108939 | F65: 2873561603 | G65: 70140000 | H65: 38093.6 | I65: 0.000543 | J65: =ARKB!H65 -> 75446.31 | K65: =F65/J65 -> 38087.504 | L65: =I65-0.0000005 -> 0.0005425 | M65: =I65+0.0000005 -> 0.0005435 | N65: =1/L65 -> 1843.318 | O65: =1/M65 -> 1839.9264 | P65: =1/I65 -> 1841.6206
A66: =SCALARS!A67 -> Thursday | B66: =SCALARS!B67 -> 46142 | C66: =SCALARS!D67 -> 1841.5751 | D66: =G66/K66 -> 1841.5755 | E66: =C66-D66 -> -0.00043822534 | F66: 2907580639 | G66: 70070000 | H66: 38049.56 | I66: 0.000543 | J66: =ARKB!H66 -> 76416.86 | K66: =F66/J66 -> 38048.942 | L66: =I66-0.0000005 -> 0.0005425 | M66: =I66+0.0000005 -> 0.0005435 | N66: =1/L66 -> 1843.318 | O66: =1/M66 -> 1839.9264 | P66: =1/I66 -> 1841.6206
A67: =SCALARS!A68 -> Friday | B67: =SCALARS!B68 -> 46143 | C67: =SCALARS!D68 -> 1841.5852 | D67: =G67/K67 -> 1841.5856 | E67: =C67-D67 -> -0.0004298473 | F67: 3010852683 | G67: 70710000 | H67: 38397.09 | I67: 0.000543 | J67: =ARKB!H67 -> 78415.26 | K67: =F67/J67 -> 38396.26 | L67: =I67-0.0000005 -> 0.0005425 | M67: =I67+0.0000005 -> 0.0005435 | N67: =1/L67 -> 1843.318 | O67: =1/M67 -> 1839.9264 | P67: =1/I67 -> 1841.6206
A68: =SCALARS!A69 -> Saturday | B68: =SCALARS!B69 -> 46144 | C68: =SCALARS!D69 -> 1841.5953
A69: =SCALARS!A70 -> Sunday | B69: =SCALARS!B70 -> 46145 | C69: =SCALARS!D70 -> 1841.6054
A70: =SCALARS!A71 -> Monday | B70: =SCALARS!B71 -> 46146 | C70: =SCALARS!D71 -> 1841.6155 | D70: =G70/K70 -> 1841.5951 | E70: =C70-D70 -> 0.020375501 | F70: 3071858869 | G70: 70710000 | H70: 38397.09 | I70: 0.000543 | J70: =ARKB!H70 -> 80004.53 | K70: =F70/J70 -> 38396.062 | L70: =I70-0.0000005 -> 0.0005425 | M70: =I70+0.0000005 -> 0.0005435 | N70: =1/L70 -> 1843.318 | O70: =1/M70 -> 1839.9264 | P70: =1/I70 -> 1841.6206
A71: =SCALARS!A72 -> Tuesday | B71: =SCALARS!B72 -> 46147 | C71: =SCALARS!D72 -> 1841.6256 | D71: =G71/K71 -> 1841.6045 | E71: =C71-D71 -> 0.021134356 | F71: 3146225747 | G71: 71040000 | H71: 38576.28 | I71: 0.000543 | J71: =ARKB!H71 -> 81561.14 | K71: =F71/J71 -> 38575.059 | L71: =I71-0.0000005 -> 0.0005425 | M71: =I71+0.0000005 -> 0.0005435 | N71: =1/L71 -> 1843.318 | O71: =1/M71 -> 1839.9264 | P71: =1/I71 -> 1841.6206
A72: =SCALARS!A73 -> Wednesday | B72: =SCALARS!B73 -> 46148 | C72: =SCALARS!D73 -> 1841.6357 | D72: =G72/K72 -> 1841.6147 | E72: =C72-D72 -> 0.021018876 | F72: 3113067408 | G72: 70470000 | H72: 38266.77 | I72: 0.000543 | J72: =ARKB!H72 -> 81354.77 | K72: =F72/J72 -> 38265.334 | L72: =I72-0.0000005 -> 0.0005425 | M72: =I72+0.0000005 -> 0.0005435 | N72: =1/L72 -> 1843.318 | O72: =1/M72 -> 1839.9264 | P72: =1/I72 -> 1841.6206
A73: =SCALARS!A74 -> Thursday | B73: =SCALARS!B74 -> 46149 | C73: =SCALARS!D74 -> 1841.6458 | D73: =G73/K73 -> 1841.6459 | E73: =C73-D73 -> -9.9235947e-05 | F73: 3064244001 | G73: 70470000 | H73: 38266.77 | I73: =I72 -> 0.000543 | J73: =ARKB!H73 -> 80080.21 | K73: =F73/J73 -> 38264.685 | L73: =I73-0.0000005 -> 0.0005425 | M73: =I73+0.0000005 -> 0.0005435 | N73: =1/L73 -> 1843.318 | O73: =1/M73 -> 1839.9264 | P73: =1/I73 -> 1841.6206
A74: =SCALARS!A75 -> Friday | B74: =SCALARS!B75 -> 46150 | C74: =SCALARS!D75 -> 1841.6559 | D74: =G74/K74 -> 1841.656 | E74: =C74-D74 -> -0.00010333603 | F74: 3063696461 | G74: 70470000 | H74: 38266.77 | I74: =I73 -> 0.000543 | J74: =ARKB!H74 -> 80066.34 | K74: =F74/J74 -> 38264.475 | L74: =I74-0.0000005 -> 0.0005425 | M74: =I74+0.0000005 -> 0.0005435 | N74: =1/L74 -> 1843.318 | O74: =1/M74 -> 1839.9264 | P74: =1/I74 -> 1841.6206
A75: =SCALARS!A76 -> Saturday | B75: =SCALARS!B76 -> 46151 | C75: =SCALARS!D76 -> 1841.666
A76: =SCALARS!A77 -> Sunday | B76: =SCALARS!B77 -> 46152 | C76: =SCALARS!D77 -> 1841.6761
A77: =SCALARS!A78 -> Monday | B77: =SCALARS!B78 -> 46153 | C77: =SCALARS!D78 -> 1841.6862 | D77: =G77/K77 -> 1841.6638 | E77: =C77-D77 -> 0.022375732 | F77: 3134421537 | G77: 70470000 | H77: 38266.77 | I77: 0.000543 | J77: =ARKB!H77 -> 81915.01 | K77: =F77/J77 -> 38264.312 | L77: =I77-0.0000005 -> 0.0005425 | M77: =I77+0.0000005 -> 0.0005435 | N77: =1/L77 -> 1843.318 | O77: =1/M77 -> 1839.9264 | P77: =1/I77 -> 1841.6206
A78: =SCALARS!A79 -> Tuesday | B78: =SCALARS!B79 -> 46154 | C78: =SCALARS!D79 -> 1841.6963 | D78: =G78/K78 -> 1841.6755 | E78: =C78-D78 -> 0.020820919 | F78: 3072578260 | G78: 70070000 | H78: 38049.58 | I78: 0.000543 | J78: =ARKB!H78 -> 80757.7 | K78: =F78/J78 -> 38046.877 | L78: =I78-0.0000005 -> 0.0005425 | M78: =I78+0.0000005 -> 0.0005435 | N78: =1/L78 -> 1843.318 | O78: =1/M78 -> 1839.9264 | P78: =1/I78 -> 1841.6206
A79: =SCALARS!A80 -> Wednesday | B79: =SCALARS!B80 -> 46155 | C79: =SCALARS!D80 -> 1841.7064 | D79: =G79/K79 -> 1841.6875 | E79: =C79-D79 -> 0.018890512 | F79: 2989193872 | G79: 69250000 | H79: 37604.33 | I79: 0.000543 | J79: =ARKB!H79 -> 79496.91 | K79: =F79/J79 -> 37601.384 | L79: =I79-0.0000005 -> 0.0005425 | M79: =I79+0.0000005 -> 0.0005435 | N79: =1/L79 -> 1843.318 | O79: =1/M79 -> 1839.9264 | P79: =1/I79 -> 1841.6206
A80: =SCALARS!A81 -> Thursday | B80: =SCALARS!B81 -> 46156 | C80: =SCALARS!D81 -> 1841.7165 | D80: =G80/K80 -> 1841.7145 | E80: =C80-D80 -> 0.0020158232 | F80: 3082623037 | G80: 69650000 | H80: 37821.52 | I80: 0.000543 | J80: =ARKB!H80 -> 81512.01 | K80: =F80/J80 -> 37818.023 | L80: =I80-0.0000005 -> 0.0005425 | M80: =I80+0.0000005 -> 0.0005435 | N80: =1/L80 -> 1843.318 | O80: =1/M80 -> 1839.9264 | P80: =1/I80 -> 1841.6206
A81: =SCALARS!A82 -> Friday | B81: =SCALARS!B82 -> 46157 | C81: =SCALARS!D82 -> 1841.7266 | D81: =G81/K81 -> 1841.7289 | E81: =C81-D81 -> -0.0022609392 | F81: 2979674561 | G81: 69380000 | H81: 37674.92 | I81: 0.000543 | J81: =ARKB!H81 -> 79097.04 | K81: =F81/J81 -> 37671.126 | L81: =I81-0.0000005 -> 0.0005425 | M81: =I81+0.0000005 -> 0.0005435 | N81: =1/L81 -> 1843.318 | O81: =1/M81 -> 1839.9264 | P81: =1/I81 -> 1841.6206
A82: =SCALARS!A83 -> Saturday | B82: =SCALARS!B83 -> 46158 | C82: =SCALARS!D83 -> 1841.7367
A83: =SCALARS!A84 -> Sunday | B83: =SCALARS!B84 -> 46159 | C83: =SCALARS!D84 -> 1841.7468
A84: =SCALARS!A85 -> Monday | B84: =SCALARS!B85 -> 46160 | C84: =SCALARS!D85 -> 1841.7569 | D84: =G84/K84 -> 1841.7445 | E84: =C84-D84 -> 0.012368002 | F84: 2879290586 | G84: 69160000 | H84: 37555.47 | I84: 0.000543 | J84: =ARKB!H84 -> 76676.08 | K84: =F84/J84 -> 37551.354 | L84: =I84-0.0000005 -> 0.0005425 | M84: =I84+0.0000005 -> 0.0005435 | N84: =1/L84 -> 1843.318 | O84: =1/M84 -> 1839.9264 | P84: =1/I84 -> 1841.6206
A85: =SCALARS!A86 -> Tuesday | B85: =SCALARS!B86 -> 46161 | C85: =SCALARS!D86 -> 1841.767 | D85: =G85/K85 -> 1841.7543 | E85: =C85-D85 -> 0.012736518 | F85: 2884708649 | G85: 69160000 | H85: 37555.47 | I85: 0.000543 | J85: =ARKB!H85 -> 76820.77 | K85: =F85/J85 -> 37551.155 | L85: =I85-0.0000005 -> 0.0005425 | M85: =I85+0.0000005 -> 0.0005435 | N85: =1/L85 -> 1843.318 | O85: =1/M85 -> 1839.9264 | P85: =1/I85 -> 1841.6206
A86: =SCALARS!A87 -> Wednesday | B86: =SCALARS!B87 -> 46162 | C86: =SCALARS!D87 -> 1841.7771 | D86: =G86/K86 -> 1841.7627 | E86: =C86-D86 -> 0.01442639 | F86: 2908978571 | G86: 69160000 | H86: 37555.47 | I86: 0.000543 | J86: =ARKB!H86 -> 77467.44 | K86: =F86/J86 -> 37550.984 | L86: =I86-0.0000005 -> 0.0005425 | M86: =I86+0.0000005 -> 0.0005435 | N86: =1/L86 -> 1843.318 | O86: =1/M86 -> 1839.9264 | P86: =1/I86 -> 1841.6206
A87: =SCALARS!A88 -> Thursday | B87: =SCALARS!B88 -> 46163 | C87: =SCALARS!D88 -> 1841.7872 | D87: =G87/K87 -> 1841.8029 | E87: =C87-D87 -> -0.015716182 | F87: 2910729435 | G87: 69160000 | H87: 37555.47 | I87: 0.000543 | J87: =ARKB!H87 -> 77515.76 | K87: =F87/J87 -> 37550.163 | L87: =I87-0.0000005 -> 0.0005425 | M87: =I87+0.0000005 -> 0.0005435 | N87: =1/L87 -> 1843.318 | O87: =1/M87 -> 1839.9264 | P87: =1/I87 -> 1841.6206
A88: =SCALARS!A89 -> Friday | B88: =SCALARS!B89 -> 46164 | C88: =SCALARS!D89 -> 1841.7973 | D88: =G88/K88 -> 1841.8174 | E88: =C88-D88 -> -0.020106212 | F88: 2853663405 | G88: 69160000 | H88: 37555.47 | I88: 0.000543 | J88: =ARKB!H88 -> 75996.63 | K88: =F88/J88 -> 37549.868 | L88: =I88-0.0000005 -> 0.0005425 | M88: =I88+0.0000005 -> 0.0005435 | N88: =1/L88 -> 1843.318 | O88: =1/M88 -> 1839.9264 | P88: =1/I88 -> 1841.6206
A89: =SCALARS!A90 -> Saturday | B89: =SCALARS!B90 -> 46165 | C89: =SCALARS!D90 -> 1841.8074
A90: =SCALARS!A91 -> Sunday | B90: =SCALARS!B91 -> 46166 | C90: =SCALARS!D91 -> 1841.8175
A91: =SCALARS!A92 -> Monday | B91: =SCALARS!B92 -> 46167 | C91: =SCALARS!D92 -> 1841.8276
A92: =SCALARS!A93 -> Tuesday | B92: =SCALARS!B93 -> 46168 | C92: =SCALARS!D93 -> 1841.8377 | D92: =G92/K92 -> 1841.8281 | E92: =C92-D92 -> 0.009557576 | F92: 2817992150 | G92: 68460000 | H92: 37175.41 | I92: 0.000543 | J92: =ARKB!H92 -> 75814.45 | K92: =F92/J92 -> 37169.592 | L92: =I92-0.0000005 -> 0.0005425 | M92: =I92+0.0000005 -> 0.0005435 | N92: =1/L92 -> 1843.318 | O92: =1/M92 -> 1839.9264 | P92: =1/I92 -> 1841.6206
A93: =SCALARS!A94 -> Wednesday | B93: =SCALARS!B94 -> 46169 | C93: =SCALARS!D94 -> 1841.8478 | D93: =G93/K93 -> 1841.8417 | E93: =C93-D93 -> 0.0061066643 | F93: 2766120364 | G93: 68030000 | H93: 36941.94 | I93: 0.000543 | J93: =ARKB!H93 -> 74889.84 | K93: =F93/J93 -> 36935.856 | L93: =I93-0.0000005 -> 0.0005425 | M93: =I93+0.0000005 -> 0.0005435 | N93: =1/L93 -> 1843.318 | O93: =1/M93 -> 1839.9264 | P93: =1/I93 -> 1841.6206
A94: =SCALARS!A95 -> Thursday | B94: =SCALARS!B95 -> 46170 | C94: =SCALARS!D95 -> 1841.8579 | D94: =G94/K94 -> 1841.878 | E94: =C94-D94 -> -0.020115795 | F94: 2710318888 | G94: 68030000 | H94: 36941.94 | I94: 0.000543 | J94: =ARKB!H94 -> 73380.52 | K94: =F94/J94 -> 36935.128 | L94: =I94-0.0000005 -> 0.0005425 | M94: =I94+0.0000005 -> 0.0005435 | N94: =1/L94 -> 1843.318 | O94: =1/M94 -> 1839.9264 | P94: =1/I94 -> 1841.6206
A95: =SCALARS!A96 -> Friday | B95: =SCALARS!B96 -> 46171 | C95: =SCALARS!D96 -> 1841.868 | D95: =G95/K95 -> 1841.888 | E95: =C95-D95 -> -0.020033783 | F95: 2710953832 | G95: 68030000 | H95: 36935.12 | I95: 0.000543 | J95: =ARKB!H95 -> 73398.11 | K95: =F95/J95 -> 36934.927 | L95: =I95-0.0000005 -> 0.0005425 | M95: =I95+0.0000005 -> 0.0005435 | N95: =1/L95 -> 1843.318 | O95: =1/M95 -> 1839.9264 | P95: =1/I95 -> 1841.6206
A96: =SCALARS!A97 -> Saturday | B96: =SCALARS!B97 -> 46172 | C96: =SCALARS!D97 -> 1841.8781
A97: =SCALARS!A98 -> Sunday | B97: =SCALARS!B98 -> 46173 | C97: =SCALARS!D98 -> 1841.8882
A98: =SCALARS!A99 -> Monday | B98: =SCALARS!B99 -> 46174 | C98: =SCALARS!D99 -> 1841.8983 | D98: =G98/K98 -> 1841.8981 | E98: =C98-D98 -> 0.00017298561 | F98: 2638200838 | G98: 68030000 | H98: 36935.12 | I98: 0.000543 | J98: =ARKB!H98 -> 71428.74 | K98: =F98/J98 -> 36934.725 | L98: =I98-0.0000005 -> 0.0005425 | M98: =I98+0.0000005 -> 0.0005435 | N98: =1/L98 -> 1843.318 | O98: =1/M98 -> 1839.9264 | P98: =1/I98 -> 1841.6206
A99: =SCALARS!A100 -> Tuesday | B99: =SCALARS!B100 -> 46175 | C99: =SCALARS!D100 -> 1841.9084 | D99: =G99/K99 -> 1841.9089 | E99: =C99-D99 -> -0.00048782945 | F99: 2474288173 | G99: 68030000 | H99: 36935.12 | I99: 0.000543 | J99: =ARKB!H99 -> 66991.23 | K99: =F99/J99 -> 36934.509 | L99: =I99-0.0000005 -> 0.0005425 | M99: =I99+0.0000005 -> 0.0005435 | N99: =1/L99 -> 1843.318 | O99: =1/M99 -> 1839.9264 | P99: =1/I99 -> 1841.6206
A100: =SCALARS!A101 -> Wednesday | B100: =SCALARS!B101 -> 46176 | C100: =SCALARS!D101 -> 1841.9185 | D100: =G100/K100 -> 1841.9194 | E100: =C100-D100 -> -0.00089639563 | F100: 2425922259 | G100: 68030000 | H100: 36935.12 | I100: 0.000543 | J100: =ARKB!H100 -> 65682.1 | K100: =F100/J100 -> 36934.298 | L100: =I100-0.0000005 -> 0.0005425 | M100: =I100+0.0000005 -> 0.0005435 | N100: =1/L100 -> 1843.318 | O100: =1/M100 -> 1839.9264 | P100: =1/I100 -> 1841.6206
A101: =SCALARS!A102 -> Thursday | B101: =SCALARS!B102 -> 46177 | C101: =SCALARS!D102 -> 1841.9286 | D101: =G101/K101 -> 1841.9506 | E101: =C101-D101 -> -0.022041409 | F101: 2338311213 | G101: 67580000 | H101: 36690.81 | I101: 0.000543 | J101: =ARKB!H101 -> 63732.67 | K101: =F101/J101 -> 36689.365 | L101: =I101-0.0000005 -> 0.0005425 | M101: =I101+0.0000005 -> 0.0005435 | N101: =1/L101 -> 1843.318 | O101: =1/M101 -> 1839.9264 | P101: =1/I101 -> 1841.6206
A102: =SCALARS!A103 -> Friday | B102: =SCALARS!B103 -> 46178 | C102: =SCALARS!D103 -> 1841.9387 | D102: =G102/K102 -> 1841.9636 | E102: =C102-D102 -> -0.024939313 | F102: 2189365558 | G102: 67580000 | H102: 36690.81 | I102: 0.000543 | J102: =ARKB!H102 -> 59673.45 | K102: =F102/J102 -> 36689.106 | L102: =I102-0.0000005 -> 0.0005425 | M102: =I102+0.0000005 -> 0.0005435 | N102: =1/L102 -> 1843.318 | O102: =1/M102 -> 1839.9264 | P102: =1/I102 -> 1841.6206
A103: =SCALARS!A104 -> Saturday | B103: =SCALARS!B104 -> 46179 | C103: =SCALARS!D104 -> 1841.9488
...

Sheet BRRR
A1: Bitcoin ETF | BRRR | CoinShares Valkyrie ETF
A5: DOW | B5: Date | C5: TODAY'S RATIO | D5: SHS/BTC | E5: DIFF | F5: SHS/ADJ BTC | G5: BITCOIN SHARES | H5: REF PRICE | I5: NET ASSETS | J5: CASH AND OTHER | K5: SHARES OUTSTANDING | L5: ADJ BTC
A6: =SCALARS!A7 -> Sunday | B6: =SCALARS!B7 -> 46082 | C6: =SCALARS!E7 -> 3543.8163
A7: =SCALARS!A8 -> Monday | B7: =SCALARS!B8 -> 46083 | C7: =SCALARS!E8 -> 3543.8406
A8: =SCALARS!A9 -> Tuesday | B8: =SCALARS!B9 -> 46084 | C8: =SCALARS!E9 -> 3543.8649
A9: =SCALARS!A10 -> Wednesday | B9: =SCALARS!B10 -> 46085 | C9: =SCALARS!E10 -> 3543.8892
A10: =SCALARS!A11 -> Thursday | B10: =SCALARS!B11 -> 46086 | C10: =SCALARS!E11 -> 3543.9135
A11: =SCALARS!A12 -> Friday | B11: =SCALARS!B12 -> 46087 | C11: =SCALARS!E12 -> 3543.9378
A12: =SCALARS!A13 -> Saturday | B12: =SCALARS!B13 -> 46088 | C12: =SCALARS!E13 -> 3543.9621
A13: =SCALARS!A14 -> Sunday | B13: =SCALARS!B14 -> 46089 | C13: =SCALARS!E14 -> 3543.9864
A14: =SCALARS!A15 -> Monday | B14: =SCALARS!B15 -> 46090 | C14: =SCALARS!E15 -> 3544.0107 | D14: =K14/G14 -> 3544.0384 | E14: =C14-D14 -> -0.027689602 | G14: 6228.77 | H14: 68865.77 | I14: 4.3303273e+08 | K14: 22075000
A15: =SCALARS!A16 -> Tuesday | B15: =SCALARS!B16 -> 46091 | C15: =SCALARS!E16 -> 3544.035 | D15: =K15/G15 -> 3544.0611 | E15: =C15-D15 -> -0.026148902 | F15: =K15/L15 -> 3544.0374 | G15: 6228.73 | H15: 70019.35 | I15: 4.3613454e+08 | K15: 22075000 | L15: =I15/H15 -> 6228.7717
A16: =SCALARS!A17 -> Wednesday | B16: =SCALARS!B17 -> 46092 | C16: =SCALARS!E17 -> 3544.0593 | D16: =K16/G16 -> 3544.0839 | E16: =C16-D16 -> -0.024608494 | F16: =K16/L16 -> 3544.0617 | G16: 6228.69 | H16: 70600.43 | I16: 4.3975095e+08 | K16: 22075000 | L16: =I16/H16 -> 6228.729
A17: =SCALARS!A18 -> Thursday | B17: =SCALARS!B18 -> 46093 | C17: =SCALARS!E18 -> 3544.0836 | D17: =K17/G17 -> 3544.1124 | E17: =C17-D17 -> -0.028758396 | F17: =K17/L17 -> 3544.086 | G17: 6228.64 | H17: 70182.71 | I17: 4.3714609e+08 | K17: 22075000 | L17: =I17/H17 -> 6228.6863
A18: =SCALARS!A19 -> Friday | B18: =SCALARS!B19 -> 46094 | C18: =SCALARS!E19 -> 3544.1079
A19: =SCALARS!A20 -> Saturday | B19: =SCALARS!B20 -> 46095 | C19: =SCALARS!E20 -> 3544.1322
A20: =SCALARS!A21 -> Sunday | B20: =SCALARS!B21 -> 46096 | C20: =SCALARS!E21 -> 3544.1565
A21: =SCALARS!A22 -> Monday | B21: =SCALARS!B22 -> 46097 | C21: =SCALARS!E22 -> 3544.1808 | G21: 6228.52 | H21: =ARKB!H21 -> 74073.23 | I21: 4.6136628e+08
A22: =SCALARS!A23 -> Tuesday | B22: =SCALARS!B23 -> 46098 | C22: =SCALARS!E23 -> 3544.2051 | D22: =K22/G22 -> 3544.2063 | E22: =C22-D22 -> -0.0011815962 | F22: =K22/L22 -> 3544.1906 | G22: 6256.69 | H22: =ARKB!H22 -> 74681.96 | I22: 4.6345528e+08 | K22: 22175000 | L22: =I22/H21 -> 6256.7176
A23: =SCALARS!A24 -> Wednesday | B23: =SCALARS!B24 -> 46099 | C23: =SCALARS!E24 -> 3544.2294 | D23: =K23/G23 -> 3544.2289 | E23: =C23-D23 -> 0.00045959259 | F23: =K23/L23 -> 3544.1998 | G23: 6256.65 | H23: =ARKB!H23 -> 71208.94 | I23: 467262730 | K23: 22175000 | L23: =I23/H22 -> 6256.7015
A24: =SCALARS!A25 -> Thursday | B24: =SCALARS!B25 -> 46100 | C24: =SCALARS!E25 -> 3544.2537 | D24: =K24/G24 -> 3544.2536 | E24: =C24-D24 -> 0.00011964534 | F24: =K24/L24 -> 3544.2321 | G24: 6301.75 | H24: =ARKB!H24 -> 70292.52 | I24: 4.4874365e+08 | K24: 22335000 | L24: =I24/H23 -> 6301.7881
A25: =SCALARS!A26 -> Friday | B25: =SCALARS!B26 -> 46101 | C25: =SCALARS!E26 -> 3544.278 | D25: =K25/G25 -> 3544.2817 | F25: =K25/L25 -> 3544.256 | G25: 6301.7 | H25: =H24 -> 70292.52 | I25: 442965588 | K25: 22335000 | L25: =I25/H24 -> 6301.7457
A26: =SCALARS!A27 -> Saturday | B26: =SCALARS!B27 -> 46102 | C26: =SCALARS!E27 -> 3544.3023
A27: =SCALARS!A28 -> Sunday | B27: =SCALARS!B28 -> 46103 | C27: =SCALARS!E28 -> 3544.3266
A28: =SCALARS!A29 -> Monday | B28: =SCALARS!B29 -> 46104 | C28: =SCALARS!E29 -> 3544.3509
A29: =SCALARS!A30 -> Tuesday | B29: =SCALARS!B30 -> 46105 | C29: =SCALARS!E30 -> 3544.3752 | D29: =K29/G29 -> 3544.3998 | E29: =C29-D29 -> -0.024616551 | G29: 6301.49 | H29: 69451.67 | I29: 4.3765209e+08 | K29: 22335000
A30: =SCALARS!A31 -> Wednesday | B30: =SCALARS!B31 -> 46106 | C30: =SCALARS!E31 -> 3544.3995 | D30: =K30/G30 -> 3544.4279 | E30: =C30-D30 -> -0.02844028 | F30: =K30/L30 -> 3544.3992 | G30: 6301.44 | H30: 70883.73 | I30: 446673198 | K30: 22335000 | L30: =I30/H30 -> 6301.4912
A31: =SCALARS!A32 -> Thursday | B31: =SCALARS!B32 -> 46107 | C31: =SCALARS!E32 -> 3544.4238 | D31: =K31/G31 -> 3544.4504 | E31: =C31-D31 -> -0.026639585 | F31: =K31/L31 -> 3544.4178 | G31: 6301.4 | H31: 68478.86 | I31: 431516667 | K31: 22335000 | L31: =I31/H31 -> 6301.4581
A32: =SCALARS!A33 -> Friday | B32: =SCALARS!B33 -> 46108 | C32: =SCALARS!E33 -> 3544.4481 | D32: =K32/G32 -> 3544.4504 | F32: =K32/L32 -> 3407.9663 | G32: 6301.4 | H32: 65842.59 | I32: 431516667 | K32: 22335000 | L32: =I32/H32 -> 6553.762
A33: =SCALARS!A34 -> Saturday | B33: =SCALARS!B34 -> 46109 | C33: =SCALARS!E34 -> 3544.4724
A34: =SCALARS!A35 -> Sunday | B34: =SCALARS!B35 -> 46110 | C34: =SCALARS!E35 -> 3544.4967
A35: =SCALARS!A36 -> Monday | B35: =SCALARS!B36 -> 46111 | C35: =SCALARS!E36 -> 3544.521 | D35: =K35/G35 -> 3544.5461 | E35: =C35-D35 -> -0.025064816 | F35: =K35/L35 -> 3544.5167 | G35: 6301.23 | H35: 66355.48 | I35: 418124601 | K35: 22335000 | L35: =I35/H35 -> 6301.2821
A36: =SCALARS!A37 -> Tuesday | B36: =SCALARS!B37 -> 46112 | C36: =SCALARS!E37 -> 3544.5453 | D36: =K36/G36 -> 3544.5742 | E36: =C36-D36 -> -0.028890866 | F36: =K36/L36 -> 3544.5532 | G36: 6301.18 | H36: 67831.76 | I36: 4.2742266e+08 | K36: 22335000 | L36: =I36/H36 -> 6301.2173 | N36: =D35 -> 3544.5461 | O36: =+C36-N36 -> -0.00076481592
A37: =SCALARS!A38 -> Wednesday | B37: =SCALARS!B38 -> 46113 | C37: =SCALARS!E38 -> 3544.5696 | D37: =K37/G37 -> 3544.5967 | E37: =C37-D37 -> -0.027092027 | F37: =K37/L37 -> 3544.5648 | G37: 6301.14 | H37: 68149.22 | I37: 429421644 | K37: 22335000 | L37: =I37/H37 -> 6301.1968 | N37: =D36 -> 3544.5742 | O37: =+C37-N37 -> -0.0045908658
A38: =SCALARS!A39 -> Thursday | B38: =SCALARS!B39 -> 46114 | C38: =SCALARS!E39 -> 3544.5939 | D38: =K38/G38 -> 3544.6923 | F38: =K38/L38 -> 3544.5896 | G38: 6300.97 | H38: 66994.87 | I38: 422144901 | K38: 22335000 | L38: =I38/H38 -> 6301.1526 | N38: =D37 -> 3544.5967 | O38: =+C38-N38 -> -0.0027920272
A39: =SCALARS!A40 -> Friday | B39: =SCALARS!B40 -> 46115 | C39: =SCALARS!E40 -> 3544.6182 | E39: HOLIDAY
A40: =SCALARS!A41 -> Saturday | B40: =SCALARS!B41 -> 46116 | C40: =SCALARS!E41 -> 3544.6425
A41: =SCALARS!A42 -> Sunday | B41: =SCALARS!B42 -> 46117 | C41: =SCALARS!E42 -> 3544.6668
A42: =SCALARS!A43 -> Monday | B42: =SCALARS!B43 -> 46118 | C42: =SCALARS!E43 -> 3544.6911 | D42: =K42/G42 -> 3544.7166 | E42: =C42-D42 -> -0.025527886 | F42: =K42/L42 -> 3544.6863 | G42: 6334.78 | H42: 69766.87 | I42: 4.4196156e+08 | K42: 22455000 | L42: =I42/H42 -> 6334.8342
A43: =SCALARS!A44 -> Tuesday | B43: =SCALARS!B44 -> 46119 | C43: =SCALARS!E44 -> 3544.7154 | D43: =K43/G43 -> 3544.739 | E43: =C43-D43 -> -0.023610599 | F43: =K43/L43 -> 3544.7221 | G43: 6334.74 | H43: 68612.35 | I43: 434643471 | K43: 22455000 | L43: =I43/H43 -> 6334.7702 | N43: =D42 -> 3544.7166 | O43: =+C43-N43 -> -0.0012278861
A44: =SCALARS!A45 -> Wednesday | B44: =SCALARS!B45 -> 46120 | C44: =SCALARS!E45 -> 3544.7397 | D44: =K44/G44 -> 3544.767 | E44: =C44-D44 -> -0.027289387 | F44: =K44/L44 -> 3544.7475 | G44: 6334.69 | H44: 71239.5 | I44: 451282626 | K44: 22455000 | L44: =I44/H44 -> 6334.7248 | N44: =D43 -> 3544.739 | O44: =+C44-N44 -> 0.0006894013
A45: =SCALARS!A46 -> Thursday | B45: =SCALARS!B46 -> 46121 | C45: =SCALARS!E46 -> 3544.764 | D45: =K45/G45 -> 3544.7894 | E45: =C45-D45 -> -0.025372736 | F45: =K45/L45 -> 3544.7583 | G45: 6334.65 | H45: 72005.03 | I45: 4.5613066e+08 | K45: 22455000 | L45: =I45/H45 -> 6334.7055 | N45: =D44 -> 3544.767 | O45: =+C45-N45 -> -0.002989387
A46: =SCALARS!A47 -> Friday | B46: =SCALARS!B47 -> 46122 | C46: =SCALARS!E47 -> 3544.7883 | D46: =K46/G46 -> 3544.8621 | F46: =K46/L46 -> 3544.7829 | G46: 6334.52 | H46: 73109.73 | I46: 463125393 | K46: 22455000 | L46: =I46/H46 -> 6334.6615 | N46: =D45 -> 3544.7894 | O46: =+C46-N46 -> -0.0010727357
A47: =SCALARS!A48 -> Saturday | B47: =SCALARS!B48 -> 46123 | C47: =SCALARS!E48 -> 3544.8126
A48: =SCALARS!A49 -> Sunday | B48: =SCALARS!B49 -> 46124 | C48: =SCALARS!E49 -> 3544.8369
A49: =SCALARS!A50 -> Monday | B49: =SCALARS!B50 -> 46125 | C49: =SCALARS!E50 -> 3544.8612 | D49: =K49/G49 -> 3544.8845 | E49: =C49-D49 -> -0.023305121 | F49: =K49/L49 -> 3544.8575 | G49: 6334.48 | H49: 72892.55 | I49: 4.6173992e+08 | K49: 22455000 | L49: =I49/H49 -> 6334.5283
A50: =SCALARS!A51 -> Tuesday | B50: =SCALARS!B51 -> 46126 | C50: =SCALARS!E51 -> 3544.8855 | D50: =K50/G50 -> 3544.9125 | E50: =C50-D50 -> -0.026986206 | F50: =K50/L50 -> 3544.8922 | G50: 6334.43 | H50: 74270.1 | I50: 4.7046144e+08 | K50: 22455000 | L50: =I50/H50 -> 6334.4662 | N50: =D49 -> 3544.8845 | O50: =+C50-N50 -> 0.00099487882
A51: =SCALARS!A52 -> Wednesday | B51: =SCALARS!B52 -> 46127 | C51: =SCALARS!E52 -> 3544.9098 | D51: =K51/G51 -> 3544.9349 | E51: =C51-D51 -> -0.025071393 | F51: =K51/L51 -> 3544.9062 | G51: 6334.39 | H51: 74853.53 | I51: 474155289 | K51: 22455000 | L51: =I51/H51 -> 6334.4413 | N51: =D50 -> 3544.9125 | O51: =+C51-N51 -> -0.0026862063
A52: =SCALARS!A53 -> Thursday | B52: =SCALARS!B53 -> 46128 | C52: =SCALARS!E53 -> 3544.9341 | D52: =K52/G52 -> 3544.9573 | E52: =C52-D52 -> -0.023156861 | F52: =K52/L52 -> 3544.9299 | G52: 6334.35 | H52: 75088.35 | I52: 4.7563956e+08 | K52: 22455000 | L52: =I52/H52 -> 6334.3989 | N52: =D51 -> 3544.9349 | O52: =+C52-N52 -> -0.00077139251
A53: =SCALARS!A54 -> Friday | B53: =SCALARS!B54 -> 46129 | C53: =SCALARS!E54 -> 3544.9584 | D53: =K53/G53 -> 3544.9573 | F53: =K53/L53 -> 3544.9299 | G53: 6334.35 | H53: 75088.35 | I53: 4.7563956e+08 | K53: 22455000 | L53: =I53/H53 -> 6334.3989 | N53: =D52 -> 3544.9573 | O53: =+C53-N53 -> 0.0011431386
A54: =SCALARS!A55 -> Saturday | B54: =SCALARS!B55 -> 46130 | C54: =SCALARS!E55 -> 3544.9827
A55: =SCALARS!A56 -> Sunday | B55: =SCALARS!B56 -> 46131 | C55: =SCALARS!E56 -> 3545.007
A56: =SCALARS!A57 -> Monday | B56: =SCALARS!B57 -> 46132 | C56: =SCALARS!E57 -> 3545.0313 | D56: =K56/G56 -> 3545.0593 | E56: =C56-D56 -> -0.028002719 | F56: =K56/L56 -> 3545.0298 | G56: 6410.33 | H56: 76318.82 | I56: 489232890 | K56: 22725000 | L56: =I56/H56 -> 6410.3833
A57: =SCALARS!A58 -> Tuesday | B57: =SCALARS!B58 -> 46133 | C57: =SCALARS!E58 -> 3545.0556 | D57: =K57/G57 -> 3545.0814 | E57: =C57-D57 -> -0.025823773 | F57: =K57/L57 -> 3545.0631 | G57: 6410.29 | H57: 75462.34 | I57: 483737985 | K57: 22725000 | L57: =I57/H57 -> 6410.3231 | N57: =D56 -> 3545.0593 | O57: =+C57-N57 -> -0.0037027192
A58: =SCALARS!A59 -> Wednesday | B58: =SCALARS!B59 -> 46134 | C58: =SCALARS!E59 -> 3545.0799 | D58: =K58/G58 -> 3545.1035 | E58: =C58-D58 -> -0.023645104 | F58: =K58/L58 -> 3545.0759 | G58: 6410.25 | H58: 78919.77 | I58: 505899405 | K58: 22725000 | L58: =I58/H58 -> 6410.3 | N58: =D57 -> 3545.0814 | O58: =+C58-N58 -> -0.0015237733
A59: =SCALARS!A60 -> Thursday | B59: =SCALARS!B60 -> 46135 | C59: =SCALARS!E60 -> 3545.1042 | D59: =K59/G59 -> 3545.1312 | E59: =C59-D59 -> -0.026997155 | F59: =K59/L59 -> 3545.0984 | G59: 6410.2 | H59: 77774.85 | I59: 4.9855696e+08 | K59: 22725000 | L59: =I59/H59 -> 6410.2593 | N59: =D58 -> 3545.1035 | O59: =+C59-N59 -> 0.00065489646
A60: =SCALARS!A61 -> Friday | B60: =SCALARS!B61 -> 46136 | C60: =SCALARS!E61 -> 3545.1285
A61: =SCALARS!A62 -> Saturday | B61: =SCALARS!B62 -> 46137 | C61: =SCALARS!E62 -> 3545.1528
A62: =SCALARS!A63 -> Sunday | B62: =SCALARS!B63 -> 46138 | C62: =SCALARS!E63 -> 3545.1771
A63: =SCALARS!A64 -> Monday | B63: =SCALARS!B64 -> 46139 | C63: =SCALARS!E64 -> 3545.2014 | D63: =K63/G63 -> 0 | F63: =K63/L63 -> #DIV/0! | G63: 6410.07 | H63: 77638.21 | L63: =I63/H63 -> 0
A64: =SCALARS!A65 -> Tuesday | B64: =SCALARS!B65 -> 46140 | C64: =SCALARS!E65 -> 3545.2257 | D64: =K64/G64 -> 3545.2252 | E64: =C64-D64 -> 0.00048264532 | F64: =K64/L64 -> 3545.2075 | G64: 6410.03 | H64: 76762.25 | I64: 492050790 | K64: 22725000 | L64: =I64/H64 -> 6410.0621
A65: =SCALARS!A66 -> Wednesday | B65: =SCALARS!B66 -> 46141 | C65: =SCALARS!E66 -> 3545.25 | D65: =K65/G65 -> 3545.2529 | E65: =C65-D65 -> -0.0028713038 | F65: =K65/L65 -> 3545.2204 | G65: 6409.98 | H65: 76184.66 | I65: 488346615 | J65: 4261.23 | K65: 22725000 | L65: =I65/H65 -> 6410.0386 | N65: ONE DAY AHEAD
A66: =SCALARS!A67 -> Thursday | B66: =SCALARS!B67 -> 46142 | C66: =SCALARS!E67 -> 3545.2743 | D66: =K66/G66 -> 3545.275 | E66: =C66-D66 -> -0.00069477374 | F66: =K66/L66 -> 3545.2594 | G66: 6409.94 | H66: 75446.31 | I66: 4.8360845e+08 | J66: 2221.89 | K66: 22725000 | L66: =I66/H66 -> 6409.9683
A67: =SCALARS!A68 -> Friday | B67: =SCALARS!B68 -> 46143 | C67: =SCALARS!E68 -> 3545.2986 | D67: =K67/G67 -> 3545.2996 | E67: =C67-D67 -> -0.0010393561 | F67: =K67/L67 -> 3545.2692 | G67: 6297.07 | H67: 76416.86 | I67: 481206445 | J67: 4168.6 | K67: 22325000 | L67: =I67/H67 -> 6297.124
A68: =SCALARS!A69 -> Saturday | B68: =SCALARS!B69 -> 46144 | C68: =SCALARS!E69 -> 3545.3229
A69: =SCALARS!A70 -> Sunday | B69: =SCALARS!B70 -> 46145 | C69: =SCALARS!E70 -> 3545.3472
A70: =SCALARS!A71 -> Monday | B70: =SCALARS!B71 -> 46146 | C70: =SCALARS!E71 -> 3545.3715 | D70: =K70/G70 -> 3545.3728 | E70: =C70-D70 -> -0.0013318834 | F70: =K70/L70 -> 3545.2982 | G70: 6296.94 | H70: 78415.26 | I70: 4.9378658e+08 | J70: 10388.73 | K70: 22325000 | L70: =I70/H70 -> 6297.0726
A71: =SCALARS!A72 -> Tuesday | B71: =SCALARS!B72 -> 46147 | C71: =SCALARS!E72 -> 3545.3958 | D71: =K71/G71 -> 3545.3954 | E71: =C71-D71 -> 0.00044673093 | F71: =K71/L71 -> 3545.3729 | G71: 6296.9 | H71: 80004.53 | I71: 5.0378372e+08 | J71: 3436.35 | K71: 22325000 | L71: =I71/H71 -> 6296.9399
A72: =SCALARS!A73 -> Wednesday | B72: =SCALARS!B73 -> 46148 | C72: =SCALARS!E73 -> 3545.4201 | D72: =K72/G72 -> 3545.4235 | E72: =C72-D72 -> -0.0034054035 | F72: =K72/L72 -> 3545.3966 | G72: 6296.85 | H72: 81561.14 | I72: 513582160 | J72: 3583.71 | K72: 22325000 | L72: =I72/H72 -> 6296.8978
A73: =SCALARS!A74 -> Thursday | B73: =SCALARS!B74 -> 46149 | C73: =SCALARS!E74 -> 3545.4444 | D73: =K73/G73 -> 3545.446 | E73: =C73-D73 -> -0.0016274329 | F73: =K73/L73 -> 3545.4263 | G73: 6296.81 | H73: 81354.77 | I73: 512278380 | J73: 2794.22 | K73: 22325000 | L73: =I73/H73 -> 6296.845
A74: =SCALARS!A75 -> Friday | B74: =SCALARS!B75 -> 46150 | C74: =SCALARS!E75 -> 3545.4687 | D74: =K74/G74 -> 3545.4685 | E74: =C74-D74 -> 0.00018877336 | F74: =K74/L74 -> 3545.4429 | G74: 6183.95 | H74: 80080.21 | I74: 495215590 | J74: 3772.18 | K74: 21925000 | L74: =I74/H74 -> 6183.9946
A75: =SCALARS!A76 -> Saturday | B75: =SCALARS!B76 -> 46151 | C75: =SCALARS!E76 -> 3545.493
A76: =SCALARS!A77 -> Sunday | B76: =SCALARS!B77 -> 46152 | C76: =SCALARS!E77 -> 3545.5173
A77: =SCALARS!A78 -> Monday | B77: =SCALARS!B78 -> 46153 | C77: =SCALARS!E78 -> 3545.5416 | D77: =K77/G77 -> 3545.543 | E77: =C77-D77 -> -0.0014462077 | F77: =K77/L77 -> 3545.4724 | G77: 6183.82 | H77: 80066.34 | I77: 4.951257e+08 | J77: 9824.85 | K77: 21925000 | L77: =I77/H77 -> 6183.9432
A78: =SCALARS!A79 -> Tuesday | B78: =SCALARS!B79 -> 46154 | C78: =SCALARS!E79 -> 3545.5659 | D78: =K78/G78 -> 3545.566 | E78: =C78-D78 -> -8.0678485e-05 | F78: =K78/L78 -> 3545.5364 | G78: 6183.78 | H78: 81915.01 | I78: 5.0654862e+08 | J78: 4376 | K78: 21925000 | L78: =I78/H78 -> 6183.8315
A79: =SCALARS!A80 -> Wednesday | B79: =SCALARS!B80 -> 46155 | C79: =SCALARS!E80 -> 3545.5902 | D79: =K79/G79 -> 3545.5889 | E79: =C79-D79 -> 0.001284554 | F79: =K79/L79 -> 3545.5655 | G79: 6183.74 | H79: 80757.7 | I79: 4.9938792e+08 | J79: 3639.74 | K79: 21925000 | L79: =I79/H79 -> 6183.7808
A80: =SCALARS!A81 -> Thursday | B80: =SCALARS!B81 -> 46156 | C80: =SCALARS!E81 -> 3545.6145 | D80: =K80/G80 -> 3545.6128 | E80: =C80-D80 -> 0.0016854922 | F80: =K80/L80 -> 3545.5977 | G80: 6123.06 | H80: 79496.91 | I80: 486766423 | J80: 2459.61 | K80: 21710000 | L80: =I80/H80 -> 6123.0861
A81: =SCALARS!A82 -> Friday | B81: =SCALARS!B82 -> 46157 | C81: =SCALARS!E82 -> 3545.6388 | D81: =K81/G81 -> 3545.6375 | E81: =C81-D81 -> 0.0012858034 | F81: =K81/L81 -> 3545.6191 | G81: 6066.61 | H81: 81512.01 | I81: 494504145 | J81: 2904.69 | K81: 21510000 | L81: =I81/H81 -> 6066.6415
A82: =SCALARS!A83 -> Saturday | B82: =SCALARS!B83 -> 46158 | C82: =SCALARS!E83 -> 3545.6631
A83: =SCALARS!A84 -> Sunday | B83: =SCALARS!B84 -> 46159 | C83: =SCALARS!E84 -> 3545.6874
A84: =SCALARS!A85 -> Monday | B84: =SCALARS!B85 -> 46160 | C84: =SCALARS!E85 -> 3545.7117 | D84: =K84/G84 -> 3545.7135 | E84: =C84-D84 -> -0.0017944811 | F84: =K84/L84 -> 3545.7128 | G84: 6066.48 | H84: 79097.04 | I84: 4.7984071e+08 | J84: 10823.85 | K84: 21510000 | L84: =I84/H84 -> 6066.4812
A85: =SCALARS!A86 -> Tuesday | B85: =SCALARS!B86 -> 46161 | C85: =SCALARS!E86 -> 3545.736 | D85: =K85/G85 -> 3545.7398 | E85: =C85-D85 -> -0.0037940529 | F85: =K85/L85 -> 3545.7147 | G85: 6017.08 | H85: 76676.08 | I85: 461369375 | J85: 2911.4 | K85: 21335000 | L85: =I85/H85 -> 6017.1226
A86: =SCALARS!A87 -> Wednesday | B86: =SCALARS!B87 -> 46162 | C86: =SCALARS!E87 -> 3545.7603 | D86: =K86/G86 -> 3545.7634 | E86: =C86-D86 -> -0.0030653757 | F86: =K86/L86 -> 3545.7322 | G86: 6017.04 | H86: 76820.77 | I86: 4.6223771e+08 | J86: 3799.92 | K86: 21335000 | L86: =I86/H86 -> 6017.0929
A87: =SCALARS!A88 -> Thursday | B87: =SCALARS!B88 -> 46163 | C87: =SCALARS!E88 -> 3545.7846 | D87: =K87/G87 -> 3545.7869 | E87: =C87-D87 -> -0.0023370118 | F87: =K87/L87 -> 3545.7614 | G87: 6017 | H87: 77467.44 | I87: 4.6612495e+08 | J87: 3188.11 | K87: 21335000 | L87: =I87/H87 -> 6017.0434
A88: =SCALARS!A89 -> Friday | B88: =SCALARS!B89 -> 46164 | C88: =SCALARS!E89 -> 3545.8089 | D88: =K88/G88 -> 3545.8105 | E88: =C88-D88 -> -0.0016089613 | F88: =K88/L88 -> 3545.7821 | G88: 6016.96 | H88: 77515.76 | I88: 466412969 | J88: 3663.61 | K88: 21335000 | L88: =I88/H88 -> 6017.0083
A89: =SCALARS!A90 -> Saturday | B89: =SCALARS!B90 -> 46165 | C89: =SCALARS!E90 -> 3545.8332
A90: =SCALARS!A91 -> Sunday | B90: =SCALARS!B91 -> 46166 | C90: =SCALARS!E91 -> 3545.8575
A91: =SCALARS!A92 -> Monday | B91: =SCALARS!B92 -> 46167 | C91: =SCALARS!E92 -> 3545.8818
A92: =SCALARS!A93 -> Tuesday | B92: =SCALARS!B93 -> 46168 | C92: =SCALARS!E93 -> 3545.9061 | D92: =K92/G92 -> 3545.9048 | E92: =C92-D92 -> 0.0013001064 | F92: =K92/L92 -> 3545.8097 | G92: 6016.8 | H92: 75996.63 | I92: 457268788 | J92: 12556.5 | K92: 21335000 | L92: =I92/H92 -> 6016.9614
A93: =SCALARS!A94 -> Wednesday | B93: =SCALARS!B94 -> 46169 | C93: =SCALARS!E94 -> 3545.9304 | D93: =K93/G93 -> 3545.9343 | E93: =C93-D93 -> -0.0038668384 | F93: =K93/L93 -> 3545.9127 | G93: 6016.75 | H93: 75814.45 | I93: 456159368 | J93: 2400.84 | K93: 21335000 | L93: =I93/H93 -> 6016.7866
A94: =SCALARS!A95 -> Thursday | B94: =SCALARS!B95 -> 46170 | C94: =SCALARS!E95 -> 3545.9547 | D94: =K94/G94 -> 3545.9578 | E94: =C94-D94 -> -0.0031407469 | F94: =K94/L94 -> 3545.9372 | G94: 6016.71 | H94: 74889.84 | I94: 4.5059307e+08 | J94: 2337.41 | K94: 21335000 | L94: =I94/H94 -> 6016.7449
A95: =SCALARS!A96 -> Friday | B95: =SCALARS!B96 -> 46171 | C95: =SCALARS!E96 -> 3545.979 | D95: =K95/G95 -> 3545.9799 | E95: =C95-D95 -> -0.00090414997 | F95: =K95/L95 -> 3545.9633 | G95: 5940.53 | H95: 73380.52 | I95: 4.3592122e+08 | J95: 2038.64 | K95: 21065000 | L95: =I95/H95 -> 5940.5577
A96: =SCALARS!A97 -> Saturday | B96: =SCALARS!B97 -> 46172 | C96: =SCALARS!E97 -> 3546.0033
A97: =SCALARS!A98 -> Sunday | B97: =SCALARS!B98 -> 46173 | C97: =SCALARS!E98 -> 3546.0276
A98: =SCALARS!A99 -> Monday | B98: =SCALARS!B99 -> 46174 | C98: =SCALARS!E99 -> 3546.0519 | D98: =K98/G98 -> 3546.0515 | E98: =C98-D98 -> 0.0003648366 | F98: =K98/L98 -> 3545.9737 | G98: 5940.41 | H98: 73398.11 | I98: 436024435 | J98: 9722.66 | K98: 21065000 | L98: =I98/H98 -> 5940.5404
A99: =SCALARS!A100 -> Tuesday | B99: =SCALARS!B100 -> 46175 | C99: =SCALARS!E100 -> 3546.0762 | D99: =K99/G99 -> 3546.0754 | E99: =C99-D99 -> 0.00078718901 | F99: =K99/L99 -> 3546.0473 | G99: 5940.37 | H99: 71428.74 | I99: 424316508 | J99: 3563.03 | K99: 21065000 | L99: =I99/H99 -> 5940.4171
A100: =SCALARS!A101 -> Wednesday | B100: =SCALARS!B101 -> 46176 | C100: =SCALARS!E101 -> 3546.1005 | D100: =K100/G100 -> 3546.0993 | E100: =C100-D100 -> 0.0012092199 | F100: =K100/L100 -> 3546.0771 | G100: 5940.33 | H100: 66991.23 | I100: 3.9795251e+08 | J100: 1773.58 | K100: 21065000 | L100: =I100/H100 -> 5940.3672
A101: =SCALARS!A102 -> Thursday | B101: =SCALARS!B102 -> 46177 | C101: =SCALARS!E102 -> 3546.1248 | D101: =K101/G101 -> 3546.1232 | E101: =C101-D101 -> 0.0016309291 | F101: =K101/L101 -> 3546.1093 | G101: 5940.29 | H101: 65682.1 | I101: 3.9017225e+08 | J101: 1801.18 | K101: 21065000 | L101: =I101/H101 -> 5940.3133
A102: =SCALARS!A103 -> Friday | B102: =SCALARS!B103 -> 46178 | C102: =SCALARS!E103 -> 3546.1491 | D102: =K102/G102 -> 3546.147 | E102: =C102-D102 -> 0.0020523168 | F102: =K102/L102 -> 3546.1216 | G102: 5940.25 | H102: 63732.67 | I102: 3.7859071e+08 | J102: 3028.7 | K102: 21065000 | L102: =I102/H102 -> 5940.2927
A103: =SCALARS!A104 -> Saturday | B103: =SCALARS!B104 -> 46179 | C103: =SCALARS!E104 -> 3546.1734
...

Sheet BTC
A1: https://etfs.grayscale.com/btc
A5: DAY OF WEEK | B5: DATE | C5: TODAY'S RATIO | D5: SHS/BTC | E5: DIFF | F5: BITCOIN PER SHARE | H5: ALT SHS/BTC | I5: SHARES OUTSTANDING | J5: TOTAL BITCOIN IN TRUST
A6: =SCALARS!A7 -> Sunday | B6: =SCALARS!B7 -> 46082 | C6: =SCALARS!F7 -> 2260.2814
A7: =SCALARS!A8 -> Monday | B7: =SCALARS!B8 -> 46083 | C7: =SCALARS!F8 -> 2260.2907
A8: =SCALARS!A9 -> Tuesday | B8: =SCALARS!B9 -> 46084 | C8: =SCALARS!F9 -> 2260.3
A9: =SCALARS!A10 -> Wednesday | B9: =SCALARS!B10 -> 46085 | C9: =SCALARS!F10 -> 2260.3093
A10: =SCALARS!A11 -> Thursday | B10: =SCALARS!B11 -> 46086 | C10: =SCALARS!F11 -> 2260.3186
A11: =SCALARS!A12 -> Friday | B11: =SCALARS!B12 -> 46087 | C11: =SCALARS!F12 -> 2260.3279
A12: =SCALARS!A13 -> Saturday | B12: =SCALARS!B13 -> 46088 | C12: =SCALARS!F13 -> 2260.3372
A13: =SCALARS!A14 -> Sunday | B13: =SCALARS!B14 -> 46089 | C13: =SCALARS!F14 -> 2260.3465
A14: =SCALARS!A15 -> Monday | B14: =SCALARS!B15 -> 46090 | C14: =SCALARS!F15 -> 2260.3558 | D14: =1/F14 -> 2260.3467 | E14: =C14-D14 -> 0.0090628105 | F14: 0.00044241 | H14: =I14/J14 -> 2260.3551 | I14: 116349963 | J14: 51474.196
A15: =SCALARS!A16 -> Tuesday | B15: =SCALARS!B16 -> 46091 | C15: =SCALARS!F16 -> 2260.3651 | D15: =1/F15 -> 2260.3467 | E15: =C15-D15 -> 0.018362811 | F15: 0.00044241 | H15: =I15/J15 -> 2260.3644 | I15: 116349963 | J15: 51473.984
A16: =SCALARS!A17 -> Wednesday | B16: =SCALARS!B17 -> 46092 | C16: =SCALARS!F17 -> 2260.3744 | D16: =1/F16 -> 2260.3978 | E16: =C16-D16 -> -0.023430018 | F16: 0.0004424 | H16: =I16/J16 -> 2260.3737 | I16: 116519963 | J16: 51548.982
A17: =SCALARS!A18 -> Thursday | B17: =SCALARS!B18 -> 46093 | C17: =SCALARS!F18 -> 2260.3837 | D17: =1/F17 -> 2260.3978 | E17: =C17-D17 -> -0.014130018 | F17: 0.0004424 | H17: =I17/J17 -> 2260.383 | I17: 116679963 | J17: 51619.554
A18: =SCALARS!A19 -> Friday | B18: =SCALARS!B19 -> 46094 | C18: =SCALARS!F19 -> 2260.393 | D18: =1/F18 -> 2260.3978 | E18: =C18-D18 -> -0.0048300181 | F18: 0.0004424 | H18: =I18/J18 -> 2260.3923 | I18: 116839963 | J18: 51690.126
A19: =SCALARS!A20 -> Saturday | B19: =SCALARS!B20 -> 46095 | C19: =SCALARS!F20 -> 2260.4023
A20: =SCALARS!A21 -> Sunday | B20: =SCALARS!B21 -> 46096 | C20: =SCALARS!F21 -> 2260.4116
A21: =SCALARS!A22 -> Monday | B21: =SCALARS!B22 -> 46097 | C21: =SCALARS!F22 -> 2260.4209 | D21: =1/F21 -> 2260.3978 | E21: =C21-D21 -> 0.023069982 | F21: 0.0004424 | H21: =I21/J21 -> 2260.4202 | I21: 116839963 | J21: 51689.489
A22: =SCALARS!A23 -> Tuesday | B22: =SCALARS!B23 -> 46098 | C22: =SCALARS!F23 -> 2260.4302 | D22: =1/F22 -> 2260.4489 | E22: =C22-D22 -> -0.018725157 | F22: 0.00044239 | H22: =I22/J22 -> 2260.4294 | I22: 116839963 | J22: 51689.277
A23: =SCALARS!A24 -> Wednesday | B23: =SCALARS!B24 -> 46099 | C23: =SCALARS!F24 -> 2260.4395 | D23: =1/F23 -> 2260.4489 | E23: =C23-D23 -> -0.0094251565 | F23: 0.00044239 | H23: =I23/J23 -> 2260.4387 | I23: 116839963 | J23: 51689.064
A24: =SCALARS!A25 -> Thursday | B24: =SCALARS!B25 -> 46100 | C24: =SCALARS!F25 -> 2260.4488 | D24: =1/F24 -> 2260.4489 | E24: =C24-D24 -> -0.00012515654 | F24: 0.00044239 | H24: =I24/J24 -> 2260.448 | I24: 116839963 | J24: 51688.852
A25: =SCALARS!A26 -> Friday | B25: =SCALARS!B26 -> 46101 | C25: =SCALARS!F26 -> 2260.4581 | D25: =1/F25 -> 2260.4489 | E25: =C25-D25 -> 0.0091748435 | F25: 0.00044239 | H25: =I25/J25 -> 2260.4573 | I25: 116989963 | J25: 51754.998
A26: =SCALARS!A27 -> Saturday | B26: =SCALARS!B27 -> 46102 | C26: =SCALARS!F27 -> 2260.4674
A27: =SCALARS!A28 -> Sunday | B27: =SCALARS!B28 -> 46103 | C27: =SCALARS!F28 -> 2260.4767
A28: =SCALARS!A29 -> Monday | B28: =SCALARS!B29 -> 46104 | C28: =SCALARS!F29 -> 2260.486
A29: =SCALARS!A30 -> Tuesday | B29: =SCALARS!B30 -> 46105 | C29: =SCALARS!F30 -> 2260.4953 | D29: =1/F29 -> 2260.5 | E29: =C29-D29 -> -0.004722605 | F29: 0.00044238 | H29: =I29/J29 -> 2260.4945 | I29: 116989963 | J29: 51754.147
A30: =SCALARS!A31 -> Wednesday | B30: =SCALARS!B31 -> 46106 | C30: =SCALARS!F31 -> 2260.5046 | D30: =1/F30 -> 2260.5 | E30: =C30-D30 -> 0.004577395 | F30: 0.00044238 | H30: =I30/J30 -> 2260.5038 | I30: 116989963 | J30: 51753.934
A31: =SCALARS!A32 -> Thursday | B31: =SCALARS!B32 -> 46107 | C31: =SCALARS!F32 -> 2260.5139 | D31: =1/F31 -> 2260.5 | E31: =C31-D31 -> 0.013877395 | F31: 0.00044238 | H31: =I31/J31 -> 2260.513 | I31: 116989963 | J31: 51753.722
A32: =SCALARS!A33 -> Friday | B32: =SCALARS!B33 -> 46108 | C32: =SCALARS!F33 -> 2260.5232 | D32: =1/F32 -> 2260.5 | E32: =C32-D32 -> 0.023177395 | F32: 0.00044238 | H32: =I32/J32 -> 2260.5223 | I32: 116809963 | J32: 51673.881
A33: =SCALARS!A34 -> Saturday | B33: =SCALARS!B34 -> 46109 | C33: =SCALARS!F34 -> 2260.5325
A34: =SCALARS!A35 -> Sunday | B34: =SCALARS!B35 -> 46110 | C34: =SCALARS!F35 -> 2260.5418
A35: =SCALARS!A36 -> Monday | B35: =SCALARS!B36 -> 46111 | C35: =SCALARS!F36 -> 2260.5511 | D35: =1/F35 -> 2260.5511 | E35: =C35-D35 -> -2.2363632e-05 | F35: 0.00044237 | H35: =I35/J35 -> 2260.5502 | I35: 116809963 | J35: 51673.244
A36: =SCALARS!A37 -> Tuesday | B36: =SCALARS!B37 -> 46112 | C36: =SCALARS!F37 -> 2260.5604 | D36: =1/F36 -> 2260.5511 | E36: =C36-D36 -> 0.0092776364 | F36: 0.00044237 | H36: =I36/J36 -> 2260.5595 | I36: 116809963 | J36: 51673.032
A37: =SCALARS!A38 -> Wednesday | B37: =SCALARS!B38 -> 46113 | C37: =SCALARS!F38 -> 2260.5697 | D37: =1/F37 -> 2260.5511 | E37: =C37-D37 -> 0.018577636 | F37: 0.00044237 | H37: =I37/J37 -> 2260.5688 | I37: 116809963 | J37: 51672.819
A38: =SCALARS!A39 -> Thursday | B38: =SCALARS!B39 -> 46114 | C38: =SCALARS!F39 -> 2260.579 | D38: =1/F38 -> 2260.6022 | E38: =C38-D38 -> -0.023224433 | F38: 0.00044236 | H38: =I38/J38 -> 2260.5781 | I38: 117149963 | J38: 51823.011
A39: =SCALARS!A40 -> Friday | B39: =SCALARS!B40 -> 46115 | C39: =SCALARS!F40 -> 2260.5883
A40: =SCALARS!A41 -> Saturday | B40: =SCALARS!B41 -> 46116 | C40: =SCALARS!F41 -> 2260.5976
A41: =SCALARS!A42 -> Sunday | B41: =SCALARS!B42 -> 46117 | C41: =SCALARS!F42 -> 2260.6069
A42: =SCALARS!A43 -> Monday | B42: =SCALARS!B43 -> 46118 | C42: =SCALARS!F43 -> 2260.6162 | D42: =1/F42 -> 2260.6022 | E42: =C42-D42 -> 0.013975567 | F42: 0.00044236 | H42: =I42/J42 -> 2260.6152 | I42: 117149963 | J42: 51822.159
A43: =SCALARS!A44 -> Tuesday | B43: =SCALARS!B44 -> 46119 | C43: =SCALARS!F44 -> 2260.6255 | D43: =1/F43 -> 2260.6022 | E43: =C43-D43 -> 0.023275567 | F43: 0.00044236 | H43: =I43/J43 -> 2260.6245 | I43: 117719963 | J43: 52074.089
A44: =SCALARS!A45 -> Wednesday | B44: =SCALARS!B45 -> 46120 | C44: =SCALARS!F45 -> 2260.6348 | D44: =1/F44 -> 2260.6533 | E44: =C44-D44 -> -0.018528812 | F44: 0.00044235 | H44: =I44/J44 -> 2260.6338 | I44: 117719963 | J44: 52073.875
A45: =SCALARS!A46 -> Thursday | B45: =SCALARS!B46 -> 46121 | C45: =SCALARS!F46 -> 2260.6441 | D45: =1/F45 -> 2260.6533 | E45: =C45-D45 -> -0.009228812 | F45: 0.00044235 | H45: =I45/J45 -> 2260.6431 | I45: 117719963 | J45: 52073.661
A46: =SCALARS!A47 -> Friday | B46: =SCALARS!B47 -> 46122 | C46: =SCALARS!F47 -> 2260.6534 | D46: =1/F46 -> 2260.6533 | E46: =C46-D46 -> 7.1187973e-05 | F46: 0.00044235 | H46: =I46/J46 -> 2260.6524 | I46: 117719963 | J46: 52073.447
A47: =SCALARS!A48 -> Saturday | B47: =SCALARS!B48 -> 46123 | C47: =SCALARS!F48 -> 2260.6627
A48: =SCALARS!A49 -> Sunday | B48: =SCALARS!B49 -> 46124 | C48: =SCALARS!F49 -> 2260.672
A49: =SCALARS!A50 -> Monday | B49: =SCALARS!B50 -> 46125 | C49: =SCALARS!F50 -> 2260.6813 | D49: =1/F49 -> 2260.7044 | E49: =C49-D49 -> -0.023135502 | F49: 0.00044234 | H49: =I49/J49 -> 2260.6802 | I49: 117999963 | J49: 52196.663
A50: =SCALARS!A51 -> Tuesday | B50: =SCALARS!B51 -> 46126 | C50: =SCALARS!F51 -> 2260.6906 | D50: =1/F50 -> 2260.7044 | E50: =C50-D50 -> -0.013835502 | F50: 0.00044234 | H50: =I50/J50 -> 2260.6895 | I50: 117659963 | J50: 52046.052
A51: =SCALARS!A52 -> Wednesday | B51: =SCALARS!B52 -> 46127 | C51: =SCALARS!F52 -> 2260.6999 | D51: =1/F51 -> 2260.7044 | E51: =C51-D51 -> -0.0045355021 | F51: 0.00044234 | H51: =I51/J51 -> 2260.6988 | I51: 117809963 | J51: 52112.189
A52: =SCALARS!A53 -> Thursday | B52: =SCALARS!B53 -> 46128 | C52: =SCALARS!F53 -> 2260.7092 | D52: =1/F52 -> 2260.7044 | E52: =C52-D52 -> 0.0047644979 | F52: 0.00044234 | H52: =I52/J52 -> 2260.7081 | I52: 117809963 | J52: 52111.975
A53: =SCALARS!A54 -> Friday | B53: =SCALARS!B54 -> 46129 | C53: =SCALARS!F54 -> 2260.7185 | D53: =1/F53 -> 2260.7044 | E53: =C53-D53 -> 0.014064498 | F53: 0.00044234 | H53: =I53/J53 -> 2260.7174 | I53: 118309963 | J53: 52332.929
A54: =SCALARS!A55 -> Saturday | B54: =SCALARS!B55 -> 46130 | C54: =SCALARS!F55 -> 2260.7278
A55: =SCALARS!A56 -> Sunday | B55: =SCALARS!B56 -> 46131 | C55: =SCALARS!F56 -> 2260.7371
A56: =SCALARS!A57 -> Monday | B56: =SCALARS!B57 -> 46132 | C56: =SCALARS!F57 -> 2260.7464 | D56: =1/F56 -> 2260.7555 | E56: =C56-D56 -> -0.009144503 | F56: 0.00044233 | H56: =I56/J56 -> 2260.7451 | I56: 119159963 | J56: 52708.269
A57: =SCALARS!A58 -> Tuesday | B57: =SCALARS!B58 -> 46133 | C57: =SCALARS!F58 -> 2260.7557 | D57: =1/F57 -> 2260.7555 | E57: =C57-D57 -> 0.00015549703 | F57: 0.00044233 | H57: =I57/J57 -> 2260.7544 | I57: 119159963 | J57: 52708.053
A58: =SCALARS!A59 -> Wednesday | B58: =SCALARS!B59 -> 46134 | C58: =SCALARS!F59 -> 2260.765 | D58: =1/F58 -> 2260.7555 | E58: =C58-D58 -> 0.009455497 | F58: 0.00044233 | H58: =I58/J58 -> 2260.7637 | I58: 119679963 | J58: 52937.847
A59: =SCALARS!A60 -> Thursday | B59: =SCALARS!B60 -> 46135 | C59: =SCALARS!F60 -> 2260.7743
A60: =SCALARS!A61 -> Friday | B60: =SCALARS!B61 -> 46136 | C60: =SCALARS!F61 -> 2260.7836 | D60: =1/F60 -> 2260.8067 | E60: =C60-D60 -> -0.023055815 | F60: 0.00044232 | H60: =I60/J60 -> 2260.7823 | I60: 119829963 | J60: 53003.76
A61: =SCALARS!A62 -> Saturday | B61: =SCALARS!B62 -> 46137 | C61: =SCALARS!F62 -> 2260.7929
A62: =SCALARS!A63 -> Sunday | B62: =SCALARS!B63 -> 46138 | C62: =SCALARS!F63 -> 2260.8022
A63: =SCALARS!A64 -> Monday | B63: =SCALARS!B64 -> 46139 | C63: =SCALARS!F64 -> 2260.8115 | D63: =1/F63 -> 2260.8067 | E63: =C63-D63 -> 0.0048441852 | F63: 0.00044232 | H63: =I63/J63 -> 2260.8102 | I63: 119829963 | J63: 53003.107
A64: =SCALARS!A65 -> Tuesday | B64: =SCALARS!B65 -> 46140 | C64: =SCALARS!F65 -> 2260.8208 | D64: =1/F64 -> 2260.8067 | E64: =C64-D64 -> 0.014144185 | F64: 0.00044232 | H64: =I64/J64 -> 2260.8195 | I64: 119829963 | J64: 53002.889
A65: =SCALARS!A66 -> Wednesday | B65: =SCALARS!B66 -> 46141 | C65: =SCALARS!F66 -> 2260.8301 | D65: =1/F65 -> 2260.8067 | E65: =C65-D65 -> 0.023444185 | F65: 0.00044232 | H65: =I65/J65 -> 2260.8287 | I65: 119829963 | J65: 53002.671
A66: =SCALARS!A67 -> Thursday | B66: =SCALARS!B67 -> 46142 | C66: =SCALARS!F67 -> 2260.8394 | D66: =1/F66 -> 2260.8578 | E66: =C66-D66 -> -0.018369438 | F66: 0.00044231 | H66: =I66/J66 -> 2260.838 | I66: 119829963 | J66: 53002.454
A67: =SCALARS!A68 -> Friday | B67: =SCALARS!B68 -> 46143 | C67: =SCALARS!F68 -> 2260.8487 | D67: =1/F67 -> 2260.8578 | E67: =C67-D67 -> -0.0090694377 | F67: 0.00044231 | H67: =I67/J67 -> 2260.8473 | I67: 119829963 | J67: 53002.236
A68: =SCALARS!A69 -> Saturday | B68: =SCALARS!B69 -> 46144 | C68: =SCALARS!F69 -> 2260.858
A69: =SCALARS!A70 -> Sunday | B69: =SCALARS!B70 -> 46145 | C69: =SCALARS!F70 -> 2260.8673
A70: =SCALARS!A71 -> Monday | B70: =SCALARS!B71 -> 46146 | C70: =SCALARS!F71 -> 2260.8766 | D70: =1/F70 -> 2260.8578 | E70: =C70-D70 -> 0.018830562 | F70: 0.00044231 | H70: =I70/J70 -> 2260.8752 | I70: 120009963 | J70: 53081.198
A71: =SCALARS!A72 -> Tuesday | B71: =SCALARS!B72 -> 46147 | C71: =SCALARS!F72 -> 2260.8859 | D71: =1/F71 -> 2260.9089 | E71: =C71-D71 -> -0.022985372 | F71: 0.0004423 | H71: =I71/J71 -> 2260.8845 | I71: 120009963 | J71: 53080.98
A72: =SCALARS!A73 -> Wednesday | B72: =SCALARS!B73 -> 46148 | C72: =SCALARS!F73 -> 2260.8952 | D72: =1/F72 -> 2260.9089 | E72: =C72-D72 -> -0.013685372 | F72: 0.0004423 | H72: =I72/J72 -> 2260.8938 | I72: 120009963 | J72: 53080.762
A73: =SCALARS!A74 -> Thursday | B73: =SCALARS!B74 -> 46149 | C73: =SCALARS!F74 -> 2260.9045 | D73: =1/F73 -> 2260.9089 | E73: =C73-D73 -> -0.0043853719 | F73: 0.0004423 | H73: =I73/J73 -> 2260.9031 | I73: 120009963 | J73: 53080.544
A74: =SCALARS!A75 -> Friday | B74: =SCALARS!B75 -> 46150 | C74: =SCALARS!F75 -> 2260.9138 | D74: =1/F74 -> 2260.9089 | E74: =C74-D74 -> 0.0049146281 | F74: 0.0004423 | H74: =I74/J74 -> 2260.9123 | I74: 120169963 | J74: 53151.093
A75: =SCALARS!A76 -> Saturday | B75: =SCALARS!B76 -> 46151 | C75: =SCALARS!F76 -> 2260.9231
A76: =SCALARS!A77 -> Sunday | B76: =SCALARS!B77 -> 46152 | C76: =SCALARS!F77 -> 2260.9324
A77: =SCALARS!A78 -> Monday | B77: =SCALARS!B78 -> 46153 | C77: =SCALARS!F78 -> 2260.9417 | D77: =1/F77 -> 2260.96 | E77: =C77-D77 -> -0.018303618 | F77: 0.00044229 | H77: =I77/J77 -> 2260.9402 | I77: 120169963 | J77: 53150.438
A78: =SCALARS!A79 -> Tuesday | B78: =SCALARS!B79 -> 46154 | C78: =SCALARS!F79 -> 2260.951 | D78: =1/F78 -> 2260.96 | E78: =C78-D78 -> -0.0090036175 | F78: 0.00044229 | H78: =I78/J78 -> 2260.9495 | I78: 120169963 | J78: 53150.22
A79: =SCALARS!A80 -> Wednesday | B79: =SCALARS!B80 -> 46155 | C79: =SCALARS!F80 -> 2260.9603 | D79: =1/F79 -> 2260.96 | E79: =C79-D79 -> 0.00029638246 | F79: 0.00044229 | H79: =I79/J79 -> 2260.9588 | I79: 120169963 | J79: 53150.001
A80: =SCALARS!A81 -> Thursday | B80: =SCALARS!B81 -> 46156 | C80: =SCALARS!F81 -> 2260.9696 | D80: =1/F80 -> 2260.96 | E80: =C80-D80 -> 0.0095963825 | F80: 0.00044229 | H80: =I80/J80 -> 2260.9681 | I80: 120169963 | J80: 53149.783
A81: =SCALARS!A82 -> Friday | B81: =SCALARS!B82 -> 46157 | C81: =SCALARS!F82 -> 2260.9789 | D81: =1/F81 -> 2260.96 | E81: =C81-D81 -> 0.018896382 | F81: 0.00044229 | H81: =I81/J81 -> 2260.9774 | I81: 120519963 | J81: 53304.365
A82: =SCALARS!A83 -> Saturday | B82: =SCALARS!B83 -> 46158 | C82: =SCALARS!F83 -> 2260.9882
A83: =SCALARS!A84 -> Sunday | B83: =SCALARS!B84 -> 46159 | C83: =SCALARS!F84 -> 2260.9975
A84: =SCALARS!A85 -> Monday | B84: =SCALARS!B85 -> 46160 | C84: =SCALARS!F85 -> 2261.0068 | D84: =1/F84 -> 2261.0111 | E84: =C84-D84 -> -0.0043241747 | F84: 0.00044228 | H84: =I84/J84 -> 2261.0053 | I84: 120519963 | J84: 53303.707
A85: =SCALARS!A86 -> Tuesday | B85: =SCALARS!B86 -> 46161 | C85: =SCALARS!F86 -> 2261.0161 | D85: =1/F85 -> 2261.0111 | E85: =C85-D85 -> 0.0049758253 | F85: 0.00044228 | H85: =I85/J85 -> 2261.0145 | I85: 120519963 | J85: 53303.488
A86: =SCALARS!A87 -> Wednesday | B86: =SCALARS!B87 -> 46162 | C86: =SCALARS!F87 -> 2261.0254 | D86: =1/F86 -> 2261.0111 | E86: =C86-D86 -> 0.014275825 | F86: 0.00044228 | H86: =I86/J86 -> 2261.0238 | I86: 120519963 | J86: 53303.269
A87: =SCALARS!A88 -> Thursday | B87: =SCALARS!B88 -> 46163 | C87: =SCALARS!F88 -> 2261.0347 | D87: =1/F87 -> 2261.0111 | E87: =C87-D87 -> 0.023575825 | F87: 0.00044228 | H87: =I87/J87 -> 2261.0331 | I87: 120519963 | J87: 53303.05
A88: =SCALARS!A89 -> Friday | B88: =SCALARS!B89 -> 46164 | C88: =SCALARS!F89 -> 2261.044 | D88: =1/F88 -> 2261.0622 | E88: =C88-D88 -> -0.018247044 | F88: 0.00044227 | H88: =I88/J88 -> 2261.0424 | I88: 120519963 | J88: 53302.831
A89: =SCALARS!A90 -> Saturday | B89: =SCALARS!B90 -> 46165 | C89: =SCALARS!F90 -> 2261.0533
A90: =SCALARS!A91 -> Sunday | B90: =SCALARS!B91 -> 46166 | C90: =SCALARS!F91 -> 2261.0626
A91: =SCALARS!A92 -> Monday | B91: =SCALARS!B92 -> 46167 | C91: =SCALARS!F92 -> 2261.0719
A92: =SCALARS!A93 -> Tuesday | B92: =SCALARS!B93 -> 46168 | C92: =SCALARS!F93 -> 2261.0812 | D92: =1/F92 -> 2261.0622 | E92: =C92-D92 -> 0.018952956 | F92: 0.00044227 | H92: =I92/J92 -> 2261.0796 | I92: 120519963 | J92: 53301.955
A93: =SCALARS!A94 -> Wednesday | B93: =SCALARS!B94 -> 46169 | C93: =SCALARS!F94 -> 2261.0905 | D93: =1/F93 -> 2261.1134 | E93: =C93-D93 -> -0.022872224 | F93: 0.00044226 | H93: =I93/J93 -> 2261.0889 | I93: 120119963 | J93: 53124.83
A94: =SCALARS!A95 -> Thursday | B94: =SCALARS!B95 -> 46170 | C94: =SCALARS!F95 -> 2261.0998 | D94: =1/F94 -> 2261.1134 | E94: =C94-D94 -> -0.013572224 | F94: 0.00044226 | H94: =I94/J94 -> 2261.0982 | I94: 119819963 | J94: 52991.933
A95: =SCALARS!A96 -> Friday | B95: =SCALARS!B96 -> 46171 | C95: =SCALARS!F96 -> 2261.1091 | D95: =1/F95 -> 2261.1134 | E95: =C95-D95 -> -0.0042722245 | F95: 0.00044226 | H95: =I95/J95 -> 2261.1075 | I95: 119819963 | J95: 52991.715
A96: =SCALARS!A97 -> Saturday | B96: =SCALARS!B97 -> 46172 | C96: =SCALARS!F97 -> 2261.1184
A97: =SCALARS!A98 -> Sunday | B97: =SCALARS!B98 -> 46173 | C97: =SCALARS!F98 -> 2261.1277
A98: =SCALARS!A99 -> Monday | B98: =SCALARS!B99 -> 46174 | C98: =SCALARS!F99 -> 2261.137 | D98: =1/F98 -> 2261.1134 | E98: =C98-D98 -> 0.023627776 | F98: 0.00044226 | H98: =I98/J98 -> 2261.1354 | I98: 119519963 | J98: 52858.384
A99: =SCALARS!A100 -> Tuesday | B99: =SCALARS!B100 -> 46175 | C99: =SCALARS!F100 -> 2261.1463 | D99: =1/F99 -> 2261.1645 | E99: =C99-D99 -> -0.018199717 | F99: 0.00044225 | H99: =I99/J99 -> 2261.1447 | I99: 119519963 | J99: 52858.167
A100: =SCALARS!A101 -> Wednesday | B100: =SCALARS!B101 -> 46176 | C100: =SCALARS!F101 -> 2261.1556 | D100: =1/F100 -> 2261.1645 | E100: =C100-D100 -> -0.0088997174 | F100: 0.00044225 | H100: =I100/J100 -> 2261.154 | I100: 119519963 | J100: 52857.95
A101: =SCALARS!A102 -> Thursday | B101: =SCALARS!B102 -> 46177 | C101: =SCALARS!F102 -> 2261.1649 | D101: =1/F101 -> 2261.1645 | E101: =C101-D101 -> 0.00040028265 | F101: 0.00044225 | H101: =I101/J101 -> 2261.1633 | I101: 119519963 | J101: 52857.732
A102: =SCALARS!A103 -> Friday | B102: =SCALARS!B103 -> 46178 | C102: =SCALARS!F103 -> 2261.1742 | D102: =1/F102 -> 2261.1645 | E102: =C102-D102 -> 0.0097002826 | F102: 0.00044225 | H102: =I102/J102 -> 2261.1726 | I102: 119519963 | J102: 52857.515
A103: =SCALARS!A104 -> Saturday | B103: =SCALARS!B104 -> 46179 | C103: =SCALARS!F104 -> 2261.1835
...

Sheet GBTC
A1: https://etfs.grayscale.com/gbtc
A5: DAY OF WEEK | B5: DATE | C5: TODAY'S RATIO | D5: MARKET BIAS | E5: SHS/BTC | F5: DIFF | G5: BITCOIN PER SHARE | I5: ALT SHS/BTC | J5: SHARES OUTSTANDING | K5: TOTAL BITCOIN IN TRUST
A6: =SCALARS!A7 -> Sunday | B6: =SCALARS!B7 -> 46082 | C6: =SCALARS!J7 -> 1282.9366 | D6: =-SCALARS!J$5 -> 0
A7: =SCALARS!A8 -> Monday | B7: =SCALARS!B8 -> 46083 | C7: =SCALARS!J8 -> 1282.9893 | D7: =-SCALARS!J$5 -> 0
A8: =SCALARS!A9 -> Tuesday | B8: =SCALARS!B9 -> 46084 | C8: =SCALARS!J9 -> 1283.042 | D8: =-SCALARS!J$5 -> 0
A9: =SCALARS!A10 -> Wednesday | B9: =SCALARS!B10 -> 46085 | C9: =SCALARS!J10 -> 1283.0947 | D9: =-SCALARS!J$5 -> 0
A10: =SCALARS!A11 -> Thursday | B10: =SCALARS!B11 -> 46086 | C10: =SCALARS!J11 -> 1283.1474 | D10: =-SCALARS!J$5 -> 0
A11: =SCALARS!A12 -> Friday | B11: =SCALARS!B12 -> 46087 | C11: =SCALARS!J12 -> 1283.2001 | D11: =-SCALARS!J$5 -> 0
A12: =SCALARS!A13 -> Saturday | B12: =SCALARS!B13 -> 46088 | C12: =SCALARS!J13 -> 1283.2528 | D12: =-SCALARS!J$5 -> 0
A13: =SCALARS!A14 -> Sunday | B13: =SCALARS!B14 -> 46089 | C13: =SCALARS!J14 -> 1283.3055 | D13: =-SCALARS!J$5 -> 0
A14: =SCALARS!A15 -> Monday | B14: =SCALARS!B15 -> 46090 | C14: =SCALARS!J15 -> 1283.3582 | D14: =-SCALARS!J$5 -> 0 | E14: =1/G14 -> 1283.3511 | F14: =C14+D14-E14 -> 0.0071136433 | G14: 0.00077921 | I14: =J14/K14 -> 0 | J14: =J11 -> 0 | K14: 156285.31
A15: =SCALARS!A16 -> Tuesday | B15: =SCALARS!B16 -> 46091 | C15: =SCALARS!J16 -> 1283.4109 | D15: =-SCALARS!J$5 -> 0 | E15: =1/G15 -> 1283.417 | F15: =C15+D15-E15 -> -0.0060693392 | G15: 0.00077917 | I15: =J15/K15 -> 0 | J15: =J14 -> 0 | K15: 156278.89
A16: =SCALARS!A17 -> Wednesday | B16: =SCALARS!B17 -> 46092 | C16: =SCALARS!J17 -> 1283.4636 | D16: =-SCALARS!J$5 -> 0 | E16: =1/G16 -> 1283.4664 | F16: =C16+D16-E16 -> -0.0027860154 | G16: 0.00077914 | I16: =J16/K16 -> 1283.4641 | J16: 200570100 | K16: 156272.47
A17: =SCALARS!A18 -> Thursday | B17: =SCALARS!B18 -> 46093 | C17: =SCALARS!J18 -> 1283.5163 | D17: =-SCALARS!J$5 -> 0 | E17: =1/G17 -> 1283.5158 | F17: =C17+D17-E17 -> 0.00049350284 | G17: 0.00077911 | I17: =J17/K17 -> 1283.5168 | J17: 200280100 | K17: 156040.1
A18: =SCALARS!A19 -> Friday | B18: =SCALARS!B19 -> 46094 | C18: =SCALARS!J19 -> 1283.569 | D18: =-SCALARS!J$5 -> 0 | E18: =1/G18 -> 1283.5652 | F18: =C18+D18-E18 -> 0.003769215 | G18: 0.00077908 | I18: =J18/K18 -> 1283.5696 | J18: 200100100 | K18: 155893.46
A19: =SCALARS!A20 -> Saturday | B19: =SCALARS!B20 -> 46095 | C19: =SCALARS!J20 -> 1283.6217 | D19: =-SCALARS!J$5 -> 0
A20: =SCALARS!A21 -> Sunday | B20: =SCALARS!B21 -> 46096 | C20: =SCALARS!J21 -> 1283.6745 | D20: =-SCALARS!J$5 -> 0
A21: =SCALARS!A22 -> Monday | B21: =SCALARS!B22 -> 46097 | C21: =SCALARS!J22 -> 1283.7273 | D21: =-SCALARS!J$5 -> 0 | E21: =1/G21 -> 1283.73 | F21: =C21+D21-E21 -> -0.0027059052 | G21: 0.00077898 | I21: =J21/K21 -> 1283.7278 | J21: 200100100 | K21: 155874.24
A22: =SCALARS!A23 -> Tuesday | B22: =SCALARS!B23 -> 46098 | C22: =SCALARS!J23 -> 1283.7801 | D22: =-SCALARS!J$5 -> 0 | E22: =1/G22 -> 1283.7794 | F22: =C22+D22-E22 -> 0.00065330894 | G22: 0.00077895 | I22: =J22/K22 -> 1283.7806 | J22: 200100100 | K22: 155867.83
A23: =SCALARS!A24 -> Wednesday | B23: =SCALARS!B24 -> 46099 | C23: =SCALARS!J24 -> 1283.8329 | D23: =-SCALARS!J$5 -> 0 | E23: =1/G23 -> 1283.8289 | F23: =C23+D23-E23 -> 0.0040087146 | G23: 0.00077892 | I23: =J23/K23 -> 1283.8334 | J23: 200100100 | K23: 155861.43
A24: =SCALARS!A25 -> Thursday | B24: =SCALARS!B25 -> 46100 | C24: =SCALARS!J25 -> 1283.8857 | D24: =-SCALARS!J$5 -> 0 | E24: =1/G24 -> 1283.8783 | F24: =C24+D24-E24 -> 0.0073603115 | G24: 0.00077889 | I24: =J24/K24 -> 1283.8861 | J24: 199760100 | K24: 155590.2
A25: =SCALARS!A26 -> Friday | B25: =SCALARS!B26 -> 46101 | C25: =SCALARS!J26 -> 1283.9385 | D25: =-SCALARS!J$5 -> 0 | E25: =1/G25 -> 1283.9443 | F25: =C25+D25-E25 -> -0.0057768184 | G25: 0.00077885 | I25: =J25/K25 -> 1283.9389 | J25: 199660100 | K25: 155505.92
A26: =SCALARS!A27 -> Saturday | B26: =SCALARS!B27 -> 46102 | C26: =SCALARS!J27 -> 1283.9913 | D26: =-SCALARS!J$5 -> 0
A27: =SCALARS!A28 -> Sunday | B27: =SCALARS!B28 -> 46103 | C27: =SCALARS!J28 -> 1284.0441 | D27: =-SCALARS!J$5 -> 0
A28: =SCALARS!A29 -> Monday | B28: =SCALARS!B29 -> 46104 | C28: =SCALARS!J29 -> 1284.0969 | D28: =-SCALARS!J$5 -> 0
A29: =SCALARS!A30 -> Tuesday | B29: =SCALARS!B30 -> 46105 | C29: =SCALARS!J30 -> 1284.1497 | D29: =-SCALARS!J$5 -> 0 | E29: =1/G29 -> 1284.1421 | F29: =C29+D29-E29 -> 0.0075711492 | G29: 0.00077873 | I29: =J29/K29 -> 1284.15 | J29: 199190100 | K29: 155114.36
A30: =SCALARS!A31 -> Wednesday | B30: =SCALARS!B31 -> 46106 | C30: =SCALARS!J31 -> 1284.2025 | D30: =-SCALARS!J$5 -> 0 | E30: =1/G30 -> 1284.2081 | F30: =C30+D30-E30 -> -0.0055930794 | G30: 0.00077869 | I30: =J30/K30 -> 1284.2027 | J30: 199190100 | K30: 155107.98
A31: =SCALARS!A32 -> Thursday | B31: =SCALARS!B32 -> 46107 | C31: =SCALARS!J32 -> 1284.2553 | D31: =-SCALARS!J$5 -> 0 | E31: =1/G31 -> 1284.2576 | F31: =C31+D31-E31 -> -0.0022706984 | G31: 0.00077866 | I31: =J31/K31 -> 1284.2555 | J31: 199190100 | K31: 155101.61
A32: =SCALARS!A33 -> Friday | B32: =SCALARS!B33 -> 46108 | C32: =SCALARS!J33 -> 1284.3081 | D32: =-SCALARS!J$5 -> 0 | E32: =1/G32 -> 1284.3071 | F32: =C32+D32-E32 -> 0.00104787 | G32: 0.00077863 | I32: =J32/K32 -> 1284.3083 | J32: 198720100 | K32: 154729.28
A33: =SCALARS!A34 -> Saturday | B33: =SCALARS!B34 -> 46109 | C33: =SCALARS!J34 -> 1284.3609 | D33: =-SCALARS!J$5 -> 0
A34: =SCALARS!A35 -> Sunday | B34: =SCALARS!B35 -> 46110 | C34: =SCALARS!J35 -> 1284.4137 | D34: =-SCALARS!J$5 -> 0
A35: =SCALARS!A36 -> Monday | B35: =SCALARS!B36 -> 46111 | C35: =SCALARS!J36 -> 1284.4665 | D35: =-SCALARS!J$5 -> 0 | E35: =1/G35 -> 1284.472 | F35: =C35+D35-E35 -> -0.0055177771 | G35: 0.00077853 | I35: =J35/K35 -> 1284.4667 | J35: 198720100 | K35: 154710.21
A36: =SCALARS!A37 -> Tuesday | B36: =SCALARS!B37 -> 46112 | C36: =SCALARS!J37 -> 1284.5193 | D36: =-SCALARS!J$5 -> 0 | E36: =1/G36 -> 1284.5215 | F36: =C36+D36-E36 -> -0.0022157354 | G36: 0.0007785 | I36: =J36/K36 -> 1284.5194 | J36: 198720100 | K36: 154703.85
A37: =SCALARS!A38 -> Wednesday | B37: =SCALARS!B38 -> 46113 | C37: =SCALARS!J38 -> 1284.5721 | D37: =-SCALARS!J$5 -> 0 | E37: =1/G37 -> 1284.571 | F37: =C37+D37-E37 -> 0.0010824913 | G37: 0.00077847 | I37: =J37/K37 -> 1284.5722 | J37: 198720100 | K37: 154697.49
A38: =SCALARS!A39 -> Thursday | B38: =SCALARS!B39 -> 46114 | C38: =SCALARS!J39 -> 1284.6249 | D38: =-SCALARS!J$5 -> 0 | E38: =1/G38 -> 1284.6205 | F38: =C38+D38-E38 -> 0.0043769025 | G38: 0.00077844 | I38: =J38/K38 -> 1284.625 | J38: 198470100 | K38: 154496.52
A39: =SCALARS!A40 -> Friday | B39: =SCALARS!B40 -> 46115 | C39: =SCALARS!J40 -> 1284.6777 | D39: =-SCALARS!J$5 -> 0
A40: =SCALARS!A41 -> Saturday | B40: =SCALARS!B41 -> 46116 | C40: =SCALARS!J41 -> 1284.7305 | D40: =-SCALARS!J$5 -> 0
A41: =SCALARS!A42 -> Sunday | B41: =SCALARS!B42 -> 46117 | C41: =SCALARS!J42 -> 1284.7833 | D41: =-SCALARS!J$5 -> 0
A42: =SCALARS!A43 -> Monday | B42: =SCALARS!B43 -> 46118 | C42: =SCALARS!J43 -> 1284.8361 | D42: =-SCALARS!J$5 -> 0 | E42: =1/G42 -> 1284.8351 | F42: =C42+D42-E42 -> 0.001008584 | G42: 0.00077831 | I42: =J42/K42 -> 1284.8362 | J42: 198470100 | K42: 154471.13
A43: =SCALARS!A44 -> Tuesday | B43: =SCALARS!B44 -> 46119 | C43: =SCALARS!J44 -> 1284.8889 | D43: =-SCALARS!J$5 -> 0 | E43: =1/G43 -> 1284.8846 | F43: =C43+D43-E43 -> 0.0042826386 | G43: 0.00077828 | I43: =J43/K43 -> 1284.889 | J43: 198470100 | K43: 154464.78
A44: =SCALARS!A45 -> Wednesday | B44: =SCALARS!B45 -> 46120 | C44: =SCALARS!J45 -> 1284.9417 | D44: =-SCALARS!J$5 -> 0 | E44: =1/G44 -> 1284.9341 | F44: =C44+D44-E44 -> 0.007552875 | G44: 0.00077825 | I44: =J44/K44 -> 1284.9418 | J44: 197690100 | K44: 153851.4
A45: =SCALARS!A46 -> Thursday | B45: =SCALARS!B46 -> 46121 | C45: =SCALARS!J46 -> 1284.9945 | D45: =-SCALARS!J$5 -> 0 | E45: =1/G45 -> 1285.0002 | F45: =C45+D45-E45 -> -0.00569275 | G45: 0.00077821 | I45: =J45/K45 -> 1284.9946 | J45: 197490100 | K45: 153689.44
A46: =SCALARS!A47 -> Friday | B46: =SCALARS!B47 -> 46122 | C46: =SCALARS!J47 -> 1285.0473 | D46: =-SCALARS!J$5 -> 0 | E46: =1/G46 -> 1285.0497 | F46: =C46+D46-E46 -> -0.0024314246 | G46: 0.00077818 | I46: =J46/K46 -> 1285.0474 | J46: 197490100 | K46: 153683.12
A47: =SCALARS!A48 -> Saturday | B47: =SCALARS!B48 -> 46123 | C47: =SCALARS!J48 -> 1285.1001 | D47: =-SCALARS!J$5 -> 0
A48: =SCALARS!A49 -> Sunday | B48: =SCALARS!B49 -> 46124 | C48: =SCALARS!J49 -> 1285.1529 | D48: =-SCALARS!J$5 -> 0
A49: =SCALARS!A50 -> Monday | B49: =SCALARS!B50 -> 46125 | C49: =SCALARS!J50 -> 1285.2057 | D49: =-SCALARS!J$5 -> 0 | E49: =1/G49 -> 1285.1984 | F49: =C49+D49-E49 -> 0.0073296315 | G49: 0.00077809 | I49: =J49/K49 -> 1285.2059 | J49: 197490100 | K49: 153664.17
A50: =SCALARS!A51 -> Tuesday | B50: =SCALARS!B51 -> 46126 | C50: =SCALARS!J51 -> 1285.2585 | D50: =-SCALARS!J$5 -> 0 | E50: =1/G50 -> 1285.2644 | F50: =C50+D50-E50 -> -0.0059431592 | G50: 0.00077805 | I50: =J50/K50 -> 1285.2587 | J50: 196820100 | K50: 153136.56
A51: =SCALARS!A52 -> Wednesday | B51: =SCALARS!B52 -> 46127 | C51: =SCALARS!J52 -> 1285.3113 | D51: =-SCALARS!J$5 -> 0 | E51: =1/G51 -> 1285.314 | F51: =C51+D51-E51 -> -0.0027022107 | G51: 0.00077802 | I51: =J51/K51 -> 1285.3115 | J51: 196820100 | K51: 153130.27
A52: =SCALARS!A53 -> Thursday | B52: =SCALARS!B53 -> 46128 | C52: =SCALARS!J53 -> 1285.3641 | D52: =-SCALARS!J$5 -> 0 | E52: =1/G52 -> 1285.3636 | F52: =C52+D52-E52 -> 0.00053491562 | G52: 0.00077799 | I52: =J52/K52 -> 1285.3644 | J52: 196420100 | K52: 152812.78
A53: =SCALARS!A54 -> Friday | B53: =SCALARS!B54 -> 46129 | C53: =SCALARS!J54 -> 1285.4169 | D53: =-SCALARS!J$5 -> 0 | E53: =1/G53 -> 1285.4131 | F53: =C53+D53-E53 -> 0.0037682194 | G53: 0.00077796 | I53: =J53/K53 -> 1285.4172 | J53: 196040100 | K53: 152510.88
A54: =SCALARS!A55 -> Saturday | B54: =SCALARS!B55 -> 46130 | C54: =SCALARS!J55 -> 1285.4697 | D54: =-SCALARS!J$5 -> 0
A55: =SCALARS!A56 -> Sunday | B55: =SCALARS!B56 -> 46131 | C55: =SCALARS!J56 -> 1285.5225 | D55: =-SCALARS!J$5 -> 0
A56: =SCALARS!A57 -> Monday | B56: =SCALARS!B57 -> 46132 | C56: =SCALARS!J57 -> 1285.5753 | D56: =-SCALARS!J$5 -> 0 | E56: =1/G56 -> 1285.5784 | F56: =C56+D56-E56 -> -0.0030817139 | G56: 0.00077786 | I56: =J56/K56 -> 1285.5756 | J56: 196110100 | K56: 152546.53
A57: =SCALARS!A58 -> Tuesday | B57: =SCALARS!B58 -> 46133 | C57: =SCALARS!J58 -> 1285.6281 | D57: =-SCALARS!J$5 -> 0 | E57: =1/G57 -> 1285.628 | F57: =C57+D57-E57 -> 0.00013502051 | G57: 0.00077783 | I57: =J57/K57 -> 1285.6285 | J57: 195690100 | K57: 152213.57
A58: =SCALARS!A59 -> Wednesday | B58: =SCALARS!B59 -> 46134 | C58: =SCALARS!J59 -> 1285.6809 | D58: =-SCALARS!J$5 -> 0 | E58: =1/G58 -> 1285.6776 | F58: =C58+D58-E58 -> 0.0033479301 | G58: 0.0007778 | I58: =J58/K58 -> 1285.6813 | J58: 195390100 | K58: 151973.98
A59: =SCALARS!A60 -> Thursday | B59: =SCALARS!B60 -> 46135 | C59: =SCALARS!J60 -> 1285.7337 | D59: =-SCALARS!J$5 -> 0
A60: =SCALARS!A61 -> Friday | B60: =SCALARS!B61 -> 46136 | C60: =SCALARS!J61 -> 1285.7865 | D60: =-SCALARS!J$5 -> 0 | E60: =1/G60 -> 1285.7933 | F60: =C60+D60-E60 -> -0.006770158 | G60: 0.00077773 | I60: =J60/K60 -> 1285.787 | J60: 195120100 | K60: 151751.5
A61: =SCALARS!A62 -> Saturday | B61: =SCALARS!B62 -> 46137 | C61: =SCALARS!J62 -> 1285.8393 | D61: =-SCALARS!J$5 -> 0
A62: =SCALARS!A63 -> Sunday | B62: =SCALARS!B63 -> 46138 | C62: =SCALARS!J63 -> 1285.8921 | D62: =-SCALARS!J$5 -> 0
A63: =SCALARS!A64 -> Monday | B63: =SCALARS!B64 -> 46139 | C63: =SCALARS!J64 -> 1285.9449 | D63: =-SCALARS!J$5 -> 0 | E63: =1/G63 -> 1285.9421 | F63: =C63+D63-E63 -> 0.0028188313 | G63: 0.00077764 | I63: =J63/K63 -> 1285.9455 | J63: 195120100 | K63: 151732.79
A64: =SCALARS!A65 -> Tuesday | B64: =SCALARS!B65 -> 46140 | C64: =SCALARS!J65 -> 1285.9977 | D64: =-SCALARS!J$5 -> 0 | E64: =1/G64 -> 1285.9917 | F64: =C64+D64-E64 -> 0.0060075063 | G64: 0.00077761 | I64: =J64/K64 -> 1285.9984 | J64: 194340100 | K64: 151120.02
A65: =SCALARS!A66 -> Wednesday | B65: =SCALARS!B66 -> 46141 | C65: =SCALARS!J66 -> 1286.0505 | D65: =-SCALARS!J$5 -> 0 | E65: =1/G65 -> 1286.0578 | F65: =C65+D65-E65 -> -0.007346882 | G65: 0.00077757 | I65: =J65/K65 -> 1286.0512 | J65: 194340100 | K65: 151113.81
A66: =SCALARS!A67 -> Thursday | B66: =SCALARS!B67 -> 46142 | C66: =SCALARS!J67 -> 1286.1034 | D66: =-SCALARS!J$5 -> 0 | E66: =1/G66 -> 1286.1075 | F66: =C66+D66-E66 -> -0.00406714 | G66: 0.00077754 | I66: =J66/K66 -> 1286.1041 | J66: 193980100 | K66: 150827.69
A67: =SCALARS!A68 -> Friday | B67: =SCALARS!B68 -> 46143 | C67: =SCALARS!J68 -> 1286.1563 | D67: =-SCALARS!J$5 -> 0 | E67: =1/G67 -> 1286.1571 | F67: =C67+D67-E67 -> -0.00079122712 | G67: 0.00077751 | I67: =J67/K67 -> 1286.1569 | J67: 193880100 | K67: 150743.74
A68: =SCALARS!A69 -> Saturday | B68: =SCALARS!B69 -> 46144 | C68: =SCALARS!J69 -> 1286.2092 | D68: =-SCALARS!J$5 -> 0
A69: =SCALARS!A70 -> Sunday | B69: =SCALARS!B70 -> 46145 | C69: =SCALARS!J70 -> 1286.2621 | D69: =-SCALARS!J$5 -> 0
A70: =SCALARS!A71 -> Monday | B70: =SCALARS!B71 -> 46146 | C70: =SCALARS!J71 -> 1286.315 | D70: =-SCALARS!J$5 -> 0 | E70: =1/G70 -> 1286.3225 | F70: =C70+D70-E70 -> -0.0075325118 | G70: 0.00077741 | I70: =J70/K70 -> 1286.3155 | J70: 193880100 | K70: 150725.15
A71: =SCALARS!A72 -> Tuesday | B71: =SCALARS!B72 -> 46147 | C71: =SCALARS!J72 -> 1286.3679 | D71: =-SCALARS!J$5 -> 0 | E71: =1/G71 -> 1286.3722 | F71: =C71+D71-E71 -> -0.0042731971 | G71: 0.00077738 | I71: =J71/K71 -> 1286.3684 | J71: 193880100 | K71: 150718.96
A72: =SCALARS!A73 -> Wednesday | B72: =SCALARS!B73 -> 46148 | C72: =SCALARS!J73 -> 1286.4208 | D72: =-SCALARS!J$5 -> 0 | E72: =1/G72 -> 1286.4218 | F72: =C72+D72-E72 -> -0.001017714 | G72: 0.00077735 | I72: =J72/K72 -> 1286.4212 | J72: 193590100 | K72: 150487.33
A73: =SCALARS!A74 -> Thursday | B73: =SCALARS!B74 -> 46149 | C73: =SCALARS!J74 -> 1286.4737 | D73: =-SCALARS!J$5 -> 0 | E73: =1/G73 -> 1286.4715 | F73: =C73+D73-E73 -> 0.0022339371 | G73: 0.00077732 | I73: =J73/K73 -> 1286.4741 | J73: 193320100 | K73: 150271.27
A74: =SCALARS!A75 -> Friday | B74: =SCALARS!B75 -> 46150 | C74: =SCALARS!J75 -> 1286.5266 | D74: =-SCALARS!J$5 -> 0 | E74: =1/G74 -> 1286.5211 | F74: =C74+D74-E74 -> 0.0054817558 | G74: 0.00077729 | I74: =J74/K74 -> 1286.527 | J74: 192890100 | K74: 149930.86
A75: =SCALARS!A76 -> Saturday | B75: =SCALARS!B76 -> 46151 | C75: =SCALARS!J76 -> 1286.5795 | D75: =-SCALARS!J$5 -> 0
A76: =SCALARS!A77 -> Sunday | B76: =SCALARS!B77 -> 46152 | C76: =SCALARS!J77 -> 1286.6324 | D76: =-SCALARS!J$5 -> 0
A77: =SCALARS!A78 -> Monday | B77: =SCALARS!B78 -> 46153 | C77: =SCALARS!J78 -> 1286.6853 | D77: =-SCALARS!J$5 -> 0 | E77: =1/G77 -> 1286.6867 | F77: =C77+D77-E77 -> -0.0013531993 | G77: 0.00077719 | I77: =J77/K77 -> 1286.6856 | J77: 192890100 | K77: 149912.38
A78: =SCALARS!A79 -> Tuesday | B78: =SCALARS!B79 -> 46154 | C78: =SCALARS!J79 -> 1286.7382 | D78: =-SCALARS!J$5 -> 0 | E78: =1/G78 -> 1286.7363 | F78: =C78+D78-E78 -> 0.0018780071 | G78: 0.00077716 | I78: =J78/K78 -> 1286.7385 | J78: 192890100 | K78: 149906.22
A79: =SCALARS!A80 -> Wednesday | B79: =SCALARS!B80 -> 46155 | C79: =SCALARS!J80 -> 1286.7911 | D79: =-SCALARS!J$5 -> 0 | E79: =1/G79 -> 1286.786 | F79: =C79+D79-E79 -> 0.0051053788 | G79: 0.00077713 | I79: =J79/K79 -> 1286.7914 | J79: 192610100 | K79: 149682.46
A80: =SCALARS!A81 -> Thursday | B80: =SCALARS!B81 -> 46156 | C80: =SCALARS!J81 -> 1286.844 | D80: =-SCALARS!J$5 -> 0 | E80: =1/G80 -> 1286.8522 | F80: =C80+D80-E80 -> -0.0082307583 | G80: 0.00077709 | I80: =J80/K80 -> 1286.8442 | J80: 192610100 | K80: 149676.31
A81: =SCALARS!A82 -> Friday | B81: =SCALARS!B82 -> 46157 | C81: =SCALARS!J82 -> 1286.8969 | D81: =-SCALARS!J$5 -> 0 | E81: =1/G81 -> 1286.9019 | F81: =C81+D81-E81 -> -0.0050123362 | G81: 0.00077706 | I81: =J81/K81 -> 1286.8971 | J81: 192110100 | K81: 149281.63
A82: =SCALARS!A83 -> Saturday | B82: =SCALARS!B83 -> 46158 | C82: =SCALARS!J83 -> 1286.9498 | D82: =-SCALARS!J$5 -> 0
A83: =SCALARS!A84 -> Sunday | B83: =SCALARS!B84 -> 46159 | C83: =SCALARS!J84 -> 1287.0027 | D83: =-SCALARS!J$5 -> 0
A84: =SCALARS!A85 -> Monday | B84: =SCALARS!B85 -> 46160 | C84: =SCALARS!J85 -> 1287.0556 | D84: =-SCALARS!J$5 -> 0 | E84: =1/G84 -> 1287.051 | F84: =C84+D84-E84 -> 0.0046199107 | G84: 0.00077697 | I84: =J84/K84 -> 1287.0562 | J84: 191400100 | K84: 148711.53
A85: =SCALARS!A86 -> Tuesday | B85: =SCALARS!B86 -> 46161 | C85: =SCALARS!J86 -> 1287.1085 | D85: =-SCALARS!J$5 -> 0 | E85: =1/G85 -> 1287.1172 | F85: =C85+D85-E85 -> -0.0087435097 | G85: 0.00077693 | I85: =J85/K85 -> 1287.1091 | J85: 191400100 | K85: 148705.42
A86: =SCALARS!A87 -> Wednesday | B86: =SCALARS!B87 -> 46162 | C86: =SCALARS!J87 -> 1287.1614 | D86: =-SCALARS!J$5 -> 0 | E86: =1/G86 -> 1287.1669 | F86: =C86+D86-E86 -> -0.0055455528 | G86: 0.0007769 | I86: =J86/K86 -> 1287.162 | J86: 191400100 | K86: 148699.31
A87: =SCALARS!A88 -> Thursday | B87: =SCALARS!B88 -> 46163 | C87: =SCALARS!J88 -> 1287.2143 | D87: =-SCALARS!J$5 -> 0 | E87: =1/G87 -> 1287.2167 | F87: =C87+D87-E87 -> -0.0023514346 | G87: 0.00077687 | I87: =J87/K87 -> 1287.2149 | J87: 191400100 | K87: 148693.2
A88: =SCALARS!A89 -> Friday | B88: =SCALARS!B89 -> 46164 | C88: =SCALARS!J89 -> 1287.2672 | D88: =-SCALARS!J$5 -> 0 | E88: =1/G88 -> 1287.2664 | F88: =C88+D88-E88 -> 0.00083884455 | G88: 0.00077684 | I88: =J88/K88 -> 1287.2678 | J88: 191400100 | K88: 148687.09
A89: =SCALARS!A90 -> Saturday | B89: =SCALARS!B90 -> 46165 | C89: =SCALARS!J90 -> 1287.3201 | D89: =-SCALARS!J$5 -> 0
A90: =SCALARS!A91 -> Sunday | B90: =SCALARS!B91 -> 46166 | C90: =SCALARS!J91 -> 1287.373 | D90: =-SCALARS!J$5 -> 0
A91: =SCALARS!A92 -> Monday | B91: =SCALARS!B92 -> 46167 | C91: =SCALARS!J92 -> 1287.4259 | D91: =-SCALARS!J$5 -> 0
A92: =SCALARS!A93 -> Tuesday | B92: =SCALARS!B93 -> 46168 | C92: =SCALARS!J93 -> 1287.4788 | D92: =-SCALARS!J$5 -> 0 | E92: =1/G92 -> 1287.4818 | F92: =C92+D92-E92 -> -0.0030143194 | G92: 0.00077671 | I92: =J92/K92 -> 1287.4794 | J92: 191400100 | K92: 148662.65
A93: =SCALARS!A94 -> Wednesday | B93: =SCALARS!B94 -> 46169 | C93: =SCALARS!J94 -> 1287.5317 | D93: =-SCALARS!J$5 -> 0 | E93: =1/G93 -> 1287.5315 | F93: =C93+D93-E93 -> 0.00015547716 | G93: 0.00077668 | I93: =J93/K93 -> 1287.5323 | J93: 190700100 | K93: 148112.86
A94: =SCALARS!A95 -> Thursday | B94: =SCALARS!B95 -> 46170 | C94: =SCALARS!J95 -> 1287.5846 | D94: =-SCALARS!J$5 -> 0 | E94: =1/G94 -> 1287.5813 | F94: =C94+D94-E94 -> 0.0033214318 | G94: 0.00077665 | I94: =J94/K94 -> 1287.5852 | J94: 188900100 | K94: 146708.81
A95: =SCALARS!A96 -> Friday | B95: =SCALARS!B96 -> 46171 | C95: =SCALARS!J96 -> 1287.6375 | D95: =-SCALARS!J$5 -> 0 | E95: =1/G95 -> 1287.631 | F95: =C95+D95-E95 -> 0.0064835441 | G95: 0.00077662 | I95: =J95/K95 -> 1287.6382 | J95: 188440100 | K95: 146345.54
A96: =SCALARS!A97 -> Saturday | B96: =SCALARS!B97 -> 46172 | C96: =SCALARS!J97 -> 1287.6904 | D96: =-SCALARS!J$5 -> 0
A97: =SCALARS!A98 -> Sunday | B97: =SCALARS!B98 -> 46173 | C97: =SCALARS!J98 -> 1287.7433 | D97: =-SCALARS!J$5 -> 0
A98: =SCALARS!A99 -> Monday | B98: =SCALARS!B99 -> 46174 | C98: =SCALARS!J99 -> 1287.7962 | D98: =-SCALARS!J$5 -> 0 | E98: =1/G98 -> 1287.7968 | F98: =C98+D98-E98 -> -0.00063717097 | G98: 0.00077652 | I98: =J98/K98 -> 1287.797 | J98: 188390100 | K98: 146288.67
A99: =SCALARS!A100 -> Tuesday | B99: =SCALARS!B100 -> 46175 | C99: =SCALARS!J100 -> 1287.8491 | D99: =-SCALARS!J$5 -> 0 | E99: =1/G99 -> 1287.8466 | F99: =C99+D99-E99 -> 0.002508286 | G99: 0.00077649 | I99: =J99/K99 -> 1287.8499 | J99: 188390100 | K99: 146282.66
A100: =SCALARS!A101 -> Wednesday | B100: =SCALARS!B101 -> 46176 | C100: =SCALARS!J101 -> 1287.902 | D100: =-SCALARS!J$5 -> 0 | E100: =1/G100 -> 1287.8964 | F100: =C100+D100-E100 -> 0.0056498983 | G100: 0.00077646 | I100: =J100/K100 -> 1287.9028 | J100: 186790100 | K100: 145034.31
A101: =SCALARS!A102 -> Thursday | B101: =SCALARS!B102 -> 46177 | C101: =SCALARS!J102 -> 1287.9549 | D101: =-SCALARS!J$5 -> 0 | E101: =1/G101 -> 1287.9627 | F101: =C101+D101-E101 -> -0.0078006002 | G101: 0.00077642 | I101: =J101/K101 -> 1287.9557 | J101: 186790100 | K101: 145028.35
A102: =SCALARS!A103 -> Friday | B102: =SCALARS!B103 -> 46178 | C102: =SCALARS!J103 -> 1288.0078 | D102: =-SCALARS!J$5 -> 0 | E102: =1/G102 -> 1288.0125 | F102: =C102+D102-E102 -> -0.0046679607 | G102: 0.00077639 | I102: =J102/K102 -> 1288.0087 | J102: 186790100 | K102: 145022.39
A103: =SCALARS!A104 -> Saturday | B103: =SCALARS!B104 -> 46179 | C103: =SCALARS!J104 -> 1288.0607 | D103: =-SCALARS!J$5 -> 0
...

Sheet HODL
A1: HODL ETF – VanEck Bitcoin ETF | Holdings & Performance | VanEck
A5: DOW | B5: Date | C5: TODAY'S RATIO | D5: SHS/BTC | E5: DIFF | F5: SHARES OUTSTANDING | G5: BITCOIN PER SHARE | H5: BITCOIN IN TRUST | I5: ROUND DOWN BTC / SH | J5: ROUND UP BTC/SH | K5: HIGH BOUND SHS/BTC | L5: LOW BOUND SHS/BTC | M5: ADJ SHS/BTC
A6: =SCALARS!A7 -> Sunday | B6: =SCALARS!B7 -> 46082 | C6: =SCALARS!K7 -> 3535.8029
A7: =SCALARS!A8 -> Monday | B7: =SCALARS!B8 -> 46083 | C7: =SCALARS!K8 -> 3535.8029
A8: =SCALARS!A9 -> Tuesday | B8: =SCALARS!B9 -> 46084 | C8: =SCALARS!K9 -> 3535.8029
A9: =SCALARS!A10 -> Wednesday | B9: =SCALARS!B10 -> 46085 | C9: =SCALARS!K10 -> 3535.8029
A10: =SCALARS!A11 -> Thursday | B10: =SCALARS!B11 -> 46086 | C10: =SCALARS!K11 -> 3535.8029
A11: =SCALARS!A12 -> Friday | B11: =SCALARS!B12 -> 46087 | C11: =SCALARS!K12 -> 3535.8029
A12: =SCALARS!A13 -> Saturday | B12: =SCALARS!B13 -> 46088 | C12: =SCALARS!K13 -> 3535.8029
A13: =SCALARS!A14 -> Sunday | B13: =SCALARS!B14 -> 46089 | C13: =SCALARS!K14 -> 3535.8029
A14: =SCALARS!A15 -> Monday | B14: =SCALARS!B15 -> 46090 | C14: =SCALARS!K15 -> 3535.8029 | D14: =F14/H14 -> 3535.8027 | E14: =C14-D14 -> 0.00019076972 | F14: 59925000 | G14: 0.000283 | H14: 16948.061 | I14: =G14-0.0000005 -> 0.0002825 | J14: =G14+0.0000005 -> 0.0002835 | K14: =1/I14 -> 3539.823 | L14: =1/J14 -> 3527.3369 | M14: =1/G14 -> 3533.5689
A15: =SCALARS!A16 -> Tuesday | B15: =SCALARS!B16 -> 46091 | C15: =SCALARS!K16 -> 3535.8029 | D15: =F15/H15 -> 3535.803 | E15: =C15-D15 -> -7.9828442e-05 | F15: 60175000 | G15: 0.000283 | H15: 17018.765 | I15: =G15-0.0000005 -> 0.0002825 | J15: =G15+0.0000005 -> 0.0002835 | K15: =1/I15 -> 3539.823 | L15: =1/J15 -> 3527.3369 | M15: =1/G15 -> 3533.5689
A16: =SCALARS!A17 -> Wednesday | B16: =SCALARS!B17 -> 46092 | C16: =SCALARS!K17 -> 3535.8029 | D16: =F16/H16 -> 3535.802 | E16: =C16-D16 -> 0.00088012303 | F16: 60475000 | G16: 0.000283 | H16: 17103.616 | I16: =G16-0.0000005 -> 0.0002825 | J16: =G16+0.0000005 -> 0.0002835 | K16: =1/I16 -> 3539.823 | L16: =1/J16 -> 3527.3369 | M16: =1/G16 -> 3533.5689
A17: =SCALARS!A18 -> Thursday | B17: =SCALARS!B18 -> 46093 | C17: =SCALARS!K18 -> 3535.8029 | D17: =F17/H17 -> 3535.7981 | F17: 60250000 | G17: 0.000283 | H17: 17040 | I17: =G17-0.0000005 -> 0.0002825 | J17: =G17+0.0000005 -> 0.0002835 | K17: =1/I17 -> 3539.823 | L17: =1/J17 -> 3527.3369 | M17: =1/G17 -> 3533.5689
