Workbook

Sheet Pivot summary
A1: P&L by Pair — normalized source summary (USD)
A2: Asset class / Pair | B2: June 2026 | H2: July 2026 | N2: August 2026 | T2: September 2026 | Z2: October 2026 | AF2: Grand total
B3: MTM P&L | C3: Commissions | D3: Borrow | E3: Dividends / PIL | F3: Other | G3: Net P&L | H3: MTM P&L | I3: Commissions | J3: Borrow | K3: Dividends / PIL | L3: Other | M3: Net P&L | N3: MTM P&L | O3: Commissions | P3: Borrow | Q3: Dividends / PIL | R3: Other | S3: Net P&L | T3: MTM P&L | U3: Commissions | V3: Borrow | W3: Dividends / PIL | X3: Other | Y3: Net P&L | Z3: MTM P&L | AA3: Commissions | AB3: Borrow | AC3: Dividends / PIL | AD3: Other | AE3: Net P&L | AF3: MTM P&L | AG3: Commissions | AH3: Borrow | AI3: Dividends / PIL | AJ3: Other | AK3: Net P&L
A4: EQUITIES
A5: IYW / XLK | B5: =SUMIFS('P&L Table'!$F$2:$F$303,'P&L Table'!$A$2:$A$303,"June",'P&L Table'!$C$2:$C$303,$A5,'P&L Table'!$E$2:$E$303,"MTM P&L") -> 0 | C5: =SUMIFS('P&L Table'!$F$2:$F$303,'P&L Table'!$A$2:$A$303,"June",'P&L Table'!$C$2:$C$303,$A5,'P&L Table'!$E$2:$E$303,"Commissions") -> 0 | D5: =SUMIFS('P&L Table'!$F$2:$F$303,'P&L Table'!$A$2:$A$303,"June",'P&L Table'!$C$2:$C$303,$A5,'P&L Table'!$E$2:$E$303,"Borrow") -> 0 | E5: =SUMIFS('P&L Table'!$F$2:$F$303,'P&L Table'!$A$2:$A$303,"June",'P&L Table'!$C$2:$C$303,$A5,'P&L Table'!$E$2:$E$303,"Dividends / PIL") -> 0 | F5: =SUMIFS('P&L Table'!$F$2:$F$303,'P&L Table'!$A$2:$A$303,"June",'P&L Table'!$C$2:$C$303,$A5,'P&L Table'!$E$2:$E$303,"Other") -> 0 | G5: =SUM(B5:F5) -> 0 | H5: =SUMIFS('P&L Table'!$F$2:$F$303,'P&L Table'!$A$2:$A$303,"July",'P&L Table'!$C$2:$C$303,$A5,'P&L Table'!$E$2:$E$303,"MTM P&L") -> 0 | I5: =SUMIFS('P&L Table'!$F$2:$F$303,'P&L Table'!$A$2:$A$303,"July",'P&L Table'!$C$2:$C$303,$A5,'P&L Table'!$E$2:$E$303,"Commissions") -> 0 | J5: =SUMIFS('P&L Table'!$F$2:$F$303,'P&L Table'!$A$2:$A$303,"July",'P&L Table'!$C$2:$C$303,$A5,'P&L Table'!$E$2:$E$303,"Borrow") -> 0 | K5: =SUMIFS('P&L Table'!$F$2:$F$303,'P&L Table'!$A$2:$A$303,"July",'P&L Table'!$C$2:$C$303,$A5,'P&L Table'!$E$2:$E$303,"Dividends / PIL") -> 0 | L5: =SUMIFS('P&L Table'!$F$2:$F$303,'P&L Table'!$A$2:$A$303,"July",'P&L Table'!$C$2:$C$303,$A5,'P&L Table'!$E$2:$E$303,"Other") -> 0 | M5: =SUM(H5:L5) -> 0 | N5: =SUMIFS('P&L Table'!$F$2:$F$303,'P&L Table'!$A$2:$A$303,"August",'P&L Table'!$C$2:$C$303,$A5,'P&L Table'!$E$2:$E$303,"MTM P&L") -> 0 | O5: =SUMIFS('P&L Table'!$F$2:$F$303,'P&L Table'!$A$2:$A$303,"August",'P&L Table'!$C$2:$C$303,$A5,'P&L Table'!$E$2:$E$303,"Commissions") -> 0 | P5: =SUMIFS('P&L Table'!$F$2:$F$303,'P&L Table'!$A$2:$A$303,"August",'P&L Table'!$C$2:$C$303,$A5,'P&L Table'!$E$2:$E$303,"Borrow") -> 0 | Q5: =SUMIFS('P&L Table'!$F$2:$F$303,'P&L Table'!$A$2:$A$303,"August",'P&L Table'!$C$2:$C$303,$A5,'P&L Table'!$E$2:$E$303,"Dividends / PIL") -> 0 | R5: =SUMIFS('P&L Table'!$F$2:$F$303,'P&L Table'!$A$2:$A$303,"August",'P&L Table'!$C$2:$C$303,$A5,'P&L Table'!$E$2:$E$303,"Other") -> 0 | S5: =SUM(N5:R5) -> 0 | T5: =SUMIFS('P&L Table'!$F$2:$F$303,'P&L Table'!$A$2:$A$303,"September",'P&L Table'!$C$2:$C$303,$A5,'P&L Table'!$E$2:$E$303,"MTM P&L") -> 10454.02 | U5: =SUMIFS('P&L Table'!$F$2:$F$303,'P&L Table'!$A$2:$A$303,"September",'P&L Table'!$C$2:$C$303,$A5,'P&L Table'!$E$2:$E$303,"Commissions") -> -321.5 | V5: =SUMIFS('P&L Table'!$F$2:$F$303,'P&L Table'!$A$2:$A$303,"September",'P&L Table'!$C$2:$C$303,$A5,'P&L Table'!$E$2:$E$303,"Borrow") -> -250.87 | W5: =SUMIFS('P&L Table'!$F$2:$F$303,'P&L Table'!$A$2:$A$303,"September",'P&L Table'!$C$2:$C$303,$A5,'P&L Table'!$E$2:$E$303,"Dividends / PIL") -> 1025.45 | X5: =SUMIFS('P&L Table'!$F$2:$F$303,'P&L Table'!$A$2:$A$303,"September",'P&L Table'!$C$2:$C$303,$A5,'P&L Table'!$E$2:$E$303,"Other") -> 0 | Y5: =SUM(T5:X5) -> 10907.1 | Z5: =SUMIFS('P&L Table'!$F$2:$F$303,'P&L Table'!$A$2:$A$303,"October",'P&L Table'!$C$2:$C$303,$A5,'P&L Table'!$E$2:$E$303,"MTM P&L") -> 1367.82 | AA5: =SUMIFS('P&L Table'!$F$2:$F$303,'P&L Table'!$A$2:$A$303,"October",'P&L Table'!$C$2:$C$303,$A5,'P&L Table'!$E$2:$E$303,"Commissions") -> -149.46 | AB5: =SUMIFS('P&L Table'!$F$2:$F$303,'P&L Table'!$A$2:$A$303,"October",'P&L Table'!$C$2:$C$303,$A5,'P&L Table'!$E$2:$E$303,"Borrow") -> -53.06 | AC5: =SUMIFS('P&L Table'!$F$2:$F$303,'P&L Table'!$A$2:$A$303,"October",'P&L Table'!$C$2:$C$303,$A5,'P&L Table'!$E$2:$E$303,"Dividends / PIL") -> 0 | AD5: =SUMIFS('P&L Table'!$F$2:$F$303,'P&L Table'!$A$2:$A$303,"October",'P&L Table'!$C$2:$C$303,$A5,'P&L Table'!$E$2:$E$303,"Other") -> 0 | AE5: =SUM(Z5:AD5) -> 1165.3 | AF5: =SUM(B5,H5,N5,T5,Z5) -> 11821.84 | AG5: =SUM(C5,I5,O5,U5,AA5) -> -470.96 | AH5: =SUM(D5,J5,P5,V5,AB5) -> -303.93 | AI5: =SUM(E5,K5,Q5,W5,AC5) -> 1025.45 | AJ5: =SUM(F5,L5,R5,X5,AD5) -> 0 | AK5: =SUM(G5,M5,S5,Y5,AE5) -> 12072.4
A6: KBE / KBWB | B6: =SUMIFS('P&L Table'!$F$2:$F$303,'P&L Table'!$A$2:$A$303,"June",'P&L Table'!$C$2:$C$303,$A6,'P&L Table'!$E$2:$E$303,"MTM P&L") -> 0 | C6: =SUMIFS('P&L Table'!$F$2:$F$303,'P&L Table'!$A$2:$A$303,"June",'P&L Table'!$C$2:$C$303,$A6,'P&L Table'!$E$2:$E$303,"Commissions") -> 0 | D6: =SUMIFS('P&L Table'!$F$2:$F$303,'P&L Table'!$A$2:$A$303,"June",'P&L Table'!$C$2:$C$303,$A6,'P&L Table'!$E$2:$E$303,"Borrow") -> 0 | E6: =SUMIFS('P&L Table'!$F$2:$F$303,'P&L Table'!$A$2:$A$303,"June",'P&L Table'!$C$2:$C$303,$A6,'P&L Table'!$E$2:$E$303,"Dividends / PIL") -> 0 | F6: =SUMIFS('P&L Table'!$F$2:$F$303,'P&L Table'!$A$2:$A$303,"June",'P&L Table'!$C$2:$C$303,$A6,'P&L Table'!$E$2:$E$303,"Other") -> 0 | G6: =SUM(B6:F6) -> 0 | H6: =SUMIFS('P&L Table'!$F$2:$F$303,'P&L Table'!$A$2:$A$303,"July",'P&L Table'!$C$2:$C$303,$A6,'P&L Table'!$E$2:$E$303,"MTM P&L") -> 0 | I6: =SUMIFS('P&L Table'!$F$2:$F$303,'P&L Table'!$A$2:$A$303,"July",'P&L Table'!$C$2:$C$303,$A6,'P&L Table'!$E$2:$E$303,"Commissions") -> 0 | J6: =SUMIFS('P&L Table'!$F$2:$F$303,'P&L Table'!$A$2:$A$303,"July",'P&L Table'!$C$2:$C$303,$A6,'P&L Table'!$E$2:$E$303,"Borrow") -> 0 | K6: =SUMIFS('P&L Table'!$F$2:$F$303,'P&L Table'!$A$2:$A$303,"July",'P&L Table'!$C$2:$C$303,$A6,'P&L Table'!$E$2:$E$303,"Dividends / PIL") -> 0 | L6: =SUMIFS('P&L Table'!$F$2:$F$303,'P&L Table'!$A$2:$A$303,"July",'P&L Table'!$C$2:$C$303,$A6,'P&L Table'!$E$2:$E$303,"Other") -> 0 | M6: =SUM(H6:L6) -> 0 | N6: =SUMIFS('P&L Table'!$F$2:$F$303,'P&L Table'!$A$2:$A$303,"August",'P&L Table'!$C$2:$C$303,$A6,'P&L Table'!$E$2:$E$303,"MTM P&L") -> 0 | O6: =SUMIFS('P&L Table'!$F$2:$F$303,'P&L Table'!$A$2:$A$303,"August",'P&L Table'!$C$2:$C$303,$A6,'P&L Table'!$E$2:$E$303,"Commissions") -> 0 | P6: =SUMIFS('P&L Table'!$F$2:$F$303,'P&L Table'!$A$2:$A$303,"August",'P&L Table'!$C$2:$C$303,$A6,'P&L Table'!$E$2:$E$303,"Borrow") -> 0 | Q6: =SUMIFS('P&L Table'!$F$2:$F$303,'P&L Table'!$A$2:$A$303,"August",'P&L Table'!$C$2:$C$303,$A6,'P&L Table'!$E$2:$E$303,"Dividends / PIL") -> 0 | R6: =SUMIFS('P&L Table'!$F$2:$F$303,'P&L Table'!$A$2:$A$303,"August",'P&L Table'!$C$2:$C$303,$A6,'P&L Table'!$E$2:$E$303,"Other") -> 0 | S6: =SUM(N6:R6) -> 0 | T6: =SUMIFS('P&L Table'!$F$2:$F$303,'P&L Table'!$A$2:$A$303,"September",'P&L Table'!$C$2:$C$303,$A6,'P&L Table'!$E$2:$E$303,"MTM P&L") -> 1483 | U6: =SUMIFS('P&L Table'!$F$2:$F$303,'P&L Table'!$A$2:$A$303,"September",'P&L Table'!$C$2:$C$303,$A6,'P&L Table'!$E$2:$E$303,"Commissions") -> -50.5 | V6: =SUMIFS('P&L Table'!$F$2:$F$303,'P&L Table'!$A$2:$A$303,"September",'P&L Table'!$C$2:$C$303,$A6,'P&L Table'!$E$2:$E$303,"Borrow") -> -128.32 | W6: =SUMIFS('P&L Table'!$F$2:$F$303,'P&L Table'!$A$2:$A$303,"September",'P&L Table'!$C$2:$C$303,$A6,'P&L Table'!$E$2:$E$303,"Dividends / PIL") -> 0 | X6: =SUMIFS('P&L Table'!$F$2:$F$303,'P&L Table'!$A$2:$A$303,"September",'P&L Table'!$C$2:$C$303,$A6,'P&L Table'!$E$2:$E$303,"Other") -> 0 | Y6: =SUM(T6:X6) -> 1304.18 | Z6: =SUMIFS('P&L Table'!$F$2:$F$303,'P&L Table'!$A$2:$A$303,"October",'P&L Table'!$C$2:$C$303,$A6,'P&L Table'!$E$2:$E$303,"MTM P&L") -> 853.98 | AA6: =SUMIFS('P&L Table'!$F$2:$F$303,'P&L Table'!$A$2:$A$303,"October",'P&L Table'!$C$2:$C$303,$A6,'P&L Table'!$E$2:$E$303,"Commissions") -> -98.37 | AB6: =SUMIFS('P&L Table'!$F$2:$F$303,'P&L Table'!$A$2:$A$303,"October",'P&L Table'!$C$2:$C$303,$A6,'P&L Table'!$E$2:$E$303,"Borrow") -> -322.73 | AC6: =SUMIFS('P&L Table'!$F$2:$F$303,'P&L Table'!$A$2:$A$303,"October",'P&L Table'!$C$2:$C$303,$A6,'P&L Table'!$E$2:$E$303,"Dividends / PIL") -> 0 | AD6: =SUMIFS('P&L Table'!$F$2:$F$303,'P&L Table'!$A$2:$A$303,"October",'P&L Table'!$C$2:$C$303,$A6,'P&L Table'!$E$2:$E$303,"Other") -> 0 | AE6: =SUM(Z6:AD6) -> 432.88 | AF6: =SUM(B6,H6,N6,T6,Z6) -> 2336.98 | AG6: =SUM(C6,I6,O6,U6,AA6) -> -148.87 | AH6: =SUM(D6,J6,P6,V6,AB6) -> -451.05 | AI6: =SUM(E6,K6,Q6,W6,AC6) -> 0 | AJ6: =SUM(F6,L6,R6,X6,AD6) -> 0 | AK6: =SUM(G6,M6,S6,Y6,AE6) -> 1737.06
A7: IYK / XLP | B7: =SUMIFS('P&L Table'!$F$2:$F$303,'P&L Table'!$A$2:$A$303,"June",'P&L Table'!$C$2:$C$303,$A7,'P&L Table'!$E$2:$E$303,"MTM P&L") -> 0 | C7: =SUMIFS('P&L Table'!$F$2:$F$303,'P&L Table'!$A$2:$A$303,"June",'P&L Table'!$C$2:$C$303,$A7,'P&L Table'!$E$2:$E$303,"Commissions") -> 0 | D7: =SUMIFS('P&L Table'!$F$2:$F$303,'P&L Table'!$A$2:$A$303,"June",'P&L Table'!$C$2:$C$303,$A7,'P&L Table'!$E$2:$E$303,"Borrow") -> 0 | E7: =SUMIFS('P&L Table'!$F$2:$F$303,'P&L Table'!$A$2:$A$303,"June",'P&L Table'!$C$2:$C$303,$A7,'P&L Table'!$E$2:$E$303,"Dividends / PIL") -> 0 | F7: =SUMIFS('P&L Table'!$F$2:$F$303,'P&L Table'!$A$2:$A$303,"June",'P&L Table'!$C$2:$C$303,$A7,'P&L Table'!$E$2:$E$303,"Other") -> 0 | G7: =SUM(B7:F7) -> 0 | H7: =SUMIFS('P&L Table'!$F$2:$F$303,'P&L Table'!$A$2:$A$303,"July",'P&L Table'!$C$2:$C$303,$A7,'P&L Table'!$E$2:$E$303,"MTM P&L") -> 0 | I7: =SUMIFS('P&L Table'!$F$2:$F$303,'P&L Table'!$A$2:$A$303,"July",'P&L Table'!$C$2:$C$303,$A7,'P&L Table'!$E$2:$E$303,"Commissions") -> 0 | J7: =SUMIFS('P&L Table'!$F$2:$F$303,'P&L Table'!$A$2:$A$303,"July",'P&L Table'!$C$2:$C$303,$A7,'P&L Table'!$E$2:$E$303,"Borrow") -> 0 | K7: =SUMIFS('P&L Table'!$F$2:$F$303,'P&L Table'!$A$2:$A$303,"July",'P&L Table'!$C$2:$C$303,$A7,'P&L Table'!$E$2:$E$303,"Dividends / PIL") -> 0 | L7: =SUMIFS('P&L Table'!$F$2:$F$303,'P&L Table'!$A$2:$A$303,"July",'P&L Table'!$C$2:$C$303,$A7,'P&L Table'!$E$2:$E$303,"Other") -> 0 | M7: =SUM(H7:L7) -> 0 | N7: =SUMIFS('P&L Table'!$F$2:$F$303,'P&L Table'!$A$2:$A$303,"August",'P&L Table'!$C$2:$C$303,$A7,'P&L Table'!$E$2:$E$303,"MTM P&L") -> 0 | O7: =SUMIFS('P&L Table'!$F$2:$F$303,'P&L Table'!$A$2:$A$303,"August",'P&L Table'!$C$2:$C$303,$A7,'P&L Table'!$E$2:$E$303,"Commissions") -> 0 | P7: =SUMIFS('P&L Table'!$F$2:$F$303,'P&L Table'!$A$2:$A$303,"August",'P&L Table'!$C$2:$C$303,$A7,'P&L Table'!$E$2:$E$303,"Borrow") -> 0 | Q7: =SUMIFS('P&L Table'!$F$2:$F$303,'P&L Table'!$A$2:$A$303,"August",'P&L Table'!$C$2:$C$303,$A7,'P&L Table'!$E$2:$E$303,"Dividends / PIL") -> 0 | R7: =SUMIFS('P&L Table'!$F$2:$F$303,'P&L Table'!$A$2:$A$303,"August",'P&L Table'!$C$2:$C$303,$A7,'P&L Table'!$E$2:$E$303,"Other") -> 0 | S7: =SUM(N7:R7) -> 0 | T7: =SUMIFS('P&L Table'!$F$2:$F$303,'P&L Table'!$A$2:$A$303,"September",'P&L Table'!$C$2:$C$303,$A7,'P&L Table'!$E$2:$E$303,"MTM P&L") -> 2006.1 | U7: =SUMIFS('P&L Table'!$F$2:$F$303,'P&L Table'!$A$2:$A$303,"September",'P&L Table'!$C$2:$C$303,$A7,'P&L Table'!$E$2:$E$303,"Commissions") -> -113.77 | V7: =SUMIFS('P&L Table'!$F$2:$F$303,'P&L Table'!$A$2:$A$303,"September",'P&L Table'!$C$2:$C$303,$A7,'P&L Table'!$E$2:$E$303,"Borrow") -> -530.93 | W7: =SUMIFS('P&L Table'!$F$2:$F$303,'P&L Table'!$A$2:$A$303,"September",'P&L Table'!$C$2:$C$303,$A7,'P&L Table'!$E$2:$E$303,"Dividends / PIL") -> -960.31 | X7: =SUMIFS('P&L Table'!$F$2:$F$303,'P&L Table'!$A$2:$A$303,"September",'P&L Table'!$C$2:$C$303,$A7,'P&L Table'!$E$2:$E$303,"Other") -> 0 | Y7: =SUM(T7:X7) -> 401.09 | Z7: =SUMIFS('P&L Table'!$F$2:$F$303,'P&L Table'!$A$2:$A$303,"October",'P&L Table'!$C$2:$C$303,$A7,'P&L Table'!$E$2:$E$303,"MTM P&L") -> 0 | AA7: =SUMIFS('P&L Table'!$F$2:$F$303,'P&L Table'!$A$2:$A$303,"October",'P&L Table'!$C$2:$C$303,$A7,'P&L Table'!$E$2:$E$303,"Commissions") -> 0 | AB7: =SUMIFS('P&L Table'!$F$2:$F$303,'P&L Table'!$A$2:$A$303,"October",'P&L Table'!$C$2:$C$303,$A7,'P&L Table'!$E$2:$E$303,"Borrow") -> -2.44 | AC7: =SUMIFS('P&L Table'!$F$2:$F$303,'P&L Table'!$A$2:$A$303,"October",'P&L Table'!$C$2:$C$303,$A7,'P&L Table'!$E$2:$E$303,"Dividends / PIL") -> 0 | AD7: =SUMIFS('P&L Table'!$F$2:$F$303,'P&L Table'!$A$2:$A$303,"October",'P&L Table'!$C$2:$C$303,$A7,'P&L Table'!$E$2:$E$303,"Other") -> 0 | AE7: =SUM(Z7:AD7) -> -2.44 | AF7: =SUM(B7,H7,N7,T7,Z7) -> 2006.1 | AG7: =SUM(C7,I7,O7,U7,AA7) -> -113.77 | AH7: =SUM(D7,J7,P7,V7,AB7) -> -533.37 | AI7: =SUM(E7,K7,Q7,W7,AC7) -> -960.31 | AJ7: =SUM(F7,L7,R7,X7,AD7) -> 0 | AK7: =SUM(G7,M7,S7,Y7,AE7) -> 398.65
A8: FWONA / FWONK | B8: =SUMIFS('P&L Table'!$F$2:$F$303,'P&L Table'!$A$2:$A$303,"June",'P&L Table'!$C$2:$C$303,$A8,'P&L Table'!$E$2:$E$303,"MTM P&L") -> 0 | C8: =SUMIFS('P&L Table'!$F$2:$F$303,'P&L Table'!$A$2:$A$303,"June",'P&L Table'!$C$2:$C$303,$A8,'P&L Table'!$E$2:$E$303,"Commissions") -> 0 | D8: =SUMIFS('P&L Table'!$F$2:$F$303,'P&L Table'!$A$2:$A$303,"June",'P&L Table'!$C$2:$C$303,$A8,'P&L Table'!$E$2:$E$303,"Borrow") -> 0 | E8: =SUMIFS('P&L Table'!$F$2:$F$303,'P&L Table'!$A$2:$A$303,"June",'P&L Table'!$C$2:$C$303,$A8,'P&L Table'!$E$2:$E$303,"Dividends / PIL") -> 0 | F8: =SUMIFS('P&L Table'!$F$2:$F$303,'P&L Table'!$A$2:$A$303,"June",'P&L Table'!$C$2:$C$303,$A8,'P&L Table'!$E$2:$E$303,"Other") -> 0 | G8: =SUM(B8:F8) -> 0 | H8: =SUMIFS('P&L Table'!$F$2:$F$303,'P&L Table'!$A$2:$A$303,"July",'P&L Table'!$C$2:$C$303,$A8,'P&L Table'!$E$2:$E$303,"MTM P&L") -> 0 | I8: =SUMIFS('P&L Table'!$F$2:$F$303,'P&L Table'!$A$2:$A$303,"July",'P&L Table'!$C$2:$C$303,$A8,'P&L Table'!$E$2:$E$303,"Commissions") -> 0 | J8: =SUMIFS('P&L Table'!$F$2:$F$303,'P&L Table'!$A$2:$A$303,"July",'P&L Table'!$C$2:$C$303,$A8,'P&L Table'!$E$2:$E$303,"Borrow") -> 0 | K8: =SUMIFS('P&L Table'!$F$2:$F$303,'P&L Table'!$A$2:$A$303,"July",'P&L Table'!$C$2:$C$303,$A8,'P&L Table'!$E$2:$E$303,"Dividends / PIL") -> 0 | L8: =SUMIFS('P&L Table'!$F$2:$F$303,'P&L Table'!$A$2:$A$303,"July",'P&L Table'!$C$2:$C$303,$A8,'P&L Table'!$E$2:$E$303,"Other") -> 0 | M8: =SUM(H8:L8) -> 0 | N8: =SUMIFS('P&L Table'!$F$2:$F$303,'P&L Table'!$A$2:$A$303,"August",'P&L Table'!$C$2:$C$303,$A8,'P&L Table'!$E$2:$E$303,"MTM P&L") -> 0 | O8: =SUMIFS('P&L Table'!$F$2:$F$303,'P&L Table'!$A$2:$A$303,"August",'P&L Table'!$C$2:$C$303,$A8,'P&L Table'!$E$2:$E$303,"Commissions") -> 0 | P8: =SUMIFS('P&L Table'!$F$2:$F$303,'P&L Table'!$A$2:$A$303,"August",'P&L Table'!$C$2:$C$303,$A8,'P&L Table'!$E$2:$E$303,"Borrow") -> 0 | Q8: =SUMIFS('P&L Table'!$F$2:$F$303,'P&L Table'!$A$2:$A$303,"August",'P&L Table'!$C$2:$C$303,$A8,'P&L Table'!$E$2:$E$303,"Dividends / PIL") -> 0 | R8: =SUMIFS('P&L Table'!$F$2:$F$303,'P&L Table'!$A$2:$A$303,"August",'P&L Table'!$C$2:$C$303,$A8,'P&L Table'!$E$2:$E$303,"Other") -> 0 | S8: =SUM(N8:R8) -> 0 | T8: =SUMIFS('P&L Table'!$F$2:$F$303,'P&L Table'!$A$2:$A$303,"September",'P&L Table'!$C$2:$C$303,$A8,'P&L Table'!$E$2:$E$303,"MTM P&L") -> 0 | U8: =SUMIFS('P&L Table'!$F$2:$F$303,'P&L Table'!$A$2:$A$303,"September",'P&L Table'!$C$2:$C$303,$A8,'P&L Table'!$E$2:$E$303,"Commissions") -> 0 | V8: =SUMIFS('P&L Table'!$F$2:$F$303,'P&L Table'!$A$2:$A$303,"September",'P&L Table'!$C$2:$C$303,$A8,'P&L Table'!$E$2:$E$303,"Borrow") -> 0 | W8: =SUMIFS('P&L Table'!$F$2:$F$303,'P&L Table'!$A$2:$A$303,"September",'P&L Table'!$C$2:$C$303,$A8,'P&L Table'!$E$2:$E$303,"Dividends / PIL") -> 0 | X8: =SUMIFS('P&L Table'!$F$2:$F$303,'P&L Table'!$A$2:$A$303,"September",'P&L Table'!$C$2:$C$303,$A8,'P&L Table'!$E$2:$E$303,"Other") -> 0 | Y8: =SUM(T8:X8) -> 0 | Z8: =SUMIFS('P&L Table'!$F$2:$F$303,'P&L Table'!$A$2:$A$303,"October",'P&L Table'!$C$2:$C$303,$A8,'P&L Table'!$E$2:$E$303,"MTM P&L") -> 231.71 | AA8: =SUMIFS('P&L Table'!$F$2:$F$303,'P&L Table'!$A$2:$A$303,"October",'P&L Table'!$C$2:$C$303,$A8,'P&L Table'!$E$2:$E$303,"Commissions") -> -15.67 | AB8: =SUMIFS('P&L Table'!$F$2:$F$303,'P&L Table'!$A$2:$A$303,"October",'P&L Table'!$C$2:$C$303,$A8,'P&L Table'!$E$2:$E$303,"Borrow") -> -1.85 | AC8: =SUMIFS('P&L Table'!$F$2:$F$303,'P&L Table'!$A$2:$A$303,"October",'P&L Table'!$C$2:$C$303,$A8,'P&L Table'!$E$2:$E$303,"Dividends / PIL") -> 0 | AD8: =SUMIFS('P&L Table'!$F$2:$F$303,'P&L Table'!$A$2:$A$303,"October",'P&L Table'!$C$2:$C$303,$A8,'P&L Table'!$E$2:$E$303,"Other") -> 0 | AE8: =SUM(Z8:AD8) -> 214.19 | AF8: =SUM(B8,H8,N8,T8,Z8) -> 231.71 | AG8: =SUM(C8,I8,O8,U8,AA8) -> -15.67 | AH8: =SUM(D8,J8,P8,V8,AB8) -> -1.85 | AI8: =SUM(E8,K8,Q8,W8,AC8) -> 0 | AJ8: =SUM(F8,L8,R8,X8,AD8) -> 0 | AK8: =SUM(G8,M8,S8,Y8,AE8) -> 214.19
A9: CMF / VTEC | B9: =SUMIFS('P&L Table'!$F$2:$F$303,'P&L Table'!$A$2:$A$303,"June",'P&L Table'!$C$2:$C$303,$A9,'P&L Table'!$E$2:$E$303,"MTM P&L") -> 0 | C9: =SUMIFS('P&L Table'!$F$2:$F$303,'P&L Table'!$A$2:$A$303,"June",'P&L Table'!$C$2:$C$303,$A9,'P&L Table'!$E$2:$E$303,"Commissions") -> 0 | D9: =SUMIFS('P&L Table'!$F$2:$F$303,'P&L Table'!$A$2:$A$303,"June",'P&L Table'!$C$2:$C$303,$A9,'P&L Table'!$E$2:$E$303,"Borrow") -> 0 | E9: =SUMIFS('P&L Table'!$F$2:$F$303,'P&L Table'!$A$2:$A$303,"June",'P&L Table'!$C$2:$C$303,$A9,'P&L Table'!$E$2:$E$303,"Dividends / PIL") -> 0 | F9: =SUMIFS('P&L Table'!$F$2:$F$303,'P&L Table'!$A$2:$A$303,"June",'P&L Table'!$C$2:$C$303,$A9,'P&L Table'!$E$2:$E$303,"Other") -> 0 | G9: =SUM(B9:F9) -> 0 | H9: =SUMIFS('P&L Table'!$F$2:$F$303,'P&L Table'!$A$2:$A$303,"July",'P&L Table'!$C$2:$C$303,$A9,'P&L Table'!$E$2:$E$303,"MTM P&L") -> 0 | I9: =SUMIFS('P&L Table'!$F$2:$F$303,'P&L Table'!$A$2:$A$303,"July",'P&L Table'!$C$2:$C$303,$A9,'P&L Table'!$E$2:$E$303,"Commissions") -> 0 | J9: =SUMIFS('P&L Table'!$F$2:$F$303,'P&L Table'!$A$2:$A$303,"July",'P&L Table'!$C$2:$C$303,$A9,'P&L Table'!$E$2:$E$303,"Borrow") -> 0 | K9: =SUMIFS('P&L Table'!$F$2:$F$303,'P&L Table'!$A$2:$A$303,"July",'P&L Table'!$C$2:$C$303,$A9,'P&L Table'!$E$2:$E$303,"Dividends / PIL") -> 0 | L9: =SUMIFS('P&L Table'!$F$2:$F$303,'P&L Table'!$A$2:$A$303,"July",'P&L Table'!$C$2:$C$303,$A9,'P&L Table'!$E$2:$E$303,"Other") -> 0 | M9: =SUM(H9:L9) -> 0 | N9: =SUMIFS('P&L Table'!$F$2:$F$303,'P&L Table'!$A$2:$A$303,"August",'P&L Table'!$C$2:$C$303,$A9,'P&L Table'!$E$2:$E$303,"MTM P&L") -> 0 | O9: =SUMIFS('P&L Table'!$F$2:$F$303,'P&L Table'!$A$2:$A$303,"August",'P&L Table'!$C$2:$C$303,$A9,'P&L Table'!$E$2:$E$303,"Commissions") -> 0 | P9: =SUMIFS('P&L Table'!$F$2:$F$303,'P&L Table'!$A$2:$A$303,"August",'P&L Table'!$C$2:$C$303,$A9,'P&L Table'!$E$2:$E$303,"Borrow") -> 0 | Q9: =SUMIFS('P&L Table'!$F$2:$F$303,'P&L Table'!$A$2:$A$303,"August",'P&L Table'!$C$2:$C$303,$A9,'P&L Table'!$E$2:$E$303,"Dividends / PIL") -> 0 | R9: =SUMIFS('P&L Table'!$F$2:$F$303,'P&L Table'!$A$2:$A$303,"August",'P&L Table'!$C$2:$C$303,$A9,'P&L Table'!$E$2:$E$303,"Other") -> 0 | S9: =SUM(N9:R9) -> 0 | T9: =SUMIFS('P&L Table'!$F$2:$F$303,'P&L Table'!$A$2:$A$303,"September",'P&L Table'!$C$2:$C$303,$A9,'P&L Table'!$E$2:$E$303,"MTM P&L") -> 171.4 | U9: =SUMIFS('P&L Table'!$F$2:$F$303,'P&L Table'!$A$2:$A$303,"September",'P&L Table'!$C$2:$C$303,$A9,'P&L Table'!$E$2:$E$303,"Commissions") -> -79.64 | V9: =SUMIFS('P&L Table'!$F$2:$F$303,'P&L Table'!$A$2:$A$303,"September",'P&L Table'!$C$2:$C$303,$A9,'P&L Table'!$E$2:$E$303,"Borrow") -> -58.18 | W9: =SUMIFS('P&L Table'!$F$2:$F$303,'P&L Table'!$A$2:$A$303,"September",'P&L Table'!$C$2:$C$303,$A9,'P&L Table'!$E$2:$E$303,"Dividends / PIL") -> 0 | X9: =SUMIFS('P&L Table'!$F$2:$F$303,'P&L Table'!$A$2:$A$303,"September",'P&L Table'!$C$2:$C$303,$A9,'P&L Table'!$E$2:$E$303,"Other") -> 0 | Y9: =SUM(T9:X9) -> 33.58 | Z9: =SUMIFS('P&L Table'!$F$2:$F$303,'P&L Table'!$A$2:$A$303,"October",'P&L Table'!$C$2:$C$303,$A9,'P&L Table'!$E$2:$E$303,"MTM P&L") -> 520.89 | AA9: =SUMIFS('P&L Table'!$F$2:$F$303,'P&L Table'!$A$2:$A$303,"October",'P&L Table'!$C$2:$C$303,$A9,'P&L Table'!$E$2:$E$303,"Commissions") -> -120.98 | AB9: =SUMIFS('P&L Table'!$F$2:$F$303,'P&L Table'!$A$2:$A$303,"October",'P&L Table'!$C$2:$C$303,$A9,'P&L Table'!$E$2:$E$303,"Borrow") -> -247.13 | AC9: =SUMIFS('P&L Table'!$F$2:$F$303,'P&L Table'!$A$2:$A$303,"October",'P&L Table'!$C$2:$C$303,$A9,'P&L Table'!$E$2:$E$303,"Dividends / PIL") -> 0 | AD9: =SUMIFS('P&L Table'!$F$2:$F$303,'P&L Table'!$A$2:$A$303,"October",'P&L Table'!$C$2:$C$303,$A9,'P&L Table'!$E$2:$E$303,"Other") -> 0 | AE9: =SUM(Z9:AD9) -> 152.78 | AF9: =SUM(B9,H9,N9,T9,Z9) -> 692.29 | AG9: =SUM(C9,I9,O9,U9,AA9) -> -200.62 | AH9: =SUM(D9,J9,P9,V9,AB9) -> -305.31 | AI9: =SUM(E9,K9,Q9,W9,AC9) -> 0 | AJ9: =SUM(F9,L9,R9,X9,AD9) -> 0 | AK9: =SUM(G9,M9,S9,Y9,AE9) -> 186.36
A10: IDU / XLU | B10: =SUMIFS('P&L Table'!$F$2:$F$303,'P&L Table'!$A$2:$A$303,"June",'P&L Table'!$C$2:$C$303,$A10,'P&L Table'!$E$2:$E$303,"MTM P&L") -> 0 | C10: =SUMIFS('P&L Table'!$F$2:$F$303,'P&L Table'!$A$2:$A$303,"June",'P&L Table'!$C$2:$C$303,$A10,'P&L Table'!$E$2:$E$303,"Commissions") -> 0 | D10: =SUMIFS('P&L Table'!$F$2:$F$303,'P&L Table'!$A$2:$A$303,"June",'P&L Table'!$C$2:$C$303,$A10,'P&L Table'!$E$2:$E$303,"Borrow") -> 0 | E10: =SUMIFS('P&L Table'!$F$2:$F$303,'P&L Table'!$A$2:$A$303,"June",'P&L Table'!$C$2:$C$303,$A10,'P&L Table'!$E$2:$E$303,"Dividends / PIL") -> 0 | F10: =SUMIFS('P&L Table'!$F$2:$F$303,'P&L Table'!$A$2:$A$303,"June",'P&L Table'!$C$2:$C$303,$A10,'P&L Table'!$E$2:$E$303,"Other") -> 0 | G10: =SUM(B10:F10) -> 0 | H10: =SUMIFS('P&L Table'!$F$2:$F$303,'P&L Table'!$A$2:$A$303,"July",'P&L Table'!$C$2:$C$303,$A10,'P&L Table'!$E$2:$E$303,"MTM P&L") -> 0 | I10: =SUMIFS('P&L Table'!$F$2:$F$303,'P&L Table'!$A$2:$A$303,"July",'P&L Table'!$C$2:$C$303,$A10,'P&L Table'!$E$2:$E$303,"Commissions") -> 0 | J10: =SUMIFS('P&L Table'!$F$2:$F$303,'P&L Table'!$A$2:$A$303,"July",'P&L Table'!$C$2:$C$303,$A10,'P&L Table'!$E$2:$E$303,"Borrow") -> 0 | K10: =SUMIFS('P&L Table'!$F$2:$F$303,'P&L Table'!$A$2:$A$303,"July",'P&L Table'!$C$2:$C$303,$A10,'P&L Table'!$E$2:$E$303,"Dividends / PIL") -> 0 | L10: =SUMIFS('P&L Table'!$F$2:$F$303,'P&L Table'!$A$2:$A$303,"July",'P&L Table'!$C$2:$C$303,$A10,'P&L Table'!$E$2:$E$303,"Other") -> 0 | M10: =SUM(H10:L10) -> 0 | N10: =SUMIFS('P&L Table'!$F$2:$F$303,'P&L Table'!$A$2:$A$303,"August",'P&L Table'!$C$2:$C$303,$A10,'P&L Table'!$E$2:$E$303,"MTM P&L") -> 0 | O10: =SUMIFS('P&L Table'!$F$2:$F$303,'P&L Table'!$A$2:$A$303,"August",'P&L Table'!$C$2:$C$303,$A10,'P&L Table'!$E$2:$E$303,"Commissions") -> 0 | P10: =SUMIFS('P&L Table'!$F$2:$F$303,'P&L Table'!$A$2:$A$303,"August",'P&L Table'!$C$2:$C$303,$A10,'P&L Table'!$E$2:$E$303,"Borrow") -> 0 | Q10: =SUMIFS('P&L Table'!$F$2:$F$303,'P&L Table'!$A$2:$A$303,"August",'P&L Table'!$C$2:$C$303,$A10,'P&L Table'!$E$2:$E$303,"Dividends / PIL") -> 0 | R10: =SUMIFS('P&L Table'!$F$2:$F$303,'P&L Table'!$A$2:$A$303,"August",'P&L Table'!$C$2:$C$303,$A10,'P&L Table'!$E$2:$E$303,"Other") -> 0 | S10: =SUM(N10:R10) -> 0 | T10: =SUMIFS('P&L Table'!$F$2:$F$303,'P&L Table'!$A$2:$A$303,"September",'P&L Table'!$C$2:$C$303,$A10,'P&L Table'!$E$2:$E$303,"MTM P&L") -> -560.18 | U10: =SUMIFS('P&L Table'!$F$2:$F$303,'P&L Table'!$A$2:$A$303,"September",'P&L Table'!$C$2:$C$303,$A10,'P&L Table'!$E$2:$E$303,"Commissions") -> -74.27 | V10: =SUMIFS('P&L Table'!$F$2:$F$303,'P&L Table'!$A$2:$A$303,"September",'P&L Table'!$C$2:$C$303,$A10,'P&L Table'!$E$2:$E$303,"Borrow") -> -198.87 | W10: =SUMIFS('P&L Table'!$F$2:$F$303,'P&L Table'!$A$2:$A$303,"September",'P&L Table'!$C$2:$C$303,$A10,'P&L Table'!$E$2:$E$303,"Dividends / PIL") -> 856.07 | X10: =SUMIFS('P&L Table'!$F$2:$F$303,'P&L Table'!$A$2:$A$303,"September",'P&L Table'!$C$2:$C$303,$A10,'P&L Table'!$E$2:$E$303,"Other") -> 0 | Y10: =SUM(T10:X10) -> 22.75 | Z10: =SUMIFS('P&L Table'!$F$2:$F$303,'P&L Table'!$A$2:$A$303,"October",'P&L Table'!$C$2:$C$303,$A10,'P&L Table'!$E$2:$E$303,"MTM P&L") -> 166.5 | AA10: =SUMIFS('P&L Table'!$F$2:$F$303,'P&L Table'!$A$2:$A$303,"October",'P&L Table'!$C$2:$C$303,$A10,'P&L Table'!$E$2:$E$303,"Commissions") -> -22.22 | AB10: =SUMIFS('P&L Table'!$F$2:$F$303,'P&L Table'!$A$2:$A$303,"October",'P&L Table'!$C$2:$C$303,$A10,'P&L Table'!$E$2:$E$303,"Borrow") -> -22.18 | AC10: =SUMIFS('P&L Table'!$F$2:$F$303,'P&L Table'!$A$2:$A$303,"October",'P&L Table'!$C$2:$C$303,$A10,'P&L Table'!$E$2:$E$303,"Dividends / PIL") -> 0 | AD10: =SUMIFS('P&L Table'!$F$2:$F$303,'P&L Table'!$A$2:$A$303,"October",'P&L Table'!$C$2:$C$303,$A10,'P&L Table'!$E$2:$E$303,"Other") -> 0 | AE10: =SUM(Z10:AD10) -> 122.1 | AF10: =SUM(B10,H10,N10,T10,Z10) -> -393.68 | AG10: =SUM(C10,I10,O10,U10,AA10) -> -96.49 | AH10: =SUM(D10,J10,P10,V10,AB10) -> -221.05 | AI10: =SUM(E10,K10,Q10,W10,AC10) -> 856.07 | AJ10: =SUM(F10,L10,R10,X10,AD10) -> 0 | AK10: =SUM(G10,M10,S10,Y10,AE10) -> 144.85
A11: CWB / ICVT | B11: =SUMIFS('P&L Table'!$F$2:$F$303,'P&L Table'!$A$2:$A$303,"June",'P&L Table'!$C$2:$C$303,$A11,'P&L Table'!$E$2:$E$303,"MTM P&L") -> 0 | C11: =SUMIFS('P&L Table'!$F$2:$F$303,'P&L Table'!$A$2:$A$303,"June",'P&L Table'!$C$2:$C$303,$A11,'P&L Table'!$E$2:$E$303,"Commissions") -> 0 | D11: =SUMIFS('P&L Table'!$F$2:$F$303,'P&L Table'!$A$2:$A$303,"June",'P&L Table'!$C$2:$C$303,$A11,'P&L Table'!$E$2:$E$303,"Borrow") -> 0 | E11: =SUMIFS('P&L Table'!$F$2:$F$303,'P&L Table'!$A$2:$A$303,"June",'P&L Table'!$C$2:$C$303,$A11,'P&L Table'!$E$2:$E$303,"Dividends / PIL") -> 0 | F11: =SUMIFS('P&L Table'!$F$2:$F$303,'P&L Table'!$A$2:$A$303,"June",'P&L Table'!$C$2:$C$303,$A11,'P&L Table'!$E$2:$E$303,"Other") -> 0 | G11: =SUM(B11:F11) -> 0 | H11: =SUMIFS('P&L Table'!$F$2:$F$303,'P&L Table'!$A$2:$A$303,"July",'P&L Table'!$C$2:$C$303,$A11,'P&L Table'!$E$2:$E$303,"MTM P&L") -> -196.2 | I11: =SUMIFS('P&L Table'!$F$2:$F$303,'P&L Table'!$A$2:$A$303,"July",'P&L Table'!$C$2:$C$303,$A11,'P&L Table'!$E$2:$E$303,"Commissions") -> -56.57 | J11: =SUMIFS('P&L Table'!$F$2:$F$303,'P&L Table'!$A$2:$A$303,"July",'P&L Table'!$C$2:$C$303,$A11,'P&L Table'!$E$2:$E$303,"Borrow") -> -31.96 | K11: =SUMIFS('P&L Table'!$F$2:$F$303,'P&L Table'!$A$2:$A$303,"July",'P&L Table'!$C$2:$C$303,$A11,'P&L Table'!$E$2:$E$303,"Dividends / PIL") -> 0 | L11: =SUMIFS('P&L Table'!$F$2:$F$303,'P&L Table'!$A$2:$A$303,"July",'P&L Table'!$C$2:$C$303,$A11,'P&L Table'!$E$2:$E$303,"Other") -> 0 | M11: =SUM(H11:L11) -> -284.73 | N11: =SUMIFS('P&L Table'!$F$2:$F$303,'P&L Table'!$A$2:$A$303,"August",'P&L Table'!$C$2:$C$303,$A11,'P&L Table'!$E$2:$E$303,"MTM P&L") -> 881.22 | O11: =SUMIFS('P&L Table'!$F$2:$F$303,'P&L Table'!$A$2:$A$303,"August",'P&L Table'!$C$2:$C$303,$A11,'P&L Table'!$E$2:$E$303,"Commissions") -> -28.47 | P11: =SUMIFS('P&L Table'!$F$2:$F$303,'P&L Table'!$A$2:$A$303,"August",'P&L Table'!$C$2:$C$303,$A11,'P&L Table'!$E$2:$E$303,"Borrow") -> -112.45 | Q11: =SUMIFS('P&L Table'!$F$2:$F$303,'P&L Table'!$A$2:$A$303,"August",'P&L Table'!$C$2:$C$303,$A11,'P&L Table'!$E$2:$E$303,"Dividends / PIL") -> -153.02 | R11: =SUMIFS('P&L Table'!$F$2:$F$303,'P&L Table'!$A$2:$A$303,"August",'P&L Table'!$C$2:$C$303,$A11,'P&L Table'!$E$2:$E$303,"Other") -> 0 | S11: =SUM(N11:R11) -> 587.28 | T11: =SUMIFS('P&L Table'!$F$2:$F$303,'P&L Table'!$A$2:$A$303,"September",'P&L Table'!$C$2:$C$303,$A11,'P&L Table'!$E$2:$E$303,"MTM P&L") -> 0 | U11: =SUMIFS('P&L Table'!$F$2:$F$303,'P&L Table'!$A$2:$A$303,"September",'P&L Table'!$C$2:$C$303,$A11,'P&L Table'!$E$2:$E$303,"Commissions") -> 0 | V11: =SUMIFS('P&L Table'!$F$2:$F$303,'P&L Table'!$A$2:$A$303,"September",'P&L Table'!$C$2:$C$303,$A11,'P&L Table'!$E$2:$E$303,"Borrow") -> 0 | W11: =SUMIFS('P&L Table'!$F$2:$F$303,'P&L Table'!$A$2:$A$303,"September",'P&L Table'!$C$2:$C$303,$A11,'P&L Table'!$E$2:$E$303,"Dividends / PIL") -> 0 | X11: =SUMIFS('P&L Table'!$F$2:$F$303,'P&L Table'!$A$2:$A$303,"September",'P&L Table'!$C$2:$C$303,$A11,'P&L Table'!$E$2:$E$303,"Other") -> 0 | Y11: =SUM(T11:X11) -> 0 | Z11: =SUMIFS('P&L Table'!$F$2:$F$303,'P&L Table'!$A$2:$A$303,"October",'P&L Table'!$C$2:$C$303,$A11,'P&L Table'!$E$2:$E$303,"MTM P&L") -> -179.53 | AA11: =SUMIFS('P&L Table'!$F$2:$F$303,'P&L Table'!$A$2:$A$303,"October",'P&L Table'!$C$2:$C$303,$A11,'P&L Table'!$E$2:$E$303,"Commissions") -> -5.16 | AB11: =SUMIFS('P&L Table'!$F$2:$F$303,'P&L Table'!$A$2:$A$303,"October",'P&L Table'!$C$2:$C$303,$A11,'P&L Table'!$E$2:$E$303,"Borrow") -> -7.05 | AC11: =SUMIFS('P&L Table'!$F$2:$F$303,'P&L Table'!$A$2:$A$303,"October",'P&L Table'!$C$2:$C$303,$A11,'P&L Table'!$E$2:$E$303,"Dividends / PIL") -> 0 | AD11: =SUMIFS('P&L Table'!$F$2:$F$303,'P&L Table'!$A$2:$A$303,"October",'P&L Table'!$C$2:$C$303,$A11,'P&L Table'!$E$2:$E$303,"Other") -> 0 | AE11: =SUM(Z11:AD11) -> -191.74 | AF11: =SUM(B11,H11,N11,T11,Z11) -> 505.49 | AG11: =SUM(C11,I11,O11,U11,AA11) -> -90.2 | AH11: =SUM(D11,J11,P11,V11,AB11) -> -151.46 | AI11: =SUM(E11,K11,Q11,W11,AC11) -> -153.02 | AJ11: =SUM(F11,L11,R11,X11,AD11) -> 0 | AK11: =SUM(G11,M11,S11,Y11,AE11) -> 110.81
A12: EMB / VWOB | B12: =SUMIFS('P&L Table'!$F$2:$F$303,'P&L Table'!$A$2:$A$303,"June",'P&L Table'!$C$2:$C$303,$A12,'P&L Table'!$E$2:$E$303,"MTM P&L") -> 0 | C12: =SUMIFS('P&L Table'!$F$2:$F$303,'P&L Table'!$A$2:$A$303,"June",'P&L Table'!$C$2:$C$303,$A12,'P&L Table'!$E$2:$E$303,"Commissions") -> 0 | D12: =SUMIFS('P&L Table'!$F$2:$F$303,'P&L Table'!$A$2:$A$303,"June",'P&L Table'!$C$2:$C$303,$A12,'P&L Table'!$E$2:$E$303,"Borrow") -> 0 | E12: =SUMIFS('P&L Table'!$F$2:$F$303,'P&L Table'!$A$2:$A$303,"June",'P&L Table'!$C$2:$C$303,$A12,'P&L Table'!$E$2:$E$303,"Dividends / PIL") -> 0 | F12: =SUMIFS('P&L Table'!$F$2:$F$303,'P&L Table'!$A$2:$A$303,"June",'P&L Table'!$C$2:$C$303,$A12,'P&L Table'!$E$2:$E$303,"Other") -> 0 | G12: =SUM(B12:F12) -> 0 | H12: =SUMIFS('P&L Table'!$F$2:$F$303,'P&L Table'!$A$2:$A$303,"July",'P&L Table'!$C$2:$C$303,$A12,'P&L Table'!$E$2:$E$303,"MTM P&L") -> 90.2 | I12: =SUMIFS('P&L Table'!$F$2:$F$303,'P&L Table'!$A$2:$A$303,"July",'P&L Table'!$C$2:$C$303,$A12,'P&L Table'!$E$2:$E$303,"Commissions") -> -29.99 | J12: =SUMIFS('P&L Table'!$F$2:$F$303,'P&L Table'!$A$2:$A$303,"July",'P&L Table'!$C$2:$C$303,$A12,'P&L Table'!$E$2:$E$303,"Borrow") -> -9.22 | K12: =SUMIFS('P&L Table'!$F$2:$F$303,'P&L Table'!$A$2:$A$303,"July",'P&L Table'!$C$2:$C$303,$A12,'P&L Table'!$E$2:$E$303,"Dividends / PIL") -> 0 | L12: =SUMIFS('P&L Table'!$F$2:$F$303,'P&L Table'!$A$2:$A$303,"July",'P&L Table'!$C$2:$C$303,$A12,'P&L Table'!$E$2:$E$303,"Other") -> 0 | M12: =SUM(H12:L12) -> 50.99 | N12: =SUMIFS('P&L Table'!$F$2:$F$303,'P&L Table'!$A$2:$A$303,"August",'P&L Table'!$C$2:$C$303,$A12,'P&L Table'!$E$2:$E$303,"MTM P&L") -> 0 | O12: =SUMIFS('P&L Table'!$F$2:$F$303,'P&L Table'!$A$2:$A$303,"August",'P&L Table'!$C$2:$C$303,$A12,'P&L Table'!$E$2:$E$303,"Commissions") -> 0 | P12: =SUMIFS('P&L Table'!$F$2:$F$303,'P&L Table'!$A$2:$A$303,"August",'P&L Table'!$C$2:$C$303,$A12,'P&L Table'!$E$2:$E$303,"Borrow") -> -6.5 | Q12: =SUMIFS('P&L Table'!$F$2:$F$303,'P&L Table'!$A$2:$A$303,"August",'P&L Table'!$C$2:$C$303,$A12,'P&L Table'!$E$2:$E$303,"Dividends / PIL") -> 0 | R12: =SUMIFS('P&L Table'!$F$2:$F$303,'P&L Table'!$A$2:$A$303,"August",'P&L Table'!$C$2:$C$303,$A12,'P&L Table'!$E$2:$E$303,"Other") -> 0 | S12: =SUM(N12:R12) -> -6.5 | T12: =SUMIFS('P&L Table'!$F$2:$F$303,'P&L Table'!$A$2:$A$303,"September",'P&L Table'!$C$2:$C$303,$A12,'P&L Table'!$E$2:$E$303,"MTM P&L") -> 0 | U12: =SUMIFS('P&L Table'!$F$2:$F$303,'P&L Table'!$A$2:$A$303,"September",'P&L Table'!$C$2:$C$303,$A12,'P&L Table'!$E$2:$E$303,"Commissions") -> 0 | V12: =SUMIFS('P&L Table'!$F$2:$F$303,'P&L Table'!$A$2:$A$303,"September",'P&L Table'!$C$2:$C$303,$A12,'P&L Table'!$E$2:$E$303,"Borrow") -> 0 | W12: =SUMIFS('P&L Table'!$F$2:$F$303,'P&L Table'!$A$2:$A$303,"September",'P&L Table'!$C$2:$C$303,$A12,'P&L Table'!$E$2:$E$303,"Dividends / PIL") -> 0 | X12: =SUMIFS('P&L Table'!$F$2:$F$303,'P&L Table'!$A$2:$A$303,"September",'P&L Table'!$C$2:$C$303,$A12,'P&L Table'!$E$2:$E$303,"Other") -> 0 | Y12: =SUM(T12:X12) -> 0 | Z12: =SUMIFS('P&L Table'!$F$2:$F$303,'P&L Table'!$A$2:$A$303,"October",'P&L Table'!$C$2:$C$303,$A12,'P&L Table'!$E$2:$E$303,"MTM P&L") -> 0 | AA12: =SUMIFS('P&L Table'!$F$2:$F$303,'P&L Table'!$A$2:$A$303,"October",'P&L Table'!$C$2:$C$303,$A12,'P&L Table'!$E$2:$E$303,"Commissions") -> 0 | AB12: =SUMIFS('P&L Table'!$F$2:$F$303,'P&L Table'!$A$2:$A$303,"October",'P&L Table'!$C$2:$C$303,$A12,'P&L Table'!$E$2:$E$303,"Borrow") -> 0 | AC12: =SUMIFS('P&L Table'!$F$2:$F$303,'P&L Table'!$A$2:$A$303,"October",'P&L Table'!$C$2:$C$303,$A12,'P&L Table'!$E$2:$E$303,"Dividends / PIL") -> 0 | AD12: =SUMIFS('P&L Table'!$F$2:$F$303,'P&L Table'!$A$2:$A$303,"October",'P&L Table'!$C$2:$C$303,$A12,'P&L Table'!$E$2:$E$303,"Other") -> 0 | AE12: =SUM(Z12:AD12) -> 0 | AF12: =SUM(B12,H12,N12,T12,Z12) -> 90.2 | AG12: =SUM(C12,I12,O12,U12,AA12) -> -29.99 | AH12: =SUM(D12,J12,P12,V12,AB12) -> -15.72 | AI12: =SUM(E12,K12,Q12,W12,AC12) -> 0 | AJ12: =SUM(F12,L12,R12,X12,AD12) -> 0 | AK12: =SUM(G12,M12,S12,Y12,AE12) -> 44.49
A13: EMLC / LEMB | B13: =SUMIFS('P&L Table'!$F$2:$F$303,'P&L Table'!$A$2:$A$303,"June",'P&L Table'!$C$2:$C$303,$A13,'P&L Table'!$E$2:$E$303,"MTM P&L") -> 0 | C13: =SUMIFS('P&L Table'!$F$2:$F$303,'P&L Table'!$A$2:$A$303,"June",'P&L Table'!$C$2:$C$303,$A13,'P&L Table'!$E$2:$E$303,"Commissions") -> 0 | D13: =SUMIFS('P&L Table'!$F$2:$F$303,'P&L Table'!$A$2:$A$303,"June",'P&L Table'!$C$2:$C$303,$A13,'P&L Table'!$E$2:$E$303,"Borrow") -> 0 | E13: =SUMIFS('P&L Table'!$F$2:$F$303,'P&L Table'!$A$2:$A$303,"June",'P&L Table'!$C$2:$C$303,$A13,'P&L Table'!$E$2:$E$303,"Dividends / PIL") -> 0 | F13: =SUMIFS('P&L Table'!$F$2:$F$303,'P&L Table'!$A$2:$A$303,"June",'P&L Table'!$C$2:$C$303,$A13,'P&L Table'!$E$2:$E$303,"Other") -> 0 | G13: =SUM(B13:F13) -> 0 | H13: =SUMIFS('P&L Table'!$F$2:$F$303,'P&L Table'!$A$2:$A$303,"July",'P&L Table'!$C$2:$C$303,$A13,'P&L Table'!$E$2:$E$303,"MTM P&L") -> 0 | I13: =SUMIFS('P&L Table'!$F$2:$F$303,'P&L Table'!$A$2:$A$303,"July",'P&L Table'!$C$2:$C$303,$A13,'P&L Table'!$E$2:$E$303,"Commissions") -> 0 | J13: =SUMIFS('P&L Table'!$F$2:$F$303,'P&L Table'!$A$2:$A$303,"July",'P&L Table'!$C$2:$C$303,$A13,'P&L Table'!$E$2:$E$303,"Borrow") -> 0 | K13: =SUMIFS('P&L Table'!$F$2:$F$303,'P&L Table'!$A$2:$A$303,"July",'P&L Table'!$C$2:$C$303,$A13,'P&L Table'!$E$2:$E$303,"Dividends / PIL") -> 0 | L13: =SUMIFS('P&L Table'!$F$2:$F$303,'P&L Table'!$A$2:$A$303,"July",'P&L Table'!$C$2:$C$303,$A13,'P&L Table'!$E$2:$E$303,"Other") -> 0 | M13: =SUM(H13:L13) -> 0 | N13: =SUMIFS('P&L Table'!$F$2:$F$303,'P&L Table'!$A$2:$A$303,"August",'P&L Table'!$C$2:$C$303,$A13,'P&L Table'!$E$2:$E$303,"MTM P&L") -> 0 | O13: =SUMIFS('P&L Table'!$F$2:$F$303,'P&L Table'!$A$2:$A$303,"August",'P&L Table'!$C$2:$C$303,$A13,'P&L Table'!$E$2:$E$303,"Commissions") -> 0 | P13: =SUMIFS('P&L Table'!$F$2:$F$303,'P&L Table'!$A$2:$A$303,"August",'P&L Table'!$C$2:$C$303,$A13,'P&L Table'!$E$2:$E$303,"Borrow") -> 0 | Q13: =SUMIFS('P&L Table'!$F$2:$F$303,'P&L Table'!$A$2:$A$303,"August",'P&L Table'!$C$2:$C$303,$A13,'P&L Table'!$E$2:$E$303,"Dividends / PIL") -> 0 | R13: =SUMIFS('P&L Table'!$F$2:$F$303,'P&L Table'!$A$2:$A$303,"August",'P&L Table'!$C$2:$C$303,$A13,'P&L Table'!$E$2:$E$303,"Other") -> 0 | S13: =SUM(N13:R13) -> 0 | T13: =SUMIFS('P&L Table'!$F$2:$F$303,'P&L Table'!$A$2:$A$303,"September",'P&L Table'!$C$2:$C$303,$A13,'P&L Table'!$E$2:$E$303,"MTM P&L") -> 0 | U13: =SUMIFS('P&L Table'!$F$2:$F$303,'P&L Table'!$A$2:$A$303,"September",'P&L Table'!$C$2:$C$303,$A13,'P&L Table'!$E$2:$E$303,"Commissions") -> 0 | V13: =SUMIFS('P&L Table'!$F$2:$F$303,'P&L Table'!$A$2:$A$303,"September",'P&L Table'!$C$2:$C$303,$A13,'P&L Table'!$E$2:$E$303,"Borrow") -> 0 | W13: =SUMIFS('P&L Table'!$F$2:$F$303,'P&L Table'!$A$2:$A$303,"September",'P&L Table'!$C$2:$C$303,$A13,'P&L Table'!$E$2:$E$303,"Dividends / PIL") -> 0 | X13: =SUMIFS('P&L Table'!$F$2:$F$303,'P&L Table'!$A$2:$A$303,"September",'P&L Table'!$C$2:$C$303,$A13,'P&L Table'!$E$2:$E$303,"Other") -> 0 | Y13: =SUM(T13:X13) -> 0 | Z13: =SUMIFS('P&L Table'!$F$2:$F$303,'P&L Table'!$A$2:$A$303,"October",'P&L Table'!$C$2:$C$303,$A13,'P&L Table'!$E$2:$E$303,"MTM P&L") -> 52.45 | AA13: =SUMIFS('P&L Table'!$F$2:$F$303,'P&L Table'!$A$2:$A$303,"October",'P&L Table'!$C$2:$C$303,$A13,'P&L Table'!$E$2:$E$303,"Commissions") -> -16.46 | AB13: =SUMIFS('P&L Table'!$F$2:$F$303,'P&L Table'!$A$2:$A$303,"October",'P&L Table'!$C$2:$C$303,$A13,'P&L Table'!$E$2:$E$303,"Borrow") -> -0.46 | AC13: =SUMIFS('P&L Table'!$F$2:$F$303,'P&L Table'!$A$2:$A$303,"October",'P&L Table'!$C$2:$C$303,$A13,'P&L Table'!$E$2:$E$303,"Dividends / PIL") -> 0 | AD13: =SUMIFS('P&L Table'!$F$2:$F$303,'P&L Table'!$A$2:$A$303,"October",'P&L Table'!$C$2:$C$303,$A13,'P&L Table'!$E$2:$E$303,"Other") -> 0 | AE13: =SUM(Z13:AD13) -> 35.53 | AF13: =SUM(B13,H13,N13,T13,Z13) -> 52.45 | AG13: =SUM(C13,I13,O13,U13,AA13) -> -16.46 | AH13: =SUM(D13,J13,P13,V13,AB13) -> -0.46 | AI13: =SUM(E13,K13,Q13,W13,AC13) -> 0 | AJ13: =SUM(F13,L13,R13,X13,AD13) -> 0 | AK13: =SUM(G13,M13,S13,Y13,AE13) -> 35.53
A14: LBTYA / LBTYK | B14: =SUMIFS('P&L Table'!$F$2:$F$303,'P&L Table'!$A$2:$A$303,"June",'P&L Table'!$C$2:$C$303,$A14,'P&L Table'!$E$2:$E$303,"MTM P&L") -> 0 | C14: =SUMIFS('P&L Table'!$F$2:$F$303,'P&L Table'!$A$2:$A$303,"June",'P&L Table'!$C$2:$C$303,$A14,'P&L Table'!$E$2:$E$303,"Commissions") -> 0 | D14: =SUMIFS('P&L Table'!$F$2:$F$303,'P&L Table'!$A$2:$A$303,"June",'P&L Table'!$C$2:$C$303,$A14,'P&L Table'!$E$2:$E$303,"Borrow") -> 0 | E14: =SUMIFS('P&L Table'!$F$2:$F$303,'P&L Table'!$A$2:$A$303,"June",'P&L Table'!$C$2:$C$303,$A14,'P&L Table'!$E$2:$E$303,"Dividends / PIL") -> 0 | F14: =SUMIFS('P&L Table'!$F$2:$F$303,'P&L Table'!$A$2:$A$303,"June",'P&L Table'!$C$2:$C$303,$A14,'P&L Table'!$E$2:$E$303,"Other") -> 0 | G14: =SUM(B14:F14) -> 0 | H14: =SUMIFS('P&L Table'!$F$2:$F$303,'P&L Table'!$A$2:$A$303,"July",'P&L Table'!$C$2:$C$303,$A14,'P&L Table'!$E$2:$E$303,"MTM P&L") -> 0 | I14: =SUMIFS('P&L Table'!$F$2:$F$303,'P&L Table'!$A$2:$A$303,"July",'P&L Table'!$C$2:$C$303,$A14,'P&L Table'!$E$2:$E$303,"Commissions") -> 0 | J14: =SUMIFS('P&L Table'!$F$2:$F$303,'P&L Table'!$A$2:$A$303,"July",'P&L Table'!$C$2:$C$303,$A14,'P&L Table'!$E$2:$E$303,"Borrow") -> 0 | K14: =SUMIFS('P&L Table'!$F$2:$F$303,'P&L Table'!$A$2:$A$303,"July",'P&L Table'!$C$2:$C$303,$A14,'P&L Table'!$E$2:$E$303,"Dividends / PIL") -> 0 | L14: =SUMIFS('P&L Table'!$F$2:$F$303,'P&L Table'!$A$2:$A$303,"July",'P&L Table'!$C$2:$C$303,$A14,'P&L Table'!$E$2:$E$303,"Other") -> 0 | M14: =SUM(H14:L14) -> 0 | N14: =SUMIFS('P&L Table'!$F$2:$F$303,'P&L Table'!$A$2:$A$303,"August",'P&L Table'!$C$2:$C$303,$A14,'P&L Table'!$E$2:$E$303,"MTM P&L") -> 0 | O14: =SUMIFS('P&L Table'!$F$2:$F$303,'P&L Table'!$A$2:$A$303,"August",'P&L Table'!$C$2:$C$303,$A14,'P&L Table'!$E$2:$E$303,"Commissions") -> 0 | P14: =SUMIFS('P&L Table'!$F$2:$F$303,'P&L Table'!$A$2:$A$303,"August",'P&L Table'!$C$2:$C$303,$A14,'P&L Table'!$E$2:$E$303,"Borrow") -> 0 | Q14: =SUMIFS('P&L Table'!$F$2:$F$303,'P&L Table'!$A$2:$A$303,"August",'P&L Table'!$C$2:$C$303,$A14,'P&L Table'!$E$2:$E$303,"Dividends / PIL") -> 0 | R14: =SUMIFS('P&L Table'!$F$2:$F$303,'P&L Table'!$A$2:$A$303,"August",'P&L Table'!$C$2:$C$303,$A14,'P&L Table'!$E$2:$E$303,"Other") -> 0 | S14: =SUM(N14:R14) -> 0 | T14: =SUMIFS('P&L Table'!$F$2:$F$303,'P&L Table'!$A$2:$A$303,"September",'P&L Table'!$C$2:$C$303,$A14,'P&L Table'!$E$2:$E$303,"MTM P&L") -> 0 | U14: =SUMIFS('P&L Table'!$F$2:$F$303,'P&L Table'!$A$2:$A$303,"September",'P&L Table'!$C$2:$C$303,$A14,'P&L Table'!$E$2:$E$303,"Commissions") -> 0 | V14: =SUMIFS('P&L Table'!$F$2:$F$303,'P&L Table'!$A$2:$A$303,"September",'P&L Table'!$C$2:$C$303,$A14,'P&L Table'!$E$2:$E$303,"Borrow") -> 0 | W14: =SUMIFS('P&L Table'!$F$2:$F$303,'P&L Table'!$A$2:$A$303,"September",'P&L Table'!$C$2:$C$303,$A14,'P&L Table'!$E$2:$E$303,"Dividends / PIL") -> 0 | X14: =SUMIFS('P&L Table'!$F$2:$F$303,'P&L Table'!$A$2:$A$303,"September",'P&L Table'!$C$2:$C$303,$A14,'P&L Table'!$E$2:$E$303,"Other") -> 0 | Y14: =SUM(T14:X14) -> 0 | Z14: =SUMIFS('P&L Table'!$F$2:$F$303,'P&L Table'!$A$2:$A$303,"October",'P&L Table'!$C$2:$C$303,$A14,'P&L Table'!$E$2:$E$303,"MTM P&L") -> -11.46 | AA14: =SUMIFS('P&L Table'!$F$2:$F$303,'P&L Table'!$A$2:$A$303,"October",'P&L Table'!$C$2:$C$303,$A14,'P&L Table'!$E$2:$E$303,"Commissions") -> -10.33 | AB14: =SUMIFS('P&L Table'!$F$2:$F$303,'P&L Table'!$A$2:$A$303,"October",'P&L Table'!$C$2:$C$303,$A14,'P&L Table'!$E$2:$E$303,"Borrow") -> -0.12 | AC14: =SUMIFS('P&L Table'!$F$2:$F$303,'P&L Table'!$A$2:$A$303,"October",'P&L Table'!$C$2:$C$303,$A14,'P&L Table'!$E$2:$E$303,"Dividends / PIL") -> 0 | AD14: =SUMIFS('P&L Table'!$F$2:$F$303,'P&L Table'!$A$2:$A$303,"October",'P&L Table'!$C$2:$C$303,$A14,'P&L Table'!$E$2:$E$303,"Other") -> 0 | AE14: =SUM(Z14:AD14) -> -21.91 | AF14: =SUM(B14,H14,N14,T14,Z14) -> -11.46 | AG14: =SUM(C14,I14,O14,U14,AA14) -> -10.33 | AH14: =SUM(D14,J14,P14,V14,AB14) -> -0.12 | AI14: =SUM(E14,K14,Q14,W14,AC14) -> 0 | AJ14: =SUM(F14,L14,R14,X14,AD14) -> 0 | AK14: =SUM(G14,M14,S14,Y14,AE14) -> -21.91
A15: BTCW / IBIT | B15: =SUMIFS('P&L Table'!$F$2:$F$303,'P&L Table'!$A$2:$A$303,"June",'P&L Table'!$C$2:$C$303,$A15,'P&L Table'!$E$2:$E$303,"MTM P&L") -> -62.99 | C15: =SUMIFS('P&L Table'!$F$2:$F$303,'P&L Table'!$A$2:$A$303,"June",'P&L Table'!$C$2:$C$303,$A15,'P&L Table'!$E$2:$E$303,"Commissions") -> -18.12 | D15: =SUMIFS('P&L Table'!$F$2:$F$303,'P&L Table'!$A$2:$A$303,"June",'P&L Table'!$C$2:$C$303,$A15,'P&L Table'!$E$2:$E$303,"Borrow") -> 0 | E15: =SUMIFS('P&L Table'!$F$2:$F$303,'P&L Table'!$A$2:$A$303,"June",'P&L Table'!$C$2:$C$303,$A15,'P&L Table'!$E$2:$E$303,"Dividends / PIL") -> 0 | F15: =SUMIFS('P&L Table'!$F$2:$F$303,'P&L Table'!$A$2:$A$303,"June",'P&L Table'!$C$2:$C$303,$A15,'P&L Table'!$E$2:$E$303,"Other") -> 0 | G15: =SUM(B15:F15) -> -81.11 | H15: =SUMIFS('P&L Table'!$F$2:$F$303,'P&L Table'!$A$2:$A$303,"July",'P&L Table'!$C$2:$C$303,$A15,'P&L Table'!$E$2:$E$303,"MTM P&L") -> 7.2 | I15: =SUMIFS('P&L Table'!$F$2:$F$303,'P&L Table'!$A$2:$A$303,"July",'P&L Table'!$C$2:$C$303,$A15,'P&L Table'!$E$2:$E$303,"Commissions") -> -14.21 | J15: =SUMIFS('P&L Table'!$F$2:$F$303,'P&L Table'!$A$2:$A$303,"July",'P&L Table'!$C$2:$C$303,$A15,'P&L Table'!$E$2:$E$303,"Borrow") -> -1.26 | K15: =SUMIFS('P&L Table'!$F$2:$F$303,'P&L Table'!$A$2:$A$303,"July",'P&L Table'!$C$2:$C$303,$A15,'P&L Table'!$E$2:$E$303,"Dividends / PIL") -> 0 | L15: =SUMIFS('P&L Table'!$F$2:$F$303,'P&L Table'!$A$2:$A$303,"July",'P&L Table'!$C$2:$C$303,$A15,'P&L Table'!$E$2:$E$303,"Other") -> 0 | M15: =SUM(H15:L15) -> -8.27 | N15: =SUMIFS('P&L Table'!$F$2:$F$303,'P&L Table'!$A$2:$A$303,"August",'P&L Table'!$C$2:$C$303,$A15,'P&L Table'!$E$2:$E$303,"MTM P&L") -> 0 | O15: =SUMIFS('P&L Table'!$F$2:$F$303,'P&L Table'!$A$2:$A$303,"August",'P&L Table'!$C$2:$C$303,$A15,'P&L Table'!$E$2:$E$303,"Commissions") -> 0 | P15: =SUMIFS('P&L Table'!$F$2:$F$303,'P&L Table'!$A$2:$A$303,"August",'P&L Table'!$C$2:$C$303,$A15,'P&L Table'!$E$2:$E$303,"Borrow") -> 0 | Q15: =SUMIFS('P&L Table'!$F$2:$F$303,'P&L Table'!$A$2:$A$303,"August",'P&L Table'!$C$2:$C$303,$A15,'P&L Table'!$E$2:$E$303,"Dividends / PIL") -> 0 | R15: =SUMIFS('P&L Table'!$F$2:$F$303,'P&L Table'!$A$2:$A$303,"August",'P&L Table'!$C$2:$C$303,$A15,'P&L Table'!$E$2:$E$303,"Other") -> 0 | S15: =SUM(N15:R15) -> 0 | T15: =SUMIFS('P&L Table'!$F$2:$F$303,'P&L Table'!$A$2:$A$303,"September",'P&L Table'!$C$2:$C$303,$A15,'P&L Table'!$E$2:$E$303,"MTM P&L") -> 0 | U15: =SUMIFS('P&L Table'!$F$2:$F$303,'P&L Table'!$A$2:$A$303,"September",'P&L Table'!$C$2:$C$303,$A15,'P&L Table'!$E$2:$E$303,"Commissions") -> 0 | V15: =SUMIFS('P&L Table'!$F$2:$F$303,'P&L Table'!$A$2:$A$303,"September",'P&L Table'!$C$2:$C$303,$A15,'P&L Table'!$E$2:$E$303,"Borrow") -> 0 | W15: =SUMIFS('P&L Table'!$F$2:$F$303,'P&L Table'!$A$2:$A$303,"September",'P&L Table'!$C$2:$C$303,$A15,'P&L Table'!$E$2:$E$303,"Dividends / PIL") -> 0 | X15: =SUMIFS('P&L Table'!$F$2:$F$303,'P&L Table'!$A$2:$A$303,"September",'P&L Table'!$C$2:$C$303,$A15,'P&L Table'!$E$2:$E$303,"Other") -> 0 | Y15: =SUM(T15:X15) -> 0 | Z15: =SUMIFS('P&L Table'!$F$2:$F$303,'P&L Table'!$A$2:$A$303,"October",'P&L Table'!$C$2:$C$303,$A15,'P&L Table'!$E$2:$E$303,"MTM P&L") -> 0 | AA15: =SUMIFS('P&L Table'!$F$2:$F$303,'P&L Table'!$A$2:$A$303,"October",'P&L Table'!$C$2:$C$303,$A15,'P&L Table'!$E$2:$E$303,"Commissions") -> 0 | AB15: =SUMIFS('P&L Table'!$F$2:$F$303,'P&L Table'!$A$2:$A$303,"October",'P&L Table'!$C$2:$C$303,$A15,'P&L Table'!$E$2:$E$303,"Borrow") -> 0 | AC15: =SUMIFS('P&L Table'!$F$2:$F$303,'P&L Table'!$A$2:$A$303,"October",'P&L Table'!$C$2:$C$303,$A15,'P&L Table'!$E$2:$E$303,"Dividends / PIL") -> 0 | AD15: =SUMIFS('P&L Table'!$F$2:$F$303,'P&L Table'!$A$2:$A$303,"October",'P&L Table'!$C$2:$C$303,$A15,'P&L Table'!$E$2:$E$303,"Other") -> 0 | AE15: =SUM(Z15:AD15) -> 0 | AF15: =SUM(B15,H15,N15,T15,Z15) -> -55.79 | AG15: =SUM(C15,I15,O15,U15,AA15) -> -32.33 | AH15: =SUM(D15,J15,P15,V15,AB15) -> -1.26 | AI15: =SUM(E15,K15,Q15,W15,AC15) -> 0 | AJ15: =SUM(F15,L15,R15,X15,AD15) -> 0 | AK15: =SUM(G15,M15,S15,Y15,AE15) -> -89.38
A16: TLT / VGLT | B16: =SUMIFS('P&L Table'!$F$2:$F$303,'P&L Table'!$A$2:$A$303,"June",'P&L Table'!$C$2:$C$303,$A16,'P&L Table'!$E$2:$E$303,"MTM P&L") -> 0 | C16: =SUMIFS('P&L Table'!$F$2:$F$303,'P&L Table'!$A$2:$A$303,"June",'P&L Table'!$C$2:$C$303,$A16,'P&L Table'!$E$2:$E$303,"Commissions") -> 0 | D16: =SUMIFS('P&L Table'!$F$2:$F$303,'P&L Table'!$A$2:$A$303,"June",'P&L Table'!$C$2:$C$303,$A16,'P&L Table'!$E$2:$E$303,"Borrow") -> 0 | E16: =SUMIFS('P&L Table'!$F$2:$F$303,'P&L Table'!$A$2:$A$303,"June",'P&L Table'!$C$2:$C$303,$A16,'P&L Table'!$E$2:$E$303,"Dividends / PIL") -> 0 | F16: =SUMIFS('P&L Table'!$F$2:$F$303,'P&L Table'!$A$2:$A$303,"June",'P&L Table'!$C$2:$C$303,$A16,'P&L Table'!$E$2:$E$303,"Other") -> 0 | G16: =SUM(B16:F16) -> 0 | H16: =SUMIFS('P&L Table'!$F$2:$F$303,'P&L Table'!$A$2:$A$303,"July",'P&L Table'!$C$2:$C$303,$A16,'P&L Table'!$E$2:$E$303,"MTM P&L") -> -45.96 | I16: =SUMIFS('P&L Table'!$F$2:$F$303,'P&L Table'!$A$2:$A$303,"July",'P&L Table'!$C$2:$C$303,$A16,'P&L Table'!$E$2:$E$303,"Commissions") -> -51.56 | J16: =SUMIFS('P&L Table'!$F$2:$F$303,'P&L Table'!$A$2:$A$303,"July",'P&L Table'!$C$2:$C$303,$A16,'P&L Table'!$E$2:$E$303,"Borrow") -> -16.17 | K16: =SUMIFS('P&L Table'!$F$2:$F$303,'P&L Table'!$A$2:$A$303,"July",'P&L Table'!$C$2:$C$303,$A16,'P&L Table'!$E$2:$E$303,"Dividends / PIL") -> 0 | L16: =SUMIFS('P&L Table'!$F$2:$F$303,'P&L Table'!$A$2:$A$303,"July",'P&L Table'!$C$2:$C$303,$A16,'P&L Table'!$E$2:$E$303,"Other") -> 0 | M16: =SUM(H16:L16) -> -113.69 | N16: =SUMIFS('P&L Table'!$F$2:$F$303,'P&L Table'!$A$2:$A$303,"August",'P&L Table'!$C$2:$C$303,$A16,'P&L Table'!$E$2:$E$303,"MTM P&L") -> -47.82 | O16: =SUMIFS('P&L Table'!$F$2:$F$303,'P&L Table'!$A$2:$A$303,"August",'P&L Table'!$C$2:$C$303,$A16,'P&L Table'!$E$2:$E$303,"Commissions") -> -35.51 | P16: =SUMIFS('P&L Table'!$F$2:$F$303,'P&L Table'!$A$2:$A$303,"August",'P&L Table'!$C$2:$C$303,$A16,'P&L Table'!$E$2:$E$303,"Borrow") -> -104.22 | Q16: =SUMIFS('P&L Table'!$F$2:$F$303,'P&L Table'!$A$2:$A$303,"August",'P&L Table'!$C$2:$C$303,$A16,'P&L Table'!$E$2:$E$303,"Dividends / PIL") -> -9.67 | R16: =SUMIFS('P&L Table'!$F$2:$F$303,'P&L Table'!$A$2:$A$303,"August",'P&L Table'!$C$2:$C$303,$A16,'P&L Table'!$E$2:$E$303,"Other") -> 0 | S16: =SUM(N16:R16) -> -197.22 | T16: =SUMIFS('P&L Table'!$F$2:$F$303,'P&L Table'!$A$2:$A$303,"September",'P&L Table'!$C$2:$C$303,$A16,'P&L Table'!$E$2:$E$303,"MTM P&L") -> 0 | U16: =SUMIFS('P&L Table'!$F$2:$F$303,'P&L Table'!$A$2:$A$303,"September",'P&L Table'!$C$2:$C$303,$A16,'P&L Table'!$E$2:$E$303,"Commissions") -> 0 | V16: =SUMIFS('P&L Table'!$F$2:$F$303,'P&L Table'!$A$2:$A$303,"September",'P&L Table'!$C$2:$C$303,$A16,'P&L Table'!$E$2:$E$303,"Borrow") -> 0 | W16: =SUMIFS('P&L Table'!$F$2:$F$303,'P&L Table'!$A$2:$A$303,"September",'P&L Table'!$C$2:$C$303,$A16,'P&L Table'!$E$2:$E$303,"Dividends / PIL") -> 0 | X16: =SUMIFS('P&L Table'!$F$2:$F$303,'P&L Table'!$A$2:$A$303,"September",'P&L Table'!$C$2:$C$303,$A16,'P&L Table'!$E$2:$E$303,"Other") -> 0 | Y16: =SUM(T16:X16) -> 0 | Z16: =SUMIFS('P&L Table'!$F$2:$F$303,'P&L Table'!$A$2:$A$303,"October",'P&L Table'!$C$2:$C$303,$A16,'P&L Table'!$E$2:$E$303,"MTM P&L") -> 0 | AA16: =SUMIFS('P&L Table'!$F$2:$F$303,'P&L Table'!$A$2:$A$303,"October",'P&L Table'!$C$2:$C$303,$A16,'P&L Table'!$E$2:$E$303,"Commissions") -> 0 | AB16: =SUMIFS('P&L Table'!$F$2:$F$303,'P&L Table'!$A$2:$A$303,"October",'P&L Table'!$C$2:$C$303,$A16,'P&L Table'!$E$2:$E$303,"Borrow") -> 0 | AC16: =SUMIFS('P&L Table'!$F$2:$F$303,'P&L Table'!$A$2:$A$303,"October",'P&L Table'!$C$2:$C$303,$A16,'P&L Table'!$E$2:$E$303,"Dividends / PIL") -> 0 | AD16: =SUMIFS('P&L Table'!$F$2:$F$303,'P&L Table'!$A$2:$A$303,"October",'P&L Table'!$C$2:$C$303,$A16,'P&L Table'!$E$2:$E$303,"Other") -> 0 | AE16: =SUM(Z16:AD16) -> 0 | AF16: =SUM(B16,H16,N16,T16,Z16) -> -93.78 | AG16: =SUM(C16,I16,O16,U16,AA16) -> -87.07 | AH16: =SUM(D16,J16,P16,V16,AB16) -> -120.39 | AI16: =SUM(E16,K16,Q16,W16,AC16) -> -9.67 | AJ16: =SUM(F16,L16,R16,X16,AD16) -> 0 | AK16: =SUM(G16,M16,S16,Y16,AE16) -> -310.91
... A27: IYF / XLF | B27: =SUMIFS('P&L Table'!$F$2:$F$303,'P&L Table'!$A$2:$A$303,"June",'P&L Table'!$C$2:$C$303,$A27,'P&L Table'!$E$2:$E$303,"MTM P&L") -> 0 | C27: =SUMIFS('P&L Table'!$F$2:$F$303,'P&L Table'!$A$2:$A$303,"June",'P&L Table'!$C$2:$C$303,$A27,'P&L Table'!$E$2:$E$303,"Commissions") -> 0 | D27: =SUMIFS('P&L Table'!$F$2:$F$303,'P&L Table'!$A$2:$A$303,"June",'P&L Table'!$C$2:$C$303,$A27,'P&L Table'!$E$2:$E$303,"Borrow") -> 0 | E27: =SUMIFS('P&L Table'!$F$2:$F$303,'P&L Table'!$A$2:$A$303,"June",'P&L Table'!$C$2:$C$303,$A27,'P&L Table'!$E$2:$E$303,"Dividends / PIL") -> 0 | F27: =SUMIFS('P&L Table'!$F$2:$F$303,'P&L Table'!$A$2:$A$303,"June",'P&L Table'!$C$2:$C$303,$A27,'P&L Table'!$E$2:$E$303,"Other") -> 0 | G27: =SUM(B27:F27) -> 0 | H27: =SUMIFS('P&L Table'!$F$2:$F$303,'P&L Table'!$A$2:$A$303,"July",'P&L Table'!$C$2:$C$303,$A27,'P&L Table'!$E$2:$E$303,"MTM P&L") -> 0 | I27: =SUMIFS('P&L Table'!$F$2:$F$303,'P&L Table'!$A$2:$A$303,"July",'P&L Table'!$C$2:$C$303,$A27,'P&L Table'!$E$2:$E$303,"Commissions") -> 0 | J27: =SUMIFS('P&L Table'!$F$2:$F$303,'P&L Table'!$A$2:$A$303,"July",'P&L Table'!$C$2:$C$303,$A27,'P&L Table'!$E$2:$E$303,"Borrow") -> 0 | K27: =SUMIFS('P&L Table'!$F$2:$F$303,'P&L Table'!$A$2:$A$303,"July",'P&L Table'!$C$2:$C$303,$A27,'P&L Table'!$E$2:$E$303,"Dividends / PIL") -> 0 | L27: =SUMIFS('P&L Table'!$F$2:$F$303,'P&L Table'!$A$2:$A$303,"July",'P&L Table'!$C$2:$C$303,$A27,'P&L Table'!$E$2:$E$303,"Other") -> 0 | M27: =SUM(H27:L27) -> 0 | N27: =SUMIFS('P&L Table'!$F$2:$F$303,'P&L Table'!$A$2:$A$303,"August",'P&L Table'!$C$2:$C$303,$A27,'P&L Table'!$E$2:$E$303,"MTM P&L") -> 0 | O27: =SUMIFS('P&L Table'!$F$2:$F$303,'P&L Table'!$A$2:$A$303,"August",'P&L Table'!$C$2:$C$303,$A27,'P&L Table'!$E$2:$E$303,"Commissions") -> 0 | P27: =SUMIFS('P&L Table'!$F$2:$F$303,'P&L Table'!$A$2:$A$303,"August",'P&L Table'!$C$2:$C$303,$A27,'P&L Table'!$E$2:$E$303,"Borrow") -> 0 | Q27: =SUMIFS('P&L Table'!$F$2:$F$303,'P&L Table'!$A$2:$A$303,"August",'P&L Table'!$C$2:$C$303,$A27,'P&L Table'!$E$2:$E$303,"Dividends / PIL") -> 0 | R27: =SUMIFS('P&L Table'!$F$2:$F$303,'P&L Table'!$A$2:$A$303,"August",'P&L Table'!$C$2:$C$303,$A27,'P&L Table'!$E$2:$E$303,"Other") -> 0 | S27: =SUM(N27:R27) -> 0 | T27: =SUMIFS('P&L Table'!$F$2:$F$303,'P&L Table'!$A$2:$A$303,"September",'P&L Table'!$C$2:$C$303,$A27,'P&L Table'!$E$2:$E$303,"MTM P&L") -> 475.3 | U27: =SUMIFS('P&L Table'!$F$2:$F$303,'P&L Table'!$A$2:$A$303,"September",'P&L Table'!$C$2:$C$303,$A27,'P&L Table'!$E$2:$E$303,"Commissions") -> -79.73 | V27: =SUMIFS('P&L Table'!$F$2:$F$303,'P&L Table'!$A$2:$A$303,"September",'P&L Table'!$C$2:$C$303,$A27,'P&L Table'!$E$2:$E$303,"Borrow") -> -9.05 | W27: =SUMIFS('P&L Table'!$F$2:$F$303,'P&L Table'!$A$2:$A$303,"September",'P&L Table'!$C$2:$C$303,$A27,'P&L Table'!$E$2:$E$303,"Dividends / PIL") -> 0 | X27: =SUMIFS('P&L Table'!$F$2:$F$303,'P&L Table'!$A$2:$A$303,"September",'P&L Table'!$C$2:$C$303,$A27,'P&L Table'!$E$2:$E$303,"Other") -> 0 | Y27: =SUM(T27:X27) -> 386.52 | Z27: =SUMIFS('P&L Table'!$F$2:$F$303,'P&L Table'!$A$2:$A$303,"October",'P&L Table'!$C$2:$C$303,$A27,'P&L Table'!$E$2:$E$303,"MTM P&L") -> -5420.47 | AA27: =SUMIFS('P&L Table'!$F$2:$F$303,'P&L Table'!$A$2:$A$303,"October",'P&L Table'!$C$2:$C$303,$A27,'P&L Table'!$E$2:$E$303,"Commissions") -> -11.67 | AB27: =SUMIFS('P&L Table'!$F$2:$F$303,'P&L Table'!$A$2:$A$303,"October",'P&L Table'!$C$2:$C$303,$A27,'P&L Table'!$E$2:$E$303,"Borrow") -> -83.51 | AC27: =SUMIFS('P&L Table'!$F$2:$F$303,'P&L Table'!$A$2:$A$303,"October",'P&L Table'!$C$2:$C$303,$A27,'P&L Table'!$E$2:$E$303,"Dividends / PIL") -> 0 | AD27: =SUMIFS('P&L Table'!$F$2:$F$303,'P&L Table'!$A$2:$A$303,"October",'P&L Table'!$C$2:$C$303,$A27,'P&L Table'!$E$2:$E$303,"Other") -> 0 | AE27: =SUM(Z27:AD27) -> -5515.65 | AF27: =SUM(B27,H27,N27,T27,Z27) -> -4945.17 | AG27: =SUM(C27,I27,O27,U27,AA27) -> -91.4 | AH27: =SUM(D27,J27,P27,V27,AB27) -> -92.56 | AI27: =SUM(E27,K27,Q27,W27,AC27) -> 0 | AJ27: =SUM(F27,L27,R27,X27,AD27) -> 0 | AK27: =SUM(G27,M27,S27,Y27,AE27) -> -5129.13
A28: Equities subtotal | B28: =SUM(B5:B27) -> -62.99 | C28: =SUM(C5:C27) -> -18.12 | D28: =SUM(D5:D27) -> 0 | E28: =SUM(E5:E27) -> 0 | F28: =SUM(F5:F27) -> 0 | G28: =SUM(G5:G27) -> -81.11 | H28: =SUM(H5:H27) -> -3551.35 | I28: =SUM(I5:I27) -> -455.67 | ... AK28: =SUM(AK5:AK27) -> -2917.45
A29: FUTURES
A30: BTC futures | B30: =SUMIFS('P&L Table'!$F$2:$F$303,'P&L Table'!$A$2:$A$303,"June",'P&L Table'!$C$2:$C$303,$A30,'P&L Table'!$E$2:$E$303,"MTM P&L") -> 10378 | C30: =SUMIFS('P&L Table'!$F$2:$F$303,'P&L Table'!$A$2:$A$303,"June",'P&L Table'!$C$2:$C$303,$A30,'P&L Table'!$E$2:$E$303,"Commissions") -> -1982.2 | D30: =SUMIFS('P&L Table'!$F$2:$F$303,'P&L Table'!$A$2:$A$303,"June",'P&L Table'!$C$2:$C$303,$A30,'P&L Table'!$E$2:$E$303,"Borrow") -> 0 | E30: =SUMIFS('P&L Table'!$F$2:$F$303,'P&L Table'!$A$2:$A$303,"June",'P&L Table'!$C$2:$C$303,$A30,'P&L Table'!$E$2:$E$303,"Dividends / PIL") -> 0 | F30: =SUMIFS('P&L Table'!$F$2:$F$303,'P&L Table'!$A$2:$A$303,"June",'P&L Table'!$C$2:$C$303,$A30,'P&L Table'!$E$2:$E$303,"Other") -> 0 | G30: =SUM(B30:F30) -> 8395.8 | H30: =SUMIFS('P&L Table'!$F$2:$F$303,'P&L Table'!$A$2:$A$303,"July",'P&L Table'!$C$2:$C$303,$A30,'P&L Table'!$E$2:$E$303,"MTM P&L") -> 1180 | I30: =SUMIFS('P&L Table'!$F$2:$F$303,'P&L Table'!$A$2:$A$303,"July",'P&L Table'!$C$2:$C$303,$A30,'P&L Table'!$E$2:$E$303,"Commissions") -> -600.52 | J30: =SUMIFS('P&L Table'!$F$2:$F$303,'P&L Table'!$A$2:$A$303,"July",'P&L Table'!$C$2:$C$303,$A30,'P&L Table'!$E$2:$E$303,"Borrow") -> 0 | K30: =SUMIFS('P&L Table'!$F$2:$F$303,'P&L Table'!$A$2:$A$303,"July",'P&L Table'!$C$2:$C$303,$A30,'P&L Table'!$E$2:$E$303,"Dividends / PIL") -> 0 | L30: =SUMIFS('P&L Table'!$F$2:$F$303,'P&L Table'!$A$2:$A$303,"July",'P&L Table'!$C$2:$C$303,$A30,'P&L Table'!$E$2:$E$303,"Other") -> 0 | M30: =SUM(H30:L30) -> 579.48 | N30: =SUMIFS('P&L Table'!$F$2:$F$303,'P&L Table'!$A$2:$A$303,"August",'P&L Table'!$C$2:$C$303,$A30,'P&L Table'!$E$2:$E$303,"MTM P&L") -> 1275 | O30: =SUMIFS('P&L Table'!$F$2:$F$303,'P&L Table'!$A$2:$A$303,"August",'P&L Table'!$C$2:$C$303,$A30,'P&L Table'!$E$2:$E$303,"Commissions") -> -250.2 | P30: =SUMIFS('P&L Table'!$F$2:$F$303,'P&L Table'!$A$2:$A$303,"August",'P&L Table'!$C$2:$C$303,$A30,'P&L Table'!$E$2:$E$303,"Borrow") -> 0 | Q30: =SUMIFS('P&L Table'!$F$2:$F$303,'P&L Table'!$A$2:$A$303,"August",'P&L Table'!$C$2:$C$303,$A30,'P&L Table'!$E$2:$E$303,"Dividends / PIL") -> 0 | R30: =SUMIFS('P&L Table'!$F$2:$F$303,'P&L Table'!$A$2:$A$303,"August",'P&L Table'!$C$2:$C$303,$A30,'P&L Table'!$E$2:$E$303,"Other") -> 0 | S30: =SUM(N30:R30) -> 1024.8 | T30: =SUMIFS('P&L Table'!$F$2:$F$303,'P&L Table'!$A$2:$A$303,"September",'P&L Table'!$C$2:$C$303,$A30,'P&L Table'!$E$2:$E$303,"MTM P&L") -> 890 | U30: =SUMIFS('P&L Table'!$F$2:$F$303,'P&L Table'!$A$2:$A$303,"September",'P&L Table'!$C$2:$C$303,$A30,'P&L Table'!$E$2:$E$303,"Commissions") -> -475.38 | V30: =SUMIFS('P&L Table'!$F$2:$F$303,'P&L Table'!$A$2:$A$303,"September",'P&L Table'!$C$2:$C$303,$A30,'P&L Table'!$E$2:$E$303,"Borrow") -> 0 | W30: =SUMIFS('P&L Table'!$F$2:$F$303,'P&L Table'!$A$2:$A$303,"September",'P&L Table'!$C$2:$C$303,$A30,'P&L Table'!$E$2:$E$303,"Dividends / PIL") -> 0 | X30: =SUMIFS('P&L Table'!$F$2:$F$303,'P&L Table'!$A$2:$A$303,"September",'P&L Table'!$C$2:$C$303,$A30,'P&L Table'!$E$2:$E$303,"Other") -> 0 | Y30: =SUM(T30:X30) -> 414.62 | Z30: =SUMIFS('P&L Table'!$F$2:$F$303,'P&L Table'!$A$2:$A$303,"October",'P&L Table'!$C$2:$C$303,$A30,'P&L Table'!$E$2:$E$303,"MTM P&L") -> 760 | AA30: =SUMIFS('P&L Table'!$F$2:$F$303,'P&L Table'!$A$2:$A$303,"October",'P&L Table'!$C$2:$C$303,$A30,'P&L Table'!$E$2:$E$303,"Commissions") -> -238.68 | AB30: =SUMIFS('P&L Table'!$F$2:$F$303,'P&L Table'!$A$2:$A$303,"October",'P&L Table'!$C$2:$C$303,$A30,'P&L Table'!$E$2:$E$303,"Borrow") -> 0 | AC30: =SUMIFS('P&L Table'!$F$2:$F$303,'P&L Table'!$A$2:$A$303,"October",'P&L Table'!$C$2:$C$303,$A30,'P&L Table'!$E$2:$E$303,"Dividends / PIL") -> 0 | AD30: =SUMIFS('P&L Table'!$F$2:$F$303,'P&L Table'!$A$2:$A$303,"October",'P&L Table'!$C$2:$C$303,$A30,'P&L Table'!$E$2:$E$303,"Other") -> 0 | AE30: =SUM(Z30:AD30) -> 521.32 | AF30: =SUM(B30,H30,N30,T30,Z30) -> 14483 | AG30: =SUM(C30,I30,O30,U30,AA30) -> -3546.98 | AH30: =SUM(D30,J30,P30,V30,AB30) -> 0 | AI30: =SUM(E30,K30,Q30,W30,AC30) -> 0 | AJ30: =SUM(F30,L30,R30,X30,AD30) -> 0 | AK30: =SUM(G30,M30,S30,Y30,AE30) -> 10936.02
A31: ETH futures | B31: =SUMIFS('P&L Table'!$F$2:$F$303,'P&L Table'!$A$2:$A$303,"June",'P&L Table'!$C$2:$C$303,$A31,'P&L Table'!$E$2:$E$303,"MTM P&L") -> 1195 | C31: =SUMIFS('P&L Table'!$F$2:$F$303,'P&L Table'!$A$2:$A$303,"June",'P&L Table'!$C$2:$C$303,$A31,'P&L Table'!$E$2:$E$303,"Commissions") -> -170.4 | D31: =SUMIFS('P&L Table'!$F$2:$F$303,'P&L Table'!$A$2:$A$303,"June",'P&L Table'!$C$2:$C$303,$A31,'P&L Table'!$E$2:$E$303,"Borrow") -> 0 | E31: =SUMIFS('P&L Table'!$F$2:$F$303,'P&L Table'!$A$2:$A$303,"June",'P&L Table'!$C$2:$C$303,$A31,'P&L Table'!$E$2:$E$303,"Dividends / PIL") -> 0 | F31: =SUMIFS('P&L Table'!$F$2:$F$303,'P&L Table'!$A$2:$A$303,"June",'P&L Table'!$C$2:$C$303,$A31,'P&L Table'!$E$2:$E$303,"Other") -> 0 | G31: =SUM(B31:F31) -> 1024.6 | H31: =SUMIFS('P&L Table'!$F$2:$F$303,'P&L Table'!$A$2:$A$303,"July",'P&L Table'!$C$2:$C$303,$A31,'P&L Table'!$E$2:$E$303,"MTM P&L") -> 275 | I31: =SUMIFS('P&L Table'!$F$2:$F$303,'P&L Table'!$A$2:$A$303,"July",'P&L Table'!$C$2:$C$303,$A31,'P&L Table'!$E$2:$E$303,"Commissions") -> -85.12 | J31: =SUMIFS('P&L Table'!$F$2:$F$303,'P&L Table'!$A$2:$A$303,"July",'P&L Table'!$C$2:$C$303,$A31,'P&L Table'!$E$2:$E$303,"Borrow") -> 0 | K31: =SUMIFS('P&L Table'!$F$2:$F$303,'P&L Table'!$A$2:$A$303,"July",'P&L Table'!$C$2:$C$303,$A31,'P&L Table'!$E$2:$E$303,"Dividends / PIL") -> 0 | L31: =SUMIFS('P&L Table'!$F$2:$F$303,'P&L Table'!$A$2:$A$303,"July",'P&L Table'!$C$2:$C$303,$A31,'P&L Table'!$E$2:$E$303,"Other") -> 0 | M31: =SUM(H31:L31) -> 189.88 | N31: =SUMIFS('P&L Table'!$F$2:$F$303,'P&L Table'!$A$2:$A$303,"August",'P&L Table'!$C$2:$C$303,$A31,'P&L Table'!$E$2:$E$303,"MTM P&L") -> 0 | O31: =SUMIFS('P&L Table'!$F$2:$F$303,'P&L Table'!$A$2:$A$303,"August",'P&L Table'!$C$2:$C$303,$A31,'P&L Table'!$E$2:$E$303,"Commissions") -> 0 | P31: =SUMIFS('P&L Table'!$F$2:$F$303,'P&L Table'!$A$2:$A$303,"August",'P&L Table'!$C$2:$C$303,$A31,'P&L Table'!$E$2:$E$303,"Borrow") -> 0 | Q31: =SUMIFS('P&L Table'!$F$2:$F$303,'P&L Table'!$A$2:$A$303,"August",'P&L Table'!$C$2:$C$303,$A31,'P&L Table'!$E$2:$E$303,"Dividends / PIL") -> 0 | R31: =SUMIFS('P&L Table'!$F$2:$F$303,'P&L Table'!$A$2:$A$303,"August",'P&L Table'!$C$2:$C$303,$A31,'P&L Table'!$E$2:$E$303,"Other") -> 0 | S31: =SUM(N31:R31) -> 0 | T31: =SUMIFS('P&L Table'!$F$2:$F$303,'P&L Table'!$A$2:$A$303,"September",'P&L Table'!$C$2:$C$303,$A31,'P&L Table'!$E$2:$E$303,"MTM P&L") -> 0 | U31: =SUMIFS('P&L Table'!$F$2:$F$303,'P&L Table'!$A$2:$A$303,"September",'P&L Table'!$C$2:$C$303,$A31,'P&L Table'!$E$2:$E$303,"Commissions") -> 0 | V31: =SUMIFS('P&L Table'!$F$2:$F$303,'P&L Table'!$A$2:$A$303,"September",'P&L Table'!$C$2:$C$303,$A31,'P&L Table'!$E$2:$E$303,"Borrow") -> 0 | W31: =SUMIFS('P&L Table'!$F$2:$F$303,'P&L Table'!$A$2:$A$303,"September",'P&L Table'!$C$2:$C$303,$A31,'P&L Table'!$E$2:$E$303,"Dividends / PIL") -> 0 | X31: =SUMIFS('P&L Table'!$F$2:$F$303,'P&L Table'!$A$2:$A$303,"September",'P&L Table'!$C$2:$C$303,$A31,'P&L Table'!$E$2:$E$303,"Other") -> 0 | Y31: =SUM(T31:X31) -> 0 | Z31: =SUMIFS('P&L Table'!$F$2:$F$303,'P&L Table'!$A$2:$A$303,"October",'P&L Table'!$C$2:$C$303,$A31,'P&L Table'!$E$2:$E$303,"MTM P&L") -> 0 | AA31: =SUMIFS('P&L Table'!$F$2:$F$303,'P&L Table'!$A$2:$A$303,"October",'P&L Table'!$C$2:$C$303,$A31,'P&L Table'!$E$2:$E$303,"Commissions") -> 0 | AB31: =SUMIFS('P&L Table'!$F$2:$F$303,'P&L Table'!$A$2:$A$303,"October",'P&L Table'!$C$2:$C$303,$A31,'P&L Table'!$E$2:$E$303,"Borrow") -> 0 | AC31: =SUMIFS('P&L Table'!$F$2:$F$303,'P&L Table'!$A$2:$A$303,"October",'P&L Table'!$C$2:$C$303,$A31,'P&L Table'!$E$2:$E$303,"Dividends / PIL") -> 0 | AD31: =SUMIFS('P&L Table'!$F$2:$F$303,'P&L Table'!$A$2:$A$303,"October",'P&L Table'!$C$2:$C$303,$A31,'P&L Table'!$E$2:$E$303,"Other") -> 0 | AE31: =SUM(Z31:AD31) -> 0 | AF31: =SUM(B31,H31,N31,T31,Z31) -> 1470 | AG31: =SUM(C31,I31,O31,U31,AA31) -> -255.52 | AH31: =SUM(D31,J31,P31,V31,AB31) -> 0 | AI31: =SUM(E31,K31,Q31,W31,AC31) -> 0 | AJ31: =SUM(F31,L31,R31,X31,AD31) -> 0 | AK31: =SUM(G31,M31,S31,Y31,AE31) -> 1214.48
A32: Fed funds futures | B32: =SUMIFS('P&L Table'!$F$2:$F$303,'P&L Table'!$A$2:$A$303,"June",'P&L Table'!$C$2:$C$303,$A32,'P&L Table'!$E$2:$E$303,"MTM P&L") -> 31.25 | C32: =SUMIFS('P&L Table'!$F$2:$F$303,'P&L Table'!$A$2:$A$303,"June",'P&L Table'!$C$2:$C$303,$A32,'P&L Table'!$E$2:$E$303,"Commissions") -> -1.83 | D32: =SUMIFS('P&L Table'!$F$2:$F$303,'P&L Table'!$A$2:$A$303,"June",'P&L Table'!$C$2:$C$303,$A32,'P&L Table'!$E$2:$E$303,"Borrow") -> 0 | E32: =SUMIFS('P&L Table'!$F$2:$F$303,'P&L Table'!$A$2:$A$303,"June",'P&L Table'!$C$2:$C$303,$A32,'P&L Table'!$E$2:$E$303,"Dividends / PIL") -> 0 | F32: =SUMIFS('P&L Table'!$F$2:$F$303,'P&L Table'!$A$2:$A$303,"June",'P&L Table'!$C$2:$C$303,$A32,'P&L Table'!$E$2:$E$303,"Other") -> 0 | G32: =SUM(B32:F32) -> 29.42 | H32: =SUMIFS('P&L Table'!$F$2:$F$303,'P&L Table'!$A$2:$A$303,"July",'P&L Table'!$C$2:$C$303,$A32,'P&L Table'!$E$2:$E$303,"MTM P&L") -> 41.68 | I32: =SUMIFS('P&L Table'!$F$2:$F$303,'P&L Table'!$A$2:$A$303,"July",'P&L Table'!$C$2:$C$303,$A32,'P&L Table'!$E$2:$E$303,"Commissions") -> -1.82 | J32: =SUMIFS('P&L Table'!$F$2:$F$303,'P&L Table'!$A$2:$A$303,"July",'P&L Table'!$C$2:$C$303,$A32,'P&L Table'!$E$2:$E$303,"Borrow") -> 0 | K32: =SUMIFS('P&L Table'!$F$2:$F$303,'P&L Table'!$A$2:$A$303,"July",'P&L Table'!$C$2:$C$303,$A32,'P&L Table'!$E$2:$E$303,"Dividends / PIL") -> 0 | L32: =SUMIFS('P&L Table'!$F$2:$F$303,'P&L Table'!$A$2:$A$303,"July",'P&L Table'!$C$2:$C$303,$A32,'P&L Table'!$E$2:$E$303,"Other") -> 0 | M32: =SUM(H32:L32) -> 39.86 | N32: =SUMIFS('P&L Table'!$F$2:$F$303,'P&L Table'!$A$2:$A$303,"August",'P&L Table'!$C$2:$C$303,$A32,'P&L Table'!$E$2:$E$303,"MTM P&L") -> -2.08 | O32: =SUMIFS('P&L Table'!$F$2:$F$303,'P&L Table'!$A$2:$A$303,"August",'P&L Table'!$C$2:$C$303,$A32,'P&L Table'!$E$2:$E$303,"Commissions") -> -1.82 | P32: =SUMIFS('P&L Table'!$F$2:$F$303,'P&L Table'!$A$2:$A$303,"August",'P&L Table'!$C$2:$C$303,$A32,'P&L Table'!$E$2:$E$303,"Borrow") -> 0 | Q32: =SUMIFS('P&L Table'!$F$2:$F$303,'P&L Table'!$A$2:$A$303,"August",'P&L Table'!$C$2:$C$303,$A32,'P&L Table'!$E$2:$E$303,"Dividends / PIL") -> 0 | R32: =SUMIFS('P&L Table'!$F$2:$F$303,'P&L Table'!$A$2:$A$303,"August",'P&L Table'!$C$2:$C$303,$A32,'P&L Table'!$E$2:$E$303,"Other") -> 0 | S32: =SUM(N32:R32) -> -3.9 | T32: =SUMIFS('P&L Table'!$F$2:$F$303,'P&L Table'!$A$2:$A$303,"September",'P&L Table'!$C$2:$C$303,$A32,'P&L Table'!$E$2:$E$303,"MTM P&L") -> -20.84 | U32: =SUMIFS('P&L Table'!$F$2:$F$303,'P&L Table'!$A$2:$A$303,"September",'P&L Table'!$C$2:$C$303,$A32,'P&L Table'!$E$2:$E$303,"Commissions") -> -5.46 | V32: =SUMIFS('P&L Table'!$F$2:$F$303,'P&L Table'!$A$2:$A$303,"September",'P&L Table'!$C$2:$C$303,$A32,'P&L Table'!$E$2:$E$303,"Borrow") -> 0 | W32: =SUMIFS('P&L Table'!$F$2:$F$303,'P&L Table'!$A$2:$A$303,"September",'P&L Table'!$C$2:$C$303,$A32,'P&L Table'!$E$2:$E$303,"Dividends / PIL") -> 0 | X32: =SUMIFS('P&L Table'!$F$2:$F$303,'P&L Table'!$A$2:$A$303,"September",'P&L Table'!$C$2:$C$303,$A32,'P&L Table'!$E$2:$E$303,"Other") -> 0 | Y32: =SUM(T32:X32) -> -26.3 | Z32: =SUMIFS('P&L Table'!$F$2:$F$303,'P&L Table'!$A$2:$A$303,"October",'P&L Table'!$C$2:$C$303,$A32,'P&L Table'!$E$2:$E$303,"MTM P&L") -> 4.17 | AA32: =SUMIFS('P&L Table'!$F$2:$F$303,'P&L Table'!$A$2:$A$303,"October",'P&L Table'!$C$2:$C$303,$A32,'P&L Table'!$E$2:$E$303,"Commissions") -> -3.64 | AB32: =SUMIFS('P&L Table'!$F$2:$F$303,'P&L Table'!$A$2:$A$303,"October",'P&L Table'!$C$2:$C$303,$A32,'P&L Table'!$E$2:$E$303,"Borrow") -> 0 | AC32: =SUMIFS('P&L Table'!$F$2:$F$303,'P&L Table'!$A$2:$A$303,"October",'P&L Table'!$C$2:$C$303,$A32,'P&L Table'!$E$2:$E$303,"Dividends / PIL") -> 0 | AD32: =SUMIFS('P&L Table'!$F$2:$F$303,'P&L Table'!$A$2:$A$303,"October",'P&L Table'!$C$2:$C$303,$A32,'P&L Table'!$E$2:$E$303,"Other") -> 0 | AE32: =SUM(Z32:AD32) -> 0.53 | AF32: =SUM(B32,H32,N32,T32,Z32) -> 54.18 | AG32: =SUM(C32,I32,O32,U32,AA32) -> -14.57 | AH32: =SUM(D32,J32,P32,V32,AB32) -> 0 | AI32: =SUM(E32,K32,Q32,W32,AC32) -> 0 | AJ32: =SUM(F32,L32,R32,X32,AD32) -> 0 | AK32: =SUM(G32,M32,S32,Y32,AE32) -> 39.61
A33: Futures subtotal | B33: =SUM(B30:B32) -> 11604.25 | C33: =SUM(C30:C32) -> -2154.43 | D33: =SUM(D30:D32) -> 0 | E33: =SUM(E30:E32) -> 0 | F33: =SUM(F30:F32) -> 0 | G33: =SUM(G30:G32) -> 9449.82 | H33: =SUM(H30:H32) -> 1496.68 | I33: =SUM(I30:I32) -> -687.46 | ... AK33: =SUM(AK30:AK32) -> 12190.11
A34: OTHER
A35: Interest | B35: =SUMIFS('P&L Table'!$F$2:$F$303,'P&L Table'!$A$2:$A$303,"June",'P&L Table'!$C$2:$C$303,$A35,'P&L Table'!$E$2:$E$303,"MTM P&L") -> 0 | C35: =SUMIFS('P&L Table'!$F$2:$F$303,'P&L Table'!$A$2:$A$303,"June",'P&L Table'!$C$2:$C$303,$A35,'P&L Table'!$E$2:$E$303,"Commissions") -> 0 | D35: =SUMIFS('P&L Table'!$F$2:$F$303,'P&L Table'!$A$2:$A$303,"June",'P&L Table'!$C$2:$C$303,$A35,'P&L Table'!$E$2:$E$303,"Borrow") -> 0 | E35: =SUMIFS('P&L Table'!$F$2:$F$303,'P&L Table'!$A$2:$A$303,"June",'P&L Table'!$C$2:$C$303,$A35,'P&L Table'!$E$2:$E$303,"Dividends / PIL") -> 0 | F35: =SUMIFS('P&L Table'!$F$2:$F$303,'P&L Table'!$A$2:$A$303,"June",'P&L Table'!$C$2:$C$303,$A35,'P&L Table'!$E$2:$E$303,"Other") -> 907.03 | G35: =SUM(B35:F35) -> 907.03 | H35: =SUMIFS('P&L Table'!$F$2:$F$303,'P&L Table'!$A$2:$A$303,"July",'P&L Table'!$C$2:$C$303,$A35,'P&L Table'!$E$2:$E$303,"MTM P&L") -> 0 | I35: =SUMIFS('P&L Table'!$F$2:$F$303,'P&L Table'!$A$2:$A$303,"July",'P&L Table'!$C$2:$C$303,$A35,'P&L Table'!$E$2:$E$303,"Commissions") -> 0 | J35: =SUMIFS('P&L Table'!$F$2:$F$303,'P&L Table'!$A$2:$A$303,"July",'P&L Table'!$C$2:$C$303,$A35,'P&L Table'!$E$2:$E$303,"Borrow") -> 0 | K35: =SUMIFS('P&L Table'!$F$2:$F$303,'P&L Table'!$A$2:$A$303,"July",'P&L Table'!$C$2:$C$303,$A35,'P&L Table'!$E$2:$E$303,"Dividends / PIL") -> 0 | L35: =SUMIFS('P&L Table'!$F$2:$F$303,'P&L Table'!$A$2:$A$303,"July",'P&L Table'!$C$2:$C$303,$A35,'P&L Table'!$E$2:$E$303,"Other") -> 686.95 | M35: =SUM(H35:L35) -> 686.95 | N35: =SUMIFS('P&L Table'!$F$2:$F$303,'P&L Table'!$A$2:$A$303,"August",'P&L Table'!$C$2:$C$303,$A35,'P&L Table'!$E$2:$E$303,"MTM P&L") -> 0 | O35: =SUMIFS('P&L Table'!$F$2:$F$303,'P&L Table'!$A$2:$A$303,"August",'P&L Table'!$C$2:$C$303,$A35,'P&L Table'!$E$2:$E$303,"Commissions") -> 0 | P35: =SUMIFS('P&L Table'!$F$2:$F$303,'P&L Table'!$A$2:$A$303,"August",'P&L Table'!$C$2:$C$303,$A35,'P&L Table'!$E$2:$E$303,"Borrow") -> 0 | Q35: =SUMIFS('P&L Table'!$F$2:$F$303,'P&L Table'!$A$2:$A$303,"August",'P&L Table'!$C$2:$C$303,$A35,'P&L Table'!$E$2:$E$303,"Dividends / PIL") -> 0 | R35: =SUMIFS('P&L Table'!$F$2:$F$303,'P&L Table'!$A$2:$A$303,"August",'P&L Table'!$C$2:$C$303,$A35,'P&L Table'!$E$2:$E$303,"Other") -> 259.36 | S35: =SUM(N35:R35) -> 259.36 | T35: =SUMIFS('P&L Table'!$F$2:$F$303,'P&L Table'!$A$2:$A$303,"September",'P&L Table'!$C$2:$C$303,$A35,'P&L Table'!$E$2:$E$303,"MTM P&L") -> 0 | U35: =SUMIFS('P&L Table'!$F$2:$F$303,'P&L Table'!$A$2:$A$303,"September",'P&L Table'!$C$2:$C$303,$A35,'P&L Table'!$E$2:$E$303,"Commissions") -> 0 | V35: =SUMIFS('P&L Table'!$F$2:$F$303,'P&L Table'!$A$2:$A$303,"September",'P&L Table'!$C$2:$C$303,$A35,'P&L Table'!$E$2:$E$303,"Borrow") -> 0 | W35: =SUMIFS('P&L Table'!$F$2:$F$303,'P&L Table'!$A$2:$A$303,"September",'P&L Table'!$C$2:$C$303,$A35,'P&L Table'!$E$2:$E$303,"Dividends / PIL") -> 0 | X35: =SUMIFS('P&L Table'!$F$2:$F$303,'P&L Table'!$A$2:$A$303,"September",'P&L Table'!$C$2:$C$303,$A35,'P&L Table'!$E$2:$E$303,"Other") -> -1177.35 | Y35: =SUM(T35:X35) -> -1177.35 | Z35: =SUMIFS('P&L Table'!$F$2:$F$303,'P&L Table'!$A$2:$A$303,"October",'P&L Table'!$C$2:$C$303,$A35,'P&L Table'!$E$2:$E$303,"MTM P&L") -> 0 | AA35: =SUMIFS('P&L Table'!$F$2:$F$303,'P&L Table'!$A$2:$A$303,"October",'P&L Table'!$C$2:$C$303,$A35,'P&L Table'!$E$2:$E$303,"Commissions") -> 0 | AB35: =SUMIFS('P&L Table'!$F$2:$F$303,'P&L Table'!$A$2:$A$303,"October",'P&L Table'!$C$2:$C$303,$A35,'P&L Table'!$E$2:$E$303,"Borrow") -> 0 | AC35: =SUMIFS('P&L Table'!$F$2:$F$303,'P&L Table'!$A$2:$A$303,"October",'P&L Table'!$C$2:$C$303,$A35,'P&L Table'!$E$2:$E$303,"Dividends / PIL") -> 0 | AD35: =SUMIFS('P&L Table'!$F$2:$F$303,'P&L Table'!$A$2:$A$303,"October",'P&L Table'!$C$2:$C$303,$A35,'P&L Table'!$E$2:$E$303,"Other") -> -761.26 | AE35: =SUM(Z35:AD35) -> -761.26 | AF35: =SUM(B35,H35,N35,T35,Z35) -> 0 | AG35: =SUM(C35,I35,O35,U35,AA35) -> 0 | AH35: =SUM(D35,J35,P35,V35,AB35) -> 0 | AI35: =SUM(E35,K35,Q35,W35,AC35) -> 0 | AJ35: =SUM(F35,L35,R35,X35,AD35) -> -85.27 | AK35: =SUM(G35,M35,S35,Y35,AE35) -> -85.27
A36: Fees | B36: =SUMIFS('P&L Table'!$F$2:$F$303,'P&L Table'!$A$2:$A$303,"June",'P&L Table'!$C$2:$C$303,$A36,'P&L Table'!$E$2:$E$303,"MTM P&L") -> 0 | C36: =SUMIFS('P&L Table'!$F$2:$F$303,'P&L Table'!$A$2:$A$303,"June",'P&L Table'!$C$2:$C$303,$A36,'P&L Table'!$E$2:$E$303,"Commissions") -> 0 | D36: =SUMIFS('P&L Table'!$F$2:$F$303,'P&L Table'!$A$2:$A$303,"June",'P&L Table'!$C$2:$C$303,$A36,'P&L Table'!$E$2:$E$303,"Borrow") -> 0 | E36: =SUMIFS('P&L Table'!$F$2:$F$303,'P&L Table'!$A$2:$A$303,"June",'P&L Table'!$C$2:$C$303,$A36,'P&L Table'!$E$2:$E$303,"Dividends / PIL") -> 0 | F36: =SUMIFS('P&L Table'!$F$2:$F$303,'P&L Table'!$A$2:$A$303,"June",'P&L Table'!$C$2:$C$303,$A36,'P&L Table'!$E$2:$E$303,"Other") -> -9.5 | G36: =SUM(B36:F36) -> -9.5 | H36: =SUMIFS('P&L Table'!$F$2:$F$303,'P&L Table'!$A$2:$A$303,"July",'P&L Table'!$C$2:$C$303,$A36,'P&L Table'!$E$2:$E$303,"MTM P&L") -> 0 | I36: =SUMIFS('P&L Table'!$F$2:$F$303,'P&L Table'!$A$2:$A$303,"July",'P&L Table'!$C$2:$C$303,$A36,'P&L Table'!$E$2:$E$303,"Commissions") -> 0 | J36: =SUMIFS('P&L Table'!$F$2:$F$303,'P&L Table'!$A$2:$A$303,"July",'P&L Table'!$C$2:$C$303,$A36,'P&L Table'!$E$2:$E$303,"Borrow") -> 0 | K36: =SUMIFS('P&L Table'!$F$2:$F$303,'P&L Table'!$A$2:$A$303,"July",'P&L Table'!$C$2:$C$303,$A36,'P&L Table'!$E$2:$E$303,"Dividends / PIL") -> 0 | L36: =SUMIFS('P&L Table'!$F$2:$F$303,'P&L Table'!$A$2:$A$303,"July",'P&L Table'!$C$2:$C$303,$A36,'P&L Table'!$E$2:$E$303,"Other") -> -9.5 | M36: =SUM(H36:L36) -> -9.5 | N36: =SUMIFS('P&L Table'!$F$2:$F$303,'P&L Table'!$A$2:$A$303,"August",'P&L Table'!$C$2:$C$303,$A36,'P&L Table'!$E$2:$E$303,"MTM P&L") -> 0 | O36: =SUMIFS('P&L Table'!$F$2:$F$303,'P&L Table'!$A$2:$A$303,"August",'P&L Table'!$C$2:$C$303,$A36,'P&L Table'!$E$2:$E$303,"Commissions") -> 0 | P36: =SUMIFS('P&L Table'!$F$2:$F$303,'P&L Table'!$A$2:$A$303,"August",'P&L Table'!$C$2:$C$303,$A36,'P&L Table'!$E$2:$E$303,"Borrow") -> 0 | Q36: =SUMIFS('P&L Table'!$F$2:$F$303,'P&L Table'!$A$2:$A$303,"August",'P&L Table'!$C$2:$C$303,$A36,'P&L Table'!$E$2:$E$303,"Dividends / PIL") -> 0 | R36: =SUMIFS('P&L Table'!$F$2:$F$303,'P&L Table'!$A$2:$A$303,"August",'P&L Table'!$C$2:$C$303,$A36,'P&L Table'!$E$2:$E$303,"Other") -> -9.5 | S36: =SUM(N36:R36) -> -9.5 | T36: =SUMIFS('P&L Table'!$F$2:$F$303,'P&L Table'!$A$2:$A$303,"September",'P&L Table'!$C$2:$C$303,$A36,'P&L Table'!$E$2:$E$303,"MTM P&L") -> 0 | U36: =SUMIFS('P&L Table'!$F$2:$F$303,'P&L Table'!$A$2:$A$303,"September",'P&L Table'!$C$2:$C$303,$A36,'P&L Table'!$E$2:$E$303,"Commissions") -> 0 | V36: =SUMIFS('P&L Table'!$F$2:$F$303,'P&L Table'!$A$2:$A$303,"September",'P&L Table'!$C$2:$C$303,$A36,'P&L Table'!$E$2:$E$303,"Borrow") -> 0 | W36: =SUMIFS('P&L Table'!$F$2:$F$303,'P&L Table'!$A$2:$A$303,"September",'P&L Table'!$C$2:$C$303,$A36,'P&L Table'!$E$2:$E$303,"Dividends / PIL") -> 0 | X36: =SUMIFS('P&L Table'!$F$2:$F$303,'P&L Table'!$A$2:$A$303,"September",'P&L Table'!$C$2:$C$303,$A36,'P&L Table'!$E$2:$E$303,"Other") -> -9.5 | Y36: =SUM(T36:X36) -> -9.5 | Z36: =SUMIFS('P&L Table'!$F$2:$F$303,'P&L Table'!$A$2:$A$303,"October",'P&L Table'!$C$2:$C$303,$A36,'P&L Table'!$E$2:$E$303,"MTM P&L") -> 0 | AA36: =SUMIFS('P&L Table'!$F$2:$F$303,'P&L Table'!$A$2:$A$303,"October",'P&L Table'!$C$2:$C$303,$A36,'P&L Table'!$E$2:$E$303,"Commissions") -> 0 | AB36: =SUMIFS('P&L Table'!$F$2:$F$303,'P&L Table'!$A$2:$A$303,"October",'P&L Table'!$C$2:$C$303,$A36,'P&L Table'!$E$2:$E$303,"Borrow") -> 0 | AC36: =SUMIFS('P&L Table'!$F$2:$F$303,'P&L Table'!$A$2:$A$303,"October",'P&L Table'!$C$2:$C$303,$A36,'P&L Table'!$E$2:$E$303,"Dividends / PIL") -> 0 | AD36: =SUMIFS('P&L Table'!$F$2:$F$303,'P&L Table'!$A$2:$A$303,"October",'P&L Table'!$C$2:$C$303,$A36,'P&L Table'!$E$2:$E$303,"Other") -> -38.5 | AE36: =SUM(Z36:AD36) -> -38.5 | AF36: =SUM(B36,H36,N36,T36,Z36) -> 0 | AG36: =SUM(C36,I36,O36,U36,AA36) -> 0 | AH36: =SUM(D36,J36,P36,V36,AB36) -> 0 | AI36: =SUM(E36,K36,Q36,W36,AC36) -> 0 | AJ36: =SUM(F36,L36,R36,X36,AD36) -> -76.5 | AK36: =SUM(G36,M36,S36,Y36,AE36) -> -76.5
A37: GRAND TOTAL | B37: =SUM(B28,B33,B35,B36) -> 11541.26 | C37: =SUM(C28,C33,C35,C36) -> -2172.55 | D37: =SUM(D28,D33,D35,D36) -> 0 | E37: =SUM(E28,E33,E35,E36) -> 0 | F37: =SUM(F28,F33,F35,F36) -> 897.53 | G37: =SUM(G28,G33,G35,G36) -> 10266.24 | H37: =SUM(H28,H33,H35,H36) -> -2054.67 | I37: =SUM(I28,I33,I35,I36) -> -1143.13 | ... AK37: =SUM(AK28,AK33,AK35,AK36) -> 9110.89
A42: Source: P&L facts table; update the table and refresh/recalculate this SUMIFS-based summary. Original Monthly P&L retained for audit.

Sheet P&L Table
A1: Month | B1: Symbol | C1: Pair / Group | D1: Asset class | E1: P&L category | F1: Amount (USD) | G1: Source report
A2: August | B2: BTCQ6 | C2: BTC futures | D2: Futures | E2: MTM P&L | F2: 7875 | G2: U3308264_202608_202608(1).pdf; MTM Performance Summary / Borrow Fee Details
A3: August | B3: BTCQ6 | C3: BTC futures | D3: Futures | E3: Commissions | F3: -125.1 | G3: U3308264_202608_202608(1).pdf; MTM Performance Summary / Borrow Fee Details
A4: August | B4: BTCU6 | C4: BTC futures | D4: Futures | E4: MTM P&L | F4: -6600 | G4: U3308264_202608_202608(1).pdf; MTM Performance Summary / Borrow Fee Details
A5: August | B5: BTCU6 | C5: BTC futures | D5: Futures | E5: Commissions | F5: -125.1 | G5: U3308264_202608_202608(1).pdf; MTM Performance Summary / Borrow Fee Details
A6: August | B6: BWX | C6: BWX / IGOV | D6: Stocks | E6: MTM P&L | F6: -713.16 | G6: U3308264_202608_202608(1).pdf; MTM Performance Summary / Borrow Fee Details
A7: August | B7: BWX | C7: BWX / IGOV | D7: Stocks | E7: Commissions | F7: -12.08 | G7: U3308264_202608_202608(1).pdf; MTM Performance Summary / Borrow Fee Details
A8: August | B8: BWX | C8: BWX / IGOV | D8: Stocks | E8: Borrow | F8: -169.12 | G8: U3308264_202608_202608(1).pdf; MTM Performance Summary / Borrow Fee Details
A9: August | B9: BWX | C9: BWX / IGOV | D9: Stocks | E9: Dividends / PIL | F9: -109.77 | G9: U3308264_202608_202608(1).pdf; MTM Performance Summary / Borrow Fee Details
A10: August | B10: CORP | C10: CORP / LQD / VTC | D10: Stocks | E10: MTM P&L | F10: 3 | G10: U3308264_202608_202608(1).pdf; MTM Performance Summary / Borrow Fee Details
A11: August | B11: CORP | C11: CORP / LQD / VTC | D11: Stocks | E11: Commissions | F11: -2.43 | G11: U3308264_202608_202608(1).pdf; MTM Performance Summary / Borrow Fee Details
A12: August | B12: CORP | C12: CORP / LQD / VTC | D12: Stocks | E12: Borrow | F12: -184.7 | G12: U3308264_202608_202608(1).pdf; MTM Performance Summary / Borrow Fee Details
A13: August | B13: CWB | C13: CWB / ICVT | D13: Stocks | E13: MTM P&L | F13: -4775.84 | G13: U3308264_202608_202608(1).pdf; MTM Performance Summary / Borrow Fee Details
... A50: August | B50: ZQN6 | C50: Fed funds futures | D50: Futures | E50: Commissions | F50: -1.82 | G50: U3308264_202608_202608(1).pdf; MTM Performance Summary / Borrow Fee Details
A51: August | C51: Interest | D51: Other | E51: Other | F51: 259.36 | G51: Mike
A52: August | C52: Fees | D52: Other | E52: Other | F52: -9.5 | G52: Mike
A53: July | B53: ANGL | C53: ANGL / FALN | D53: Stocks | E53: MTM P&L | F53: -40 | G53: U3308264_202607_202607.pdf; MTM Performance Summary / Borrow Fee Details
A54: July | B54: ANGL | C54: ANGL / FALN | D54: Stocks | E54: Commissions | F54: -4.82 | G54: U3308264_202607_202607.pdf; MTM Performance Summary / Borrow Fee Details
A55: July | B55: BTCN6 | C55: BTC futures | D55: Futures | E55: MTM P&L | F55: 261975 | G55: U3308264_202607_202607.pdf; MTM Performance Summary / Borrow Fee Details
A56: July | B56: BTCN6 | C56: BTC futures | D56: Futures | E56: Commissions | F56: -162.64 | G56: U3308264_202607_202607.pdf; MTM Performance Summary / Borrow Fee Details
A57: July | B57: BTCQ6 | C57: BTC futures | D57: Futures | E57: MTM P&L | F57: -340945 | G57: U3308264_202607_202607.pdf; MTM Performance Summary / Borrow Fee Details
A58: July | B58: BTCQ6 | C58: BTC futures | D58: Futures | E58: Commissions | F58: -225.2 | G58: U3308264_202607_202607.pdf; MTM Performance Summary / Borrow Fee Details
A59: July | B59: BTCU6 | C59: BTC futures | D59: Futures | E59: MTM P&L | F59: -96140 | G59: U3308264_202607_202607.pdf; MTM Performance Summary / Borrow Fee Details
A60: July | B60: BTCU6 | C60: BTC futures | D60: Futures | E60: Commissions | F60: -137.62 | G60: U3308264_202607_202607.pdf; MTM Performance Summary / Borrow Fee Details
A61: July | B61: BTCV6 | C61: BTC futures | D61: Futures | E61: MTM P&L | F61: 176290 | G61: U3308264_202607_202607.pdf; MTM Performance Summary / Borrow Fee Details
A62: July | B62: BTCV6 | C62: BTC futures | D62: Futures | E62: Commissions | F62: -75.06 | G62: U3308264_202607_202607.pdf; MTM Performance Summary / Borrow Fee Details
A63: July | B63: BTCW | C63: BTCW / IBIT | D63: Stocks | E63: MTM P&L | F63: 58.46 | G63: U3308264_202607_202607.pdf; MTM Performance Summary / Borrow Fee Details
A64: July | B64: BTCW | C64: BTCW / IBIT | D64: Stocks | E64: Commissions | F64: -5.59 | G64: U3308264_202607_202607.pdf; MTM Performance Summary / Borrow Fee Details
... A113: July | B113: ZQQ6 | C113: Fed funds futures | D113: Futures | E113: Commissions | F113: -1.82 | G113: U3308264_202607_202607.pdf; MTM Performance Summary / Borrow Fee Details
A114: July | C114: Interest | D114: Other | E114: Other | F114: 686.95 | G114: Mike
A115: July | C115: Fees | D115: Other | E115: Other | F115: -9.5 | G115: Mike
A116: June | B116: BTCM6 | C116: BTC futures | D116: Futures | E116: MTM P&L | F116: 362750 | G116: U3308264_202606_202606.pdf; MTM Performance Summary / Borrow Fee Details
A117: June | B117: BTCM6 | C117: BTC futures | D117: Futures | E117: Commissions | F117: -538.36 | G117: U3308264_202606_202606.pdf; MTM Performance Summary / Borrow Fee Details
A118: June | B118: BTCN6 | C118: BTC futures | D118: Futures | E118: MTM P&L | F118: -775010 | G118: U3308264_202606_202606.pdf; MTM Performance Summary / Borrow Fee Details
A119: June | B119: BTCN6 | C119: BTC futures | D119: Futures | E119: Commissions | F119: -801.28 | G119: U3308264_202606_202606.pdf; MTM Performance Summary / Borrow Fee Details
A120: June | B120: BTCQ6 | C120: BTC futures | D120: Futures | E120: MTM P&L | F120: 273230 | G120: U3308264_202606_202606.pdf; MTM Performance Summary / Borrow Fee Details
A121: June | B121: BTCQ6 | C121: BTC futures | D121: Futures | E121: Commissions | F121: -375.6 | G121: U3308264_202606_202606.pdf; MTM Performance Summary / Borrow Fee Details
A122: June | B122: BTCU6 | C122: BTC futures | D122: Futures | E122: MTM P&L | F122: 166260 | G122: U3308264_202606_202606.pdf; MTM Performance Summary / Borrow Fee Details
A123: June | B123: BTCU6 | C123: BTC futures | D123: Futures | E123: Commissions | F123: -187.8 | G123: U3308264_202606_202606.pdf; MTM Performance Summary / Borrow Fee Details
A124: June | B124: BTCV6 | C124: BTC futures | D124: Futures | E124: MTM P&L | F124: -16930 | G124: U3308264_202606_202606.pdf; MTM Performance Summary / Borrow Fee Details
A125: June | B125: BTCV6 | C125: BTC futures | D125: Futures | E125: Commissions | F125: -75.12 | G125: U3308264_202606_202606.pdf; MTM Performance Summary / Borrow Fee Details
A126: June | B126: BTCW | C126: BTCW / IBIT | D126: Stocks | E126: MTM P&L | F126: -25.99 | G126: U3308264_202606_202606.pdf; MTM Performance Summary / Borrow Fee Details
A127: June | B127: BTCW | C127: BTCW / IBIT | D127: Stocks | E127: Commissions | F127: -10.49 | G127: U3308264_202606_202606.pdf; MTM Performance Summary / Borrow Fee Details
... A141: June | B141: ZQN6 | C141: Fed funds futures | D141: Futures | E141: Commissions | F141: -1.83 | G141: U3308264_202606_202606.pdf; MTM Performance Summary / Borrow Fee Details
A142: June | C142: Interest | D142: Other | E142: Other | F142: 907.03 | G142: Mike
A143: June | C143: Fees | D143: Other | E143: Other | F143: -9.5 | G143: Mike
A144: October | B144: ANGL | C144: ANGL / FALN | D144: Stocks | E144: MTM P&L | F144: -921.62 | G144: U3308264_20261001_20261016.pdf; MTM Performance Summary / Borrow Fee Details
A145: October | B145: ANGL | C145: ANGL / FALN | D145: Stocks | E145: Commissions | F145: -22.01 | G145: U3308264_20261001_20261016.pdf; MTM Performance Summary / Borrow Fee Details
A146: October | B146: BTCV6 | C146: BTC futures | D146: Futures | E146: MTM P&L | F146: 6050 | G146: U3308264_20261001_20261016.pdf; MTM Performance Summary / Borrow Fee Details
A147: October | B147: BTCV6 | C147: BTC futures | D147: Futures | E147: Commissions | F147: -53.04 | G147: U3308264_20261001_20261016.pdf; MTM Performance Summary / Borrow Fee Details
A148: October | B148: BTCX6 | C148: BTC futures | D148: Futures | E148: MTM P&L | F148: -215 | G148: U3308264_20261001_20261016.pdf; MTM Performance Summary / Borrow Fee Details
A149: October | B149: BTCX6 | C149: BTC futures | D149: Futures | E149: Commissions | F149: -119.34 | G149: U3308264_20261001_20261016.pdf; MTM Performance Summary / Borrow Fee Details
A150: October | B150: BTCZ6 | C150: BTC futures | D150: Futures | E150: MTM P&L | F150: -5075 | G150: U3308264_20261001_20261016.pdf; MTM Performance Summary / Borrow Fee Details
A151: October | B151: BTCZ6 | C151: BTC futures | D151: Futures | E151: Commissions | F151: -66.3 | G151: U3308264_20261001_20261016.pdf; MTM Performance Summary / Borrow Fee Details
A152: October | B152: BWX | C152: BWX / IGOV | D152: Stocks | E152: MTM P&L | F152: -477.3 | G152: U3308264_20261001_20261016.pdf; MTM Performance Summary / Borrow Fee Details
A153: October | B153: BWX | C153: BWX / IGOV | D153: Stocks | E153: Commissions | F153: -16.1 | G153: U3308264_20261001_20261016.pdf; MTM Performance Summary / Borrow Fee Details
A154: October | B154: BWX | C154: BWX / IGOV | D154: Stocks | E154: Borrow | F154: -71.89 | G154: U3308264_20261001_20261016.pdf; MTM Performance Summary / Borrow Fee Details
A155: October | B155: CMF | C155: CMF / VTEC | D155: Stocks | E155: MTM P&L | F155: -1785.46 | G155: U3308264_20261001_20261016.pdf; MTM Performance Summary / Borrow Fee Details
... A229: October | B229: ZQU6 | C229: Fed funds futures | D229: Futures | E229: Commissions | F229: -3.64 | G229: U3308264_20261001_20261016.pdf; MTM Performance Summary / Borrow Fee Details
A230: October | C230: Interest | D230: Other | E230: Other | F230: -761.26 | G230: Mike
A231: October | C231: Fees | D231: Other | E231: Other | F231: -38.5 | G231: Mike
A232: September | B232: BTCU6 | C232: BTC futures | D232: Futures | E232: MTM P&L | F232: 131075 | G232: U3308264_202609_202609 (1).pdf; MTM Performance Summary / Borrow Fee Details
A233: September | B233: BTCU6 | C233: BTC futures | D233: Futures | E233: Commissions | F233: -250.2 | G233: U3308264_202609_202609 (1).pdf; MTM Performance Summary / Borrow Fee Details
A234: September | B234: BTCV6 | C234: BTC futures | D234: Futures | E234: MTM P&L | F234: -130185 | G234: U3308264_202609_202609 (1).pdf; MTM Performance Summary / Borrow Fee Details
A235: September | B235: BTCV6 | C235: BTC futures | D235: Futures | E235: Commissions | F235: -225.18 | G235: U3308264_202609_202609 (1).pdf; MTM Performance Summary / Borrow Fee Details
A236: September | B236: BWX | C236: BWX / IGOV | D236: Stocks | E236: MTM P&L | F236: 3719.65 | G236: U3308264_202609_202609 (1).pdf; MTM Performance Summary / Borrow Fee Details
A237: September | B237: BWX | C237: BWX / IGOV | D237: Stocks | E237: Commissions | F237: -49.01 | G237: U3308264_202609_202609 (1).pdf; MTM Performance Summary / Borrow Fee Details
A238: September | B238: BWX | C238: BWX / IGOV | D238: Stocks | E238: Borrow | F238: -288.58 | G238: U3308264_202609_202609 (1).pdf; MTM Performance Summary / Borrow Fee Details
A239: September | B239: CMF | C239: CMF / VTEC | D239: Stocks | E239: MTM P&L | F239: 1046.4 | G239: U3308264_202609_202609 (1).pdf; MTM Performance Summary / Borrow Fee Details
A240: September | B240: CMF | C240: CMF / VTEC | D240: Stocks | E240: Commissions | F240: -49.32 | G240: U3308264_202609_202609 (1).pdf; MTM Performance Summary / Borrow Fee Details
A241: September | B241: CMF | C241: CMF / VTEC | D241: Stocks | E241: Borrow | F241: -58.18 | G241: U3308264_202609_202609 (1).pdf; MTM Performance Summary / Borrow Fee Details
A242: September | B242: IDU | C242: IDU / XLU | D242: Stocks | E242: MTM P&L | F242: 1472.95 | G242: U3308264_202609_202609 (1).pdf; MTM Performance Summary / Borrow Fee Details
A243: September | B243: IDU | C243: IDU / XLU | D243: Stocks | E243: Commissions | F243: -26.19 | G243: U3308264_202609_202609 (1).pdf; MTM Performance Summary / Borrow Fee Details
... A301: September | B301: ZQU6 | C301: Fed funds futures | D301: Futures | E301: Commissions | F301: -3.64 | G301: U3308264_202609_202609 (1).pdf; MTM Performance Summary / Borrow Fee Details
A302: September | C302: Interest | D302: Other | E302: Other | F302: -1177.35 | G302: Mike
A303: September | C303: Fees | D303: Other | E303: Other | F303: -9.5 | G303: Mike

Sheet Pair mapping
A1: Symbol | B1: Pair / Group | C1: Asset class
A2: ANGL | B2: ANGL / FALN | C2: Stocks
A3: FALN | B3: ANGL / FALN | C3: Stocks
A4: BTCM6 | B4: BTC futures | C4: Futures
A5: BTCN6 | B5: BTC futures | C5: Futures
A6: BTCQ6 | B6: BTC futures | C6: Futures
A7: BTCU6 | B7: BTC futures | C7: Futures
A8: BTCV6 | B8: BTC futures | C8: Futures
A9: BTCX6 | B9: BTC futures | C9: Futures
A10: BTCZ6 | B10: BTC futures | C10: Futures
A11: MBTM6 | B11: BTC futures | C11: Futures
A12: BTCW | B12: BTCW / IBIT | C12: Stocks
... A61: VGLT | B61: TLT / VGLT | C61: Stocks
